{
  "type": "Feature",
  "properties": {
    "gn:admin1_code":"08",
    "gn:asciiname":"Los Cimientos",
    "gn:country_code":"GT",
    "gn:dem":1733,
    "gn:feature_class":"P",
    "gn:feature_code":"PPL",
    "gn:name":"Los Cimientos",
    "gn:population":0,
    "gn:timezone":"America/Guatemala",
    "iso:country":"GT",
    "name:spa_x_preferred":[
        "Los Cimientos"
    ],
    "wof:name":"Los Cimientos",
    "wof:placetype":"locality"
},
  "geometry": {"coordinates":[-92.04409,15.386],"type":"Point"}
}