{
  "type": "Feature",
  "properties": {
    "gn:admin1_code":"07",
    "gn:asciiname":"Los Lopez",
    "gn:country_code":"GT",
    "gn:dem":1832,
    "gn:feature_class":"P",
    "gn:feature_code":"PPL",
    "gn:name":"Los L\u00f3pez",
    "gn:population":0,
    "gn:timezone":"America/Guatemala",
    "iso:country":"GT",
    "wof:name":"Los Lopez",
    "wof:placetype":"locality"
},
  "geometry": {"coordinates":[-90.45,14.58333],"type":"Point"}
}