{
  "type": "Feature",
  "properties": {
    "gn:admin1_code":"10",
    "gn:asciiname":"Pinalito",
    "gn:country_code":"GT",
    "gn:dem":1106,
    "gn:feature_class":"P",
    "gn:feature_code":"PPL",
    "gn:name":"Pinalito",
    "gn:population":0,
    "gn:timezone":"America/Guatemala",
    "iso:country":"GT",
    "wof:name":"Pinalito",
    "wof:placetype":"locality"
},
  "geometry": {"coordinates":[-89.88333,14.65],"type":"Point"}
}