{
  "type": "Feature",
  "properties": {
    "gn:admin1_code":"06",
    "gn:asciiname":"Otacingo",
    "gn:country_code":"GT",
    "gn:dem":29,
    "gn:feature_class":"P",
    "gn:feature_code":"PPL",
    "gn:name":"Otacingo",
    "gn:population":0,
    "gn:timezone":"America/Guatemala",
    "iso:country":"GT",
    "wof:name":"Otacingo",
    "wof:placetype":"locality"
},
  "geometry": {"coordinates":[-90.89361,13.9925],"type":"Point"}
}