{
  "type": "Feature",
  "properties": {
    "gn:admin1_code":"12",
    "gn:asciiname":"El Capulinar",
    "gn:country_code":"GT",
    "gn:dem":230,
    "gn:feature_class":"P",
    "gn:feature_code":"PPL",
    "gn:name":"El Capulinar",
    "gn:population":0,
    "gn:timezone":"America/Guatemala",
    "iso:country":"GT",
    "name:spa_x_preferred":[
        "El Capulinar"
    ],
    "wof:name":"El Capulinar",
    "wof:placetype":"locality"
},
  "geometry": {"coordinates":[-89.68138,17.00869],"type":"Point"}
}