{
  "type": "Feature",
  "properties": {
    "gn:admin1_code":"11",
    "gn:asciiname":"El Mangal",
    "gn:country_code":"GT",
    "gn:dem":495,
    "gn:feature_class":"P",
    "gn:feature_code":"PPL",
    "gn:name":"El Mangal",
    "gn:population":0,
    "gn:timezone":"America/Guatemala",
    "iso:country":"GT",
    "wof:name":"El Mangal",
    "wof:placetype":"locality"
},
  "geometry": {"coordinates":[-89.58333,14.35],"type":"Point"}
}