{
  "type": "Feature",
  "properties": {
    "gn:admin1_code":"22",
    "gn:asciiname":"Monte Grande",
    "gn:country_code":"GT",
    "gn:dem":219,
    "gn:feature_class":"P",
    "gn:feature_code":"PPL",
    "gn:name":"Monte Grande",
    "gn:population":0,
    "gn:timezone":"America/Guatemala",
    "iso:country":"GT",
    "wof:name":"Monte Grande",
    "wof:placetype":"locality"
},
  "geometry": {"coordinates":[-89.66667,15.01667],"type":"Point"}
}