{
  "type": "Feature",
  "properties": {
    "gn:admin1_code":"04",
    "gn:asciiname":"Vega Arriba",
    "gn:country_code":"GT",
    "gn:dem":488,
    "gn:feature_class":"P",
    "gn:feature_code":"PPL",
    "gn:name":"Vega Arriba",
    "gn:population":0,
    "gn:timezone":"America/Guatemala",
    "iso:country":"GT",
    "wof:name":"Vega Arriba",
    "wof:placetype":"locality"
},
  "geometry": {"coordinates":[-89.56667,14.76667],"type":"Point"}
}