{
  "type": "Feature",
  "properties": {
    "gn:admin1_code":"17",
    "gn:asciiname":"Tres Puentes",
    "gn:country_code":"GT",
    "gn:dem":2177,
    "gn:feature_class":"P",
    "gn:feature_code":"PPL",
    "gn:name":"Tres Puentes",
    "gn:population":0,
    "gn:timezone":"America/Guatemala",
    "iso:country":"GT",
    "name:spa_x_preferred":[
        "Tres Puentes"
    ],
    "wof:name":"Tres Puentes",
    "wof:placetype":"locality"
},
  "geometry": {"coordinates":[-92.08708,15.23743],"type":"Point"}
}