{
  "type": "Feature",
  "properties": {
    "gn:admin1_code":"06",
    "gn:asciiname":"Texcuaco",
    "gn:country_code":"GT",
    "gn:dem":28,
    "gn:feature_class":"P",
    "gn:feature_code":"PPL",
    "gn:name":"Texcuaco",
    "gn:population":0,
    "gn:timezone":"America/Guatemala",
    "iso:country":"GT",
    "wof:name":"Texcuaco",
    "wof:placetype":"locality"
},
  "geometry": {"coordinates":[-91.21666999999999,14.08333],"type":"Point"}
}