{
  "type": "Feature",
  "properties": {
    "gn:admin1_code":"19",
    "gn:asciiname":"Tzucubal",
    "gn:country_code":"GT",
    "gn:dem":853,
    "gn:feature_class":"P",
    "gn:feature_code":"PPL",
    "gn:name":"Tzucubal",
    "gn:population":0,
    "gn:timezone":"America/Guatemala",
    "iso:country":"GT",
    "wof:name":"Tzucubal",
    "wof:placetype":"locality"
},
  "geometry": {"coordinates":[-91.45,14.61667],"type":"Point"}
}