{
  "type": "Feature",
  "properties": {
    "gn:admin1_code":"14",
    "gn:asciiname":"Bipecbalam",
    "gn:country_code":"GT",
    "gn:dem":2172,
    "gn:feature_class":"P",
    "gn:feature_code":"PPL",
    "gn:name":"Bipecbalam",
    "gn:population":0,
    "gn:timezone":"America/Guatemala",
    "iso:country":"GT",
    "name:spa_x_preferred":[
        "Bipecbalam"
    ],
    "wof:name":"Bipecbalam",
    "wof:placetype":"locality"
},
  "geometry": {"coordinates":[-91.18895999999999,15.46418],"type":"Point"}
}