{
  "type": "Feature",
  "properties": {
    "gn:admin1_code":"08",
    "gn:asciiname":"Laguna Chinaca",
    "gn:country_code":"GT",
    "gn:dem":2038,
    "gn:feature_class":"P",
    "gn:feature_code":"PPL",
    "gn:name":"Laguna Chinac\u00e1",
    "gn:population":0,
    "gn:timezone":"America/Guatemala",
    "iso:country":"GT",
    "name:spa_x_preferred":[
        "Laguna Chinac\u00e1"
    ],
    "wof:name":"Laguna Chinaca",
    "wof:placetype":"locality"
},
  "geometry": {"coordinates":[-91.43096,15.33557],"type":"Point"}
}