{
  "type": "Feature",
  "properties": {
    "gn:admin1_code":"14",
    "gn:asciiname":"Muluba",
    "gn:country_code":"GT",
    "gn:dem":1493,
    "gn:feature_class":"P",
    "gn:feature_code":"PPL",
    "gn:name":"Mulub\u00e1",
    "gn:population":0,
    "gn:timezone":"America/Guatemala",
    "iso:country":"GT",
    "name:spa_x_preferred":[
        "Mulub\u00e1"
    ],
    "wof:name":"Muluba",
    "wof:placetype":"locality"
},
  "geometry": {"coordinates":[-91.04794,15.19727],"type":"Point"}
}