{
  "type": "Feature",
  "properties": {
    "iso:country":"GT",
    "name:ceb_x_preferred":[
        "Pal\u00edn"
    ],
    "name:eng_x_preferred":[
        "Pal\u00edn"
    ],
    "name:ita_x_preferred":[
        "Pal\u00edn"
    ],
    "name:nld_x_preferred":[
        "Pal\u00edn"
    ],
    "name:pol_x_preferred":[
        "Pal\u00edn"
    ],
    "name:por_x_preferred":[
        "Pal\u00edn"
    ],
    "name:spa_x_preferred":[
        "Pal\u00edn"
    ],
    "name:swe_x_preferred":[
        "Pal\u00edn"
    ],
    "name:urd_x_preferred":[
        "\u067e\u0627\u0644\u06cc\u0646\u060c \u0627\u06cc\u0633\u06a9\u0648\u06cc\u0646\u062a\u0644\u0627"
    ],
    "name:urd_x_variant":[
        "\u067e\u0627\u0644\u06cc\u0646"
    ],
    "name:zho_x_preferred":[
        "\u5e15\u6797"
    ],
    "qs:gn_country":"GT",
    "qs:gn_fcode":"PPL",
    "qs:gn_pop":31329,
    "qs:name":"Pal\u00edn",
    "qs:name_adm0":"Guatemala",
    "qs:name_adm1":"Escuintla",
    "qs:photos":123,
    "qs:photos_1k":25,
    "qs:photos_9k":1,
    "qs:photos_9r":3,
    "qs:photos_all":123,
    "qs:photos_sr":3,
    "qs:placetype":"Town",
    "qs:pop_sr":"7",
    "qs:woe_adm0":23424834,
    "wd:wordcount":1085,
    "wof:name":"Pal\u00edn",
    "wof:placetype":"locality",
    "wof:population":31329
},
  "geometry": {"coordinates":[-90.69833,14.40556],"type":"Point"}
}