{
  "type": "Feature",
  "properties": {
    "gn:admin1_code":"11",
    "gn:asciiname":"Carrizal",
    "gn:cc2":"GT",
    "gn:country_code":"GT",
    "gn:dem":678,
    "gn:feature_class":"P",
    "gn:feature_code":"PPL",
    "gn:name":"Carrizal",
    "gn:population":0,
    "gn:timezone":"America/Guatemala",
    "iso:country":"GT",
    "name:ceb_x_preferred":[
        "Carrizal"
    ],
    "name:fra_x_preferred":[
        "Carrizal"
    ],
    "name:ita_x_preferred":[
        "Carrizal"
    ],
    "name:jpn_x_preferred":[
        "\u30ab\u30ea\u30b5\u30eb"
    ],
    "name:mlg_x_preferred":[
        "Carrizal"
    ],
    "name:por_x_preferred":[
        "Carrizal"
    ],
    "name:rus_x_preferred":[
        "\u041a\u0430\u0440\u0440\u0438\u0441\u0430\u043b\u044c"
    ],
    "name:spa_x_preferred":[
        "Carrizal"
    ],
    "name:swe_x_preferred":[
        "Carrizal"
    ],
    "name:und_x_variant":[
        "El Carrizal",
        "Carrizal"
    ],
    "wof:name":"Carrizal",
    "wof:placetype":"locality"
},
  "geometry": {"coordinates":[-89.51666999999998,14.46667],"type":"Point"}
}