{
  "type": "Feature",
  "properties": {
    "gn:admin1_code":"17",
    "gn:asciiname":"El Malacate",
    "gn:country_code":"GT",
    "gn:dem":2407,
    "gn:feature_class":"P",
    "gn:feature_code":"PPL",
    "gn:name":"El Malacate",
    "gn:population":0,
    "gn:timezone":"America/Guatemala",
    "iso:country":"GT",
    "name:spa_x_preferred":[
        "El Malacate"
    ],
    "wof:name":"El Malacate",
    "wof:placetype":"locality"
},
  "geometry": {"coordinates":[-92.04015,15.12288],"type":"Point"}
}