{
  "type": "Feature",
  "properties": {
    "gn:admin1_code":"17",
    "gn:asciiname":"Guapinol",
    "gn:country_code":"GT",
    "gn:dem":72,
    "gn:feature_class":"P",
    "gn:feature_code":"PPL",
    "gn:name":"Guapinol",
    "gn:population":0,
    "gn:timezone":"America/Guatemala",
    "iso:country":"GT",
    "wof:name":"Guapinol",
    "wof:placetype":"locality"
},
  "geometry": {"coordinates":[-92.11667,14.76667],"type":"Point"}
}