{
  "type": "Feature",
  "properties": {
    "gn:admin1_code":"14",
    "gn:asciiname":"Patzite",
    "gn:country_code":"GT",
    "gn:dem":1935,
    "gn:feature_class":"P",
    "gn:feature_code":"PPL",
    "gn:name":"Patzit\u00e9",
    "gn:population":0,
    "gn:timezone":"America/Guatemala",
    "iso:country":"GT",
    "name:spa_x_preferred":[
        "Patzit\u00e9"
    ],
    "wof:name":"Patzite",
    "wof:placetype":"locality"
},
  "geometry": {"coordinates":[-91.25788,15.17265],"type":"Point"}
}