{
  "type": "Feature",
  "properties": {
    "gn:admin1_code":"07",
    "gn:asciiname":"Acatan",
    "gn:country_code":"GT",
    "gn:dem":1557,
    "gn:feature_class":"P",
    "gn:feature_code":"PPL",
    "gn:name":"Acat\u00e1n",
    "gn:population":0,
    "gn:timezone":"America/Guatemala",
    "iso:country":"GT",
    "wof:name":"Acatan",
    "wof:placetype":"locality"
},
  "geometry": {"coordinates":[-90.46666999999999,14.61667],"type":"Point"}
}