{
  "type": "Feature",
  "properties": {
    "gn:admin1_code":"17",
    "gn:asciiname":"Tuisajchin",
    "gn:country_code":"GT",
    "gn:dem":2605,
    "gn:feature_class":"P",
    "gn:feature_code":"PPL",
    "gn:name":"Tuisajch\u00edn",
    "gn:population":0,
    "gn:timezone":"America/Guatemala",
    "iso:country":"GT",
    "name:spa_x_preferred":[
        "Tuisajch\u00edn"
    ],
    "wof:name":"Tuisajchin",
    "wof:placetype":"locality"
},
  "geometry": {"coordinates":[-91.84371,15.29913],"type":"Point"}
}