{
  "type": "Feature",
  "properties": {
    "gn:admin1_code":"01",
    "gn:asciiname":"Cojcam",
    "gn:country_code":"GT",
    "gn:dem":456,
    "gn:feature_class":"P",
    "gn:feature_code":"PPL",
    "gn:name":"Cojcam",
    "gn:population":0,
    "gn:timezone":"America/Guatemala",
    "iso:country":"GT",
    "wof:name":"Cojcam",
    "wof:placetype":"locality"
},
  "geometry": {"coordinates":[-90.23333,15.75],"type":"Point"}
}