{
  "type": "Feature",
  "properties": {
    "gn:admin1_code":"15",
    "gn:asciiname":"Toncontin",
    "gn:country_code":"GT",
    "gn:dem":11,
    "gn:feature_class":"P",
    "gn:feature_code":"PPL",
    "gn:name":"Toncont\u00edn",
    "gn:population":0,
    "gn:timezone":"America/Guatemala",
    "iso:country":"GT",
    "wof:name":"Toncontin",
    "wof:placetype":"locality"
},
  "geometry": {"coordinates":[-91.90000000000001,14.33333],"type":"Point"}
}