{
  "type": "Feature",
  "properties": {
    "gn:admin1_code":"11",
    "gn:asciiname":"El Sauce",
    "gn:country_code":"GT",
    "gn:dem":848,
    "gn:feature_class":"P",
    "gn:feature_code":"PPL",
    "gn:name":"El Sauce",
    "gn:population":0,
    "gn:timezone":"America/Guatemala",
    "iso:country":"GT",
    "name:ceb_x_preferred":[
        "El Sauce"
    ],
    "name:ita_x_preferred":[
        "El Sauce"
    ],
    "name:por_x_preferred":[
        "El Sauce"
    ],
    "name:spa_x_preferred":[
        "El Sauce"
    ],
    "name:zho_x_preferred":[
        "\u57c3\u723e\u7d39\u585e"
    ],
    "wof:name":"El Sauce",
    "wof:placetype":"locality"
},
  "geometry": {"coordinates":[-89.78333000000001,14.21667],"type":"Point"}
}