{
  "type": "Feature",
  "properties": {
    "gn:admin1_code":"21",
    "gn:asciiname":"Xocojom",
    "gn:country_code":"GT",
    "gn:dem":2415,
    "gn:feature_class":"P",
    "gn:feature_code":"PPL",
    "gn:name":"Xocoj\u00f3m",
    "gn:population":0,
    "gn:timezone":"America/Guatemala",
    "iso:country":"GT",
    "name:spa_x_preferred":[
        "Xocoj\u00f3m"
    ],
    "wof:name":"Xocojom",
    "wof:placetype":"locality"
},
  "geometry": {"coordinates":[-91.41146000000001,15.01231],"type":"Point"}
}