{
  "type": "Feature",
  "properties": {
    "gn:admin1_code":"02",
    "gn:asciiname":"Chirrum",
    "gn:country_code":"GT",
    "gn:dem":1366,
    "gn:feature_class":"P",
    "gn:feature_code":"PPL",
    "gn:name":"Chirrum",
    "gn:population":0,
    "gn:timezone":"America/Guatemala",
    "iso:country":"GT",
    "wof:name":"Chirrum",
    "wof:placetype":"locality"
},
  "geometry": {"coordinates":[-90.45,15.05],"type":"Point"}
}