{
  "type": "Feature",
  "properties": {
    "gn:admin1_code":"13",
    "gn:asciiname":"Tzanjuyu",
    "gn:country_code":"GT",
    "gn:dem":2726,
    "gn:feature_class":"P",
    "gn:feature_code":"PPL",
    "gn:name":"Tzanjuy\u00fa",
    "gn:population":0,
    "gn:timezone":"America/Guatemala",
    "iso:country":"GT",
    "wof:name":"Tzanjuyu",
    "wof:placetype":"locality"
},
  "geometry": {"coordinates":[-91.53333000000001,14.91667],"type":"Point"}
}