{
  "type": "Feature",
  "properties": {
    "gn:admin1_code":"17",
    "gn:asciiname":"Sichivila",
    "gn:country_code":"GT",
    "gn:dem":2732,
    "gn:feature_class":"P",
    "gn:feature_code":"PPL",
    "gn:name":"Sichivil\u00e1",
    "gn:population":0,
    "gn:timezone":"America/Guatemala",
    "iso:country":"GT",
    "name:spa_x_preferred":[
        "Sichivil\u00e1"
    ],
    "wof:name":"Sichivila",
    "wof:placetype":"locality"
},
  "geometry": {"coordinates":[-91.86868,15.31991],"type":"Point"}
}