{
  "type": "Feature",
  "properties": {
    "gn:admin1_code":"03",
    "gn:asciiname":"Agua Escondida",
    "gn:country_code":"GT",
    "gn:dem":2504,
    "gn:feature_class":"P",
    "gn:feature_code":"PPL",
    "gn:name":"Agua Escondida",
    "gn:population":0,
    "gn:timezone":"America/Guatemala",
    "iso:country":"GT",
    "wof:name":"Agua Escondida",
    "wof:placetype":"locality"
},
  "geometry": {"coordinates":[-91.03333000000001,14.81667],"type":"Point"}
}