{
  "type": "Feature",
  "properties": {
    "gn:admin1_code":"07",
    "gn:asciiname":"El Barrancon",
    "gn:country_code":"GT",
    "gn:dem":2012,
    "gn:feature_class":"P",
    "gn:feature_code":"PPL",
    "gn:name":"El Barranc\u00f3n",
    "gn:population":0,
    "gn:timezone":"America/Guatemala",
    "iso:country":"GT",
    "wof:name":"El Barrancon",
    "wof:placetype":"locality"
},
  "geometry": {"coordinates":[-90.28333000000001,14.61667],"type":"Point"}
}