{
  "type": "Feature",
  "properties": {
    "gn:admin1_code":"17",
    "gn:asciiname":"Ladrillera",
    "gn:country_code":"GT",
    "gn:dem":2641,
    "gn:feature_class":"P",
    "gn:feature_code":"PPL",
    "gn:name":"Ladrillera",
    "gn:population":0,
    "gn:timezone":"America/Guatemala",
    "iso:country":"GT",
    "name:spa_x_preferred":[
        "Ladrillera"
    ],
    "wof:name":"Ladrillera",
    "wof:placetype":"locality"
},
  "geometry": {"coordinates":[-91.77118,15.22575],"type":"Point"}
}