{
  "type": "Feature",
  "properties": {
    "iso:country":"GT",
    "name:deu_x_preferred":[
        "Comitancillo"
    ],
    "name:eng_x_preferred":[
        "Comitancillo"
    ],
    "name:fra_x_preferred":[
        "Comitancillo"
    ],
    "name:ita_x_preferred":[
        "Comitancillo"
    ],
    "name:nld_x_preferred":[
        "Comitancillo"
    ],
    "name:pol_x_preferred":[
        "Comitancillo"
    ],
    "name:por_x_preferred":[
        "Comitancillo"
    ],
    "name:spa_x_preferred":[
        "Comitancillo"
    ],
    "name:swe_x_preferred":[
        "Comitancillo"
    ],
    "name:unk_x_variant":[
        "Comitacillo"
    ],
    "name:urd_x_preferred":[
        "\u06a9\u0648\u0645\u06cc\u062a\u0627\u0646\u0633\u06cc\u0648"
    ],
    "name:zho_x_preferred":[
        "\u79d1\u7c73\u5766\u897f\u7d04"
    ],
    "qs:gn_country":"GT",
    "qs:gn_fcode":"PPL",
    "qs:gn_pop":19669,
    "qs:name":"Comitancillo",
    "qs:name_adm0":"Guatemala",
    "qs:name_adm1":"San Marcos",
    "qs:photos":0,
    "qs:photos_1k":0,
    "qs:photos_9k":1,
    "qs:photos_9r":2,
    "qs:photos_all":47,
    "qs:photos_sr":0,
    "qs:placetype":"Town",
    "qs:pop_sr":"6",
    "qs:woe_adm0":23424834,
    "wd:wordcount":772,
    "wof:name":"Comitancillo",
    "wof:placetype":"locality",
    "wof:population":19669
},
  "geometry": {"coordinates":[-91.71666999999999,15.08333],"type":"Point"}
}