{
  "type": "Feature",
  "properties": {
    "gn:admin1_code":"10",
    "gn:asciiname":"Los Riscos",
    "gn:cc2":"GT",
    "gn:country_code":"GT",
    "gn:dem":1193,
    "gn:feature_class":"P",
    "gn:feature_code":"PPL",
    "gn:name":"Los Riscos",
    "gn:population":0,
    "gn:timezone":"America/Guatemala",
    "iso:country":"GT",
    "name:und_x_variant":[
        "Rinc\u00f3n",
        "Los Riscos"
    ],
    "wof:name":"Los Riscos",
    "wof:placetype":"locality"
},
  "geometry": {"coordinates":[-89.91667,14.65],"type":"Point"}
}