{
  "type": "Feature",
  "properties": {
    "gn:admin1_code":"17",
    "gn:asciiname":"Nueva Democracia",
    "gn:country_code":"GT",
    "gn:dem":2835,
    "gn:feature_class":"P",
    "gn:feature_code":"PPL",
    "gn:name":"Nueva Democracia",
    "gn:population":0,
    "gn:timezone":"America/Guatemala",
    "iso:country":"GT",
    "name:spa_x_preferred":[
        "Nueva Democracia"
    ],
    "wof:name":"Nueva Democracia",
    "wof:placetype":"locality"
},
  "geometry": {"coordinates":[-91.83373,15.2502],"type":"Point"}
}