{
  "type": "Feature",
  "properties": {
    "gn:admin1_code":"17",
    "gn:asciiname":"Michel",
    "gn:country_code":"GT",
    "gn:dem":2710,
    "gn:feature_class":"P",
    "gn:feature_code":"PPL",
    "gn:name":"M\u00edchel",
    "gn:population":0,
    "gn:timezone":"America/Guatemala",
    "iso:country":"GT",
    "name:ceb_x_preferred":[
        "Michel"
    ],
    "name:ces_x_preferred":[
        "Michel"
    ],
    "name:deu_x_preferred":[
        "Michel"
    ],
    "name:heb_x_preferred":[
        "\u05de\u05d9\u05e9\u05dc"
    ],
    "name:hsb_x_preferred":[
        "Michel"
    ],
    "name:ita_x_preferred":[
        "Michel"
    ],
    "name:jpn_x_preferred":[
        "\u30df\u30b7\u30a7\u30eb"
    ],
    "name:nld_x_preferred":[
        "Michel"
    ],
    "name:slv_x_preferred":[
        "Michel"
    ],
    "name:spa_x_preferred":[
        "M\u00edchel"
    ],
    "name:spa_x_variant":[
        "Michel"
    ],
    "name:swe_x_preferred":[
        "Michel"
    ],
    "wof:name":"Michel",
    "wof:placetype":"locality"
},
  "geometry": {"coordinates":[-91.78278,15.23592],"type":"Point"}
}