{
  "type": "Feature",
  "properties": {
    "gn:admin1_code":"08",
    "gn:asciiname":"Talpetate",
    "gn:country_code":"GT",
    "gn:dem":1843,
    "gn:feature_class":"P",
    "gn:feature_code":"PPL",
    "gn:name":"Talpetate",
    "gn:population":0,
    "gn:timezone":"America/Guatemala",
    "iso:country":"GT",
    "name:spa_x_preferred":[
        "Talpetate"
    ],
    "wof:name":"Talpetate",
    "wof:placetype":"locality"
},
  "geometry": {"coordinates":[-91.58732000000001,15.36962],"type":"Point"}
}