{
  "type": "Feature",
  "properties": {
    "gn:admin1_code":"14",
    "gn:asciiname":"Magdalena La Abundancia",
    "gn:country_code":"GT",
    "gn:dem":1857,
    "gn:feature_class":"P",
    "gn:feature_code":"PPL",
    "gn:name":"Magdalena La Abundancia",
    "gn:population":0,
    "gn:timezone":"America/Guatemala",
    "iso:country":"GT",
    "name:spa_x_preferred":[
        "Magdalena La Abundancia"
    ],
    "wof:name":"Magdalena La Abundancia",
    "wof:placetype":"locality"
},
  "geometry": {"coordinates":[-91.12886,15.33577],"type":"Point"}
}