{
  "type": "Feature",
  "properties": {
    "gn:admin1_code":"04",
    "gn:asciiname":"Horepon",
    "gn:country_code":"GT",
    "gn:dem":426,
    "gn:feature_class":"P",
    "gn:feature_code":"PPL",
    "gn:name":"Horep\u00f3n",
    "gn:population":0,
    "gn:timezone":"America/Guatemala",
    "iso:country":"GT",
    "wof:name":"Horepon",
    "wof:placetype":"locality"
},
  "geometry": {"coordinates":[-89.55,14.81667],"type":"Point"}
}