{
  "type": "Feature",
  "properties": {
    "gn:admin1_code":"12",
    "gn:asciiname":"San Pedro Cadenas",
    "gn:country_code":"GT",
    "gn:dem":14,
    "gn:feature_class":"P",
    "gn:feature_code":"PPL",
    "gn:name":"San Pedro Cadenas",
    "gn:population":0,
    "gn:timezone":"America/Guatemala",
    "iso:country":"GT",
    "wof:name":"San Pedro Cadenas",
    "wof:placetype":"locality"
},
  "geometry": {"coordinates":[-89.23997,15.93537],"type":"Point"}
}