{
  "type": "Feature",
  "properties": {
    "gn:admin1_code":"17",
    "gn:asciiname":"Chequim",
    "gn:country_code":"GT",
    "gn:dem":3013,
    "gn:feature_class":"P",
    "gn:feature_code":"PPL",
    "gn:name":"Chequim",
    "gn:population":0,
    "gn:timezone":"America/Guatemala",
    "iso:country":"GT",
    "name:spa_x_preferred":[
        "Chequim"
    ],
    "wof:name":"Chequim",
    "wof:placetype":"locality"
},
  "geometry": {"coordinates":[-92.13375000000001,15.25221],"type":"Point"}
}