{
  "type": "Feature",
  "properties": {
    "gn:admin1_code":"13",
    "gn:asciiname":"Chitay",
    "gn:country_code":"GT",
    "gn:dem":2340,
    "gn:feature_class":"P",
    "gn:feature_code":"PPL",
    "gn:name":"Chitay",
    "gn:population":0,
    "gn:timezone":"America/Guatemala",
    "iso:country":"GT",
    "wof:name":"Chitay",
    "wof:placetype":"locality"
},
  "geometry": {"coordinates":[-91.48333,14.85],"type":"Point"}
}