{
  "type": "Feature",
  "properties": {
    "iso:country":"GT",
    "name:chi_x_preferred":[
        "\u54c8\u5361\u723e\u7279\u5357\u6208"
    ],
    "name:deu_x_preferred":[
        "Jacaltenango"
    ],
    "name:dut_x_preferred":[
        "Jacaltenango"
    ],
    "name:eng_x_preferred":[
        "Jacaltenango"
    ],
    "name:fra_x_preferred":[
        "Jacaltenango"
    ],
    "name:fre_x_preferred":[
        "Jacaltenango"
    ],
    "name:ger_x_preferred":[
        "Jacaltenango"
    ],
    "name:ita_x_preferred":[
        "Jacaltenango"
    ],
    "name:lit_x_preferred":[
        "Chakaltenangas"
    ],
    "name:pol_x_preferred":[
        "Jacaltenango"
    ],
    "name:por_x_preferred":[
        "Jacaltenango"
    ],
    "name:rus_x_preferred":[
        "\u0425\u0430\u043a\u0430\u043b\u044c\u0442\u0435\u043d\u0430\u043d\u0433\u043e"
    ],
    "name:spa_x_preferred":[
        "Jacaltenango"
    ],
    "name:swe_x_preferred":[
        "Jacaltenango"
    ],
    "name:urd_x_preferred":[
        "\u062c\u06a9\u0644\u0679\u0646\u0627\u0646\u06af\u0648"
    ],
    "name:zho_x_preferred":[
        "\u54c8\u5361\u723e\u7279\u5357\u6208"
    ],
    "qs:gn_country":"GT",
    "qs:gn_fcode":"PPL",
    "qs:gn_pop":34084,
    "qs:name":"Jacaltenango",
    "qs:name_adm0":"Guatemala",
    "qs:name_adm1":"Huehuetenango",
    "qs:photos":0,
    "qs:photos_1k":0,
    "qs:photos_9k":1,
    "qs:photos_9r":3,
    "qs:photos_all":84,
    "qs:photos_sr":0,
    "qs:placetype":"Town",
    "qs:pop_sr":"7",
    "qs:woe_adm0":23424834,
    "wof:name":"Jacaltenango",
    "wof:placetype":"locality",
    "wof:population":34084
},
  "geometry": {"coordinates":[-91.73333,15.66667],"type":"Point"}
}