{
  "type": "Feature",
  "properties": {
    "gn:admin1_code":"08",
    "gn:asciiname":"Ixdurazna",
    "gn:country_code":"GT",
    "gn:dem":2484,
    "gn:feature_class":"P",
    "gn:feature_code":"PPL",
    "gn:name":"Ixdurazn\u00e1",
    "gn:population":0,
    "gn:timezone":"America/Guatemala",
    "iso:country":"GT",
    "name:spa_x_preferred":[
        "Ixdurazn\u00e1"
    ],
    "wof:name":"Ixdurazna",
    "wof:placetype":"locality"
},
  "geometry": {"coordinates":[-91.43965,15.70351],"type":"Point"}
}