{
  "type": "Feature",
  "properties": {
    "gn:admin1_code":"13",
    "gn:asciiname":"Chanchil",
    "gn:country_code":"GT",
    "gn:dem":2246,
    "gn:feature_class":"P",
    "gn:feature_code":"PPL",
    "gn:name":"Chanchil",
    "gn:population":0,
    "gn:timezone":"America/Guatemala",
    "iso:country":"GT",
    "wof:name":"Chanchil",
    "wof:placetype":"locality"
},
  "geometry": {"coordinates":[-91.73333,14.88333],"type":"Point"}
}