{
  "type": "Feature",
  "properties": {
    "gn:admin1_code":"02",
    "gn:asciiname":"Los Lochuyes",
    "gn:country_code":"GT",
    "gn:dem":1048,
    "gn:feature_class":"P",
    "gn:feature_code":"PPL",
    "gn:name":"Los Lochuyes",
    "gn:population":0,
    "gn:timezone":"America/Guatemala",
    "iso:country":"GT",
    "wof:name":"Los Lochuyes",
    "wof:placetype":"locality"
},
  "geometry": {"coordinates":[-90.48333,14.93333],"type":"Point"}
}