{
  "type": "Feature",
  "properties": {
    "iso:country":"GT",
    "name:ceb_x_preferred":[
        "Teculut\u00e1n"
    ],
    "name:deu_x_preferred":[
        "Teculut\u00e1n"
    ],
    "name:eng_x_preferred":[
        "Teculut\u00e1n"
    ],
    "name:eng_x_variant":[
        "pericaines"
    ],
    "name:fra_x_preferred":[
        "Teculut\u00e1n"
    ],
    "name:ita_x_preferred":[
        "Teculut\u00e1n"
    ],
    "name:nld_x_preferred":[
        "Teculut\u00e1n"
    ],
    "name:pol_x_preferred":[
        "Teculut\u00e1n"
    ],
    "name:por_x_preferred":[
        "Teculut\u00e1n"
    ],
    "name:spa_x_preferred":[
        "Teculut\u00e1n"
    ],
    "name:swe_x_preferred":[
        "Teculut\u00e1n"
    ],
    "name:zho_x_preferred":[
        "\u7279\u5eab\u76e7\u5766"
    ],
    "qs:gn_country":"GT",
    "qs:gn_fcode":"PPL",
    "qs:gn_pop":6407,
    "qs:name":"Teculut\u00e1n",
    "qs:name_adm0":"Guatemala",
    "qs:name_adm1":"Zacapa",
    "qs:photos":0,
    "qs:photos_1k":0,
    "qs:photos_9k":1,
    "qs:photos_9r":1,
    "qs:photos_all":1,
    "qs:photos_sr":0,
    "qs:placetype":"Town",
    "qs:pop_sr":"5",
    "qs:woe_adm0":23424834,
    "wd:wordcount":65,
    "wof:name":"Teculut\u00e1n",
    "wof:placetype":"locality",
    "wof:population":6407
},
  "geometry": {"coordinates":[-89.71666999999999,14.98333],"type":"Point"}
}