{
  "type": "Feature",
  "properties": {
    "gn:admin1_code":"22",
    "gn:asciiname":"Manzanotes",
    "gn:cc2":"GT",
    "gn:country_code":"GT",
    "gn:dem":206,
    "gn:feature_class":"P",
    "gn:feature_code":"PPL",
    "gn:name":"Manzanotes",
    "gn:population":0,
    "gn:timezone":"America/Guatemala",
    "iso:country":"GT",
    "name:und_x_variant":[
        "Manzapote",
        "Manzanotes"
    ],
    "wof:name":"Manzanotes",
    "wof:placetype":"locality"
},
  "geometry": {"coordinates":[-89.56667,15.05],"type":"Point"}
}