{
  "type": "Feature",
  "properties": {
    "gn:admin1_code":"08",
    "gn:asciiname":"Cruz Malpais",
    "gn:country_code":"GT",
    "gn:dem":1226,
    "gn:feature_class":"P",
    "gn:feature_code":"PPL",
    "gn:name":"Cruz Malpa\u00eds",
    "gn:population":0,
    "gn:timezone":"America/Guatemala",
    "iso:country":"GT",
    "name:spa_x_preferred":[
        "Cruz Malpa\u00eds"
    ],
    "wof:name":"Cruz Malpais",
    "wof:placetype":"locality"
},
  "geometry": {"coordinates":[-91.22184,15.85088],"type":"Point"}
}