{
  "type": "Feature",
  "properties": {
    "gn:admin1_code":"14",
    "gn:asciiname":"Chitac",
    "gn:cc2":"GT",
    "gn:country_code":"GT",
    "gn:dem":1852,
    "gn:feature_class":"P",
    "gn:feature_code":"PPL",
    "gn:name":"Chitac",
    "gn:population":0,
    "gn:timezone":"America/Guatemala",
    "iso:country":"GT",
    "name:und_x_variant":[
        "Pachitac",
        "Chitac"
    ],
    "wof:name":"Chitac",
    "wof:placetype":"locality"
},
  "geometry": {"coordinates":[-90.75,15.26667],"type":"Point"}
}