{
  "type": "Feature",
  "properties": {
    "gn:admin1_code":"13",
    "gn:asciiname":"El Castano",
    "gn:country_code":"GT",
    "gn:dem":126,
    "gn:feature_class":"P",
    "gn:feature_code":"PPL",
    "gn:name":"El Casta\u00f1o",
    "gn:population":0,
    "gn:timezone":"America/Guatemala",
    "iso:country":"GT",
    "name:spa_x_preferred":[
        "El Casta\u00f1o"
    ],
    "wof:name":"El Castano",
    "wof:placetype":"locality"
},
  "geometry": {"coordinates":[-92.01112999999999,14.70507],"type":"Point"}
}