{
  "type": "Feature",
  "properties": {
    "gn:admin1_code":"08",
    "gn:asciiname":"Tuitzloch",
    "gn:country_code":"GT",
    "gn:dem":1559,
    "gn:feature_class":"P",
    "gn:feature_code":"PPL",
    "gn:name":"Tuitzloch",
    "gn:population":0,
    "gn:timezone":"America/Guatemala",
    "iso:country":"GT",
    "name:spa_x_preferred":[
        "Tuitzloch"
    ],
    "wof:name":"Tuitzloch",
    "wof:placetype":"locality"
},
  "geometry": {"coordinates":[-91.71348,15.41737],"type":"Point"}
}