{
  "type": "Feature",
  "properties": {
    "gn:admin1_code":"11",
    "gn:asciiname":"El Chile",
    "gn:country_code":"GT",
    "gn:dem":1332,
    "gn:feature_class":"P",
    "gn:feature_code":"PPL",
    "gn:name":"El Chile",
    "gn:population":0,
    "gn:timezone":"America/Guatemala",
    "iso:country":"GT",
    "wof:name":"El Chile",
    "wof:placetype":"locality"
},
  "geometry": {"coordinates":[-90.05,14.05],"type":"Point"}
}