{
  "type": "Feature",
  "properties": {
    "gn:admin1_code":"08",
    "gn:asciiname":"Los Tarayes",
    "gn:country_code":"GT",
    "gn:dem":976,
    "gn:feature_class":"P",
    "gn:feature_code":"PPL",
    "gn:name":"Los Tarayes",
    "gn:population":0,
    "gn:timezone":"America/Guatemala",
    "iso:country":"GT",
    "name:spa_x_preferred":[
        "Los Tarayes"
    ],
    "wof:name":"Los Tarayes",
    "wof:placetype":"locality"
},
  "geometry": {"coordinates":[-91.89019999999999,15.62002],"type":"Point"}
}