{
  "type": "Feature",
  "properties": {
    "gn:admin1_code":"14",
    "gn:asciiname":"Monterrey",
    "gn:country_code":"GT",
    "gn:dem":159,
    "gn:feature_class":"P",
    "gn:feature_code":"PPL",
    "gn:name":"Monterrey",
    "gn:population":0,
    "gn:timezone":"America/Guatemala",
    "iso:country":"GT",
    "name:spa_x_preferred":[
        "Monterrey"
    ],
    "wof:name":"Monterrey",
    "wof:placetype":"locality"
},
  "geometry": {"coordinates":[-90.56492,16.06205],"type":"Point"}
}