{
  "type": "Feature",
  "properties": {
    "iso:country":"GT",
    "name:ceb_x_preferred":[
        "Santa Ana Huista"
    ],
    "name:eng_x_preferred":[
        "Santa Ana Huista"
    ],
    "name:fra_x_preferred":[
        "Santa Ana Huista"
    ],
    "name:ita_x_preferred":[
        "Santa Ana Huista"
    ],
    "name:nan_x_preferred":[
        "Santa Ana Huista"
    ],
    "name:nld_x_preferred":[
        "Santa Ana Huista"
    ],
    "name:pol_x_preferred":[
        "Santa Ana Huista"
    ],
    "name:por_x_preferred":[
        "Santa Ana Huista"
    ],
    "name:spa_x_preferred":[
        "Santa Ana Huista"
    ],
    "name:swe_x_preferred":[
        "Santa Ana Huista"
    ],
    "name:zho_x_preferred":[
        "\u8056\u5b89\u5a1c\u7dad\u65af\u5854"
    ],
    "qs:gn_country":"GT",
    "qs:gn_fcode":"PPL",
    "qs:gn_pop":2004,
    "qs:name":"Santa Ana Huista",
    "qs:name_adm0":"Guatemala",
    "qs:name_adm1":"Huehuetenango",
    "qs:photos":0,
    "qs:photos_1k":0,
    "qs:photos_9k":0,
    "qs:photos_9r":0,
    "qs:photos_all":0,
    "qs:photos_sr":0,
    "qs:placetype":"Town",
    "qs:pop_sr":"4",
    "qs:woe_adm0":23424834,
    "wd:wordcount":34,
    "wof:name":"Santa Ana Huista",
    "wof:placetype":"locality",
    "wof:population":2004
},
  "geometry": {"coordinates":[-91.81667,15.68333],"type":"Point"}
}