{
  "type": "Feature",
  "properties": {
    "gn:admin1_code":"12",
    "gn:asciiname":"Parcelamiento Agrario El Abano",
    "gn:country_code":"GT",
    "gn:dem":137,
    "gn:feature_class":"P",
    "gn:feature_code":"PPLF",
    "gn:name":"Parcelamiento Agrario El Abano",
    "gn:population":0,
    "gn:timezone":"America/Guatemala",
    "iso:country":"GT",
    "name:spa_x_preferred":[
        "Parcelamiento Agrario El Abano"
    ],
    "wof:name":"Parcelamiento Agrario El Abano",
    "wof:placetype":"locality"
},
  "geometry": {"coordinates":[-90.10557,17.10519],"type":"Point"}
}