{
  "type": "Feature",
  "properties": {
    "gn:admin1_code":"11",
    "gn:asciiname":"Las Victorias",
    "gn:cc2":"GT",
    "gn:country_code":"GT",
    "gn:dem":1282,
    "gn:feature_class":"P",
    "gn:feature_code":"PPL",
    "gn:name":"Las Victorias",
    "gn:population":0,
    "gn:timezone":"America/Guatemala",
    "iso:country":"GT",
    "name:fra_x_preferred":[
        "Las Victorias"
    ],
    "name:spa_x_preferred":[
        "Parque nacional Las Victorias"
    ],
    "name:und_x_variant":[
        "El Zapote",
        "Las Victorias"
    ],
    "wof:name":"Las Victorias",
    "wof:placetype":"locality"
},
  "geometry": {"coordinates":[-89.95,14.35],"type":"Point"}
}