{
  "type": "Feature",
  "properties": {
    "gn:admin1_code":"14",
    "gn:asciiname":"Juliboj",
    "gn:cc2":"GT",
    "gn:country_code":"GT",
    "gn:dem":2289,
    "gn:feature_class":"P",
    "gn:feature_code":"PPL",
    "gn:name":"Juliboj",
    "gn:population":0,
    "gn:timezone":"America/Guatemala",
    "iso:country":"GT",
    "name:und_x_variant":[
        "Juliboy",
        "Juliboj"
    ],
    "wof:name":"Juliboj",
    "wof:placetype":"locality"
},
  "geometry": {"coordinates":[-91.05,14.86667],"type":"Point"}
}