{
  "type": "Feature",
  "properties": {
    "gn:admin1_code":"17",
    "gn:asciiname":"Valle Verde",
    "gn:country_code":"GT",
    "gn:dem":2448,
    "gn:feature_class":"P",
    "gn:feature_code":"PPL",
    "gn:name":"Valle Verde",
    "gn:population":0,
    "gn:timezone":"America/Guatemala",
    "iso:country":"GT",
    "name:spa_x_preferred":[
        "Valle Verde"
    ],
    "wof:name":"Valle Verde",
    "wof:placetype":"locality"
},
  "geometry": {"coordinates":[-91.81801,15.10323],"type":"Point"}
}