{
  "type": "Feature",
  "properties": {
    "gn:admin1_code":"08",
    "gn:asciiname":"Morales",
    "gn:country_code":"GT",
    "gn:dem":1814,
    "gn:feature_class":"P",
    "gn:feature_code":"PPL",
    "gn:name":"Morales",
    "gn:population":0,
    "gn:timezone":"America/Guatemala",
    "iso:country":"GT",
    "name:spa_x_preferred":[
        "Morales"
    ],
    "wof:name":"Morales",
    "wof:placetype":"locality"
},
  "geometry": {"coordinates":[-91.73945999999999,15.44575],"type":"Point"}
}