{
  "type": "Feature",
  "properties": {
    "gn:admin1_code":"08",
    "gn:asciiname":"Morales",
    "gn:country_code":"GT",
    "gn:dem":1814,
    "gn:feature_class":"P",
    "gn:feature_code":"PPL",
    "gn:name":"Morales",
    "gn:population":0,
    "gn:timezone":"America/Guatemala",
    "iso:country":"GT",
    "name:ces_x_preferred":[
        "Morales"
    ],
    "name:deu_x_preferred":[
        "Morales"
    ],
    "name:lav_x_preferred":[
        "Moraless"
    ],
    "name:spa_x_preferred":[
        "Morales"
    ],
    "name:srp_x_preferred":[
        "\u041c\u043e\u0440\u0430\u043b\u0435\u0441"
    ],
    "wof:name":"Morales",
    "wof:placetype":"locality"
},
  "geometry": {"coordinates":[-91.73945999999999,15.44575],"type":"Point"}
}