{
  "type": "Feature",
  "properties": {
    "gn:admin1_code":"19",
    "gn:asciiname":"Corral",
    "gn:country_code":"GT",
    "gn:dem":2811,
    "gn:feature_class":"P",
    "gn:feature_code":"PPL",
    "gn:name":"Corral",
    "gn:population":0,
    "gn:timezone":"America/Guatemala",
    "iso:country":"GT",
    "wof:name":"Corral",
    "wof:placetype":"locality"
},
  "geometry": {"coordinates":[-91.41667,14.75],"type":"Point"}
}