{
  "type": "Feature",
  "properties": {
    "gn:admin1_code":"08",
    "gn:asciiname":"Cochico",
    "gn:country_code":"GT",
    "gn:dem":2727,
    "gn:feature_class":"P",
    "gn:feature_code":"PPL",
    "gn:name":"Cochic\u00f3",
    "gn:population":0,
    "gn:timezone":"America/Guatemala",
    "iso:country":"GT",
    "name:spa_x_preferred":[
        "Cochic\u00f3"
    ],
    "wof:name":"Cochico",
    "wof:placetype":"locality"
},
  "geometry": {"coordinates":[-91.50993,15.41402],"type":"Point"}
}