{
  "type": "Feature",
  "properties": {
    "gn:admin1_code":"17",
    "gn:asciiname":"Ixcamche",
    "gn:country_code":"GT",
    "gn:dem":2393,
    "gn:feature_class":"P",
    "gn:feature_code":"PPL",
    "gn:name":"Ixcamche",
    "gn:population":0,
    "gn:timezone":"America/Guatemala",
    "iso:country":"GT",
    "name:spa_x_preferred":[
        "Ixcamche"
    ],
    "name:und_x_variant":[
        "Ixcamiche"
    ],
    "wof:name":"Ixcamche",
    "wof:placetype":"locality"
},
  "geometry": {"coordinates":[-91.81394,15.31406],"type":"Point"}
}