{
  "type": "Feature",
  "properties": {
    "gn:admin1_code":"08",
    "gn:asciiname":"Amelco",
    "gn:country_code":"GT",
    "gn:dem":1691,
    "gn:feature_class":"P",
    "gn:feature_code":"PPL",
    "gn:name":"Amelco",
    "gn:population":0,
    "gn:timezone":"America/Guatemala",
    "iso:country":"GT",
    "wof:name":"Amelco",
    "wof:placetype":"locality"
},
  "geometry": {"coordinates":[-91.31667,15.76667],"type":"Point"}
}