{
  "type": "Feature",
  "properties": {
    "gn:admin1_code":"04",
    "gn:asciiname":"Las Cruces",
    "gn:country_code":"GT",
    "gn:dem":1480,
    "gn:feature_class":"P",
    "gn:feature_code":"PPL",
    "gn:name":"Las Cruces",
    "gn:population":0,
    "gn:timezone":"America/Guatemala",
    "iso:country":"GT",
    "name:ast_x_preferred":[
        "Las Cruces"
    ],
    "name:bre_x_preferred":[
        "Cruces"
    ],
    "name:ceb_x_preferred":[
        "Las Cruces"
    ],
    "name:fra_x_preferred":[
        "Las Cruces"
    ],
    "name:ita_x_preferred":[
        "Las Cruces"
    ],
    "name:sco_x_preferred":[
        "Las Cruces"
    ],
    "name:spa_x_preferred":[
        "Cruces"
    ],
    "name:swe_x_preferred":[
        "Las Cruces"
    ],
    "wof:name":"Las Cruces",
    "wof:placetype":"locality"
},
  "geometry": {"coordinates":[-89.68333,14.78333],"type":"Point"}
}