{
  "type": "Feature",
  "properties": {
    "gn:admin1_code":"01",
    "gn:asciiname":"Sesoch",
    "gn:country_code":"GT",
    "gn:dem":1250,
    "gn:feature_class":"P",
    "gn:feature_code":"PPL",
    "gn:name":"Sesoch",
    "gn:population":0,
    "gn:timezone":"America/Guatemala",
    "iso:country":"GT",
    "wof:name":"Sesoch",
    "wof:placetype":"locality"
},
  "geometry": {"coordinates":[-89.84999999999999,15.41667],"type":"Point"}
}