{
  "type": "Feature",
  "properties": {
    "gn:admin1_code":"14",
    "gn:asciiname":"Xetzajel",
    "gn:country_code":"GT",
    "gn:dem":1277,
    "gn:feature_class":"P",
    "gn:feature_code":"PPL",
    "gn:name":"Xetzajel",
    "gn:population":0,
    "gn:timezone":"America/Guatemala",
    "iso:country":"GT",
    "name:spa_x_preferred":[
        "Xetzajel"
    ],
    "wof:name":"Xetzajel",
    "wof:placetype":"locality"
},
  "geometry": {"coordinates":[-91.16361000000001,15.29615],"type":"Point"}
}