{
  "type": "Feature",
  "properties": {
    "gn:admin1_code":"17",
    "gn:asciiname":"Quipambe",
    "gn:country_code":"GT",
    "gn:dem":2683,
    "gn:feature_class":"P",
    "gn:feature_code":"PPL",
    "gn:name":"Quipamb\u00e9",
    "gn:population":0,
    "gn:timezone":"America/Guatemala",
    "iso:country":"GT",
    "name:spa_x_preferred":[
        "Quipamb\u00e9"
    ],
    "wof:name":"Quipambe",
    "wof:placetype":"locality"
},
  "geometry": {"coordinates":[-91.83158,15.12868],"type":"Point"}
}