{
  "type": "Feature",
  "properties": {
    "gn:admin1_code":"10",
    "gn:asciiname":"San Francisco Poza Verde",
    "gn:country_code":"GT",
    "gn:dem":1725,
    "gn:feature_class":"P",
    "gn:feature_code":"PPL",
    "gn:name":"San Francisco Poza Verde",
    "gn:population":0,
    "gn:timezone":"America/Guatemala",
    "iso:country":"GT",
    "wof:name":"San Francisco Poza Verde",
    "wof:placetype":"locality"
},
  "geometry": {"coordinates":[-90.13333,14.61667],"type":"Point"}
}