{
  "type": "Feature",
  "properties": {
    "gn:admin1_code":"11",
    "gn:asciiname":"Las Cuarentiuna",
    "gn:country_code":"GT",
    "gn:dem":10,
    "gn:feature_class":"P",
    "gn:feature_code":"PPL",
    "gn:name":"Las Cuarentiuna",
    "gn:population":0,
    "gn:timezone":"America/Guatemala",
    "iso:country":"GT",
    "wof:name":"Las Cuarentiuna",
    "wof:placetype":"locality"
},
  "geometry": {"coordinates":[-90.15555999999999,13.81306],"type":"Point"}
}