{
  "type": "Feature",
  "properties": {
    "gn:admin1_code":"08",
    "gn:asciiname":"Txanjkum",
    "gn:country_code":"GT",
    "gn:dem":2390,
    "gn:feature_class":"P",
    "gn:feature_code":"PPL",
    "gn:name":"Txanjkum",
    "gn:population":0,
    "gn:timezone":"America/Guatemala",
    "iso:country":"GT",
    "name:spa_x_preferred":[
        "Txanjkum"
    ],
    "wof:name":"Txanjkum",
    "wof:placetype":"locality"
},
  "geometry": {"coordinates":[-91.45565999999999,15.75282],"type":"Point"}
}