{
  "type": "Feature",
  "properties": {
    "gn:admin1_code":"04",
    "gn:asciiname":"Loma Alta",
    "gn:country_code":"GT",
    "gn:dem":966,
    "gn:feature_class":"P",
    "gn:feature_code":"PPL",
    "gn:name":"Loma Alta",
    "gn:population":0,
    "gn:timezone":"America/Guatemala",
    "iso:country":"GT",
    "wof:name":"Loma Alta",
    "wof:placetype":"locality"
},
  "geometry": {"coordinates":[-89.18333,14.61667],"type":"Point"}
}