{
  "type": "Feature",
  "properties": {
    "gn:admin1_code":"03",
    "gn:asciiname":"Pacorral",
    "gn:country_code":"GT",
    "gn:dem":2249,
    "gn:feature_class":"P",
    "gn:feature_code":"PPL",
    "gn:name":"Pacorral",
    "gn:population":0,
    "gn:timezone":"America/Guatemala",
    "iso:country":"GT",
    "wof:name":"Pacorral",
    "wof:placetype":"locality"
},
  "geometry": {"coordinates":[-90.95,14.73333],"type":"Point"}
}