{
  "type": "Feature",
  "properties": {
    "gn:admin1_code":"08",
    "gn:asciiname":"Taltzu",
    "gn:country_code":"GT",
    "gn:dem":1985,
    "gn:feature_class":"P",
    "gn:feature_code":"PPL",
    "gn:name":"Taltz\u00fa",
    "gn:population":0,
    "gn:timezone":"America/Guatemala",
    "iso:country":"GT",
    "name:spa_x_preferred":[
        "Taltz\u00fa"
    ],
    "wof:name":"Taltzu",
    "wof:placetype":"locality"
},
  "geometry": {"coordinates":[-92.06434,15.31942],"type":"Point"}
}