{
  "type": "Feature",
  "properties": {
    "gn:admin1_code":"08",
    "gn:asciiname":"Chumel",
    "gn:country_code":"GT",
    "gn:dem":1985,
    "gn:feature_class":"P",
    "gn:feature_code":"PPL",
    "gn:name":"Chumel",
    "gn:population":0,
    "gn:timezone":"America/Guatemala",
    "iso:country":"GT",
    "name:spa_x_preferred":[
        "Chumel"
    ],
    "wof:name":"Chumel",
    "wof:placetype":"locality"
},
  "geometry": {"coordinates":[-91.76585,15.36128],"type":"Point"}
}