{
  "type": "Feature",
  "properties": {
    "gn:admin1_code":"14",
    "gn:asciiname":"Carrizal",
    "gn:country_code":"GT",
    "gn:dem":1657,
    "gn:feature_class":"P",
    "gn:feature_code":"PPL",
    "gn:name":"Carrizal",
    "gn:population":0,
    "gn:timezone":"America/Guatemala",
    "iso:country":"GT",
    "name:spa_x_preferred":[
        "Carrizal"
    ],
    "wof:name":"Carrizal",
    "wof:placetype":"locality"
},
  "geometry": {"coordinates":[-91.03907,15.18359],"type":"Point"}
}