{
  "type": "Feature",
  "properties": {
    "gn:admin1_code":"02",
    "gn:asciiname":"El Rancho",
    "gn:country_code":"GT",
    "gn:dem":1318,
    "gn:feature_class":"P",
    "gn:feature_code":"PPL",
    "gn:name":"El Rancho",
    "gn:population":0,
    "gn:timezone":"America/Guatemala",
    "iso:country":"GT",
    "name:ceb_x_preferred":[
        "El Rancho"
    ],
    "name:deu_x_preferred":[
        "El Rancho"
    ],
    "name:ita_x_preferred":[
        "El Rancho"
    ],
    "name:spa_x_preferred":[
        "El Rancho"
    ],
    "name:srp_x_preferred":[
        "\u0415\u043b \u0420\u0430\u043d\u0447\u043e"
    ],
    "name:swe_x_preferred":[
        "El Rancho"
    ],
    "name:ukr_x_preferred":[
        "\u0415\u043b\u044c-\u0420\u0430\u043d\u0447\u043e"
    ],
    "wof:name":"El Rancho",
    "wof:placetype":"locality"
},
  "geometry": {"coordinates":[-90.59999999999999,14.93333],"type":"Point"}
}