{
  "type": "Feature",
  "properties": {
    "gn:admin1_code":"21",
    "gn:asciiname":"Xesaclac",
    "gn:country_code":"GT",
    "gn:dem":1895,
    "gn:feature_class":"P",
    "gn:feature_code":"PPL",
    "gn:name":"Xesaclac",
    "gn:population":0,
    "gn:timezone":"America/Guatemala",
    "iso:country":"GT",
    "name:spa_x_preferred":[
        "Xesaclac"
    ],
    "wof:name":"Xesaclac",
    "wof:placetype":"locality"
},
  "geometry": {"coordinates":[-91.33302,15.09291],"type":"Point"}
}