{
  "type": "Feature",
  "properties": {
    "gn:admin1_code":"14",
    "gn:asciiname":"Chiut",
    "gn:country_code":"GT",
    "gn:dem":2295,
    "gn:feature_class":"P",
    "gn:feature_code":"PPL",
    "gn:name":"Chiut",
    "gn:population":0,
    "gn:timezone":"America/Guatemala",
    "iso:country":"GT",
    "name:spa_x_preferred":[
        "Chiut"
    ],
    "wof:name":"Chiut",
    "wof:placetype":"locality"
},
  "geometry": {"coordinates":[-91.0339,15.08184],"type":"Point"}
}