{
  "type": "Feature",
  "properties": {
    "gn:admin1_code":"14",
    "gn:asciiname":"Los Cipreses",
    "gn:country_code":"GT",
    "gn:dem":2023,
    "gn:feature_class":"P",
    "gn:feature_code":"PPLL",
    "gn:name":"Los Cipreses",
    "gn:population":0,
    "gn:timezone":"America/Guatemala",
    "iso:country":"GT",
    "name:ceb_x_preferred":[
        "Los Cipreses"
    ],
    "name:sco_x_preferred":[
        "Los Cipreses"
    ],
    "name:spa_x_preferred":[
        "Los Cipreses"
    ],
    "wof:name":"Los Cipreses",
    "wof:placetype":"locality"
},
  "geometry": {"coordinates":[-91.20036,15.16839],"type":"Point"}
}