{
  "type": "Feature",
  "properties": {
    "gn:admin1_code":"08",
    "gn:asciiname":"Amelco",
    "gn:country_code":"GT",
    "gn:dem":508,
    "gn:feature_class":"P",
    "gn:feature_code":"PPL",
    "gn:name":"Amelco",
    "gn:population":0,
    "gn:timezone":"America/Guatemala",
    "iso:country":"GT",
    "name:spa_x_preferred":[
        "Amelco"
    ],
    "wof:name":"Amelco",
    "wof:placetype":"locality"
},
  "geometry": {"coordinates":[-91.24529,15.75313],"type":"Point"}
}