{
  "type": "Feature",
  "properties": {
    "gn:admin1_code":"08",
    "gn:asciiname":"Platanar",
    "gn:country_code":"GT",
    "gn:dem":1663,
    "gn:feature_class":"P",
    "gn:feature_code":"PPL",
    "gn:name":"Platanar",
    "gn:population":0,
    "gn:timezone":"America/Guatemala",
    "iso:country":"GT",
    "name:spa_x_preferred":[
        "Platanar"
    ],
    "wof:name":"Platanar",
    "wof:placetype":"locality"
},
  "geometry": {"coordinates":[-91.78552999999999,15.41182],"type":"Point"}
}