{
  "type": "Feature",
  "properties": {
    "gn:admin1_code":"08",
    "gn:asciiname":"Platanar",
    "gn:country_code":"GT",
    "gn:dem":1663,
    "gn:feature_class":"P",
    "gn:feature_code":"PPL",
    "gn:name":"Platanar",
    "gn:population":0,
    "gn:timezone":"America/Guatemala",
    "iso:country":"GT",
    "name:fra_x_preferred":[
        "Platanar"
    ],
    "name:nor_x_preferred":[
        "Platanar"
    ],
    "name:pol_x_preferred":[
        "Platanar"
    ],
    "name:slk_x_preferred":[
        "Platanar"
    ],
    "name:spa_x_preferred":[
        "Platanar"
    ],
    "name:spa_x_variant":[
        "Volc\u00e1n Platanar"
    ],
    "name:zho_x_preferred":[
        "\u666e\u62c9\u5854\u7d0d\u723e\u706b\u5c71"
    ],
    "wof:name":"Platanar",
    "wof:placetype":"locality"
},
  "geometry": {"coordinates":[-91.78552999999999,15.41182],"type":"Point"}
}