{
  "type": "Feature",
  "properties": {
    "gn:admin1_code":"13",
    "gn:asciiname":"Los Leones",
    "gn:country_code":"GT",
    "gn:dem":2006,
    "gn:feature_class":"P",
    "gn:feature_code":"PPL",
    "gn:name":"Los Leones",
    "gn:population":0,
    "gn:timezone":"America/Guatemala",
    "iso:country":"GT",
    "name:spa_x_preferred":[
        "Los Leones"
    ],
    "wof:name":"Los Leones",
    "wof:placetype":"locality"
},
  "geometry": {"coordinates":[-91.53316,15.18042],"type":"Point"}
}