{
  "type": "Feature",
  "properties": {
    "gn:admin1_code":"17",
    "gn:asciiname":"Poza Honda",
    "gn:country_code":"GT",
    "gn:dem":11,
    "gn:feature_class":"P",
    "gn:feature_code":"PPL",
    "gn:name":"Poza Honda",
    "gn:population":0,
    "gn:timezone":"America/Guatemala",
    "iso:country":"GT",
    "name:spa_x_preferred":[
        "Poza Honda"
    ],
    "wof:name":"Poza Honda",
    "wof:placetype":"locality"
},
  "geometry": {"coordinates":[-92.12043,14.53132],"type":"Point"}
}