{
  "type": "Feature",
  "properties": {
    "gn:admin1_code":"08",
    "gn:asciiname":"Cumbre La Avanzada",
    "gn:country_code":"GT",
    "gn:dem":2608,
    "gn:feature_class":"P",
    "gn:feature_code":"PPL",
    "gn:name":"Cumbre La Avanzada",
    "gn:population":0,
    "gn:timezone":"America/Guatemala",
    "iso:country":"GT",
    "name:spa_x_preferred":[
        "Cumbre La Avanzada"
    ],
    "wof:name":"Cumbre La Avanzada",
    "wof:placetype":"locality"
},
  "geometry": {"coordinates":[-92.04951,15.27746],"type":"Point"}
}