{
  "type": "Feature",
  "properties": {
    "gn:admin1_code":"11",
    "gn:asciiname":"Tierra Colorada",
    "gn:country_code":"GT",
    "gn:dem":753,
    "gn:feature_class":"P",
    "gn:feature_code":"PPL",
    "gn:name":"Tierra Colorada",
    "gn:population":0,
    "gn:timezone":"America/Guatemala",
    "iso:country":"GT",
    "wof:name":"Tierra Colorada",
    "wof:placetype":"locality"
},
  "geometry": {"coordinates":[-89.71666999999999,14.45],"type":"Point"}
}