{
  "type": "Feature",
  "properties": {
    "gn:admin1_code":"11",
    "gn:asciiname":"Tierra Colorada",
    "gn:country_code":"GT",
    "gn:dem":753,
    "gn:feature_class":"P",
    "gn:feature_code":"PPL",
    "gn:name":"Tierra Colorada",
    "gn:population":0,
    "gn:timezone":"America/Guatemala",
    "iso:country":"GT",
    "name:deu_x_preferred":[
        "Tierra Colorada"
    ],
    "name:ita_x_preferred":[
        "Tierra Colorada"
    ],
    "name:rus_x_preferred":[
        "\u0422\u044c\u0435\u0440\u0440\u0430-\u041a\u043e\u043b\u043e\u0440\u0430\u0434\u0430"
    ],
    "name:spa_x_preferred":[
        "Tierra Colorada"
    ],
    "wof:name":"Tierra Colorada",
    "wof:placetype":"locality"
},
  "geometry": {"coordinates":[-89.71666999999999,14.45],"type":"Point"}
}