{
  "type": "Feature",
  "properties": {
    "gn:admin1_code":"14",
    "gn:asciiname":"Los Angeles",
    "gn:country_code":"GT",
    "gn:dem":194,
    "gn:feature_class":"P",
    "gn:feature_code":"PPL",
    "gn:name":"Los \u00c1ngeles",
    "gn:population":0,
    "gn:timezone":"America/Guatemala",
    "iso:country":"GT",
    "name:spa_x_preferred":[
        "Los \u00c1ngeles"
    ],
    "wof:name":"Los Angeles",
    "wof:placetype":"locality"
},
  "geometry": {"coordinates":[-91.06506,16.04722000000001],"type":"Point"}
}