{
  "type": "Feature",
  "properties": {
    "gn:admin1_code":"05",
    "gn:asciiname":"El Portezuelo",
    "gn:cc2":"GT",
    "gn:country_code":"GT",
    "gn:dem":993,
    "gn:feature_class":"P",
    "gn:feature_code":"PPL",
    "gn:name":"El Portezuelo",
    "gn:population":0,
    "gn:timezone":"America/Guatemala",
    "iso:country":"GT",
    "name:und_x_variant":[
        "Pontezuelas",
        "Portezuelo",
        "El Portezuelo"
    ],
    "wof:name":"El Portezuelo",
    "wof:placetype":"locality"
},
  "geometry": {"coordinates":[-90.21666999999999,14.91667],"type":"Point"}
}