{
  "type": "Feature",
  "properties": {
    "gn:admin1_code":"08",
    "gn:asciiname":"Xobila",
    "gn:country_code":"GT",
    "gn:dem":2469,
    "gn:feature_class":"P",
    "gn:feature_code":"PPL",
    "gn:name":"Xobil\u00e1",
    "gn:population":0,
    "gn:timezone":"America/Guatemala",
    "iso:country":"GT",
    "name:spa_x_preferred":[
        "Xobil\u00e1"
    ],
    "wof:name":"Xobila",
    "wof:placetype":"locality"
},
  "geometry": {"coordinates":[-91.43297,15.60719],"type":"Point"}
}