{
  "type": "Feature",
  "properties": {
    "gn:admin1_code":"08",
    "gn:asciiname":"Nueva Independencia",
    "gn:country_code":"GT",
    "gn:dem":2198,
    "gn:feature_class":"P",
    "gn:feature_code":"PPL",
    "gn:name":"Nueva Independencia",
    "gn:population":0,
    "gn:timezone":"America/Guatemala",
    "iso:country":"GT",
    "name:spa_x_preferred":[
        "Nueva Independencia"
    ],
    "wof:name":"Nueva Independencia",
    "wof:placetype":"locality"
},
  "geometry": {"coordinates":[-91.94484,15.3512],"type":"Point"}
}