{
  "type": "Feature",
  "properties": {
    "iso:country":"GT",
    "name:ceb_x_preferred":[
        "Pueblo Nuevo"
    ],
    "name:eng_x_preferred":[
        "Pueblo Nuevo"
    ],
    "name:ita_x_preferred":[
        "Pueblo Nuevo"
    ],
    "name:nld_x_preferred":[
        "Pueblo Nuevo"
    ],
    "name:pol_x_preferred":[
        "Pueblo Nuevo"
    ],
    "name:por_x_preferred":[
        "Pueblo Nuevo"
    ],
    "name:spa_x_preferred":[
        "Pueblo Nuevo"
    ],
    "name:swe_x_preferred":[
        "Pueblo Nuevo"
    ],
    "name:zho_x_preferred":[
        "\u65b0\u57ce"
    ],
    "qs:gn_country":"GT",
    "qs:gn_fcode":"PPL",
    "qs:gn_pop":3116,
    "qs:name":"Pueblo Nuevo",
    "qs:name_adm0":"Guatemala",
    "qs:name_adm1":"Suchitepequez",
    "qs:photos":0,
    "qs:photos_1k":0,
    "qs:photos_9k":1,
    "qs:photos_9r":1,
    "qs:photos_all":4,
    "qs:photos_sr":0,
    "qs:placetype":"Town",
    "qs:pop_sr":"4",
    "qs:woe_adm0":23424834,
    "wd:wordcount":30,
    "wof:name":"Pueblo Nuevo",
    "wof:placetype":"locality",
    "wof:population":3116
},
  "geometry": {"coordinates":[-91.53333000000001,14.65],"type":"Point"}
}