{
  "type": "Feature",
  "properties": {
    "gn:admin1_code":"05",
    "gn:asciiname":"Jute de la Cobana",
    "gn:country_code":"GT",
    "gn:dem":894,
    "gn:feature_class":"P",
    "gn:feature_code":"PPL",
    "gn:name":"Jute de la Cobana",
    "gn:population":0,
    "gn:timezone":"America/Guatemala",
    "iso:country":"GT",
    "wof:name":"Jute de la Cobana",
    "wof:placetype":"locality"
},
  "geometry": {"coordinates":[-90.06667,14.98333],"type":"Point"}
}