{
  "type": "Feature",
  "properties": {
    "gn:admin1_code":"12",
    "gn:asciiname":"Arroyo del Guarda",
    "gn:country_code":"GT",
    "gn:dem":109,
    "gn:feature_class":"P",
    "gn:feature_code":"PPL",
    "gn:name":"Arroyo del Guarda",
    "gn:population":0,
    "gn:timezone":"America/Guatemala",
    "iso:country":"GT",
    "name:spa_x_preferred":[
        "Arroyo del Guarda"
    ],
    "wof:name":"Arroyo del Guarda",
    "wof:placetype":"locality"
},
  "geometry": {"coordinates":[-89.15148000000001,17.11823],"type":"Point"}
}