{
  "type": "Feature",
  "properties": {
    "gn:admin1_code":"05",
    "gn:asciiname":"Las Morales",
    "gn:country_code":"GT",
    "gn:dem":593,
    "gn:feature_class":"P",
    "gn:feature_code":"PPL",
    "gn:name":"Las Morales",
    "gn:population":0,
    "gn:timezone":"America/Guatemala",
    "iso:country":"GT",
    "wof:name":"Las Morales",
    "wof:placetype":"locality"
},
  "geometry": {"coordinates":[-90.11667,14.85],"type":"Point"}
}