{
  "type": "Feature",
  "properties": {
    "gn:admin1_code":"08",
    "gn:asciiname":"Quecchoch",
    "gn:country_code":"GT",
    "gn:dem":1973,
    "gn:feature_class":"P",
    "gn:feature_code":"PPL",
    "gn:name":"Quecchoch",
    "gn:population":0,
    "gn:timezone":"America/Guatemala",
    "iso:country":"GT",
    "wof:name":"Quecchoch",
    "wof:placetype":"locality"
},
  "geometry": {"coordinates":[-91.36556,15.80222],"type":"Point"}
}