{
  "type": "Feature",
  "properties": {
    "gn:admin1_code":"08",
    "gn:asciiname":"Yulguayul",
    "gn:country_code":"GT",
    "gn:dem":2293,
    "gn:feature_class":"P",
    "gn:feature_code":"PPL",
    "gn:name":"Yulguayul",
    "gn:population":0,
    "gn:timezone":"America/Guatemala",
    "iso:country":"GT",
    "name:spa_x_preferred":[
        "Yulguayul"
    ],
    "wof:name":"Yulguayul",
    "wof:placetype":"locality"
},
  "geometry": {"coordinates":[-91.43465999999999,15.648],"type":"Point"}
}