{
  "type": "Feature",
  "properties": {
    "gn:admin1_code":"17",
    "gn:asciiname":"Santillana",
    "gn:country_code":"GT",
    "gn:dem":336,
    "gn:feature_class":"P",
    "gn:feature_code":"PPL",
    "gn:name":"Santillana",
    "gn:population":0,
    "gn:timezone":"America/Guatemala",
    "iso:country":"GT",
    "name:spa_x_preferred":[
        "Santillana"
    ],
    "wof:name":"Santillana",
    "wof:placetype":"locality"
},
  "geometry": {"coordinates":[-92.02007999999999,14.79708],"type":"Point"}
}