{
  "type": "Feature",
  "properties": {
    "gn:admin1_code":"14",
    "gn:asciiname":"San Pedro Los Amates",
    "gn:country_code":"GT",
    "gn:dem":238,
    "gn:feature_class":"P",
    "gn:feature_code":"PPL",
    "gn:name":"San Pedro Los Amates",
    "gn:population":0,
    "gn:timezone":"America/Guatemala",
    "iso:country":"GT",
    "name:spa_x_preferred":[
        "San Pedro Los Amates"
    ],
    "wof:name":"San Pedro Los Amates",
    "wof:placetype":"locality"
},
  "geometry": {"coordinates":[-91.0244,15.83448],"type":"Point"}
}