{
  "type": "Feature",
  "properties": {
    "gn:admin1_code":"08",
    "gn:asciiname":"El Aguacate II",
    "gn:country_code":"GT",
    "gn:dem":2378,
    "gn:feature_class":"P",
    "gn:feature_code":"PPL",
    "gn:name":"El Aguacate II",
    "gn:population":0,
    "gn:timezone":"America/Guatemala",
    "iso:country":"GT",
    "name:spa_x_preferred":[
        "El Aguacate II"
    ],
    "wof:name":"El Aguacate II",
    "wof:placetype":"locality"
},
  "geometry": {"coordinates":[-91.92538999999999,15.53014],"type":"Point"}
}