{
  "type": "Feature",
  "properties": {
    "gn:admin1_code":"08",
    "gn:asciiname":"Casaca",
    "gn:country_code":"GT",
    "gn:dem":1733,
    "gn:feature_class":"P",
    "gn:feature_code":"PPL",
    "gn:name":"Casaca",
    "gn:population":0,
    "gn:timezone":"America/Guatemala",
    "iso:country":"GT",
    "name:spa_x_preferred":[
        "Casaca"
    ],
    "wof:name":"Casaca",
    "wof:placetype":"locality"
},
  "geometry": {"coordinates":[-91.79246000000001,15.41836],"type":"Point"}
}