{
  "type": "Feature",
  "properties": {
    "gn:admin1_code":"17",
    "gn:asciiname":"El Carmen Puntarenas",
    "gn:country_code":"GT",
    "gn:dem":128,
    "gn:feature_class":"P",
    "gn:feature_code":"PPL",
    "gn:name":"El Carmen Puntarenas",
    "gn:population":0,
    "gn:timezone":"America/Guatemala",
    "iso:country":"GT",
    "name:spa_x_preferred":[
        "El Carmen Puntarenas"
    ],
    "wof:name":"El Carmen Puntarenas",
    "wof:placetype":"locality"
},
  "geometry": {"coordinates":[-92.04943,14.74145],"type":"Point"}
}