{
  "type": "Feature",
  "properties": {
    "gn:admin1_code":"21",
    "gn:asciiname":"Chuicruz",
    "gn:country_code":"GT",
    "gn:dem":2416,
    "gn:feature_class":"P",
    "gn:feature_code":"PPL",
    "gn:name":"Chuicruz",
    "gn:population":0,
    "gn:timezone":"America/Guatemala",
    "iso:country":"GT",
    "wof:name":"Chuicruz",
    "wof:placetype":"locality"
},
  "geometry": {"coordinates":[-91.38333,14.91667],"type":"Point"}
}