{
  "type": "Feature",
  "properties": {
    "gn:admin1_code":"08",
    "gn:asciiname":"Villa Nueva",
    "gn:country_code":"GT",
    "gn:dem":1314,
    "gn:feature_class":"P",
    "gn:feature_code":"PPL",
    "gn:name":"Villa Nueva",
    "gn:population":0,
    "gn:timezone":"America/Guatemala",
    "iso:country":"GT",
    "name:ceb_x_preferred":[
        "Villa Nueva"
    ],
    "name:deu_x_preferred":[
        "Villa Nueva"
    ],
    "name:fra_x_preferred":[
        "Villa Nueva"
    ],
    "name:ita_x_preferred":[
        "Villa Nueva"
    ],
    "name:nld_x_preferred":[
        "Villa Nueva"
    ],
    "name:pol_x_preferred":[
        "Villa Nueva"
    ],
    "name:por_x_preferred":[
        "Villa Nueva"
    ],
    "name:sco_x_preferred":[
        "Villa Nueva"
    ],
    "name:spa_x_preferred":[
        "Villa Nueva"
    ],
    "name:swe_x_preferred":[
        "Villa Nueva"
    ],
    "wof:name":"Villa Nueva",
    "wof:placetype":"locality"
},
  "geometry": {"coordinates":[-91.78945,15.58698],"type":"Point"}
}