{
  "type": "Feature",
  "properties": {
    "gn:admin1_code":"08",
    "gn:asciiname":"Bajual",
    "gn:country_code":"GT",
    "gn:dem":2134,
    "gn:feature_class":"P",
    "gn:feature_code":"PPL",
    "gn:name":"Bajual",
    "gn:population":0,
    "gn:timezone":"America/Guatemala",
    "iso:country":"GT",
    "name:spa_x_preferred":[
        "Bajual"
    ],
    "wof:name":"Bajual",
    "wof:placetype":"locality"
},
  "geometry": {"coordinates":[-91.38639000000001,15.64496],"type":"Point"}
}