{
  "type": "Feature",
  "properties": {
    "gn:admin1_code":"14",
    "gn:asciiname":"Palo Grande",
    "gn:country_code":"GT",
    "gn:dem":987,
    "gn:feature_class":"P",
    "gn:feature_code":"PPL",
    "gn:name":"Palo Grande",
    "gn:population":0,
    "gn:timezone":"America/Guatemala",
    "iso:country":"GT",
    "name:spa_x_preferred":[
        "Palo Grande"
    ],
    "wof:name":"Palo Grande",
    "wof:placetype":"locality"
},
  "geometry": {"coordinates":[-91.19204999999999,15.66804],"type":"Point"}
}