{
  "type": "Feature",
  "properties": {
    "gn:admin1_code":"12",
    "gn:asciiname":"El Corozal",
    "gn:country_code":"GT",
    "gn:dem":228,
    "gn:feature_class":"P",
    "gn:feature_code":"PPL",
    "gn:name":"El Corozal",
    "gn:population":0,
    "gn:timezone":"America/Guatemala",
    "iso:country":"GT",
    "name:spa_x_preferred":[
        "El Corozal"
    ],
    "wof:name":"El Corozal",
    "wof:placetype":"locality"
},
  "geometry": {"coordinates":[-89.88784,17.12837],"type":"Point"}
}