{
  "type": "Feature",
  "properties": {
    "gn:admin1_code":"21",
    "gn:asciiname":"Pachaguacan",
    "gn:country_code":"GT",
    "gn:dem":2120,
    "gn:feature_class":"P",
    "gn:feature_code":"PPLL",
    "gn:name":"Pachaguac\u00e1n",
    "gn:population":0,
    "gn:timezone":"America/Guatemala",
    "iso:country":"GT",
    "name:spa_x_preferred":[
        "Pachaguac\u00e1n"
    ],
    "wof:name":"Pachaguacan",
    "wof:placetype":"locality"
},
  "geometry": {"coordinates":[-91.3939,15.06608],"type":"Point"}
}