{
  "type": "Feature",
  "properties": {
    "gn:admin1_code":"03",
    "gn:asciiname":"Cuchuya",
    "gn:country_code":"GT",
    "gn:dem":1473,
    "gn:feature_class":"P",
    "gn:feature_code":"PPL",
    "gn:name":"Cuchuy\u00e1",
    "gn:population":0,
    "gn:timezone":"America/Guatemala",
    "iso:country":"GT",
    "wof:name":"Cuchuya",
    "wof:placetype":"locality"
},
  "geometry": {"coordinates":[-90.75,14.76667],"type":"Point"}
}