{
  "type": "Feature",
  "properties": {
    "gn:admin1_code":"08",
    "gn:asciiname":"San Carlos Chancolin",
    "gn:country_code":"GT",
    "gn:dem":681,
    "gn:feature_class":"P",
    "gn:feature_code":"PPL",
    "gn:name":"San Carlos Chancol\u00edn",
    "gn:population":0,
    "gn:timezone":"America/Guatemala",
    "iso:country":"GT",
    "name:spa_x_preferred":[
        "San Carlos Chancol\u00edn"
    ],
    "wof:name":"San Carlos Chancolin",
    "wof:placetype":"locality"
},
  "geometry": {"coordinates":[-91.24437,15.95278],"type":"Point"}
}