{
  "type": "Feature",
  "properties": {
    "gn:admin1_code":"01",
    "gn:asciiname":"Sacaal",
    "gn:country_code":"GT",
    "gn:dem":1667,
    "gn:feature_class":"P",
    "gn:feature_code":"PPL",
    "gn:name":"Sacaal",
    "gn:population":0,
    "gn:timezone":"America/Guatemala",
    "iso:country":"GT",
    "wof:name":"Sacaal",
    "wof:placetype":"locality"
},
  "geometry": {"coordinates":[-90.46666999999999,15.45],"type":"Point"}
}