{
  "type": "Feature",
  "properties": {
    "gn:admin1_code":"08",
    "gn:asciiname":"Cuca",
    "gn:country_code":"GT",
    "gn:dem":2509,
    "gn:feature_class":"P",
    "gn:feature_code":"PPL",
    "gn:name":"Cuc\u00e1",
    "gn:population":0,
    "gn:timezone":"America/Guatemala",
    "iso:country":"GT",
    "name:ceb_x_preferred":[
        "Cuca"
    ],
    "name:deu_x_preferred":[
        "Cuca"
    ],
    "name:fas_x_preferred":[
        "\u06a9\u0648\u06a9\u0627"
    ],
    "name:fra_x_preferred":[
        "Cuca"
    ],
    "name:hrv_x_preferred":[
        "Cuca"
    ],
    "name:hun_x_preferred":[
        "Cuca"
    ],
    "name:ita_x_preferred":[
        "Cuca"
    ],
    "name:mkd_x_preferred":[
        "\u041a\u0443\u043a\u0430"
    ],
    "name:nld_x_preferred":[
        "Cuca"
    ],
    "name:por_x_preferred":[
        "Cuca"
    ],
    "name:ron_x_preferred":[
        "Cuca"
    ],
    "name:spa_x_preferred":[
        "Cuc\u00e1"
    ],
    "name:spa_x_variant":[
        "Cuca"
    ],
    "name:swe_x_preferred":[
        "Cuca"
    ],
    "name:vol_x_preferred":[
        "Cuca"
    ],
    "wof:name":"Cuca",
    "wof:placetype":"locality"
},
  "geometry": {"coordinates":[-91.45053,15.67142],"type":"Point"}
}