{
  "type": "Feature",
  "properties": {
    "gn:admin1_code":"14",
    "gn:asciiname":"Colonia Los Celajes",
    "gn:country_code":"GT",
    "gn:dem":2005,
    "gn:feature_class":"P",
    "gn:feature_code":"PPLL",
    "gn:name":"Colonia Los Celajes",
    "gn:population":0,
    "gn:timezone":"America/Guatemala",
    "iso:country":"GT",
    "name:spa_x_preferred":[
        "Colonia Los Celajes"
    ],
    "wof:name":"Colonia Los Celajes",
    "wof:placetype":"locality"
},
  "geometry": {"coordinates":[-91.16193,15.01533],"type":"Point"}
}