{
  "type": "Feature",
  "properties": {
    "gn:admin1_code":"14",
    "gn:asciiname":"Vicampanavitz",
    "gn:country_code":"GT",
    "gn:dem":2438,
    "gn:feature_class":"P",
    "gn:feature_code":"PPL",
    "gn:name":"Vicampanavitz",
    "gn:population":0,
    "gn:timezone":"America/Guatemala",
    "iso:country":"GT",
    "name:spa_x_preferred":[
        "Vicampanavitz"
    ],
    "wof:name":"Vicampanavitz",
    "wof:placetype":"locality"
},
  "geometry": {"coordinates":[-91.18798,15.51966],"type":"Point"}
}