{
  "type": "Feature",
  "properties": {
    "gn:admin1_code":"17",
    "gn:asciiname":"Las Guayabas",
    "gn:country_code":"GT",
    "gn:dem":2045,
    "gn:feature_class":"P",
    "gn:feature_code":"PPL",
    "gn:name":"Las Guayabas",
    "gn:population":0,
    "gn:timezone":"America/Guatemala",
    "iso:country":"GT",
    "wof:name":"Las Guayabas",
    "wof:placetype":"locality"
},
  "geometry": {"coordinates":[-91.76667,14.93333],"type":"Point"}
}