{
  "type": "Feature",
  "properties": {
    "gn:admin1_code":"01",
    "gn:asciiname":"Secampana",
    "gn:cc2":"GT",
    "gn:country_code":"GT",
    "gn:dem":1830,
    "gn:feature_class":"P",
    "gn:feature_code":"PPL",
    "gn:name":"Secampana",
    "gn:population":0,
    "gn:timezone":"America/Guatemala",
    "iso:country":"GT",
    "name:und_x_variant":[
        "Secampam\u00e1",
        "Secampana"
    ],
    "wof:name":"Secampana",
    "wof:placetype":"locality"
},
  "geometry": {"coordinates":[-89.95,15.38333],"type":"Point"}
}