{
  "type": "Feature",
  "properties": {
    "iso:country":"GT",
    "qs:gn_country":"GT",
    "qs:gn_fcode":"PPL",
    "qs:gn_pop":0,
    "qs:name":"Ciudad Pedro de Alvarado",
    "qs:name_adm0":"Guatemala",
    "qs:name_adm1":"Jutiapa",
    "qs:photos":14,
    "qs:photos_1k":3,
    "qs:photos_9k":1,
    "qs:photos_9r":1,
    "qs:photos_all":14,
    "qs:photos_sr":1,
    "qs:placetype":"Town",
    "qs:pop_sr":"0",
    "qs:woe_adm0":23424834,
    "wof:name":"Ciudad Pedro de Alvarado",
    "wof:placetype":"locality"
},
  "geometry": {"coordinates":[-90.0925,13.87028],"type":"Point"}
}