{
  "type": "Feature",
  "properties": {
    "gn:admin1_code":"12",
    "gn:asciiname":"El Xex",
    "gn:cc2":"GT",
    "gn:country_code":"GT",
    "gn:dem":164,
    "gn:feature_class":"P",
    "gn:feature_code":"PPL",
    "gn:name":"El Xex",
    "gn:population":0,
    "gn:timezone":"America/Guatemala",
    "iso:country":"GT",
    "name:und_x_variant":[
        "El Yex",
        "El Xex"
    ],
    "wof:name":"El Xex",
    "wof:placetype":"locality"
},
  "geometry": {"coordinates":[-89.78333000000001,16.91667],"type":"Point"}
}