{
  "type": "Feature",
  "properties": {
    "gn:admin1_code":"17",
    "gn:asciiname":"Santa Rosa de Lima",
    "gn:country_code":"GT",
    "gn:dem":283,
    "gn:feature_class":"P",
    "gn:feature_code":"PPL",
    "gn:name":"Santa Rosa de Lima",
    "gn:population":0,
    "gn:timezone":"America/Guatemala",
    "iso:country":"GT",
    "name:spa_x_preferred":[
        "Santa Rosa de Lima"
    ],
    "name:srp_x_preferred":[
        "\u0421\u0430\u043d\u0442\u0430 \u0420\u043e\u0441\u0430 \u0434\u0435 \u041b\u0438\u043c\u0430"
    ],
    "wof:name":"Santa Rosa de Lima",
    "wof:placetype":"locality"
},
  "geometry": {"coordinates":[-92.10836999999999,14.94882],"type":"Point"}
}