{
  "type": "Feature",
  "properties": {
    "gn:admin1_code":"14",
    "gn:asciiname":"Pabaquit",
    "gn:country_code":"GT",
    "gn:dem":1799,
    "gn:feature_class":"P",
    "gn:feature_code":"PPL",
    "gn:name":"Pabaquit",
    "gn:population":0,
    "gn:timezone":"America/Guatemala",
    "iso:country":"GT",
    "name:spa_x_preferred":[
        "Pabaquit"
    ],
    "wof:name":"Pabaquit",
    "wof:placetype":"locality"
},
  "geometry": {"coordinates":[-91.26908,15.18509],"type":"Point"}
}