{
  "type": "Feature",
  "properties": {
    "gn:admin1_code":"08",
    "gn:asciiname":"Las Majadas",
    "gn:country_code":"GT",
    "gn:dem":2213,
    "gn:feature_class":"P",
    "gn:feature_code":"PPL",
    "gn:name":"Las Majadas",
    "gn:population":0,
    "gn:timezone":"America/Guatemala",
    "iso:country":"GT",
    "name:spa_x_preferred":[
        "Las Majadas"
    ],
    "wof:name":"Las Majadas",
    "wof:placetype":"locality"
},
  "geometry": {"coordinates":[-91.24442999999999,15.36501],"type":"Point"}
}