{
  "type": "Feature",
  "properties": {
    "gn:admin1_code":"13",
    "gn:asciiname":"Estancia de La Virgen",
    "gn:country_code":"GT",
    "gn:dem":1979,
    "gn:feature_class":"P",
    "gn:feature_code":"PPL",
    "gn:name":"Estancia de La Virgen",
    "gn:population":0,
    "gn:timezone":"America/Guatemala",
    "iso:country":"GT",
    "name:und_x_variant":[
        "Estancia La Virgen",
        "Estancia de La Virgen"
    ],
    "wof:name":"Estancia de La Virgen",
    "wof:placetype":"locality"
},
  "geometry": {"coordinates":[-91.53993,15.1821],"type":"Point"}
}