{
  "type": "Feature",
  "properties": {
    "gn:admin1_code":"04",
    "gn:asciiname":"La Palmilla",
    "gn:country_code":"GT",
    "gn:dem":1155,
    "gn:feature_class":"P",
    "gn:feature_code":"PPL",
    "gn:name":"La Palmilla",
    "gn:population":0,
    "gn:timezone":"America/Guatemala",
    "iso:country":"GT",
    "wof:name":"La Palmilla",
    "wof:placetype":"locality"
},
  "geometry": {"coordinates":[-89.36667,14.88333],"type":"Point"}
}