{
  "type": "Feature",
  "properties": {
    "gn:admin1_code":"01",
    "gn:asciiname":"Linterna Dos",
    "gn:country_code":"GT",
    "gn:dem":194,
    "gn:feature_class":"P",
    "gn:feature_code":"PPL",
    "gn:name":"Linterna Dos",
    "gn:population":0,
    "gn:timezone":"America/Guatemala",
    "iso:country":"GT",
    "name:spa_x_preferred":[
        "Linterna Dos"
    ],
    "wof:name":"Linterna Dos",
    "wof:placetype":"locality"
},
  "geometry": {"coordinates":[-90.22878,16.03888],"type":"Point"}
}