{
  "type": "Feature",
  "properties": {
    "gn:admin1_code":"17",
    "gn:asciiname":"Chicajalaj",
    "gn:country_code":"GT",
    "gn:dem":2281,
    "gn:feature_class":"P",
    "gn:feature_code":"PPL",
    "gn:name":"Chicajalaj",
    "gn:population":0,
    "gn:timezone":"America/Guatemala",
    "iso:country":"GT",
    "name:spa_x_preferred":[
        "Chicajalaj"
    ],
    "wof:name":"Chicajalaj",
    "wof:placetype":"locality"
},
  "geometry": {"coordinates":[-91.72878,15.09669],"type":"Point"}
}