{
  "type": "Feature",
  "properties": {
    "gn:admin1_code":"10",
    "gn:asciiname":"Garay",
    "gn:cc2":"GT",
    "gn:country_code":"GT",
    "gn:dem":1025,
    "gn:feature_class":"P",
    "gn:feature_code":"PPL",
    "gn:name":"Garay",
    "gn:population":0,
    "gn:timezone":"America/Guatemala",
    "iso:country":"GT",
    "name:und_x_variant":[
        "Garay Viejo",
        "Garay"
    ],
    "wof:name":"Garay",
    "wof:placetype":"locality"
},
  "geometry": {"coordinates":[-89.93333,14.51667],"type":"Point"}
}