{
  "type": "Feature",
  "properties": {
    "gn:admin1_code":"10",
    "gn:asciiname":"Garay",
    "gn:cc2":"GT",
    "gn:country_code":"GT",
    "gn:dem":1025,
    "gn:feature_class":"P",
    "gn:feature_code":"PPL",
    "gn:name":"Garay",
    "gn:population":0,
    "gn:timezone":"America/Guatemala",
    "iso:country":"GT",
    "name:bak_x_preferred":[
        "\u0413\u04d9\u0440\u04d9\u0439"
    ],
    "name:ceb_x_preferred":[
        "Garay"
    ],
    "name:deu_x_preferred":[
        "Garay"
    ],
    "name:fra_x_preferred":[
        "Garay"
    ],
    "name:hye_x_preferred":[
        "\u0533\u0561\u0580\u0561\u0575"
    ],
    "name:ita_x_preferred":[
        "Garay"
    ],
    "name:jpn_x_preferred":[
        "\u30ac\u30e9\u30a4"
    ],
    "name:kor_x_preferred":[
        "\uac00\ub77c\uc774"
    ],
    "name:nld_x_preferred":[
        "Garay"
    ],
    "name:pol_x_preferred":[
        "Garay"
    ],
    "name:por_x_preferred":[
        "Garay"
    ],
    "name:rus_x_preferred":[
        "\u0413\u0430\u0440\u0430\u0439"
    ],
    "name:sco_x_preferred":[
        "Garay"
    ],
    "name:spa_x_preferred":[
        "Garay"
    ],
    "name:swe_x_preferred":[
        "Garay"
    ],
    "name:und_x_variant":[
        "Garay Viejo"
    ],
    "wof:name":"Garay",
    "wof:placetype":"locality"
},
  "geometry": {"coordinates":[-89.93333,14.51667],"type":"Point"}
}