{
  "type": "Feature",
  "properties": {
    "gn:admin1_code":"14",
    "gn:asciiname":"Xesic Primero",
    "gn:country_code":"GT",
    "gn:dem":2141,
    "gn:feature_class":"P",
    "gn:feature_code":"PPL",
    "gn:name":"Xesic Primero",
    "gn:population":0,
    "gn:timezone":"America/Guatemala",
    "iso:country":"GT",
    "name:spa_x_preferred":[
        "Xesic Primero"
    ],
    "name:und_x_variant":[
        "Xesic"
    ],
    "wof:name":"Xesic Primero",
    "wof:placetype":"locality"
},
  "geometry": {"coordinates":[-91.13129000000001,15.05591],"type":"Point"}
}