{
  "type": "Feature",
  "properties": {
    "gn:admin1_code":"08",
    "gn:asciiname":"Yolaquecna",
    "gn:country_code":"GT",
    "gn:dem":1656,
    "gn:feature_class":"P",
    "gn:feature_code":"PPL",
    "gn:name":"Yolaquecn\u00e1",
    "gn:population":0,
    "gn:timezone":"America/Guatemala",
    "iso:country":"GT",
    "name:spa_x_preferred":[
        "Yolaquecn\u00e1"
    ],
    "wof:name":"Yolaquecna",
    "wof:placetype":"locality"
},
  "geometry": {"coordinates":[-91.6016,15.78913],"type":"Point"}
}