{
  "type": "Feature",
  "properties": {
    "gn:admin1_code":"02",
    "gn:asciiname":"Chuacusito",
    "gn:country_code":"GT",
    "gn:dem":947,
    "gn:feature_class":"P",
    "gn:feature_code":"PPL",
    "gn:name":"Chuacusito",
    "gn:population":0,
    "gn:timezone":"America/Guatemala",
    "iso:country":"GT",
    "wof:name":"Chuacusito",
    "wof:placetype":"locality"
},
  "geometry": {"coordinates":[-90.33333,14.98333],"type":"Point"}
}