{
  "type": "Feature",
  "properties": {
    "gn:admin1_code":"08",
    "gn:asciiname":"Pino Pacho",
    "gn:country_code":"GT",
    "gn:dem":1105,
    "gn:feature_class":"P",
    "gn:feature_code":"PPL",
    "gn:name":"Pino Pacho",
    "gn:population":0,
    "gn:timezone":"America/Guatemala",
    "iso:country":"GT",
    "name:spa_x_preferred":[
        "Pino Pacho"
    ],
    "wof:name":"Pino Pacho",
    "wof:placetype":"locality"
},
  "geometry": {"coordinates":[-92.07883,15.40062],"type":"Point"}
}