{
  "type": "Feature",
  "properties": {
    "gn:admin1_code":"11",
    "gn:asciiname":"El Pretil",
    "gn:country_code":"GT",
    "gn:dem":592,
    "gn:feature_class":"P",
    "gn:feature_code":"PPL",
    "gn:name":"El Pretil",
    "gn:population":0,
    "gn:timezone":"America/Guatemala",
    "iso:country":"GT",
    "wof:name":"El Pretil",
    "wof:placetype":"locality"
},
  "geometry": {"coordinates":[-89.70583000000001,14.19889],"type":"Point"}
}