{
  "type": "Feature",
  "properties": {
    "gn:admin1_code":"08",
    "gn:asciiname":"Tzisbaj",
    "gn:country_code":"GT",
    "gn:dem":920,
    "gn:feature_class":"P",
    "gn:feature_code":"PPL",
    "gn:name":"Tzisbaj",
    "gn:population":0,
    "gn:timezone":"America/Guatemala",
    "iso:country":"GT",
    "name:spa_x_preferred":[
        "Tzisbaj"
    ],
    "wof:name":"Tzisbaj",
    "wof:placetype":"locality"
},
  "geometry": {"coordinates":[-91.78149000000001,15.70206],"type":"Point"}
}