{
  "type": "Feature",
  "properties": {
    "iso:country":"GT",
    "name:eng_x_preferred":[
        "Santa Luc\u00eda Utatl\u00e1n"
    ],
    "name:fra_x_preferred":[
        "Santa Luc\u00eda Utatl\u00e1n"
    ],
    "name:ita_x_preferred":[
        "Santa Luc\u00eda Utatl\u00e1n"
    ],
    "name:nld_x_preferred":[
        "Santa Luc\u00eda Utatl\u00e1n"
    ],
    "name:pol_x_preferred":[
        "Santa Luc\u00eda Utatl\u00e1n"
    ],
    "name:por_x_preferred":[
        "Santa Luc\u00eda Utatl\u00e1n"
    ],
    "name:spa_x_preferred":[
        "Santa Luc\u00eda Utatl\u00e1n"
    ],
    "name:swe_x_preferred":[
        "Santa Luc\u00eda Utatl\u00e1n"
    ],
    "name:unk_x_variant":[
        "Santa Luc\u00eda"
    ],
    "name:zho_x_preferred":[
        "\u8056\u76e7\u897f\u4e9e\u70cf\u5854\u7279\u862d"
    ],
    "qs:gn_country":"GT",
    "qs:gn_fcode":"PPL",
    "qs:gn_pop":1305,
    "qs:name":"Santa Luc\u00eda Utatl\u00e1n",
    "qs:name_adm0":"Guatemala",
    "qs:name_adm1":"Solola",
    "qs:photos":263,
    "qs:photos_1k":53,
    "qs:photos_9k":1,
    "qs:photos_9r":4,
    "qs:photos_all":263,
    "qs:photos_sr":5,
    "qs:placetype":"Town",
    "qs:pop_sr":"3",
    "qs:woe_adm0":23424834,
    "wof:name":"Santa Luc\u00eda Utatl\u00e1n",
    "wof:placetype":"locality",
    "wof:population":1305
},
  "geometry": {"coordinates":[-91.26667,14.76667],"type":"Point"}
}