{
  "type": "Feature",
  "properties": {
    "gn:admin1_code":"22",
    "gn:asciiname":"El Filo",
    "gn:cc2":"GT",
    "gn:country_code":"GT",
    "gn:dem":731,
    "gn:feature_class":"P",
    "gn:feature_code":"PPL",
    "gn:name":"El Filo",
    "gn:population":0,
    "gn:timezone":"America/Guatemala",
    "iso:country":"GT",
    "name:und_x_variant":[
        "Tafu",
        "Filo",
        "El Filo"
    ],
    "wof:name":"El Filo",
    "wof:placetype":"locality"
},
  "geometry": {"coordinates":[-89.34999999999999,15.01667],"type":"Point"}
}