{
  "type": "Feature",
  "properties": {
    "gn:admin1_code":"08",
    "gn:asciiname":"Gema",
    "gn:country_code":"GT",
    "gn:dem":2316,
    "gn:feature_class":"P",
    "gn:feature_code":"PPL",
    "gn:name":"Gem\u00e1",
    "gn:population":0,
    "gn:timezone":"America/Guatemala",
    "iso:country":"GT",
    "name:spa_x_preferred":[
        "Gem\u00e1"
    ],
    "wof:name":"Gema",
    "wof:placetype":"locality"
},
  "geometry": {"coordinates":[-91.39852999999999,15.68093],"type":"Point"}
}