{
  "type": "Feature",
  "properties": {
    "gn:admin1_code":"17",
    "gn:asciiname":"Honduras",
    "gn:country_code":"GT",
    "gn:dem":267,
    "gn:feature_class":"P",
    "gn:feature_code":"PPL",
    "gn:name":"Honduras",
    "gn:population":0,
    "gn:timezone":"America/Guatemala",
    "iso:country":"GT",
    "name:spa_x_preferred":[
        "Honduras"
    ],
    "wof:name":"Honduras",
    "wof:placetype":"locality"
},
  "geometry": {"coordinates":[-92.06618,14.85656],"type":"Point"}
}