{
  "type": "Feature",
  "properties": {
    "gn:admin1_code":"04",
    "gn:asciiname":"Las Crucitas",
    "gn:country_code":"GT",
    "gn:dem":1211,
    "gn:feature_class":"P",
    "gn:feature_code":"PPL",
    "gn:name":"Las Crucitas",
    "gn:population":0,
    "gn:timezone":"America/Guatemala",
    "iso:country":"GT",
    "wof:name":"Las Crucitas",
    "wof:placetype":"locality"
},
  "geometry": {"coordinates":[-89.34999999999999,14.65],"type":"Point"}
}