{
  "type": "Feature",
  "properties": {
    "gn:admin1_code":"07",
    "gn:asciiname":"La Manzana",
    "gn:country_code":"GT",
    "gn:dem":1069,
    "gn:feature_class":"P",
    "gn:feature_code":"PPL",
    "gn:name":"La Manzana",
    "gn:population":0,
    "gn:timezone":"America/Guatemala",
    "iso:country":"GT",
    "wof:name":"La Manzana",
    "wof:placetype":"locality"
},
  "geometry": {"coordinates":[-90.51667,14.35],"type":"Point"}
}