{
  "type": "Feature",
  "properties": {
    "gn:admin1_code":"08",
    "gn:asciiname":"Tajguactze",
    "gn:country_code":"GT",
    "gn:dem":1973,
    "gn:feature_class":"P",
    "gn:feature_code":"PPL",
    "gn:name":"Tajguactz\u00e9",
    "gn:population":0,
    "gn:timezone":"America/Guatemala",
    "iso:country":"GT",
    "name:spa_x_preferred":[
        "Tajguactz\u00e9"
    ],
    "wof:name":"Tajguactze",
    "wof:placetype":"locality"
},
  "geometry": {"coordinates":[-91.85629,15.35209],"type":"Point"}
}