{
  "type": "Feature",
  "properties": {
    "gn:admin1_code":"08",
    "gn:asciiname":"Lotes",
    "gn:country_code":"GT",
    "gn:dem":971,
    "gn:feature_class":"P",
    "gn:feature_code":"PPL",
    "gn:name":"Lotes",
    "gn:population":0,
    "gn:timezone":"America/Guatemala",
    "iso:country":"GT",
    "name:spa_x_preferred":[
        "Lotes"
    ],
    "wof:name":"Lotes",
    "wof:placetype":"locality"
},
  "geometry": {"coordinates":[-91.88523000000001,15.61954],"type":"Point"}
}