{
  "type": "Feature",
  "properties": {
    "gn:admin1_code":"17",
    "gn:asciiname":"Julisboch",
    "gn:country_code":"GT",
    "gn:dem":2801,
    "gn:feature_class":"P",
    "gn:feature_code":"PPL",
    "gn:name":"Julisboch",
    "gn:population":0,
    "gn:timezone":"America/Guatemala",
    "iso:country":"GT",
    "name:spa_x_preferred":[
        "Julisboch"
    ],
    "wof:name":"Julisboch",
    "wof:placetype":"locality"
},
  "geometry": {"coordinates":[-91.83229,15.24459],"type":"Point"}
}