{
  "type": "Feature",
  "properties": {
    "gn:admin1_code":"14",
    "gn:asciiname":"Las Rosas",
    "gn:country_code":"GT",
    "gn:dem":204,
    "gn:feature_class":"P",
    "gn:feature_code":"PPL",
    "gn:name":"Las Rosas",
    "gn:population":0,
    "gn:timezone":"America/Guatemala",
    "iso:country":"GT",
    "name:spa_x_preferred":[
        "Las Rosas"
    ],
    "wof:name":"Las Rosas",
    "wof:placetype":"locality"
},
  "geometry": {"coordinates":[-90.72512,16.06247999999999],"type":"Point"}
}