{
  "type": "Feature",
  "properties": {
    "gn:admin1_code":"14",
    "gn:asciiname":"Tres Laguna",
    "gn:country_code":"GT",
    "gn:dem":162,
    "gn:feature_class":"P",
    "gn:feature_code":"PPL",
    "gn:name":"Tres Laguna",
    "gn:population":0,
    "gn:timezone":"America/Guatemala",
    "iso:country":"GT",
    "name:spa_x_preferred":[
        "Tres Laguna"
    ],
    "wof:name":"Tres Laguna",
    "wof:placetype":"locality"
},
  "geometry": {"coordinates":[-90.58823,16.03913],"type":"Point"}
}