{
  "type": "Feature",
  "properties": {
    "gn:admin1_code":"22",
    "gn:asciiname":"Las Minas",
    "gn:cc2":"GT",
    "gn:country_code":"GT",
    "gn:dem":369,
    "gn:feature_class":"P",
    "gn:feature_code":"PPL",
    "gn:name":"Las Minas",
    "gn:population":0,
    "gn:timezone":"America/Guatemala",
    "iso:country":"GT",
    "name:ceb_x_preferred":[
        "Las Minas"
    ],
    "name:deu_x_preferred":[
        "Las Minas"
    ],
    "name:spa_x_preferred":[
        "Las Minas"
    ],
    "name:swe_x_preferred":[
        "Las Minas"
    ],
    "name:und_x_variant":[
        "Finca Las Minas",
        "Las Minas"
    ],
    "wof:name":"Las Minas",
    "wof:placetype":"locality"
},
  "geometry": {"coordinates":[-89.71666999999999,15.01667],"type":"Point"}
}