{
  "type": "Feature",
  "properties": {
    "gn:admin1_code":"14",
    "gn:asciiname":"Mactzuloxib",
    "gn:cc2":"GT",
    "gn:country_code":"GT",
    "gn:dem":2195,
    "gn:feature_class":"P",
    "gn:feature_code":"PPL",
    "gn:name":"Mactzuloxib",
    "gn:population":0,
    "gn:timezone":"America/Guatemala",
    "iso:country":"GT",
    "name:und_x_variant":[
        "Mactzul Tercero",
        "Mactzuloxib"
    ],
    "wof:name":"Mactzuloxib",
    "wof:placetype":"locality"
},
  "geometry": {"coordinates":[-91.18333,14.95],"type":"Point"}
}