{
  "type": "Feature",
  "properties": {
    "gn:admin1_code":"13",
    "gn:asciiname":"Xejuyup",
    "gn:country_code":"GT",
    "gn:dem":2821,
    "gn:feature_class":"P",
    "gn:feature_code":"PPL",
    "gn:name":"Xejuyup",
    "gn:population":0,
    "gn:timezone":"America/Guatemala",
    "iso:country":"GT",
    "name:spa_x_preferred":[
        "Xejuyup"
    ],
    "wof:name":"Xejuyup",
    "wof:placetype":"locality"
},
  "geometry": {"coordinates":[-91.56138,15.08673],"type":"Point"}
}