{
  "type": "Feature",
  "properties": {
    "gn:admin1_code":"17",
    "gn:asciiname":"Colcojhuitz",
    "gn:country_code":"GT",
    "gn:dem":3015,
    "gn:feature_class":"P",
    "gn:feature_code":"PPL",
    "gn:name":"Colcojhuitz",
    "gn:population":0,
    "gn:timezone":"America/Guatemala",
    "iso:country":"GT",
    "name:spa_x_preferred":[
        "Colcojhuitz"
    ],
    "wof:name":"Colcojhuitz",
    "wof:placetype":"locality"
},
  "geometry": {"coordinates":[-91.98537,15.15926],"type":"Point"}
}