{
  "type": "Feature",
  "properties": {
    "gn:admin1_code":"21",
    "gn:asciiname":"Pachaj",
    "gn:country_code":"GT",
    "gn:dem":2578,
    "gn:feature_class":"P",
    "gn:feature_code":"PPL",
    "gn:name":"Pachaj",
    "gn:population":0,
    "gn:timezone":"America/Guatemala",
    "iso:country":"GT",
    "wof:name":"Pachaj",
    "wof:placetype":"locality"
},
  "geometry": {"coordinates":[-91.46666999999999,14.95],"type":"Point"}
}