{
  "type": "Feature",
  "properties": {
    "gn:admin1_code":"12",
    "gn:asciiname":"Cruz de Piedra",
    "gn:country_code":"GT",
    "gn:dem":201,
    "gn:feature_class":"P",
    "gn:feature_code":"PPLL",
    "gn:name":"Cruz de Piedra",
    "gn:population":0,
    "gn:timezone":"America/Guatemala",
    "iso:country":"GT",
    "name:spa_x_preferred":[
        "Cruz de Piedra"
    ],
    "wof:name":"Cruz de Piedra",
    "wof:placetype":"locality"
},
  "geometry": {"coordinates":[-90.09623999999999,16.87885],"type":"Point"}
}