{
  "type": "Feature",
  "properties": {
    "gn:admin1_code":"17",
    "gn:asciiname":"San Juan Los Altos",
    "gn:country_code":"GT",
    "gn:dem":2573,
    "gn:feature_class":"P",
    "gn:feature_code":"PPL",
    "gn:name":"San Ju\u00e1n Los Altos",
    "gn:population":0,
    "gn:timezone":"America/Guatemala",
    "iso:country":"GT",
    "name:spa_x_preferred":[
        "San Ju\u00e1n Los Altos"
    ],
    "wof:name":"San Juan Los Altos",
    "wof:placetype":"locality"
},
  "geometry": {"coordinates":[-91.94265,15.12194],"type":"Point"}
}