{
  "type": "Feature",
  "properties": {
    "gn:admin1_code":"13",
    "gn:asciiname":"San Miguelito Calahuache",
    "gn:country_code":"GT",
    "gn:dem":957,
    "gn:feature_class":"P",
    "gn:feature_code":"PPL",
    "gn:name":"San Miguelito Calahuach\u00e9",
    "gn:population":0,
    "gn:timezone":"America/Guatemala",
    "iso:country":"GT",
    "wof:name":"San Miguelito Calahuache",
    "wof:placetype":"locality"
},
  "geometry": {"coordinates":[-91.55,14.66667],"type":"Point"}
}