{
  "type": "Feature",
  "properties": {
    "gn:admin1_code":"21",
    "gn:asciiname":"Xuliaj",
    "gn:country_code":"GT",
    "gn:dem":2171,
    "gn:feature_class":"P",
    "gn:feature_code":"PPLL",
    "gn:name":"Xuliaj",
    "gn:population":0,
    "gn:timezone":"America/Guatemala",
    "iso:country":"GT",
    "name:spa_x_preferred":[
        "Xuliaj"
    ],
    "wof:name":"Xuliaj",
    "wof:placetype":"locality"
},
  "geometry": {"coordinates":[-91.48336999999999,15.12645],"type":"Point"}
}