{
  "type": "Feature",
  "properties": {
    "gn:admin1_code":"11",
    "gn:asciiname":"Carbonera",
    "gn:country_code":"GT",
    "gn:dem":1020,
    "gn:feature_class":"P",
    "gn:feature_code":"PPL",
    "gn:name":"Carbonera",
    "gn:population":0,
    "gn:timezone":"America/Guatemala",
    "iso:country":"GT",
    "wof:name":"Carbonera",
    "wof:placetype":"locality"
},
  "geometry": {"coordinates":[-89.76666999999998,14.36667],"type":"Point"}
}