{
  "type": "Feature",
  "properties": {
    "gn:admin1_code":"04",
    "gn:asciiname":"Laguna",
    "gn:country_code":"GT",
    "gn:dem":862,
    "gn:feature_class":"P",
    "gn:feature_code":"PPL",
    "gn:name":"Laguna",
    "gn:population":0,
    "gn:timezone":"America/Guatemala",
    "iso:country":"GT",
    "wof:name":"Laguna",
    "wof:placetype":"locality"
},
  "geometry": {"coordinates":[-89.55,14.63333],"type":"Point"}
}