{
  "type": "Feature",
  "properties": {
    "gn:admin1_code":"11",
    "gn:asciiname":"Las Marias",
    "gn:country_code":"GT",
    "gn:dem":68,
    "gn:feature_class":"P",
    "gn:feature_code":"PPL",
    "gn:name":"Las Mar\u00edas",
    "gn:population":0,
    "gn:timezone":"America/Guatemala",
    "iso:country":"GT",
    "wof:name":"Las Marias",
    "wof:placetype":"locality"
},
  "geometry": {"coordinates":[-90.20361,13.94722],"type":"Point"}
}