{
  "type": "Feature",
  "properties": {
    "gn:admin1_code":"17",
    "gn:asciiname":"San Luis",
    "gn:country_code":"GT",
    "gn:dem":2766,
    "gn:feature_class":"P",
    "gn:feature_code":"PPL",
    "gn:name":"San Luis",
    "gn:population":0,
    "gn:timezone":"America/Guatemala",
    "iso:country":"GT",
    "name:spa_x_preferred":[
        "San Luis"
    ],
    "wof:name":"San Luis",
    "wof:placetype":"locality"
},
  "geometry": {"coordinates":[-91.93419,15.28834],"type":"Point"}
}