{
  "type": "Feature",
  "properties": {
    "gn:admin1_code":"14",
    "gn:asciiname":"Tuchabuc",
    "gn:country_code":"GT",
    "gn:dem":2224,
    "gn:feature_class":"P",
    "gn:feature_code":"PPL",
    "gn:name":"Tuchabuc",
    "gn:population":0,
    "gn:timezone":"America/Guatemala",
    "iso:country":"GT",
    "name:spa_x_preferred":[
        "Tuchabuc"
    ],
    "wof:name":"Tuchabuc",
    "wof:placetype":"locality"
},
  "geometry": {"coordinates":[-91.25451,15.45862],"type":"Point"}
}