{
  "type": "Feature",
  "properties": {
    "gn:admin1_code":"14",
    "gn:asciiname":"Chinimaquim",
    "gn:cc2":"GT",
    "gn:country_code":"GT",
    "gn:dem":2389,
    "gn:feature_class":"P",
    "gn:feature_code":"PPL",
    "gn:name":"Chinimaquim",
    "gn:population":0,
    "gn:timezone":"America/Guatemala",
    "iso:country":"GT",
    "name:und_x_variant":[
        "Chinimaqu\u00edn",
        "Chinimaquim"
    ],
    "wof:name":"Chinimaquim",
    "wof:placetype":"locality"
},
  "geometry": {"coordinates":[-90.90000000000001,15.41667],"type":"Point"}
}