{
  "type": "Feature",
  "properties": {
    "gn:admin1_code":"05",
    "gn:asciiname":"Los Izotes",
    "gn:country_code":"GT",
    "gn:dem":610,
    "gn:feature_class":"P",
    "gn:feature_code":"PPL",
    "gn:name":"Los Izotes",
    "gn:population":0,
    "gn:timezone":"America/Guatemala",
    "iso:country":"GT",
    "wof:name":"Los Izotes",
    "wof:placetype":"locality"
},
  "geometry": {"coordinates":[-90.18333,14.85],"type":"Point"}
}