{
  "type": "Feature",
  "properties": {
    "gn:admin1_code":"17",
    "gn:asciiname":"Chipomal",
    "gn:country_code":"GT",
    "gn:dem":2676,
    "gn:feature_class":"P",
    "gn:feature_code":"PPL",
    "gn:name":"Chipomal",
    "gn:population":0,
    "gn:timezone":"America/Guatemala",
    "iso:country":"GT",
    "name:spa_x_preferred":[
        "Chipomal"
    ],
    "wof:name":"Chipomal",
    "wof:placetype":"locality"
},
  "geometry": {"coordinates":[-91.81274000000001,15.27477],"type":"Point"}
}