{
  "type": "Feature",
  "properties": {
    "gn:admin1_code":"14",
    "gn:asciiname":"Xevitz",
    "gn:country_code":"GT",
    "gn:dem":2115,
    "gn:feature_class":"P",
    "gn:feature_code":"PPL",
    "gn:name":"Xevitz",
    "gn:population":0,
    "gn:timezone":"America/Guatemala",
    "iso:country":"GT",
    "name:spa_x_preferred":[
        "Xevitz"
    ],
    "wof:name":"Xevitz",
    "wof:placetype":"locality"
},
  "geometry": {"coordinates":[-91.12002,15.38688],"type":"Point"}
}