{
  "type": "Feature",
  "properties": {
    "gn:admin1_code":"05",
    "gn:asciiname":"Cienaguitas",
    "gn:cc2":"GT",
    "gn:country_code":"GT",
    "gn:dem":584,
    "gn:feature_class":"P",
    "gn:feature_code":"PPL",
    "gn:name":"Cienaguitas",
    "gn:population":0,
    "gn:timezone":"America/Guatemala",
    "iso:country":"GT",
    "name:und_x_variant":[
        "La Cieneguita",
        "Cienaguitas"
    ],
    "wof:name":"Cienaguitas",
    "wof:placetype":"locality"
},
  "geometry": {"coordinates":[-90.28333000000001,14.86667],"type":"Point"}
}