{
  "type": "Feature",
  "properties": {
    "gn:admin1_code":"14",
    "gn:asciiname":"Las Tres Cruces",
    "gn:country_code":"GT",
    "gn:dem":1651,
    "gn:feature_class":"P",
    "gn:feature_code":"PPL",
    "gn:name":"Las Tres Cruces",
    "gn:population":0,
    "gn:timezone":"America/Guatemala",
    "iso:country":"GT",
    "wof:name":"Las Tres Cruces",
    "wof:placetype":"locality"
},
  "geometry": {"coordinates":[-90.66667,14.98333],"type":"Point"}
}