{
  "type": "Feature",
  "properties": {
    "gn:admin1_code":"14",
    "gn:asciiname":"Chulumbal",
    "gn:country_code":"GT",
    "gn:dem":2313,
    "gn:feature_class":"P",
    "gn:feature_code":"PPL",
    "gn:name":"Chulumbal",
    "gn:population":0,
    "gn:timezone":"America/Guatemala",
    "iso:country":"GT",
    "name:spa_x_preferred":[
        "Chulumbal"
    ],
    "name:und_x_variant":[
        "Culumbal"
    ],
    "wof:name":"Chulumbal",
    "wof:placetype":"locality"
},
  "geometry": {"coordinates":[-91.05593,15.0864],"type":"Point"}
}