{
  "type": "Feature",
  "properties": {
    "gn:admin1_code":"02",
    "gn:asciiname":"Sinanja",
    "gn:country_code":"GT",
    "gn:dem":461,
    "gn:feature_class":"P",
    "gn:feature_code":"PPL",
    "gn:name":"Sinanj\u00e1",
    "gn:population":0,
    "gn:timezone":"America/Guatemala",
    "iso:country":"GT",
    "wof:name":"Sinanja",
    "wof:placetype":"locality"
},
  "geometry": {"coordinates":[-90.06667,15.21667],"type":"Point"}
}