{
  "type": "Feature",
  "properties": {
    "gn:admin1_code":"05",
    "gn:asciiname":"El Jabillo",
    "gn:country_code":"GT",
    "gn:dem":489,
    "gn:feature_class":"P",
    "gn:feature_code":"PPL",
    "gn:name":"El Jabillo",
    "gn:population":0,
    "gn:timezone":"America/Guatemala",
    "iso:country":"GT",
    "wof:name":"El Jabillo",
    "wof:placetype":"locality"
},
  "geometry": {"coordinates":[-89.91667,14.88333],"type":"Point"}
}