{
  "type": "Feature",
  "properties": {
    "gn:admin1_code":"21",
    "gn:asciiname":"Chuaquisis",
    "gn:country_code":"GT",
    "gn:dem":2262,
    "gn:feature_class":"P",
    "gn:feature_code":"PPLL",
    "gn:name":"Chuaquis\u00eds",
    "gn:population":0,
    "gn:timezone":"America/Guatemala",
    "iso:country":"GT",
    "name:spa_x_preferred":[
        "Chuaquis\u00eds"
    ],
    "wof:name":"Chuaquisis",
    "wof:placetype":"locality"
},
  "geometry": {"coordinates":[-91.38932,15.00218],"type":"Point"}
}