{
  "type": "Feature",
  "properties": {
    "gn:admin1_code":"08",
    "gn:asciiname":"La Botija",
    "gn:country_code":"GT",
    "gn:dem":3217,
    "gn:feature_class":"P",
    "gn:feature_code":"PPL",
    "gn:name":"La Botija",
    "gn:population":0,
    "gn:timezone":"America/Guatemala",
    "iso:country":"GT",
    "name:spa_x_preferred":[
        "La Botija"
    ],
    "wof:name":"La Botija",
    "wof:placetype":"locality"
},
  "geometry": {"coordinates":[-91.39951000000001,15.46865],"type":"Point"}
}