{
  "type": "Feature",
  "properties": {
    "gn:admin1_code":"17",
    "gn:asciiname":"Toninchicalaj",
    "gn:country_code":"GT",
    "gn:dem":2665,
    "gn:feature_class":"P",
    "gn:feature_code":"PPL",
    "gn:name":"Toninchicalaj",
    "gn:population":0,
    "gn:timezone":"America/Guatemala",
    "iso:country":"GT",
    "name:spa_x_preferred":[
        "Toninchicalaj"
    ],
    "wof:name":"Toninchicalaj",
    "wof:placetype":"locality"
},
  "geometry": {"coordinates":[-92.08425,15.20159],"type":"Point"}
}