{
  "type": "Feature",
  "properties": {
    "gn:admin1_code":"02",
    "gn:asciiname":"Conculito",
    "gn:cc2":"GT",
    "gn:country_code":"GT",
    "gn:dem":1836,
    "gn:feature_class":"P",
    "gn:feature_code":"PPL",
    "gn:name":"Conculito",
    "gn:population":0,
    "gn:timezone":"America/Guatemala",
    "iso:country":"GT",
    "name:und_x_variant":[
        "Concul",
        "Conculito"
    ],
    "wof:name":"Conculito",
    "wof:placetype":"locality"
},
  "geometry": {"coordinates":[-90.53333000000001,15.01667],"type":"Point"}
}