{
  "type": "Feature",
  "properties": {
    "gn:admin1_code":"13",
    "gn:asciiname":"San Antonio El Naranjo",
    "gn:country_code":"GT",
    "gn:dem":45,
    "gn:feature_class":"P",
    "gn:feature_code":"PPL",
    "gn:name":"San Antonio El Naranjo",
    "gn:population":0,
    "gn:timezone":"America/Guatemala",
    "iso:country":"GT",
    "name:spa_x_preferred":[
        "San Antonio El Naranjo"
    ],
    "name:und_x_variant":[
        "El Naranjo",
        "Hacienda San Antonio Naranjo",
        "San Antonio",
        "Hacienda San Antonio El Naranjo"
    ],
    "wof:name":"San Antonio El Naranjo",
    "wof:placetype":"locality"
},
  "geometry": {"coordinates":[-92.08824,14.66337],"type":"Point"}
}