{
  "type": "Feature",
  "properties": {
    "gn:admin1_code":"08",
    "gn:asciiname":"Meste",
    "gn:country_code":"GT",
    "gn:dem":1558,
    "gn:feature_class":"P",
    "gn:feature_code":"PPL",
    "gn:name":"Mest\u00e9",
    "gn:population":0,
    "gn:timezone":"America/Guatemala",
    "iso:country":"GT",
    "name:spa_x_preferred":[
        "Mest\u00e9"
    ],
    "wof:name":"Meste",
    "wof:placetype":"locality"
},
  "geometry": {"coordinates":[-91.68181,15.6654],"type":"Point"}
}