{
  "type": "Feature",
  "properties": {
    "gn:admin1_code":"08",
    "gn:asciiname":"Terrero Alto",
    "gn:country_code":"GT",
    "gn:dem":1903,
    "gn:feature_class":"P",
    "gn:feature_code":"PPL",
    "gn:name":"Terrero Alto",
    "gn:population":0,
    "gn:timezone":"America/Guatemala",
    "iso:country":"GT",
    "name:spa_x_preferred":[
        "Terrero Alto"
    ],
    "wof:name":"Terrero Alto",
    "wof:placetype":"locality"
},
  "geometry": {"coordinates":[-91.48260000000001,15.33657],"type":"Point"}
}