{
  "type": "Feature",
  "properties": {
    "gn:admin1_code":"08",
    "gn:asciiname":"Chenicham II",
    "gn:country_code":"GT",
    "gn:dem":1808,
    "gn:feature_class":"P",
    "gn:feature_code":"PPL",
    "gn:name":"Chenicham II",
    "gn:population":0,
    "gn:timezone":"America/Guatemala",
    "iso:country":"GT",
    "name:spa_x_preferred":[
        "Chenicham II"
    ],
    "wof:name":"Chenicham II",
    "wof:placetype":"locality"
},
  "geometry": {"coordinates":[-91.66524,15.75943],"type":"Point"}
}