{
  "type": "Feature",
  "properties": {
    "gn:admin1_code":"14",
    "gn:asciiname":"Parramos Chiquito",
    "gn:country_code":"GT",
    "gn:dem":2216,
    "gn:feature_class":"P",
    "gn:feature_code":"PPL",
    "gn:name":"Parramos Chiquito",
    "gn:population":0,
    "gn:timezone":"America/Guatemala",
    "iso:country":"GT",
    "name:spa_x_preferred":[
        "Parramos Chiquito"
    ],
    "wof:name":"Parramos Chiquito",
    "wof:placetype":"locality"
},
  "geometry": {"coordinates":[-91.26504,15.46751],"type":"Point"}
}