{
  "type": "Feature",
  "properties": {
    "gn:admin1_code":"17",
    "gn:asciiname":"Clarita",
    "gn:country_code":"GT",
    "gn:dem":1014,
    "gn:feature_class":"P",
    "gn:feature_code":"PPL",
    "gn:name":"Clarita",
    "gn:population":0,
    "gn:timezone":"America/Guatemala",
    "iso:country":"GT",
    "name:deu_x_preferred":[
        "Clarita"
    ],
    "name:spa_x_preferred":[
        "Clarita"
    ],
    "wof:name":"Clarita",
    "wof:placetype":"locality"
},
  "geometry": {"coordinates":[-92.03752,14.98921],"type":"Point"}
}