{
  "type": "Feature",
  "properties": {
    "gn:admin1_code":"12",
    "gn:asciiname":"Parcelamiento El Bajo",
    "gn:country_code":"GT",
    "gn:dem":118,
    "gn:feature_class":"P",
    "gn:feature_code":"PPLF",
    "gn:name":"Parcelamiento El Bajo",
    "gn:population":0,
    "gn:timezone":"America/Guatemala",
    "iso:country":"GT",
    "name:spa_x_preferred":[
        "Parcelamiento El Bajo"
    ],
    "wof:name":"Parcelamiento El Bajo",
    "wof:placetype":"locality"
},
  "geometry": {"coordinates":[-89.94714,17.15949],"type":"Point"}
}