{
  "type": "Feature",
  "properties": {
    "iso:country":"GT",
    "name:bul_x_preferred":[
        "\u0421\u0430\u043d\u0442\u0430 \u041a\u0430\u0442\u0430\u0440\u0438\u043d\u0430 \u041f\u0438\u043d\u0443\u043b\u0430"
    ],
    "name:ceb_x_preferred":[
        "Santa Catarina Pinula"
    ],
    "name:deu_x_preferred":[
        "Santa Catarina Pinula"
    ],
    "name:eng_x_preferred":[
        "Santa Catarina Pinula"
    ],
    "name:fra_x_preferred":[
        "Santa Catarina Pinula"
    ],
    "name:ita_x_preferred":[
        "Santa Catarina Pinula"
    ],
    "name:nan_x_preferred":[
        "Santa Catarina Pinula"
    ],
    "name:nld_x_preferred":[
        "Santa Catarina Pinula"
    ],
    "name:pol_x_preferred":[
        "Santa Catarina Pinula"
    ],
    "name:por_x_preferred":[
        "Santa Catarina Pinula"
    ],
    "name:sco_x_preferred":[
        "Santa Catarina Pinula"
    ],
    "name:spa_x_preferred":[
        "Santa Catarina Pinula"
    ],
    "name:swe_x_preferred":[
        "Santa Catarina Pinula"
    ],
    "name:zho_x_preferred":[
        "\u8056\u5361\u5854\u91cc\u7d0d\u76ae\u52aa\u62c9"
    ],
    "qs:gn_country":"GT",
    "qs:gn_fcode":"PPL",
    "qs:gn_pop":67994,
    "qs:name":"Santa Catarina Pinula",
    "qs:name_adm0":"Guatemala",
    "qs:name_adm1":"Guatemala",
    "qs:photos":372,
    "qs:photos_1k":75,
    "qs:photos_9k":2,
    "qs:photos_9r":5,
    "qs:photos_all":372,
    "qs:photos_sr":6,
    "qs:placetype":"Town",
    "qs:pop_sr":"8",
    "qs:woe_adm0":23424834,
    "wd:wordcount":625,
    "wof:name":"Santa Catarina Pinula",
    "wof:placetype":"locality",
    "wof:population":67994
},
  "geometry": {"coordinates":[-90.49527999999999,14.56889],"type":"Point"}
}