{
  "type": "Feature",
  "properties": {
    "gn:admin1_code":"21",
    "gn:asciiname":"Pavoronche",
    "gn:country_code":"GT",
    "gn:dem":1937,
    "gn:feature_class":"P",
    "gn:feature_code":"PPL",
    "gn:name":"Pavoronch\u00e9",
    "gn:population":0,
    "gn:timezone":"America/Guatemala",
    "iso:country":"GT",
    "name:spa_x_preferred":[
        "Pavoronch\u00e9"
    ],
    "wof:name":"Pavoronche",
    "wof:placetype":"locality"
},
  "geometry": {"coordinates":[-91.40573000000001,15.10844],"type":"Point"}
}