{
  "type": "Feature",
  "properties": {
    "gn:admin1_code":"17",
    "gn:asciiname":"San Jose Ixcaniche",
    "gn:country_code":"GT",
    "gn:dem":1956,
    "gn:feature_class":"P",
    "gn:feature_code":"PPL",
    "gn:name":"San Jos\u00e9 Ixcaniche",
    "gn:population":0,
    "gn:timezone":"America/Guatemala",
    "iso:country":"GT",
    "name:spa_x_preferred":[
        "San Jos\u00e9 Ixcaniche"
    ],
    "wof:name":"San Jose Ixcaniche",
    "wof:placetype":"locality"
},
  "geometry": {"coordinates":[-91.68559999999999,15.24946],"type":"Point"}
}