{
  "type": "Feature",
  "properties": {
    "iso:country":"GT",
    "name:ceb_x_preferred":[
        "Todos Santos Cuchumat\u00e1n"
    ],
    "name:eng_x_preferred":[
        "Todos Santos Cuchumat\u00e1n"
    ],
    "name:fra_x_preferred":[
        "Todos Santos Cuchumat\u00e1n"
    ],
    "name:ita_x_preferred":[
        "Todos Santos Cuchumat\u00e1n"
    ],
    "name:lit_x_preferred":[
        "Todos Santos Ku\u010dumatanas"
    ],
    "name:lit_x_variant":[
        "Todos Santos Ku\u010diumatanas"
    ],
    "name:nld_x_preferred":[
        "Todos Santos Cuchumat\u00e1n"
    ],
    "name:pol_x_preferred":[
        "Todos Santos Cuchumat\u00e1n"
    ],
    "name:por_x_preferred":[
        "Todos Santos Cuchumat\u00e1n"
    ],
    "name:spa_x_preferred":[
        "Todos Santos Cuchumat\u00e1n"
    ],
    "name:swe_x_preferred":[
        "Todos Santos Cuchumat\u00e1n"
    ],
    "name:unk_x_variant":[
        "Cuchumatan"
    ],
    "name:zho_x_preferred":[
        "\u6258\u591a\u65af\u6851\u6258\u65af\u5eab\u4e18\u99ac\u5766"
    ],
    "qs:gn_country":"GT",
    "qs:gn_fcode":"PPL",
    "qs:gn_pop":3289,
    "qs:name":"Todos Santos Cuchumat\u00e1n",
    "qs:name_adm0":"Guatemala",
    "qs:name_adm1":"Huehuetenango",
    "qs:photos":351,
    "qs:photos_1k":71,
    "qs:photos_9k":2,
    "qs:photos_9r":5,
    "qs:photos_all":351,
    "qs:photos_sr":6,
    "qs:placetype":"Town",
    "qs:pop_sr":"4",
    "qs:woe_adm0":23424834,
    "wof:name":"Todos Santos Cuchumat\u00e1n",
    "wof:placetype":"locality",
    "wof:population":3289
},
  "geometry": {"coordinates":[-91.61667,15.51667],"type":"Point"}
}