{
  "type": "Feature",
  "properties": {
    "gn:admin1_code":"14",
    "gn:asciiname":"Tixelap",
    "gn:country_code":"GT",
    "gn:dem":1794,
    "gn:feature_class":"P",
    "gn:feature_code":"PPL",
    "gn:name":"Tixelap",
    "gn:population":0,
    "gn:timezone":"America/Guatemala",
    "iso:country":"GT",
    "name:spa_x_preferred":[
        "Tixelap"
    ],
    "wof:name":"Tixelap",
    "wof:placetype":"locality"
},
  "geometry": {"coordinates":[-91.03086999999999,15.43919],"type":"Point"}
}