{
  "type": "Feature",
  "properties": {
    "gn:admin1_code":"09",
    "gn:asciiname":"Eskimo",
    "gn:country_code":"GT",
    "gn:dem":18,
    "gn:feature_class":"P",
    "gn:feature_code":"PPL",
    "gn:name":"\u00c9skimo",
    "gn:population":0,
    "gn:timezone":"America/Guatemala",
    "iso:country":"GT",
    "wof:name":"Eskimo",
    "wof:placetype":"locality"
},
  "geometry": {"coordinates":[-88.46666999999999,15.61667],"type":"Point"}
}