{
  "type": "Feature",
  "properties": {
    "gn:admin1_code":"03",
    "gn:asciiname":"Mixcolabaj",
    "gn:country_code":"GT",
    "gn:dem":2095,
    "gn:feature_class":"P",
    "gn:feature_code":"PPL",
    "gn:name":"Mixcolabaj",
    "gn:population":0,
    "gn:timezone":"America/Guatemala",
    "iso:country":"GT",
    "wof:name":"Mixcolabaj",
    "wof:placetype":"locality"
},
  "geometry": {"coordinates":[-90.86667,14.78333],"type":"Point"}
}