{
  "type": "Feature",
  "properties": {
    "gn:admin1_code":"08",
    "gn:asciiname":"Cruz Chex",
    "gn:country_code":"GT",
    "gn:dem":2501,
    "gn:feature_class":"P",
    "gn:feature_code":"PPL",
    "gn:name":"Cruz Chex",
    "gn:population":0,
    "gn:timezone":"America/Guatemala",
    "iso:country":"GT",
    "name:spa_x_preferred":[
        "Cruz Chex"
    ],
    "wof:name":"Cruz Chex",
    "wof:placetype":"locality"
},
  "geometry": {"coordinates":[-91.28198999999999,15.37239],"type":"Point"}
}