{
  "type": "Feature",
  "properties": {
    "gn:admin1_code":"09",
    "gn:asciiname":"Rubelpec",
    "gn:country_code":"GT",
    "gn:dem":310,
    "gn:feature_class":"P",
    "gn:feature_code":"PPL",
    "gn:name":"Rubelpec",
    "gn:population":0,
    "gn:timezone":"America/Guatemala",
    "iso:country":"GT",
    "wof:name":"Rubelpec",
    "wof:placetype":"locality"
},
  "geometry": {"coordinates":[-89.38333,15.58333],"type":"Point"}
}