{
  "type": "Feature",
  "properties": {
    "gn:admin1_code":"08",
    "gn:asciiname":"Los Alisos",
    "gn:country_code":"GT",
    "gn:dem":1984,
    "gn:feature_class":"P",
    "gn:feature_code":"PPL",
    "gn:name":"Los Alisos",
    "gn:population":0,
    "gn:timezone":"America/Guatemala",
    "iso:country":"GT",
    "name:spa_x_preferred":[
        "Los Alisos"
    ],
    "wof:name":"Los Alisos",
    "wof:placetype":"locality"
},
  "geometry": {"coordinates":[-91.73845,15.4966],"type":"Point"}
}