{
  "type": "Feature",
  "properties": {
    "gn:admin1_code":"17",
    "gn:asciiname":"Estancia de La Virgen",
    "gn:country_code":"GT",
    "gn:dem":3076,
    "gn:feature_class":"P",
    "gn:feature_code":"PPL",
    "gn:name":"Estancia de La Virgen",
    "gn:population":0,
    "gn:timezone":"America/Guatemala",
    "iso:country":"GT",
    "name:spa_x_preferred":[
        "Estancia de La Virgen"
    ],
    "wof:name":"Estancia de La Virgen",
    "wof:placetype":"locality"
},
  "geometry": {"coordinates":[-91.85805999999999,15.2083],"type":"Point"}
}