{
  "type": "Feature",
  "properties": {
    "gn:admin1_code":"08",
    "gn:asciiname":"Yolaxito",
    "gn:country_code":"GT",
    "gn:dem":2479,
    "gn:feature_class":"P",
    "gn:feature_code":"PPL",
    "gn:name":"Yolaxito",
    "gn:population":0,
    "gn:timezone":"America/Guatemala",
    "iso:country":"GT",
    "name:spa_x_preferred":[
        "Yolaxito"
    ],
    "wof:name":"Yolaxito",
    "wof:placetype":"locality"
},
  "geometry": {"coordinates":[-91.55884,15.74967],"type":"Point"}
}