{
  "type": "Feature",
  "properties": {
    "gn:admin1_code":"11",
    "gn:asciiname":"La Parada",
    "gn:country_code":"GT",
    "gn:dem":932,
    "gn:feature_class":"P",
    "gn:feature_code":"PPL",
    "gn:name":"La Parada",
    "gn:population":0,
    "gn:timezone":"America/Guatemala",
    "iso:country":"GT",
    "wof:name":"La Parada",
    "wof:placetype":"locality"
},
  "geometry": {"coordinates":[-89.61667,14.53333],"type":"Point"}
}