{
  "type": "Feature",
  "properties": {
    "gn:admin1_code":"13",
    "gn:asciiname":"Estancia Vieja",
    "gn:country_code":"GT",
    "gn:dem":3015,
    "gn:feature_class":"P",
    "gn:feature_code":"PPL",
    "gn:name":"Estancia Vieja",
    "gn:population":0,
    "gn:timezone":"America/Guatemala",
    "iso:country":"GT",
    "wof:name":"Estancia Vieja",
    "wof:placetype":"locality"
},
  "geometry": {"coordinates":[-91.66667,14.91667],"type":"Point"}
}