{
  "type": "Feature",
  "properties": {
    "gn:admin1_code":"07",
    "gn:asciiname":"Pamoca",
    "gn:country_code":"GT",
    "gn:dem":1634,
    "gn:feature_class":"P",
    "gn:feature_code":"PPL",
    "gn:name":"Pamoc\u00e1",
    "gn:population":0,
    "gn:timezone":"America/Guatemala",
    "iso:country":"GT",
    "wof:name":"Pamoca",
    "wof:placetype":"locality"
},
  "geometry": {"coordinates":[-90.58333,14.78333],"type":"Point"}
}