{
  "type": "Feature",
  "properties": {
    "gn:admin1_code":"17",
    "gn:asciiname":"Tuismach",
    "gn:country_code":"GT",
    "gn:dem":2704,
    "gn:feature_class":"P",
    "gn:feature_code":"PPL",
    "gn:name":"Tuismach",
    "gn:population":0,
    "gn:timezone":"America/Guatemala",
    "iso:country":"GT",
    "name:spa_x_preferred":[
        "Tuismach"
    ],
    "wof:name":"Tuismach",
    "wof:placetype":"locality"
},
  "geometry": {"coordinates":[-92.08748,15.28924],"type":"Point"}
}