{
  "type": "Feature",
  "properties": {
    "gn:admin1_code":"14",
    "gn:asciiname":"Bipo",
    "gn:country_code":"GT",
    "gn:dem":1887,
    "gn:feature_class":"P",
    "gn:feature_code":"PPL",
    "gn:name":"Bipo",
    "gn:population":0,
    "gn:timezone":"America/Guatemala",
    "iso:country":"GT",
    "name:spa_x_preferred":[
        "Bipo"
    ],
    "wof:name":"Bipo",
    "wof:placetype":"locality"
},
  "geometry": {"coordinates":[-91.14194999999999,15.41324],"type":"Point"}
}