{
  "type": "Feature",
  "properties": {
    "gn:admin1_code":"10",
    "gn:asciiname":"Carrizal Grande",
    "gn:country_code":"GT",
    "gn:dem":1728,
    "gn:feature_class":"P",
    "gn:feature_code":"PPL",
    "gn:name":"Carrizal Grande",
    "gn:population":0,
    "gn:timezone":"America/Guatemala",
    "iso:country":"GT",
    "wof:name":"Carrizal Grande",
    "wof:placetype":"locality"
},
  "geometry": {"coordinates":[-89.90000000000001,14.76667],"type":"Point"}
}