{
  "type": "Feature",
  "properties": {
    "gn:admin1_code":"04",
    "gn:asciiname":"Agua Fria",
    "gn:country_code":"GT",
    "gn:dem":814,
    "gn:feature_class":"P",
    "gn:feature_code":"PPL",
    "gn:name":"Agua Fr\u00eda",
    "gn:population":0,
    "gn:timezone":"America/Guatemala",
    "iso:country":"GT",
    "name:ceb_x_preferred":[
        "Agua Fria"
    ],
    "name:deu_x_preferred":[
        "Agua Fria"
    ],
    "name:swe_x_preferred":[
        "Agua Fria"
    ],
    "wof:name":"Agua Fria",
    "wof:placetype":"locality"
},
  "geometry": {"coordinates":[-89.34999999999999,14.86667],"type":"Point"}
}