{
  "type": "Feature",
  "properties": {
    "gn:admin1_code":"08",
    "gn:asciiname":"Jolomtaj",
    "gn:country_code":"GT",
    "gn:dem":1007,
    "gn:feature_class":"P",
    "gn:feature_code":"PPL",
    "gn:name":"Jolomtaj",
    "gn:population":0,
    "gn:timezone":"America/Guatemala",
    "iso:country":"GT",
    "name:spa_x_preferred":[
        "Jolomtaj"
    ],
    "wof:name":"Jolomtaj",
    "wof:placetype":"locality"
},
  "geometry": {"coordinates":[-91.22784,15.78606],"type":"Point"}
}