{
  "type": "Feature",
  "properties": {
    "gn:admin1_code":"15",
    "gn:asciiname":"El Chahurte",
    "gn:country_code":"GT",
    "gn:dem":8,
    "gn:feature_class":"P",
    "gn:feature_code":"PPL",
    "gn:name":"El Chahurte",
    "gn:population":0,
    "gn:timezone":"America/Guatemala",
    "iso:country":"GT",
    "wof:name":"El Chahurte",
    "wof:placetype":"locality"
},
  "geometry": {"coordinates":[-91.98333,14.41667],"type":"Point"}
}