{
  "type": "Feature",
  "properties": {
    "iso:country":"GT",
    "name:ceb_x_preferred":[
        "Ipala"
    ],
    "name:eng_x_preferred":[
        "Ipala"
    ],
    "name:fra_x_preferred":[
        "Ipala"
    ],
    "name:ita_x_preferred":[
        "Ipala"
    ],
    "name:nan_x_preferred":[
        "Ipala"
    ],
    "name:nld_x_preferred":[
        "Ipala"
    ],
    "name:pol_x_preferred":[
        "Ipala"
    ],
    "name:por_x_preferred":[
        "Ipala"
    ],
    "name:spa_x_preferred":[
        "Ipala"
    ],
    "name:swe_x_preferred":[
        "Ipala"
    ],
    "name:und_x_variant":[
        "Jilotepeque"
    ],
    "name:zho_x_preferred":[
        "\u4f0a\u5e15\u62c9"
    ],
    "qs:gn_country":"GT",
    "qs:gn_fcode":"PPL",
    "qs:gn_pop":5283,
    "qs:name":"Ipala",
    "qs:name_adm0":"Guatemala",
    "qs:name_adm1":"Chiquimula",
    "qs:photos":0,
    "qs:photos_1k":0,
    "qs:photos_9k":1,
    "qs:photos_9r":1,
    "qs:photos_all":1,
    "qs:photos_sr":0,
    "qs:placetype":"Town",
    "qs:pop_sr":"5",
    "qs:woe_adm0":23424834,
    "wof:name":"Ipala",
    "wof:placetype":"locality",
    "wof:population":5283
},
  "geometry": {"coordinates":[-89.61667,14.61667],"type":"Point"}
}