{
  "type": "Feature",
  "properties": {
    "gn:admin1_code":"17",
    "gn:asciiname":"Saquipaque",
    "gn:country_code":"GT",
    "gn:dem":2964,
    "gn:feature_class":"P",
    "gn:feature_code":"PPL",
    "gn:name":"Saquipaque",
    "gn:population":0,
    "gn:timezone":"America/Guatemala",
    "iso:country":"GT",
    "name:spa_x_preferred":[
        "Saquipaque"
    ],
    "wof:name":"Saquipaque",
    "wof:placetype":"locality"
},
  "geometry": {"coordinates":[-91.96911,15.24173],"type":"Point"}
}