{
  "type": "Feature",
  "properties": {
    "gn:admin1_code":"12",
    "gn:asciiname":"Saclac",
    "gn:cc2":"GT",
    "gn:country_code":"GT",
    "gn:dem":307,
    "gn:feature_class":"P",
    "gn:feature_code":"PPL",
    "gn:name":"Saclac",
    "gn:population":0,
    "gn:timezone":"America/Guatemala",
    "iso:country":"GT",
    "name:und_x_variant":[
        "Seclac",
        "Saclac"
    ],
    "wof:name":"Saclac",
    "wof:placetype":"locality"
},
  "geometry": {"coordinates":[-89.39944,16.18111],"type":"Point"}
}