{
  "type": "Feature",
  "properties": {
    "gn:admin1_code":"14",
    "gn:asciiname":"Comunidad Victoria Veinte de Enero",
    "gn:country_code":"GT",
    "gn:dem":168,
    "gn:feature_class":"P",
    "gn:feature_code":"PPL",
    "gn:name":"Comunidad Victoria Veinte de Enero",
    "gn:population":0,
    "gn:timezone":"America/Guatemala",
    "iso:country":"GT",
    "name:spa_x_preferred":[
        "Comunidad Victoria Veinte de Enero"
    ],
    "wof:name":"Comunidad Victoria Veinte de Enero",
    "wof:placetype":"locality"
},
  "geometry": {"coordinates":[-90.91343000000001,16.03506],"type":"Point"}
}