{
  "type": "Feature",
  "properties": {
    "gn:admin1_code":"20",
    "gn:asciiname":"Chacalte Aparicio",
    "gn:country_code":"GT",
    "gn:dem":278,
    "gn:feature_class":"P",
    "gn:feature_code":"PPL",
    "gn:name":"Chacalt\u00e9 Aparicio",
    "gn:population":0,
    "gn:timezone":"America/Guatemala",
    "iso:country":"GT",
    "wof:name":"Chacalte Aparicio",
    "wof:placetype":"locality"
},
  "geometry": {"coordinates":[-91.56667,14.51667],"type":"Point"}
}