{
  "type": "Feature",
  "properties": {
    "gn:admin1_code":"14",
    "gn:asciiname":"San Jose El Tunal",
    "gn:country_code":"GT",
    "gn:dem":1598,
    "gn:feature_class":"P",
    "gn:feature_code":"PPL",
    "gn:name":"San Jos\u00e9 El Tunal",
    "gn:population":0,
    "gn:timezone":"America/Guatemala",
    "iso:country":"GT",
    "name:spa_x_preferred":[
        "San Jos\u00e9 El Tunal"
    ],
    "wof:name":"San Jose El Tunal",
    "wof:placetype":"locality"
},
  "geometry": {"coordinates":[-91.29881,15.25782],"type":"Point"}
}