{
  "type": "Feature",
  "properties": {
    "iso:country":"GT",
    "name:cat_x_preferred":[
        "Esquipulas"
    ],
    "name:deu_x_preferred":[
        "Esquipulas"
    ],
    "name:eng_x_preferred":[
        "Esquipulas"
    ],
    "name:fra_x_preferred":[
        "Esquipulas"
    ],
    "name:ind_x_preferred":[
        "Esquipulas"
    ],
    "name:ita_x_preferred":[
        "Esquipulas"
    ],
    "name:jpn_x_preferred":[
        "\u30a8\u30b9\u30af\u30a4\u30d7\u30e9\u30b9"
    ],
    "name:lit_x_preferred":[
        "Eskipulasas"
    ],
    "name:nld_x_preferred":[
        "Esquipulas"
    ],
    "name:pol_x_preferred":[
        "Esquipulas"
    ],
    "name:por_x_preferred":[
        "Esquipulas"
    ],
    "name:spa_x_preferred":[
        "Esquipulas"
    ],
    "name:zho_x_preferred":[
        "\u57c3\u65af\u57fa\u666e\u62c9\u65af"
    ],
    "qs:gn_country":"GT",
    "qs:gn_fcode":"PPL",
    "qs:gn_pop":20674,
    "qs:name":"Esquipulas",
    "qs:name_adm0":"Guatemala",
    "qs:name_adm1":"Chiquimula",
    "qs:photos":488,
    "qs:photos_1k":99,
    "qs:photos_9k":2,
    "qs:photos_9r":5,
    "qs:photos_all":488,
    "qs:photos_sr":7,
    "qs:placetype":"Town",
    "qs:pop_sr":"7",
    "qs:woe_adm0":23424834,
    "wd:wordcount":2651,
    "wof:name":"Esquipulas",
    "wof:placetype":"locality",
    "wof:population":20674
},
  "geometry": {"coordinates":[-89.34999999999999,14.56667],"type":"Point"}
}