{
  "type": "Feature",
  "properties": {
    "gn:admin1_code":"14",
    "gn:asciiname":"La Barranca",
    "gn:country_code":"GT",
    "gn:dem":1954,
    "gn:feature_class":"P",
    "gn:feature_code":"PPL",
    "gn:name":"La Barranca",
    "gn:population":0,
    "gn:timezone":"America/Guatemala",
    "iso:country":"GT",
    "name:spa_x_preferred":[
        "La Barranca"
    ],
    "wof:name":"La Barranca",
    "wof:placetype":"locality"
},
  "geometry": {"coordinates":[-91.18073,15.18327],"type":"Point"}
}