{
  "type": "Feature",
  "properties": {
    "gn:admin1_code":"17",
    "gn:asciiname":"El Moral",
    "gn:country_code":"GT",
    "gn:dem":173,
    "gn:feature_class":"P",
    "gn:feature_code":"PPL",
    "gn:name":"El Moral",
    "gn:population":0,
    "gn:timezone":"America/Guatemala",
    "iso:country":"GT",
    "name:und_x_variant":[
        "Moral",
        "El Moral"
    ],
    "wof:name":"El Moral",
    "wof:placetype":"locality"
},
  "geometry": {"coordinates":[-92.15000000000001,14.86667],"type":"Point"}
}