{
  "type": "Feature",
  "properties": {
    "gn:admin1_code":"17",
    "gn:asciiname":"Tuiscol",
    "gn:country_code":"GT",
    "gn:dem":2529,
    "gn:feature_class":"P",
    "gn:feature_code":"PPL",
    "gn:name":"Tuiscol",
    "gn:population":0,
    "gn:timezone":"America/Guatemala",
    "iso:country":"GT",
    "name:spa_x_preferred":[
        "Tuiscol"
    ],
    "wof:name":"Tuiscol",
    "wof:placetype":"locality"
},
  "geometry": {"coordinates":[-91.81704000000001,15.12093],"type":"Point"}
}