{
  "type": "Feature",
  "properties": {
    "gn:admin1_code":"05",
    "gn:asciiname":"Pila de los Moscos",
    "gn:cc2":"GT",
    "gn:country_code":"GT",
    "gn:dem":1086,
    "gn:feature_class":"P",
    "gn:feature_code":"PPL",
    "gn:name":"Pila de los Moscos",
    "gn:population":0,
    "gn:timezone":"America/Guatemala",
    "iso:country":"GT",
    "name:und_x_variant":[
        "Pila de Moscoso",
        "Pila de los Moscos"
    ],
    "wof:name":"Pila de los Moscos",
    "wof:placetype":"locality"
},
  "geometry": {"coordinates":[-89.91667,14.85],"type":"Point"}
}