{
  "type": "Feature",
  "properties": {
    "gn:admin1_code":"06",
    "gn:asciiname":"Ceiba Amelia",
    "gn:country_code":"GT",
    "gn:dem":95,
    "gn:feature_class":"P",
    "gn:feature_code":"PPL",
    "gn:name":"Ceiba Amelia",
    "gn:population":0,
    "gn:timezone":"America/Guatemala",
    "iso:country":"GT",
    "wof:name":"Ceiba Amelia",
    "wof:placetype":"locality"
},
  "geometry": {"coordinates":[-90.965,14.1675],"type":"Point"}
}