{
  "type": "Feature",
  "properties": {
    "gn:admin1_code":"13",
    "gn:asciiname":"Las Barrancas",
    "gn:country_code":"GT",
    "gn:dem":2462,
    "gn:feature_class":"P",
    "gn:feature_code":"PPL",
    "gn:name":"Las Barrancas",
    "gn:population":0,
    "gn:timezone":"America/Guatemala",
    "iso:country":"GT",
    "name:spa_x_preferred":[
        "Las Barrancas"
    ],
    "wof:name":"Las Barrancas",
    "wof:placetype":"locality"
},
  "geometry": {"coordinates":[-91.66719000000001,15.09619],"type":"Point"}
}