{
  "type": "Feature",
  "properties": {
    "gn:admin1_code":"17",
    "gn:asciiname":"Union La Loma",
    "gn:country_code":"GT",
    "gn:dem":2281,
    "gn:feature_class":"P",
    "gn:feature_code":"PPL",
    "gn:name":"Uni\u00f3n La Loma",
    "gn:population":0,
    "gn:timezone":"America/Guatemala",
    "iso:country":"GT",
    "name:spa_x_preferred":[
        "Uni\u00f3n La Loma"
    ],
    "wof:name":"Union La Loma",
    "wof:placetype":"locality"
},
  "geometry": {"coordinates":[-91.98197999999999,15.124],"type":"Point"}
}