{
  "type": "Feature",
  "properties": {
    "gn:admin1_code":"21",
    "gn:asciiname":"Chucutinez",
    "gn:country_code":"GT",
    "gn:dem":1993,
    "gn:feature_class":"P",
    "gn:feature_code":"PPL",
    "gn:name":"Chucutinez",
    "gn:population":0,
    "gn:timezone":"America/Guatemala",
    "iso:country":"GT",
    "name:spa_x_preferred":[
        "Chucutinez"
    ],
    "wof:name":"Chucutinez",
    "wof:placetype":"locality"
},
  "geometry": {"coordinates":[-91.30797,15.04807],"type":"Point"}
}