{
  "type": "Feature",
  "properties": {
    "gn:admin1_code":"10",
    "gn:asciiname":"Limarcito",
    "gn:country_code":"GT",
    "gn:dem":1510,
    "gn:feature_class":"P",
    "gn:feature_code":"PPL",
    "gn:name":"Limarcito",
    "gn:population":0,
    "gn:timezone":"America/Guatemala",
    "iso:country":"GT",
    "wof:name":"Limarcito",
    "wof:placetype":"locality"
},
  "geometry": {"coordinates":[-89.78333000000001,14.66667],"type":"Point"}
}