{
  "type": "Feature",
  "properties": {
    "gn:admin1_code":"08",
    "gn:asciiname":"Tzunhuitz",
    "gn:country_code":"GT",
    "gn:dem":1907,
    "gn:feature_class":"P",
    "gn:feature_code":"PPL",
    "gn:name":"Tzunhuitz",
    "gn:population":0,
    "gn:timezone":"America/Guatemala",
    "iso:country":"GT",
    "name:spa_x_preferred":[
        "Tzunhuitz"
    ],
    "wof:name":"Tzunhuitz",
    "wof:placetype":"locality"
},
  "geometry": {"coordinates":[-91.68594,15.61496],"type":"Point"}
}