{
  "type": "Feature",
  "properties": {
    "gn:admin1_code":"22",
    "gn:asciiname":"La Jigua",
    "gn:cc2":"GT",
    "gn:country_code":"GT",
    "gn:dem":993,
    "gn:feature_class":"P",
    "gn:feature_code":"PPL",
    "gn:name":"La Jigua",
    "gn:population":0,
    "gn:timezone":"America/Guatemala",
    "iso:country":"GT",
    "name:und_x_variant":[
        "Jigua",
        "La Jigua"
    ],
    "wof:name":"La Jigua",
    "wof:placetype":"locality"
},
  "geometry": {"coordinates":[-89.31667,14.93333],"type":"Point"}
}