{
  "type": "Feature",
  "properties": {
    "gn:admin1_code":"08",
    "gn:asciiname":"Ucpi",
    "gn:country_code":"GT",
    "gn:dem":2579,
    "gn:feature_class":"P",
    "gn:feature_code":"PPL",
    "gn:name":"Ucp\u00ed",
    "gn:population":0,
    "gn:timezone":"America/Guatemala",
    "iso:country":"GT",
    "name:spa_x_preferred":[
        "Ucp\u00ed"
    ],
    "wof:name":"Ucpi",
    "wof:placetype":"locality"
},
  "geometry": {"coordinates":[-91.39534,15.69538],"type":"Point"}
}