{
  "type": "Feature",
  "properties": {
    "gn:admin1_code":"04",
    "gn:asciiname":"Filincas",
    "gn:country_code":"GT",
    "gn:dem":884,
    "gn:feature_class":"P",
    "gn:feature_code":"PPL",
    "gn:name":"Filincas",
    "gn:population":0,
    "gn:timezone":"America/Guatemala",
    "iso:country":"GT",
    "wof:name":"Filincas",
    "wof:placetype":"locality"
},
  "geometry": {"coordinates":[-89.23333000000002,14.81667],"type":"Point"}
}