{
  "type": "Feature",
  "properties": {
    "gn:admin1_code":"14",
    "gn:asciiname":"Las Canoas",
    "gn:country_code":"GT",
    "gn:dem":2059,
    "gn:feature_class":"P",
    "gn:feature_code":"PPL",
    "gn:name":"Las Canoas",
    "gn:population":0,
    "gn:timezone":"America/Guatemala",
    "iso:country":"GT",
    "name:spa_x_preferred":[
        "Las Canoas"
    ],
    "wof:name":"Las Canoas",
    "wof:placetype":"locality"
},
  "geometry": {"coordinates":[-91.15091,15.17847],"type":"Point"}
}