{
  "type": "Feature",
  "properties": {
    "gn:admin1_code":"08",
    "gn:asciiname":"Estcapuczi",
    "gn:country_code":"GT",
    "gn:dem":3053,
    "gn:feature_class":"P",
    "gn:feature_code":"PPL",
    "gn:name":"Estcapucz\u00ed",
    "gn:population":0,
    "gn:timezone":"America/Guatemala",
    "iso:country":"GT",
    "name:spa_x_preferred":[
        "Estcapucz\u00ed"
    ],
    "wof:name":"Estcapuczi",
    "wof:placetype":"locality"
},
  "geometry": {"coordinates":[-91.37429,15.4946],"type":"Point"}
}