{
  "type": "Feature",
  "properties": {
    "gn:admin1_code":"21",
    "gn:asciiname":"Pasaniep",
    "gn:country_code":"GT",
    "gn:dem":1966,
    "gn:feature_class":"P",
    "gn:feature_code":"PPLL",
    "gn:name":"Pasaniep",
    "gn:population":0,
    "gn:timezone":"America/Guatemala",
    "iso:country":"GT",
    "name:spa_x_preferred":[
        "Pasaniep"
    ],
    "wof:name":"Pasaniep",
    "wof:placetype":"locality"
},
  "geometry": {"coordinates":[-91.41451000000001,15.11157],"type":"Point"}
}