{
  "type": "Feature",
  "properties": {
    "gn:admin1_code":"08",
    "gn:asciiname":"Yalijau",
    "gn:country_code":"GT",
    "gn:dem":945,
    "gn:feature_class":"P",
    "gn:feature_code":"PPL",
    "gn:name":"Yalijau",
    "gn:population":0,
    "gn:timezone":"America/Guatemala",
    "iso:country":"GT",
    "name:spa_x_preferred":[
        "Yalijau"
    ],
    "wof:name":"Yalijau",
    "wof:placetype":"locality"
},
  "geometry": {"coordinates":[-91.75996000000001,15.81677],"type":"Point"}
}