{
  "type": "Feature",
  "properties": {
    "gn:admin1_code":"08",
    "gn:asciiname":"Hermosillo",
    "gn:country_code":"GT",
    "gn:dem":1645,
    "gn:feature_class":"P",
    "gn:feature_code":"PPL",
    "gn:name":"Hermosillo",
    "gn:population":0,
    "gn:timezone":"America/Guatemala",
    "iso:country":"GT",
    "name:spa_x_preferred":[
        "Hermosillo"
    ],
    "wof:name":"Hermosillo",
    "wof:placetype":"locality"
},
  "geometry": {"coordinates":[-91.99001,15.38929],"type":"Point"}
}