{
  "type": "Feature",
  "properties": {
    "gn:admin1_code":"12",
    "gn:asciiname":"San Francisco El Tumbo",
    "gn:country_code":"GT",
    "gn:dem":122,
    "gn:feature_class":"P",
    "gn:feature_code":"PPL",
    "gn:name":"San Francisco El Tumbo",
    "gn:population":0,
    "gn:timezone":"America/Guatemala",
    "iso:country":"GT",
    "name:spa_x_preferred":[
        "San Francisco El Tumbo"
    ],
    "wof:name":"San Francisco El Tumbo",
    "wof:placetype":"locality"
},
  "geometry": {"coordinates":[-90.43937,16.53751],"type":"Point"}
}