{
  "type": "Feature",
  "properties": {
    "gn:admin1_code":"17",
    "gn:asciiname":"Pena Flor",
    "gn:country_code":"GT",
    "gn:dem":2706,
    "gn:feature_class":"P",
    "gn:feature_code":"PPL",
    "gn:name":"Pe\u00f1a Flor",
    "gn:population":0,
    "gn:timezone":"America/Guatemala",
    "iso:country":"GT",
    "name:spa_x_preferred":[
        "Pe\u00f1a Flor"
    ],
    "wof:name":"Pena Flor",
    "wof:placetype":"locality"
},
  "geometry": {"coordinates":[-91.79252,15.07812],"type":"Point"}
}