{
  "type": "Feature",
  "properties": {
    "gn:admin1_code":"14",
    "gn:asciiname":"Tacachat",
    "gn:country_code":"GT",
    "gn:dem":1393,
    "gn:feature_class":"P",
    "gn:feature_code":"PPL",
    "gn:name":"Tacachat",
    "gn:population":0,
    "gn:timezone":"America/Guatemala",
    "iso:country":"GT",
    "name:spa_x_preferred":[
        "Tacachat"
    ],
    "wof:name":"Tacachat",
    "wof:placetype":"locality"
},
  "geometry": {"coordinates":[-91.02179,15.20949],"type":"Point"}
}