{
  "type": "Feature",
  "properties": {
    "gn:admin1_code":"08",
    "gn:asciiname":"El Boqueron",
    "gn:country_code":"GT",
    "gn:dem":974,
    "gn:feature_class":"P",
    "gn:feature_code":"PPL",
    "gn:name":"El Boquer\u00f3n",
    "gn:population":0,
    "gn:timezone":"America/Guatemala",
    "iso:country":"GT",
    "name:spa_x_preferred":[
        "El Boquer\u00f3n"
    ],
    "wof:name":"El Boqueron",
    "wof:placetype":"locality"
},
  "geometry": {"coordinates":[-91.85359,15.55862],"type":"Point"}
}