{
  "type": "Feature",
  "properties": {
    "gn:admin1_code":"06",
    "gn:asciiname":"Montecristo",
    "gn:country_code":"GT",
    "gn:dem":41,
    "gn:feature_class":"P",
    "gn:feature_code":"PPL",
    "gn:name":"Montecristo",
    "gn:population":0,
    "gn:timezone":"America/Guatemala",
    "iso:country":"GT",
    "wof:name":"Montecristo",
    "wof:placetype":"locality"
},
  "geometry": {"coordinates":[-90.86667,14.06667],"type":"Point"}
}