{
  "type": "Feature",
  "properties": {
    "iso:country":"GT",
    "name:bul_x_preferred":[
        "\u041f\u0430\u0442\u0443\u043b\u0443\u043b"
    ],
    "name:chi_x_preferred":[
        "\u5e15\u5716\u76e7\u723e"
    ],
    "name:dut_x_preferred":[
        "Patulul"
    ],
    "name:eng_x_preferred":[
        "Patulul"
    ],
    "name:fra_x_preferred":[
        "Patulul"
    ],
    "name:fre_x_preferred":[
        "Patulul"
    ],
    "name:ita_x_preferred":[
        "Patulul"
    ],
    "name:pol_x_preferred":[
        "Patulul"
    ],
    "name:por_x_preferred":[
        "Patulul"
    ],
    "name:spa_x_preferred":[
        "Patulul"
    ],
    "name:swe_x_preferred":[
        "Patulul"
    ],
    "name:urd_x_preferred":[
        "\u067e\u0627\u062a\u0648\u0644\u0648\u0644"
    ],
    "name:zho_x_preferred":[
        "\u5e15\u5716\u76e7\u723e"
    ],
    "qs:gn_country":"GT",
    "qs:gn_fcode":"PPL",
    "qs:gn_pop":14196,
    "qs:name":"Patulul",
    "qs:name_adm0":"Guatemala",
    "qs:name_adm1":"Suchitepequez",
    "qs:photos":0,
    "qs:photos_1k":0,
    "qs:photos_9k":1,
    "qs:photos_9r":1,
    "qs:photos_all":13,
    "qs:photos_sr":0,
    "qs:placetype":"Town",
    "qs:pop_sr":"6",
    "qs:woe_adm0":23424834,
    "wd:wordcount":77,
    "wof:name":"Patulul",
    "wof:placetype":"locality",
    "wof:population":14196
},
  "geometry": {"coordinates":[-91.16667,14.41667],"type":"Point"}
}