{
  "type": "Feature",
  "properties": {
    "gn:admin1_code":"08",
    "gn:asciiname":"Chiquilila",
    "gn:country_code":"GT",
    "gn:dem":1929,
    "gn:feature_class":"P",
    "gn:feature_code":"PPL",
    "gn:name":"Chiquilil\u00e1",
    "gn:population":0,
    "gn:timezone":"America/Guatemala",
    "iso:country":"GT",
    "name:spa_x_preferred":[
        "Chiquilil\u00e1"
    ],
    "wof:name":"Chiquilila",
    "wof:placetype":"locality"
},
  "geometry": {"coordinates":[-91.82308,15.49044],"type":"Point"}
}