{
  "type": "Feature",
  "properties": {
    "gn:admin1_code":"17",
    "gn:asciiname":"Saquimlaj",
    "gn:country_code":"GT",
    "gn:dem":2075,
    "gn:feature_class":"P",
    "gn:feature_code":"PPL",
    "gn:name":"Saquimlaj",
    "gn:population":0,
    "gn:timezone":"America/Guatemala",
    "iso:country":"GT",
    "name:spa_x_preferred":[
        "Saquimlaj"
    ],
    "wof:name":"Saquimlaj",
    "wof:placetype":"locality"
},
  "geometry": {"coordinates":[-91.65349000000001,15.20766],"type":"Point"}
}