{
  "type": "Feature",
  "properties": {
    "gn:admin1_code":"08",
    "gn:asciiname":"El Astillero",
    "gn:country_code":"GT",
    "gn:dem":1347,
    "gn:feature_class":"P",
    "gn:feature_code":"PPL",
    "gn:name":"El Astillero",
    "gn:population":0,
    "gn:timezone":"America/Guatemala",
    "iso:country":"GT",
    "name:ara_x_preferred":[
        "\u0625\u0644 \u0623\u0633\u062a\u064a\u0631\u064a\u0644\u0648"
    ],
    "name:arg_x_preferred":[
        "El Astillero"
    ],
    "name:cat_x_preferred":[
        "El Astillero"
    ],
    "name:ceb_x_preferred":[
        "El Astillero"
    ],
    "name:deu_x_preferred":[
        "El Astillero"
    ],
    "name:epo_x_preferred":[
        "El Astillero"
    ],
    "name:eus_x_preferred":[
        "El Astillero"
    ],
    "name:fra_x_preferred":[
        "El Astillero"
    ],
    "name:glg_x_preferred":[
        "El Astillero"
    ],
    "name:hun_x_preferred":[
        "El Astillero"
    ],
    "name:ina_x_preferred":[
        "El Astillero"
    ],
    "name:ita_x_preferred":[
        "El Astillero"
    ],
    "name:msa_x_preferred":[
        "El Astillero"
    ],
    "name:nld_x_preferred":[
        "El Astillero"
    ],
    "name:oci_x_preferred":[
        "El Astillero"
    ],
    "name:pam_x_preferred":[
        "El Astillero"
    ],
    "name:pol_x_preferred":[
        "El Astillero"
    ],
    "name:por_x_preferred":[
        "El Astillero"
    ],
    "name:rus_x_preferred":[
        "\u042d\u043b\u044c-\u0410\u0441\u0442\u0438\u043b\u044c\u0435\u0440\u043e"
    ],
    "name:sco_x_preferred":[
        "El Astillero"
    ],
    "name:spa_x_preferred":[
        "El Astillero"
    ],
    "name:sqi_x_preferred":[
        "El Astillero"
    ],
    "name:tur_x_preferred":[
        "El Astillero"
    ],
    "name:ukr_x_preferred":[
        "\u0415\u043b\u044c-\u0410\u0441\u0442\u0456\u043b\u044c\u0454\u0440\u043e"
    ],
    "name:uzb_x_preferred":[
        "El Astillero"
    ],
    "name:vie_x_preferred":[
        "El Astillero"
    ],
    "name:war_x_preferred":[
        "El Astillero"
    ],
    "name:zho_x_preferred":[
        "\u57c3\u62c9\u65af\u8482\u5217\u7f57"
    ],
    "wof:name":"El Astillero",
    "wof:placetype":"locality"
},
  "geometry": {"coordinates":[-92.02016999999999,15.41925],"type":"Point"}
}