{
  "type": "Feature",
  "properties": {
    "gn:admin1_code":"14",
    "gn:asciiname":"Quibala",
    "gn:country_code":"GT",
    "gn:dem":2200,
    "gn:feature_class":"P",
    "gn:feature_code":"PPL",
    "gn:name":"Quibal\u00e1",
    "gn:population":0,
    "gn:timezone":"America/Guatemala",
    "iso:country":"GT",
    "name:spa_x_preferred":[
        "Quibal\u00e1"
    ],
    "wof:name":"Quibala",
    "wof:placetype":"locality"
},
  "geometry": {"coordinates":[-91.03363,15.11348],"type":"Point"}
}