{
  "type": "Feature",
  "properties": {
    "gn:admin1_code":"14",
    "gn:asciiname":"Quibala",
    "gn:country_code":"GT",
    "gn:dem":2200,
    "gn:feature_class":"P",
    "gn:feature_code":"PPL",
    "gn:name":"Quibal\u00e1",
    "gn:population":0,
    "gn:timezone":"America/Guatemala",
    "iso:country":"GT",
    "name:ara_x_preferred":[
        "\u0643\u0648\u064a\u0628\u0627\u0644\u0627"
    ],
    "name:azb_x_preferred":[
        "\u06a9\u0648\u06cc\u0628\u0644\u0627"
    ],
    "name:ben_x_preferred":[
        "\u0995\u09c1\u0987\u09ac\u09be\u09b2\u09be"
    ],
    "name:cat_x_preferred":[
        "Quibala"
    ],
    "name:deu_x_preferred":[
        "Quibala"
    ],
    "name:ell_x_preferred":[
        "\u039a\u03b9\u03bc\u03c0\u03ac\u03bb\u03b1"
    ],
    "name:fas_x_preferred":[
        "\u06a9\u0648\u06cc\u0628\u0644\u0627"
    ],
    "name:fra_x_preferred":[
        "Quibala"
    ],
    "name:heb_x_preferred":[
        "\u05e7\u05d9\u05d1\u05dc\u05d4"
    ],
    "name:hin_x_preferred":[
        "\u0915\u094d\u0935\u093f\u092c\u093e\u0932\u093e"
    ],
    "name:hun_x_preferred":[
        "Quibala"
    ],
    "name:ind_x_preferred":[
        "Quibala"
    ],
    "name:ita_x_preferred":[
        "Kibala"
    ],
    "name:kor_x_preferred":[
        "\ud0a4\ubc1c\ub77c"
    ],
    "name:por_x_preferred":[
        "Quibala"
    ],
    "name:rus_x_preferred":[
        "\u041a\u0438\u0431\u0430\u043b\u0430"
    ],
    "name:spa_x_preferred":[
        "Quibal\u00e1"
    ],
    "name:spa_x_variant":[
        "Quibala"
    ],
    "name:tur_x_preferred":[
        "Quibala"
    ],
    "name:ukr_x_preferred":[
        "\u041a\u0432\u0456\u0431\u0430\u043b\u0430"
    ],
    "name:urd_x_preferred":[
        "\u06a9\u06cc\u0648\u0628\u0627\u0644\u0627"
    ],
    "name:vie_x_preferred":[
        "Quibala"
    ],
    "name:zho_x_preferred":[
        "\u57fa\u5df4\u62c9"
    ],
    "wof:name":"Quibala",
    "wof:placetype":"locality"
},
  "geometry": {"coordinates":[-91.03363,15.11348],"type":"Point"}
}