{
  "type": "Feature",
  "properties": {
    "gn:admin1_code":"17",
    "gn:asciiname":"Agua Tibia",
    "gn:country_code":"GT",
    "gn:dem":2381,
    "gn:feature_class":"P",
    "gn:feature_code":"PPL",
    "gn:name":"Agua Tibia",
    "gn:population":0,
    "gn:timezone":"America/Guatemala",
    "iso:country":"GT",
    "name:spa_x_preferred":[
        "Agua Tibia"
    ],
    "wof:name":"Agua Tibia",
    "wof:placetype":"locality"
},
  "geometry": {"coordinates":[-91.76412000000001,15.0747],"type":"Point"}
}