{
  "type": "Feature",
  "properties": {
    "gn:admin1_code":"17",
    "gn:asciiname":"Ciudad de Los Locos",
    "gn:country_code":"GT",
    "gn:dem":7,
    "gn:feature_class":"P",
    "gn:feature_code":"PPL",
    "gn:name":"Ciudad de Los Locos",
    "gn:population":0,
    "gn:timezone":"America/Guatemala",
    "iso:country":"GT",
    "name:spa_x_preferred":[
        "Ciudad de Los Locos"
    ],
    "name:spa_x_variant":[
        "Ciudad de Los Logos"
    ],
    "wof:name":"Ciudad de Los Locos",
    "wof:placetype":"locality"
},
  "geometry": {"coordinates":[-92.16913,14.49151],"type":"Point"}
}