{
  "type": "Feature",
  "properties": {
    "gn:admin1_code":"11",
    "gn:asciiname":"El Resgate",
    "gn:country_code":"GT",
    "gn:dem":630,
    "gn:feature_class":"P",
    "gn:feature_code":"PPL",
    "gn:name":"El Resgate",
    "gn:population":0,
    "gn:timezone":"America/Guatemala",
    "iso:country":"GT",
    "wof:name":"El Resgate",
    "wof:placetype":"locality"
},
  "geometry": {"coordinates":[-89.75,14.03333],"type":"Point"}
}