{
  "type": "Feature",
  "properties": {
    "gn:admin1_code":"09",
    "gn:asciiname":"Merendoncito",
    "gn:country_code":"GT",
    "gn:dem":843,
    "gn:feature_class":"P",
    "gn:feature_code":"PPL",
    "gn:name":"Merendoncito",
    "gn:population":0,
    "gn:timezone":"America/Guatemala",
    "iso:country":"GT",
    "wof:name":"Merendoncito",
    "wof:placetype":"locality"
},
  "geometry": {"coordinates":[-88.60444,15.42417],"type":"Point"}
}