{
  "type": "Feature",
  "properties": {
    "gn:admin1_code":"13",
    "gn:asciiname":"Chiquisis",
    "gn:country_code":"GT",
    "gn:dem":2696,
    "gn:feature_class":"P",
    "gn:feature_code":"PPL",
    "gn:name":"Chiquisis",
    "gn:population":0,
    "gn:timezone":"America/Guatemala",
    "iso:country":"GT",
    "name:spa_x_preferred":[
        "Chiquisis"
    ],
    "wof:name":"Chiquisis",
    "wof:placetype":"locality"
},
  "geometry": {"coordinates":[-91.57134000000001,15.10031],"type":"Point"}
}