{
  "type": "Feature",
  "properties": {
    "gn:admin1_code":"17",
    "gn:asciiname":"Barrio Villa Hermosa",
    "gn:country_code":"GT",
    "gn:dem":2447,
    "gn:feature_class":"P",
    "gn:feature_code":"PPL",
    "gn:name":"Barrio Villa Hermosa",
    "gn:population":0,
    "gn:timezone":"America/Guatemala",
    "iso:country":"GT",
    "name:spa_x_preferred":[
        "Barrio Villa Hermosa"
    ],
    "wof:name":"Barrio Villa Hermosa",
    "wof:placetype":"locality"
},
  "geometry": {"coordinates":[-92.10086,15.23143],"type":"Point"}
}