{
  "type": "Feature",
  "properties": {
    "gn:admin1_code":"21",
    "gn:asciiname":"Sajcamilaj",
    "gn:country_code":"GT",
    "gn:dem":1788,
    "gn:feature_class":"P",
    "gn:feature_code":"PPL",
    "gn:name":"Sajcamilaj",
    "gn:population":0,
    "gn:timezone":"America/Guatemala",
    "iso:country":"GT",
    "name:spa_x_preferred":[
        "Sajcamilaj"
    ],
    "wof:name":"Sajcamilaj",
    "wof:placetype":"locality"
},
  "geometry": {"coordinates":[-91.30087,15.13365],"type":"Point"}
}