{
  "type": "Feature",
  "properties": {
    "gn:admin1_code":"17",
    "gn:asciiname":"Nueva Esperanza",
    "gn:country_code":"GT",
    "gn:dem":3328,
    "gn:feature_class":"P",
    "gn:feature_code":"PPL",
    "gn:name":"Nueva Esperanza",
    "gn:population":0,
    "gn:timezone":"America/Guatemala",
    "iso:country":"GT",
    "name:spa_x_preferred":[
        "Nueva Esperanza"
    ],
    "wof:name":"Nueva Esperanza",
    "wof:placetype":"locality"
},
  "geometry": {"coordinates":[-91.94928,15.20848],"type":"Point"}
}