{
  "type": "Feature",
  "properties": {
    "gn:admin1_code":"03",
    "gn:asciiname":"Palama",
    "gn:country_code":"GT",
    "gn:dem":2284,
    "gn:feature_class":"P",
    "gn:feature_code":"PPL",
    "gn:name":"Palam\u00e1",
    "gn:population":0,
    "gn:timezone":"America/Guatemala",
    "iso:country":"GT",
    "wof:name":"Palama",
    "wof:placetype":"locality"
},
  "geometry": {"coordinates":[-91.01667,14.86667],"type":"Point"}
}