{
  "type": "Feature",
  "properties": {
    "gn:admin1_code":"07",
    "gn:asciiname":"Los Chorritos",
    "gn:country_code":"GT",
    "gn:dem":1917,
    "gn:feature_class":"P",
    "gn:feature_code":"PPL",
    "gn:name":"Los Chorritos",
    "gn:population":0,
    "gn:timezone":"America/Guatemala",
    "iso:country":"GT",
    "wof:name":"Los Chorritos",
    "wof:placetype":"locality"
},
  "geometry": {"coordinates":[-90.26667,14.68333],"type":"Point"}
}