{
  "type": "Feature",
  "properties": {
    "gn:admin1_code":"18",
    "gn:asciiname":"El Paredon",
    "gn:country_code":"GT",
    "gn:dem":10,
    "gn:feature_class":"P",
    "gn:feature_code":"PPL",
    "gn:name":"El Pared\u00f3n",
    "gn:population":0,
    "gn:timezone":"America/Guatemala",
    "iso:country":"GT",
    "wof:name":"El Paredon",
    "wof:placetype":"locality"
},
  "geometry": {"coordinates":[-90.25611000000001,13.79889],"type":"Point"}
}