{
  "type": "Feature",
  "properties": {
    "gn:admin1_code":"01",
    "gn:asciiname":"Las Flores",
    "gn:country_code":"GT",
    "gn:dem":164,
    "gn:feature_class":"P",
    "gn:feature_code":"PPL",
    "gn:name":"Las Flores",
    "gn:population":0,
    "gn:timezone":"America/Guatemala",
    "iso:country":"GT",
    "name:cat_x_preferred":[
        "Las Flores"
    ],
    "name:ceb_x_preferred":[
        "Las Flores"
    ],
    "name:deu_x_preferred":[
        "Las Flores"
    ],
    "name:fra_x_preferred":[
        "Las Flores"
    ],
    "name:ita_x_preferred":[
        "Las Flores"
    ],
    "name:nds_x_preferred":[
        "Las Flores"
    ],
    "name:nld_x_preferred":[
        "Las Flores"
    ],
    "name:por_x_preferred":[
        "Las Flores"
    ],
    "name:spa_x_preferred":[
        "Las Flores"
    ],
    "name:srp_x_preferred":[
        "\u041b\u0430\u0441 \u0424\u043b\u043e\u0440\u0435\u0441"
    ],
    "name:swe_x_preferred":[
        "Las Flores"
    ],
    "name:ukr_x_preferred":[
        "\u041b\u0430\u0441-\u0424\u043b\u043e\u0440\u0435\u0441"
    ],
    "wof:name":"Las Flores",
    "wof:placetype":"locality"
},
  "geometry": {"coordinates":[-90.6049,16.0455],"type":"Point"}
}