{
  "type": "Feature",
  "properties": {
    "gn:admin1_code":"17",
    "gn:asciiname":"Ojetenam",
    "gn:country_code":"GT",
    "gn:dem":2661,
    "gn:feature_class":"P",
    "gn:feature_code":"PPL",
    "gn:name":"Ojetenam",
    "gn:population":0,
    "gn:timezone":"America/Guatemala",
    "iso:country":"GT",
    "name:spa_x_preferred":[
        "Ojetenam"
    ],
    "wof:name":"Ojetenam",
    "wof:placetype":"locality"
},
  "geometry": {"coordinates":[-91.95859,15.24934],"type":"Point"}
}