{
  "type": "Feature",
  "properties": {
    "gn:admin1_code":"17",
    "gn:asciiname":"Chiquila",
    "gn:country_code":"GT",
    "gn:dem":2353,
    "gn:feature_class":"P",
    "gn:feature_code":"PPL",
    "gn:name":"Chiquil\u00e1",
    "gn:population":0,
    "gn:timezone":"America/Guatemala",
    "iso:country":"GT",
    "name:spa_x_preferred":[
        "Chiquila"
    ],
    "name:spa_x_variant":[
        "Chiquil\u00e1"
    ],
    "wof:name":"Chiquila",
    "wof:placetype":"locality"
},
  "geometry": {"coordinates":[-92.05419999999999,15.24851],"type":"Point"}
}