{
  "type": "Feature",
  "properties": {
    "gn:admin1_code":"13",
    "gn:asciiname":"La Empalizada",
    "gn:country_code":"GT",
    "gn:dem":2689,
    "gn:feature_class":"P",
    "gn:feature_code":"PPL",
    "gn:name":"La Empalizada",
    "gn:population":0,
    "gn:timezone":"America/Guatemala",
    "iso:country":"GT",
    "name:spa_x_preferred":[
        "La Empalizada"
    ],
    "wof:name":"La Empalizada",
    "wof:placetype":"locality"
},
  "geometry": {"coordinates":[-91.63467,15.03457],"type":"Point"}
}