{
  "type": "Feature",
  "properties": {
    "gn:admin1_code":"14",
    "gn:asciiname":"Patzajel",
    "gn:country_code":"GT",
    "gn:dem":1219,
    "gn:feature_class":"P",
    "gn:feature_code":"PPL",
    "gn:name":"Patzajel",
    "gn:population":0,
    "gn:timezone":"America/Guatemala",
    "iso:country":"GT",
    "name:spa_x_preferred":[
        "Patzajel"
    ],
    "wof:name":"Patzajel",
    "wof:placetype":"locality"
},
  "geometry": {"coordinates":[-91.13446,15.27393],"type":"Point"}
}