{
  "type": "Feature",
  "properties": {
    "gn:admin1_code":"14",
    "gn:asciiname":"Chemala",
    "gn:country_code":"GT",
    "gn:dem":1921,
    "gn:feature_class":"P",
    "gn:feature_code":"PPL",
    "gn:name":"Chemal\u00e1",
    "gn:population":0,
    "gn:timezone":"America/Guatemala",
    "iso:country":"GT",
    "name:spa_x_preferred":[
        "Chemal\u00e1"
    ],
    "wof:name":"Chemala",
    "wof:placetype":"locality"
},
  "geometry": {"coordinates":[-91.16034000000001,15.43234],"type":"Point"}
}