{
  "type": "Feature",
  "properties": {
    "gn:admin1_code":"13",
    "gn:asciiname":"Paso Hondo",
    "gn:country_code":"GT",
    "gn:dem":1939,
    "gn:feature_class":"P",
    "gn:feature_code":"PPL",
    "gn:name":"Paso Hondo",
    "gn:population":0,
    "gn:timezone":"America/Guatemala",
    "iso:country":"GT",
    "name:spa_x_preferred":[
        "Paso Hondo"
    ],
    "wof:name":"Paso Hondo",
    "wof:placetype":"locality"
},
  "geometry": {"coordinates":[-91.53066,15.19641],"type":"Point"}
}