{
  "type": "Feature",
  "properties": {
    "gn:admin1_code":"21",
    "gn:asciiname":"San Luis Cajula",
    "gn:country_code":"GT",
    "gn:dem":1703,
    "gn:feature_class":"P",
    "gn:feature_code":"PPL",
    "gn:name":"San Luis Cajul\u00e1",
    "gn:population":0,
    "gn:timezone":"America/Guatemala",
    "iso:country":"GT",
    "name:spa_x_preferred":[
        "San Luis Cajul\u00e1"
    ],
    "wof:name":"San Luis Cajula",
    "wof:placetype":"locality"
},
  "geometry": {"coordinates":[-91.37039,15.15649],"type":"Point"}
}