{
  "type": "Feature",
  "properties": {
    "gn:admin1_code":"17",
    "gn:asciiname":"Loma de Barrios",
    "gn:country_code":"GT",
    "gn:dem":2992,
    "gn:feature_class":"P",
    "gn:feature_code":"PPLL",
    "gn:name":"Loma de Barrios",
    "gn:population":0,
    "gn:timezone":"America/Guatemala",
    "iso:country":"GT",
    "name:spa_x_preferred":[
        "Loma de Barrios"
    ],
    "wof:name":"Loma de Barrios",
    "wof:placetype":"locality"
},
  "geometry": {"coordinates":[-91.97886,15.23912],"type":"Point"}
}