{
  "type": "Feature",
  "properties": {
    "gn:admin1_code":"04",
    "gn:asciiname":"San Cayetano",
    "gn:country_code":"GT",
    "gn:dem":873,
    "gn:feature_class":"P",
    "gn:feature_code":"PPL",
    "gn:name":"San Cayetano",
    "gn:population":0,
    "gn:timezone":"America/Guatemala",
    "iso:country":"GT",
    "name:ceb_x_preferred":[
        "San Cayetano"
    ],
    "name:deu_x_preferred":[
        "San Cayetano"
    ],
    "name:fra_x_preferred":[
        "San Cayetano"
    ],
    "name:ita_x_preferred":[
        "San Cayetano"
    ],
    "name:msa_x_preferred":[
        "San Cayetano"
    ],
    "name:nld_x_preferred":[
        "San Cayetano"
    ],
    "name:por_x_preferred":[
        "San Cayetano"
    ],
    "name:sco_x_preferred":[
        "San Cayetano"
    ],
    "name:spa_x_preferred":[
        "San Cayetano"
    ],
    "name:swe_x_preferred":[
        "San Cayetano"
    ],
    "name:war_x_preferred":[
        "San Cayetano"
    ],
    "wof:name":"San Cayetano",
    "wof:placetype":"locality"
},
  "geometry": {"coordinates":[-89.59999999999999,14.66667],"type":"Point"}
}