{
  "type": "Feature",
  "properties": {
    "gn:admin1_code":"08",
    "gn:asciiname":"Teninquim",
    "gn:country_code":"GT",
    "gn:dem":2532,
    "gn:feature_class":"P",
    "gn:feature_code":"PPL",
    "gn:name":"Teninquim",
    "gn:population":0,
    "gn:timezone":"America/Guatemala",
    "iso:country":"GT",
    "name:spa_x_preferred":[
        "Teninqu\u00edn"
    ],
    "name:spa_x_variant":[
        "Teninquim"
    ],
    "wof:name":"Teninquim",
    "wof:placetype":"locality"
},
  "geometry": {"coordinates":[-92.0714,15.28847],"type":"Point"}
}