{
  "type": "Feature",
  "properties": {
    "gn:admin1_code":"10",
    "gn:asciiname":"Fuentes de la Montana",
    "gn:cc2":"GT",
    "gn:country_code":"GT",
    "gn:dem":1851,
    "gn:feature_class":"P",
    "gn:feature_code":"PPL",
    "gn:name":"Fuentes de la Monta\u00f1a",
    "gn:population":0,
    "gn:timezone":"America/Guatemala",
    "iso:country":"GT",
    "name:und_x_variant":[
        "Puente de la Monta\u00f1a",
        "La Puente",
        "La Fuente de la Monta\u00f1a",
        "Fuentes de la Monta\u00f1a"
    ],
    "wof:name":"Fuentes de la Montana",
    "wof:placetype":"locality"
},
  "geometry": {"coordinates":[-90.06667,14.61667],"type":"Point"}
}