{
  "type": "Feature",
  "properties": {
    "gn:admin1_code":"05",
    "gn:asciiname":"Los Cerritos",
    "gn:cc2":"GT",
    "gn:country_code":"GT",
    "gn:dem":759,
    "gn:feature_class":"P",
    "gn:feature_code":"PPL",
    "gn:name":"Los Cerritos",
    "gn:population":0,
    "gn:timezone":"America/Guatemala",
    "iso:country":"GT",
    "name:und_x_variant":[
        "Cerritos",
        "Los Cerritos"
    ],
    "wof:name":"Los Cerritos",
    "wof:placetype":"locality"
},
  "geometry": {"coordinates":[-90.11667,14.76667],"type":"Point"}
}