{
  "type": "Feature",
  "properties": {
    "gn:admin1_code":"08",
    "gn:asciiname":"Sacchoch",
    "gn:country_code":"GT",
    "gn:dem":3585,
    "gn:feature_class":"P",
    "gn:feature_code":"PPL",
    "gn:name":"Sacchoch",
    "gn:population":0,
    "gn:timezone":"America/Guatemala",
    "iso:country":"GT",
    "name:spa_x_preferred":[
        "Sacchoch"
    ],
    "wof:name":"Sacchoch",
    "wof:placetype":"locality"
},
  "geometry": {"coordinates":[-91.53503000000001,15.53388],"type":"Point"}
}