{
  "type": "Feature",
  "properties": {
    "gn:admin1_code":"14",
    "gn:asciiname":"Xecoja",
    "gn:country_code":"GT",
    "gn:dem":2305,
    "gn:feature_class":"P",
    "gn:feature_code":"PPL",
    "gn:name":"Xecoj\u00e1",
    "gn:population":0,
    "gn:timezone":"America/Guatemala",
    "iso:country":"GT",
    "wof:name":"Xecoja",
    "wof:placetype":"locality"
},
  "geometry": {"coordinates":[-91.08333,14.88333],"type":"Point"}
}