{
  "type": "Feature",
  "properties": {
    "gn:admin1_code":"17",
    "gn:asciiname":"Loma de Huitzitzil",
    "gn:country_code":"GT",
    "gn:dem":329,
    "gn:feature_class":"P",
    "gn:feature_code":"PPL",
    "gn:name":"Loma de Huitzitzil",
    "gn:population":0,
    "gn:timezone":"America/Guatemala",
    "iso:country":"GT",
    "name:und_x_variant":[
        "Loma Huitzitzil"
    ],
    "wof:name":"Loma de Huitzitzil",
    "wof:placetype":"locality"
},
  "geometry": {"coordinates":[-92.06211999999999,14.86489],"type":"Point"}
}