{
  "type": "Feature",
  "properties": {
    "gn:admin1_code":"08",
    "gn:asciiname":"Queva",
    "gn:country_code":"GT",
    "gn:dem":1341,
    "gn:feature_class":"P",
    "gn:feature_code":"PPL",
    "gn:name":"Quev\u00e1",
    "gn:population":0,
    "gn:timezone":"America/Guatemala",
    "iso:country":"GT",
    "name:und_x_variant":[
        "Cueva",
        "Quev\u00e1"
    ],
    "wof:name":"Queva",
    "wof:placetype":"locality"
},
  "geometry": {"coordinates":[-91.92059,15.41487],"type":"Point"}
}