{
  "type": "Feature",
  "properties": {
    "gn:admin1_code":"09",
    "gn:admin2_code":"3593233.0",
    "gn:asciiname":"El Rico",
    "gn:country_code":"GT",
    "gn:dem":103,
    "gn:feature_class":"P",
    "gn:feature_code":"PPL",
    "gn:name":"El Rico",
    "gn:population":0,
    "gn:timezone":"America/Guatemala",
    "iso:country":"GT",
    "wof:name":"El Rico",
    "wof:placetype":"locality"
},
  "geometry": {"coordinates":[-89.11421999999997,15.24664],"type":"Point"}
}