{
  "type": "Feature",
  "properties": {
    "gn:admin1_code":"08",
    "gn:asciiname":"San Pablo",
    "gn:country_code":"GT",
    "gn:dem":3142,
    "gn:feature_class":"P",
    "gn:feature_code":"PPL",
    "gn:name":"San Pablo",
    "gn:population":0,
    "gn:timezone":"America/Guatemala",
    "iso:country":"GT",
    "name:spa_x_preferred":[
        "San Pablo"
    ],
    "wof:name":"San Pablo",
    "wof:placetype":"locality"
},
  "geometry": {"coordinates":[-91.4534,15.41825],"type":"Point"}
}