{
  "type": "Feature",
  "properties": {
    "gn:admin1_code":"22",
    "gn:asciiname":"Manzanote",
    "gn:country_code":"GT",
    "gn:dem":489,
    "gn:feature_class":"P",
    "gn:feature_code":"PPL",
    "gn:name":"Manzanote",
    "gn:population":0,
    "gn:timezone":"America/Guatemala",
    "iso:country":"GT",
    "wof:name":"Manzanote",
    "wof:placetype":"locality"
},
  "geometry": {"coordinates":[-89.83333,14.98333],"type":"Point"}
}