{
  "type": "Feature",
  "properties": {
    "gn:admin1_code":"08",
    "gn:asciiname":"La Haciendita",
    "gn:country_code":"GT",
    "gn:dem":1862,
    "gn:feature_class":"P",
    "gn:feature_code":"PPLL",
    "gn:name":"La Haciendita",
    "gn:population":0,
    "gn:timezone":"America/Guatemala",
    "iso:country":"GT",
    "name:spa_x_preferred":[
        "La Haciendita"
    ],
    "wof:name":"La Haciendita",
    "wof:placetype":"locality"
},
  "geometry": {"coordinates":[-91.95162999999999,15.3702],"type":"Point"}
}