{
  "type": "Feature",
  "properties": {
    "gn:admin1_code":"18",
    "gn:asciiname":"Madre Vieja",
    "gn:country_code":"GT",
    "gn:dem":6,
    "gn:feature_class":"P",
    "gn:feature_code":"PPL",
    "gn:name":"Madre Vieja",
    "gn:population":0,
    "gn:timezone":"America/Guatemala",
    "iso:country":"GT",
    "wof:name":"Madre Vieja",
    "wof:placetype":"locality"
},
  "geometry": {"coordinates":[-90.57889,13.92194],"type":"Point"}
}