{
  "type": "Feature",
  "properties": {
    "gn:admin1_code":"08",
    "gn:asciiname":"Bella Linda",
    "gn:country_code":"GT",
    "gn:dem":766,
    "gn:feature_class":"P",
    "gn:feature_code":"PPL",
    "gn:name":"Bella Linda",
    "gn:population":0,
    "gn:timezone":"America/Guatemala",
    "iso:country":"GT",
    "name:spa_x_preferred":[
        "Bella Linda"
    ],
    "wof:name":"Bella Linda",
    "wof:placetype":"locality"
},
  "geometry": {"coordinates":[-91.40224000000001,16.06322],"type":"Point"}
}