{
  "type": "Feature",
  "properties": {
    "gn:admin1_code":"08",
    "gn:asciiname":"Nubila",
    "gn:country_code":"GT",
    "gn:dem":802,
    "gn:feature_class":"P",
    "gn:feature_code":"PPL",
    "gn:name":"Nubil\u00e1",
    "gn:population":0,
    "gn:timezone":"America/Guatemala",
    "iso:country":"GT",
    "name:spa_x_preferred":[
        "Nubil\u00e1"
    ],
    "wof:name":"Nubila",
    "wof:placetype":"locality"
},
  "geometry": {"coordinates":[-91.77596,15.74909],"type":"Point"}
}