{
  "type": "Feature",
  "properties": {
    "gn:admin1_code":"20",
    "gn:asciiname":"Masa",
    "gn:country_code":"GT",
    "gn:dem":817,
    "gn:feature_class":"P",
    "gn:feature_code":"PPL",
    "gn:name":"Mas\u00e1",
    "gn:population":0,
    "gn:timezone":"America/Guatemala",
    "iso:country":"GT",
    "wof:name":"Masa",
    "wof:placetype":"locality"
},
  "geometry": {"coordinates":[-91.40000000000001,14.63333],"type":"Point"}
}