{
  "type": "Feature",
  "properties": {
    "gn:admin1_code":"20",
    "gn:asciiname":"Masa",
    "gn:country_code":"GT",
    "gn:dem":817,
    "gn:feature_class":"P",
    "gn:feature_code":"PPL",
    "gn:name":"Mas\u00e1",
    "gn:population":0,
    "gn:timezone":"America/Guatemala",
    "iso:country":"GT",
    "name:fra_x_preferred":[
        "Masa"
    ],
    "name:kor_x_preferred":[
        "\ub9c8\uc0ac"
    ],
    "name:msa_x_preferred":[
        "Masa"
    ],
    "name:ukr_x_preferred":[
        "\u041c\u0430\u0441\u0430"
    ],
    "name:zho_x_preferred":[
        "\u9a6c\u8428"
    ],
    "wof:name":"Masa",
    "wof:placetype":"locality"
},
  "geometry": {"coordinates":[-91.40000000000001,14.63333],"type":"Point"}
}