{
  "type": "Feature",
  "properties": {
    "gn:admin1_code":"13",
    "gn:asciiname":"Toj Guavil",
    "gn:cc2":"GT",
    "gn:country_code":"GT",
    "gn:dem":2727,
    "gn:feature_class":"P",
    "gn:feature_code":"PPL",
    "gn:name":"Toj Guavil",
    "gn:population":0,
    "gn:timezone":"America/Guatemala",
    "iso:country":"GT",
    "name:und_x_variant":[
        "Toj Guabil",
        "Toj Guavil"
    ],
    "wof:name":"Toj Guavil",
    "wof:placetype":"locality"
},
  "geometry": {"coordinates":[-91.71666999999999,14.91667],"type":"Point"}
}