{
  "type": "Feature",
  "properties": {
    "gn:admin1_code":"03",
    "gn:asciiname":"Estancia de La Virgen",
    "gn:cc2":"GT",
    "gn:country_code":"GT",
    "gn:dem":1586,
    "gn:feature_class":"P",
    "gn:feature_code":"PPL",
    "gn:name":"Estancia de La Virgen",
    "gn:population":0,
    "gn:timezone":"America/Guatemala",
    "iso:country":"GT",
    "name:und_x_variant":[
        "La Virgen",
        "Estancia de La Virgen"
    ],
    "wof:name":"Estancia de La Virgen",
    "wof:placetype":"locality"
},
  "geometry": {"coordinates":[-90.73333,14.78333],"type":"Point"}
}