{
  "type": "Feature",
  "properties": {
    "gn:admin1_code":"08",
    "gn:asciiname":"Xacal",
    "gn:country_code":"GT",
    "gn:dem":2493,
    "gn:feature_class":"P",
    "gn:feature_code":"PPL",
    "gn:name":"Xacal",
    "gn:population":0,
    "gn:timezone":"America/Guatemala",
    "iso:country":"GT",
    "name:spa_x_preferred":[
        "Xacal"
    ],
    "wof:name":"Xacal",
    "wof:placetype":"locality"
},
  "geometry": {"coordinates":[-91.45017,15.61455],"type":"Point"}
}