{
  "type": "Feature",
  "properties": {
    "gn:admin1_code":"08",
    "gn:asciiname":"El Palmar",
    "gn:country_code":"GT",
    "gn:dem":2203,
    "gn:feature_class":"P",
    "gn:feature_code":"PPLL",
    "gn:name":"El Palmar",
    "gn:population":0,
    "gn:timezone":"America/Guatemala",
    "iso:country":"GT",
    "name:ceb_x_preferred":[
        "El Palmar"
    ],
    "name:fra_x_preferred":[
        "El Palmar"
    ],
    "name:glg_x_preferred":[
        "El Palmar"
    ],
    "name:lit_x_preferred":[
        "El Palmaras"
    ],
    "name:spa_x_preferred":[
        "El Palmar"
    ],
    "name:srp_x_preferred":[
        "\u0415\u043b \u041f\u0430\u043b\u043c\u0430\u0440"
    ],
    "name:swe_x_preferred":[
        "El Palmar"
    ],
    "wof:name":"El Palmar",
    "wof:placetype":"locality"
},
  "geometry": {"coordinates":[-91.87307,15.44355],"type":"Point"}
}