{
  "type": "Feature",
  "properties": {
    "gn:admin1_code":"14",
    "gn:asciiname":"El Aguacate",
    "gn:cc2":"GT",
    "gn:country_code":"GT",
    "gn:dem":2076,
    "gn:feature_class":"P",
    "gn:feature_code":"PPL",
    "gn:name":"El Aguacate",
    "gn:population":0,
    "gn:timezone":"America/Guatemala",
    "iso:country":"GT",
    "name:und_x_variant":[
        "Aguacate",
        "El Aguacate"
    ],
    "wof:name":"El Aguacate",
    "wof:placetype":"locality"
},
  "geometry": {"coordinates":[-91.01667,15.08333],"type":"Point"}
}