{
  "type": "Feature",
  "properties": {
    "gn:admin1_code":"06",
    "gn:asciiname":"Rio Santiago",
    "gn:country_code":"GT",
    "gn:dem":452,
    "gn:feature_class":"P",
    "gn:feature_code":"PPL",
    "gn:name":"R\u00edo Santiago",
    "gn:population":0,
    "gn:timezone":"America/Guatemala",
    "iso:country":"GT",
    "name:ceb_x_preferred":[
        "Rio Santiago"
    ],
    "name:swe_x_preferred":[
        "Rio Santiago"
    ],
    "wof:name":"Rio Santiago",
    "wof:placetype":"locality"
},
  "geometry": {"coordinates":[-91.01667,14.35],"type":"Point"}
}