{
  "type": "Feature",
  "properties": {
    "gn:admin1_code":"17",
    "gn:asciiname":"Las Tablas",
    "gn:country_code":"GT",
    "gn:dem":2960,
    "gn:feature_class":"P",
    "gn:feature_code":"PPL",
    "gn:name":"Las Tablas",
    "gn:population":0,
    "gn:timezone":"America/Guatemala",
    "iso:country":"GT",
    "name:spa_x_preferred":[
        "Las Tablas"
    ],
    "wof:name":"Las Tablas",
    "wof:placetype":"locality"
},
  "geometry": {"coordinates":[-91.88606,15.28575],"type":"Point"}
}