{
  "type": "Feature",
  "properties": {
    "gn:admin1_code":"12",
    "gn:asciiname":"Puerta Negra",
    "gn:country_code":"GT",
    "gn:dem":131,
    "gn:feature_class":"P",
    "gn:feature_code":"PPL",
    "gn:name":"Puerta Negra",
    "gn:population":0,
    "gn:timezone":"America/Guatemala",
    "iso:country":"GT",
    "name:spa_x_preferred":[
        "Puerta Negra"
    ],
    "wof:name":"Puerta Negra",
    "wof:placetype":"locality"
},
  "geometry": {"coordinates":[-90.65903,16.74397],"type":"Point"}
}