{
  "type": "Feature",
  "properties": {
    "gn:admin1_code":"08",
    "gn:asciiname":"Rio Negro",
    "gn:country_code":"GT",
    "gn:dem":327,
    "gn:feature_class":"P",
    "gn:feature_code":"PPL",
    "gn:name":"R\u00edo Negro",
    "gn:population":0,
    "gn:timezone":"America/Guatemala",
    "iso:country":"GT",
    "name:spa_x_preferred":[
        "R\u00edo Negro"
    ],
    "wof:name":"Rio Negro",
    "wof:placetype":"locality"
},
  "geometry": {"coordinates":[-91.17775,15.85502],"type":"Point"}
}