{
  "type": "Feature",
  "properties": {
    "gn:admin1_code":"12",
    "gn:asciiname":"Tiquinsacan",
    "gn:cc2":"GT",
    "gn:country_code":"GT",
    "gn:dem":279,
    "gn:feature_class":"P",
    "gn:feature_code":"PPL",
    "gn:name":"Tiquinsac\u00e1n",
    "gn:population":0,
    "gn:timezone":"America/Guatemala",
    "iso:country":"GT",
    "name:und_x_variant":[
        "Tikan Sakan",
        "Tecelchac\u00e1n",
        "Tiquinsac\u00e1n"
    ],
    "wof:name":"Tiquinsacan",
    "wof:placetype":"locality"
},
  "geometry": {"coordinates":[-89.26666999999998,17.03333],"type":"Point"}
}