{
  "type": "Feature",
  "properties": {
    "gn:admin1_code":"12",
    "gn:asciiname":"Jovente Abajo",
    "gn:country_code":"GT",
    "gn:dem":367,
    "gn:feature_class":"P",
    "gn:feature_code":"PPL",
    "gn:name":"Jovent\u00e9 Abajo",
    "gn:population":0,
    "gn:timezone":"America/Guatemala",
    "iso:country":"GT",
    "wof:name":"Jovente Abajo",
    "wof:placetype":"locality"
},
  "geometry": {"coordinates":[-89.28971999999997,16.18306],"type":"Point"}
}