{
  "type": "Feature",
  "properties": {
    "gn:admin1_code":"18",
    "gn:asciiname":"Rodeo Alto",
    "gn:cc2":"GT",
    "gn:country_code":"GT",
    "gn:dem":717,
    "gn:feature_class":"P",
    "gn:feature_code":"PPL",
    "gn:name":"Rodeo Alto",
    "gn:population":0,
    "gn:timezone":"America/Guatemala",
    "iso:country":"GT",
    "name:und_x_variant":[
        "Rodeo",
        "Rodeo Alto"
    ],
    "wof:name":"Rodeo Alto",
    "wof:placetype":"locality"
},
  "geometry": {"coordinates":[-90.31667,14.26667],"type":"Point"}
}