{
  "type": "Feature",
  "properties": {
    "gn:admin1_code":"13",
    "gn:asciiname":"Colonia Chiquita",
    "gn:country_code":"GT",
    "gn:dem":2647,
    "gn:feature_class":"P",
    "gn:feature_code":"PPL",
    "gn:name":"Colonia Chiquita",
    "gn:population":0,
    "gn:timezone":"America/Guatemala",
    "iso:country":"GT",
    "wof:name":"Colonia Chiquita",
    "wof:placetype":"locality"
},
  "geometry": {"coordinates":[-91.68333,14.98333],"type":"Point"}
}