{
  "type": "Feature",
  "properties": {
    "gn:admin1_code":"03",
    "gn:asciiname":"Chichoy",
    "gn:country_code":"GT",
    "gn:dem":2117,
    "gn:feature_class":"P",
    "gn:feature_code":"PPL",
    "gn:name":"Chichoy",
    "gn:population":0,
    "gn:timezone":"America/Guatemala",
    "iso:country":"GT",
    "wof:name":"Chichoy",
    "wof:placetype":"locality"
},
  "geometry": {"coordinates":[-91.06667,14.68333],"type":"Point"}
}