{
  "type": "Feature",
  "properties": {
    "gn:admin1_code":"14",
    "gn:asciiname":"Tzancorral",
    "gn:country_code":"GT",
    "gn:dem":1960,
    "gn:feature_class":"P",
    "gn:feature_code":"PPLL",
    "gn:name":"Tzancorral",
    "gn:population":0,
    "gn:timezone":"America/Guatemala",
    "iso:country":"GT",
    "name:spa_x_preferred":[
        "Tzancorral"
    ],
    "wof:name":"Tzancorral",
    "wof:placetype":"locality"
},
  "geometry": {"coordinates":[-91.20419,15.12079],"type":"Point"}
}