{
  "type": "Feature",
  "properties": {
    "gn:admin1_code":"08",
    "gn:asciiname":"Rio Blanco La Vega",
    "gn:country_code":"GT",
    "gn:dem":1429,
    "gn:feature_class":"P",
    "gn:feature_code":"PPL",
    "gn:name":"R\u00edo Blanco La Vega",
    "gn:population":0,
    "gn:timezone":"America/Guatemala",
    "iso:country":"GT",
    "name:spa_x_preferred":[
        "R\u00edo Blanco La Vega"
    ],
    "wof:name":"Rio Blanco La Vega",
    "wof:placetype":"locality"
},
  "geometry": {"coordinates":[-91.20868,15.32672],"type":"Point"}
}