{
  "type": "Feature",
  "properties": {
    "gn:admin1_code":"14",
    "gn:asciiname":"Xetzac",
    "gn:country_code":"GT",
    "gn:dem":2314,
    "gn:feature_class":"P",
    "gn:feature_code":"PPL",
    "gn:name":"Xetzac",
    "gn:population":0,
    "gn:timezone":"America/Guatemala",
    "iso:country":"GT",
    "name:spa_x_preferred":[
        "Xetzac"
    ],
    "wof:name":"Xetzac",
    "wof:placetype":"locality"
},
  "geometry": {"coordinates":[-91.0577,15.3541],"type":"Point"}
}