{
  "type": "Feature",
  "properties": {
    "gn:admin1_code":"07",
    "gn:asciiname":"Suacite",
    "gn:cc2":"GT",
    "gn:country_code":"GT",
    "gn:dem":1284,
    "gn:feature_class":"P",
    "gn:feature_code":"PPL",
    "gn:name":"Suacit\u00e9",
    "gn:population":0,
    "gn:timezone":"America/Guatemala",
    "iso:country":"GT",
    "name:und_x_variant":[
        "Concepci\u00f3n Suacit\u00e9",
        "Suacit\u00e9"
    ],
    "wof:name":"Suacite",
    "wof:placetype":"locality"
},
  "geometry": {"coordinates":[-90.61667,14.81667],"type":"Point"}
}