{
  "type": "Feature",
  "properties": {
    "gn:admin1_code":"12",
    "gn:asciiname":"La Mica",
    "gn:country_code":"GT",
    "gn:dem":116,
    "gn:feature_class":"P",
    "gn:feature_code":"PPL",
    "gn:name":"La Mica",
    "gn:population":0,
    "gn:timezone":"America/Guatemala",
    "iso:country":"GT",
    "name:spa_x_preferred":[
        "La Mica"
    ],
    "wof:name":"La Mica",
    "wof:placetype":"locality"
},
  "geometry": {"coordinates":[-90.66495999999999,16.58161],"type":"Point"}
}