{
  "type": "Feature",
  "properties": {
    "gn:admin1_code":"17",
    "gn:asciiname":"Tujelec",
    "gn:country_code":"GT",
    "gn:dem":2643,
    "gn:feature_class":"P",
    "gn:feature_code":"PPL",
    "gn:name":"Tujelec",
    "gn:population":0,
    "gn:timezone":"America/Guatemala",
    "iso:country":"GT",
    "name:spa_x_preferred":[
        "Tujelec"
    ],
    "wof:name":"Tujelec",
    "wof:placetype":"locality"
},
  "geometry": {"coordinates":[-91.80983000000001,15.22341],"type":"Point"}
}