{
  "type": "Feature",
  "properties": {
    "gn:admin1_code":"17",
    "gn:asciiname":"San Jose Suchiate",
    "gn:country_code":"GT",
    "gn:dem":315,
    "gn:feature_class":"P",
    "gn:feature_code":"PPL",
    "gn:name":"San Jos\u00e9 Suchiate",
    "gn:population":0,
    "gn:timezone":"America/Guatemala",
    "iso:country":"GT",
    "name:spa_x_preferred":[
        "San Jos\u00e9 Suchiate"
    ],
    "wof:name":"San Jose Suchiate",
    "wof:placetype":"locality"
},
  "geometry": {"coordinates":[-92.14637999999999,14.95019],"type":"Point"}
}