{
  "type": "Feature",
  "properties": {
    "gn:admin1_code":"08",
    "gn:asciiname":"Pabiltzaj",
    "gn:country_code":"GT",
    "gn:dem":2134,
    "gn:feature_class":"P",
    "gn:feature_code":"PPL",
    "gn:name":"Pabiltzaj",
    "gn:population":0,
    "gn:timezone":"America/Guatemala",
    "iso:country":"GT",
    "name:spa_x_preferred":[
        "Pabiltzaj"
    ],
    "wof:name":"Pabiltzaj",
    "wof:placetype":"locality"
},
  "geometry": {"coordinates":[-91.92281,15.36265],"type":"Point"}
}