{
  "type": "Feature",
  "properties": {
    "gn:admin1_code":"10",
    "gn:asciiname":"Damian",
    "gn:country_code":"GT",
    "gn:dem":1021,
    "gn:feature_class":"P",
    "gn:feature_code":"PPL",
    "gn:name":"Dami\u00e1n",
    "gn:population":0,
    "gn:timezone":"America/Guatemala",
    "iso:country":"GT",
    "wof:name":"Damian",
    "wof:placetype":"locality"
},
  "geometry": {"coordinates":[-89.83333,14.53333],"type":"Point"}
}