{
  "type": "Feature",
  "properties": {
    "gn:admin1_code":"09",
    "gn:asciiname":"Lagartos",
    "gn:country_code":"GT",
    "gn:dem":83,
    "gn:feature_class":"P",
    "gn:feature_code":"PPL",
    "gn:name":"Lagartos",
    "gn:population":0,
    "gn:timezone":"America/Guatemala",
    "iso:country":"GT",
    "name:cat_x_preferred":[
        "Lagartos"
    ],
    "name:ceb_x_preferred":[
        "Lagartos"
    ],
    "name:eus_x_preferred":[
        "Lagartos"
    ],
    "name:fas_x_preferred":[
        "\u0644\u0627\u06af\u0627\u0631\u062a\u0633"
    ],
    "name:fra_x_preferred":[
        "Lagartos"
    ],
    "name:glg_x_preferred":[
        "Lagartos"
    ],
    "name:hun_x_preferred":[
        "Lagartos"
    ],
    "name:ina_x_preferred":[
        "Lagartos"
    ],
    "name:ita_x_preferred":[
        "Lagartos"
    ],
    "name:msa_x_preferred":[
        "Lagartos"
    ],
    "name:nld_x_preferred":[
        "Lagartos"
    ],
    "name:pol_x_preferred":[
        "Lagartos"
    ],
    "name:por_x_preferred":[
        "Lagartos"
    ],
    "name:spa_x_preferred":[
        "Lagartos"
    ],
    "name:swe_x_preferred":[
        "Lagartos"
    ],
    "name:ukr_x_preferred":[
        "\u041b\u0430\u0433\u0430\u0440\u0442\u043e\u0441"
    ],
    "name:vie_x_preferred":[
        "Lagartos"
    ],
    "name:war_x_preferred":[
        "Lagartos"
    ],
    "name:zho_x_preferred":[
        "\u62c9\u52a0\u5c14\u6258\u65af"
    ],
    "wof:name":"Lagartos",
    "wof:placetype":"locality"
},
  "geometry": {"coordinates":[-88.98333000000002,15.26667],"type":"Point"}
}