{
  "type": "Feature",
  "properties": {
    "gn:admin1_code":"21",
    "gn:asciiname":"Pala Grande",
    "gn:country_code":"GT",
    "gn:dem":2688,
    "gn:feature_class":"P",
    "gn:feature_code":"PPL",
    "gn:name":"Pal\u00e1 Grande",
    "gn:population":0,
    "gn:timezone":"America/Guatemala",
    "iso:country":"GT",
    "name:spa_x_preferred":[
        "Pal\u00e1 Grande"
    ],
    "wof:name":"Pala Grande",
    "wof:placetype":"locality"
},
  "geometry": {"coordinates":[-91.48272,15.03471],"type":"Point"}
}