{
  "type": "Feature",
  "properties": {
    "gn:admin1_code":"22",
    "gn:asciiname":"Los Puentes",
    "gn:country_code":"GT",
    "gn:dem":239,
    "gn:feature_class":"P",
    "gn:feature_code":"PPL",
    "gn:name":"Los Puentes",
    "gn:population":0,
    "gn:timezone":"America/Guatemala",
    "iso:country":"GT",
    "wof:name":"Los Puentes",
    "wof:placetype":"locality"
},
  "geometry": {"coordinates":[-89.71666999999999,14.98333],"type":"Point"}
}