{
  "type": "Feature",
  "properties": {
    "gn:admin1_code":"13",
    "gn:asciiname":"Roble Grande",
    "gn:country_code":"GT",
    "gn:dem":2566,
    "gn:feature_class":"P",
    "gn:feature_code":"PPL",
    "gn:name":"Roble Grande",
    "gn:population":0,
    "gn:timezone":"America/Guatemala",
    "iso:country":"GT",
    "wof:name":"Roble Grande",
    "wof:placetype":"locality"
},
  "geometry": {"coordinates":[-91.63333,14.86667],"type":"Point"}
}