{
  "type": "Feature",
  "properties": {
    "gn:admin1_code":"08",
    "gn:asciiname":"Xolpic",
    "gn:country_code":"GT",
    "gn:dem":1458,
    "gn:feature_class":"P",
    "gn:feature_code":"PPL",
    "gn:name":"Xolpic",
    "gn:population":0,
    "gn:timezone":"America/Guatemala",
    "iso:country":"GT",
    "name:spa_x_preferred":[
        "Xolpic"
    ],
    "wof:name":"Xolpic",
    "wof:placetype":"locality"
},
  "geometry": {"coordinates":[-91.26860000000001,15.28574],"type":"Point"}
}