{
  "type": "Feature",
  "properties": {
    "gn:admin1_code":"07",
    "gn:asciiname":"San Rafael Las Flores",
    "gn:cc2":"GT",
    "gn:country_code":"GT",
    "gn:dem":1509,
    "gn:feature_class":"P",
    "gn:feature_code":"PPL",
    "gn:name":"San Rafael Las Flores",
    "gn:population":0,
    "gn:timezone":"America/Guatemala",
    "iso:country":"GT",
    "name:ceb_x_preferred":[
        "San Rafael Las Flores"
    ],
    "name:fra_x_preferred":[
        "San Rafael Las Flores"
    ],
    "name:ita_x_preferred":[
        "San Rafael las Flores"
    ],
    "name:pol_x_preferred":[
        "San Rafael Las Flores"
    ],
    "name:por_x_preferred":[
        "San Rafael Las Flores"
    ],
    "name:spa_x_preferred":[
        "San Rafael las Flores"
    ],
    "name:swe_x_preferred":[
        "San Rafael Las Flores"
    ],
    "name:und_x_variant":[
        "San Rafael",
        "San Rafael Las Flores"
    ],
    "wof:name":"San Rafael Las Flores",
    "wof:placetype":"locality"
},
  "geometry": {"coordinates":[-90.53333000000001,14.76667],"type":"Point"}
}