{
  "type": "Feature",
  "properties": {
    "gn:admin1_code":"09",
    "gn:asciiname":"Cambalache",
    "gn:country_code":"GT",
    "gn:dem":18,
    "gn:feature_class":"P",
    "gn:feature_code":"PPL",
    "gn:name":"Cambalache",
    "gn:population":0,
    "gn:timezone":"America/Guatemala",
    "iso:country":"GT",
    "wof:name":"Cambalache",
    "wof:placetype":"locality"
},
  "geometry": {"coordinates":[-88.56667,15.91667],"type":"Point"}
}