{
  "type": "Feature",
  "properties": {
    "gn:admin1_code":"21",
    "gn:asciiname":"Chucruz",
    "gn:country_code":"GT",
    "gn:dem":2372,
    "gn:feature_class":"P",
    "gn:feature_code":"PPLL",
    "gn:name":"Chucruz",
    "gn:population":0,
    "gn:timezone":"America/Guatemala",
    "iso:country":"GT",
    "name:spa_x_preferred":[
        "Chucruz"
    ],
    "wof:name":"Chucruz",
    "wof:placetype":"locality"
},
  "geometry": {"coordinates":[-91.41603000000001,15.01362],"type":"Point"}
}