{
  "type": "Feature",
  "properties": {
    "gn:admin1_code":"08",
    "gn:asciiname":"Bixben",
    "gn:country_code":"GT",
    "gn:dem":593,
    "gn:feature_class":"P",
    "gn:feature_code":"PPL",
    "gn:name":"Bixb\u00e9n",
    "gn:population":0,
    "gn:timezone":"America/Guatemala",
    "iso:country":"GT",
    "name:spa_x_preferred":[
        "Bixb\u00e9n"
    ],
    "wof:name":"Bixben",
    "wof:placetype":"locality"
},
  "geometry": {"coordinates":[-91.29591000000001,16.04891],"type":"Point"}
}