{
  "type": "Feature",
  "properties": {
    "gn:admin1_code":"16",
    "gn:asciiname":"El Manzanillo",
    "gn:cc2":"GT",
    "gn:country_code":"GT",
    "gn:dem":2071,
    "gn:feature_class":"P",
    "gn:feature_code":"PPL",
    "gn:name":"El Manzanillo",
    "gn:population":0,
    "gn:timezone":"America/Guatemala",
    "iso:country":"GT",
    "name:und_x_variant":[
        "Manzanillo",
        "Manzamillo",
        "El Manzanillo"
    ],
    "wof:name":"El Manzanillo",
    "wof:placetype":"locality"
},
  "geometry": {"coordinates":[-90.66667,14.63333],"type":"Point"}
}