{
  "type": "Feature",
  "properties": {
    "gn:admin1_code":"09",
    "gn:asciiname":"Sexamoch",
    "gn:cc2":"GT",
    "gn:country_code":"GT",
    "gn:dem":653,
    "gn:feature_class":"P",
    "gn:feature_code":"PPL",
    "gn:name":"Sexamoch",
    "gn:population":0,
    "gn:timezone":"America/Guatemala",
    "iso:country":"GT",
    "name:und_x_variant":[
        "Sexamch",
        "Seyamch",
        "Sexamoch"
    ],
    "wof:name":"Sexamoch",
    "wof:placetype":"locality"
},
  "geometry": {"coordinates":[-89.45,15.61667],"type":"Point"}
}