{
  "type": "Feature",
  "properties": {
    "gn:admin1_code":"17",
    "gn:asciiname":"Tuimuj",
    "gn:country_code":"GT",
    "gn:dem":2753,
    "gn:feature_class":"P",
    "gn:feature_code":"PPL",
    "gn:name":"Tuimuj",
    "gn:population":0,
    "gn:timezone":"America/Guatemala",
    "iso:country":"GT",
    "name:spa_x_preferred":[
        "Tuimuj"
    ],
    "wof:name":"Tuimuj",
    "wof:placetype":"locality"
},
  "geometry": {"coordinates":[-91.76345999999999,15.17057],"type":"Point"}
}