{
  "type": "Feature",
  "properties": {
    "gn:admin1_code":"01",
    "gn:admin2_code":"3588857.0",
    "gn:asciiname":"Sepacuite",
    "gn:cc2":"GT",
    "gn:country_code":"GT",
    "gn:dem":516,
    "gn:feature_class":"P",
    "gn:feature_code":"PPL",
    "gn:name":"Sepacuit\u00e9",
    "gn:population":0,
    "gn:timezone":"America/Guatemala",
    "iso:country":"GT",
    "name:und_x_variant":[
        "Sepacvit\u00e9",
        "Sepacuit\u00e9"
    ],
    "wof:name":"Sepacuite",
    "wof:placetype":"locality"
},
  "geometry": {"coordinates":[-89.75135,15.43378],"type":"Point"}
}