{
  "type": "Feature",
  "properties": {
    "gn:admin1_code":"15",
    "gn:asciiname":"La Lagartera",
    "gn:country_code":"GT",
    "gn:dem":8,
    "gn:feature_class":"P",
    "gn:feature_code":"PPL",
    "gn:name":"La Lagartera",
    "gn:population":0,
    "gn:timezone":"America/Guatemala",
    "iso:country":"GT",
    "name:spa_x_preferred":[
        "La Lagartera"
    ],
    "wof:name":"La Lagartera",
    "wof:placetype":"locality"
},
  "geometry": {"coordinates":[-92.12694,14.46222],"type":"Point"}
}