{
  "type": "Feature",
  "properties": {
    "gn:admin1_code":"01",
    "gn:asciiname":"Sequixquib",
    "gn:country_code":"GT",
    "gn:dem":1499,
    "gn:feature_class":"P",
    "gn:feature_code":"PPL",
    "gn:name":"Sequixquib",
    "gn:population":0,
    "gn:timezone":"America/Guatemala",
    "iso:country":"GT",
    "wof:name":"Sequixquib",
    "wof:placetype":"locality"
},
  "geometry": {"coordinates":[-90.05,15.41667],"type":"Point"}
}