{
  "type": "Feature",
  "properties": {
    "gn:admin1_code":"21",
    "gn:asciiname":"Iximche",
    "gn:country_code":"GT",
    "gn:dem":1832,
    "gn:feature_class":"P",
    "gn:feature_code":"PPLL",
    "gn:name":"Iximch\u00e9",
    "gn:population":0,
    "gn:timezone":"America/Guatemala",
    "iso:country":"GT",
    "name:spa_x_preferred":[
        "Iximch\u00e9"
    ],
    "wof:name":"Iximche",
    "wof:placetype":"locality"
},
  "geometry": {"coordinates":[-91.2736,15.14279],"type":"Point"}
}