{
  "type": "Feature",
  "properties": {
    "gn:admin1_code":"21",
    "gn:asciiname":"Iximche",
    "gn:country_code":"GT",
    "gn:dem":1832,
    "gn:feature_class":"P",
    "gn:feature_code":"PPLL",
    "gn:name":"Iximch\u00e9",
    "gn:population":0,
    "gn:timezone":"America/Guatemala",
    "iso:country":"GT",
    "name:ceb_x_preferred":[
        "Iximch\u00e9"
    ],
    "name:deu_x_preferred":[
        "Iximch\u00e9"
    ],
    "name:fra_x_preferred":[
        "Iximch\u00e9"
    ],
    "name:hun_x_preferred":[
        "Iximch\u00e9"
    ],
    "name:ind_x_preferred":[
        "Iximche"
    ],
    "name:ita_x_preferred":[
        "Iximche"
    ],
    "name:jpn_x_preferred":[
        "\u30a4\u30b7\u30e0\u30c1\u30a7"
    ],
    "name:lit_x_preferred":[
        "I\u0161im\u010d\u0117"
    ],
    "name:mkd_x_preferred":[
        "\u0418\u0448\u0438\u043c\u0447\u0435"
    ],
    "name:nld_x_preferred":[
        "Iximch\u00e9"
    ],
    "name:por_x_preferred":[
        "Iximch\u00e9"
    ],
    "name:rus_x_preferred":[
        "\u0418\u0448\u0438\u043c\u0447\u0435"
    ],
    "name:spa_x_preferred":[
        "Iximch\u00e9"
    ],
    "name:swe_x_preferred":[
        "Iximch\u00e9"
    ],
    "name:ukr_x_preferred":[
        "\u0406\u0448\u0456\u043c\u0447\u0435"
    ],
    "wof:name":"Iximche",
    "wof:placetype":"locality"
},
  "geometry": {"coordinates":[-91.2736,15.14279],"type":"Point"}
}