{
  "type": "Feature",
  "properties": {
    "gn:admin1_code":"12",
    "gn:asciiname":"El Sibal",
    "gn:country_code":"GT",
    "gn:dem":143,
    "gn:feature_class":"P",
    "gn:feature_code":"PPL",
    "gn:name":"El Sibal",
    "gn:population":0,
    "gn:timezone":"America/Guatemala",
    "iso:country":"GT",
    "name:spa_x_preferred":[
        "El Sibal"
    ],
    "name:spa_x_variant":[
        "El Sibal I"
    ],
    "wof:name":"El Sibal",
    "wof:placetype":"locality"
},
  "geometry": {"coordinates":[-90.67068999999999,16.74111],"type":"Point"}
}