{
  "type": "Feature",
  "properties": {
    "gn:admin1_code":"14",
    "gn:asciiname":"Tzicub",
    "gn:country_code":"GT",
    "gn:dem":1977,
    "gn:feature_class":"P",
    "gn:feature_code":"PPL",
    "gn:name":"Tzicub",
    "gn:population":0,
    "gn:timezone":"America/Guatemala",
    "iso:country":"GT",
    "name:spa_x_preferred":[
        "Tzicub"
    ],
    "wof:name":"Tzicub",
    "wof:placetype":"locality"
},
  "geometry": {"coordinates":[-91.10835,15.43096],"type":"Point"}
}