{
  "type": "Feature",
  "properties": {
    "gn:admin1_code":"08",
    "gn:asciiname":"El Injerto",
    "gn:country_code":"GT",
    "gn:dem":1430,
    "gn:feature_class":"P",
    "gn:feature_code":"PPL",
    "gn:name":"El Injerto",
    "gn:population":0,
    "gn:timezone":"America/Guatemala",
    "iso:country":"GT",
    "name:spa_x_preferred":[
        "El Injerto"
    ],
    "wof:name":"El Injerto",
    "wof:placetype":"locality"
},
  "geometry": {"coordinates":[-91.79546999999999,15.49138],"type":"Point"}
}