{
  "type": "Feature",
  "properties": {
    "gn:admin1_code":"05",
    "gn:asciiname":"Las Pitas",
    "gn:cc2":"GT",
    "gn:country_code":"GT",
    "gn:dem":309,
    "gn:feature_class":"P",
    "gn:feature_code":"PPL",
    "gn:name":"Las Pitas",
    "gn:population":0,
    "gn:timezone":"America/Guatemala",
    "iso:country":"GT",
    "name:und_x_variant":[
        "Finca Las Pitas",
        "Las Pitas"
    ],
    "wof:name":"Las Pitas",
    "wof:placetype":"locality"
},
  "geometry": {"coordinates":[-90.09999999999999,14.91667],"type":"Point"}
}