{
  "type": "Feature",
  "properties": {
    "gn:admin1_code":"17",
    "gn:asciiname":"Plan Grande",
    "gn:country_code":"GT",
    "gn:dem":1904,
    "gn:feature_class":"P",
    "gn:feature_code":"PPL",
    "gn:name":"Plan Grande",
    "gn:population":0,
    "gn:timezone":"America/Guatemala",
    "iso:country":"GT",
    "name:spa_x_preferred":[
        "Plan Grande"
    ],
    "wof:name":"Plan Grande",
    "wof:placetype":"locality"
},
  "geometry": {"coordinates":[-91.63894000000001,15.22931],"type":"Point"}
}