{
  "type": "Feature",
  "properties": {
    "iso:country":"GT",
    "name:ceb_x_preferred":[
        "Santa Luc\u00eda Milpas Altas"
    ],
    "name:eng_x_preferred":[
        "Santa Luc\u00eda Milpas Altas"
    ],
    "name:fra_x_preferred":[
        "Santa Luc\u00eda Milpas Altas"
    ],
    "name:ita_x_preferred":[
        "Santa Luc\u00eda Milpas Altas"
    ],
    "name:nld_x_preferred":[
        "Santa Luc\u00eda Milpas Altas"
    ],
    "name:pol_x_preferred":[
        "Santa Luc\u00eda Milpas Altas"
    ],
    "name:por_x_preferred":[
        "Santa Luc\u00eda Milpas Altas"
    ],
    "name:sco_x_preferred":[
        "Santa Luc\u00eda Milpas Altas"
    ],
    "name:spa_x_preferred":[
        "Santa Luc\u00eda Milpas Altas"
    ],
    "name:swe_x_preferred":[
        "Santa Luc\u00eda Milpas Altas"
    ],
    "name:unk_x_variant":[
        "Santa Luc\u00eda"
    ],
    "name:zho_x_preferred":[
        "\u8056\u76e7\u897f\u4e9e\u7c73\u723e\u5e15\u65af\u963f\u723e\u5854\u65af"
    ],
    "qs:gn_country":"GT",
    "qs:gn_fcode":"PPL",
    "qs:gn_pop":13001,
    "qs:name":"Santa Luc\u00eda Milpas Altas",
    "qs:name_adm0":"Guatemala",
    "qs:name_adm1":"Sacatepequez",
    "qs:photos":172,
    "qs:photos_1k":35,
    "qs:photos_9k":1,
    "qs:photos_9r":4,
    "qs:photos_all":172,
    "qs:photos_sr":4,
    "qs:placetype":"Town",
    "qs:pop_sr":"6",
    "qs:woe_adm0":23424834,
    "wd:wordcount":270,
    "wof:name":"Santa Luc\u00eda Milpas Altas",
    "wof:placetype":"locality",
    "wof:population":13001
},
  "geometry": {"coordinates":[-90.67861000000001,14.57583],"type":"Point"}
}