{
  "type": "Feature",
  "properties": {
    "gn:admin1_code":"17",
    "gn:asciiname":"Los Arcos",
    "gn:country_code":"GT",
    "gn:dem":2474,
    "gn:feature_class":"P",
    "gn:feature_code":"PPL",
    "gn:name":"Los Arcos",
    "gn:population":0,
    "gn:timezone":"America/Guatemala",
    "iso:country":"GT",
    "name:spa_x_preferred":[
        "Los Arcos"
    ],
    "wof:name":"Los Arcos",
    "wof:placetype":"locality"
},
  "geometry": {"coordinates":[-91.81802999999999,15.09891],"type":"Point"}
}