{
  "type": "Feature",
  "properties": {
    "gn:admin1_code":"08",
    "gn:asciiname":"El Mul",
    "gn:country_code":"GT",
    "gn:dem":2300,
    "gn:feature_class":"P",
    "gn:feature_code":"PPL",
    "gn:name":"El Mul",
    "gn:population":0,
    "gn:timezone":"America/Guatemala",
    "iso:country":"GT",
    "name:spa_x_preferred":[
        "El Mul"
    ],
    "wof:name":"El Mul",
    "wof:placetype":"locality"
},
  "geometry": {"coordinates":[-91.66571999999999,15.69407],"type":"Point"}
}