{
  "type": "Feature",
  "properties": {
    "gn:admin1_code":"14",
    "gn:asciiname":"Xeputul",
    "gn:country_code":"GT",
    "gn:dem":1822,
    "gn:feature_class":"P",
    "gn:feature_code":"PPL",
    "gn:name":"Xeputul",
    "gn:population":0,
    "gn:timezone":"America/Guatemala",
    "iso:country":"GT",
    "wof:name":"Xeputul",
    "wof:placetype":"locality"
},
  "geometry": {"coordinates":[-91.05,15.45],"type":"Point"}
}