{
  "type": "Feature",
  "properties": {
    "gn:admin1_code":"04",
    "gn:asciiname":"Vuelta El Roble",
    "gn:country_code":"GT",
    "gn:dem":721,
    "gn:feature_class":"P",
    "gn:feature_code":"PPL",
    "gn:name":"Vuelta El Roble",
    "gn:population":0,
    "gn:timezone":"America/Guatemala",
    "iso:country":"GT",
    "wof:name":"Vuelta El Roble",
    "wof:placetype":"locality"
},
  "geometry": {"coordinates":[-89.45,14.75],"type":"Point"}
}