{
  "type": "Feature",
  "properties": {
    "gn:admin1_code":"08",
    "gn:asciiname":"San Ramon",
    "gn:country_code":"GT",
    "gn:dem":1750,
    "gn:feature_class":"P",
    "gn:feature_code":"PPL",
    "gn:name":"San Ram\u00f3n",
    "gn:population":0,
    "gn:timezone":"America/Guatemala",
    "iso:country":"GT",
    "name:spa_x_preferred":[
        "San Ram\u00f3n"
    ],
    "wof:name":"San Ramon",
    "wof:placetype":"locality"
},
  "geometry": {"coordinates":[-91.47109,15.23081],"type":"Point"}
}