{
  "type": "Feature",
  "properties": {
    "gn:admin1_code":"22",
    "gn:asciiname":"Santa Elena",
    "gn:country_code":"GT",
    "gn:dem":614,
    "gn:feature_class":"P",
    "gn:feature_code":"PPL",
    "gn:name":"Santa Elena",
    "gn:population":0,
    "gn:timezone":"America/Guatemala",
    "iso:country":"GT",
    "name:cat_x_preferred":[
        "Santa Elena"
    ],
    "name:ceb_x_preferred":[
        "Santa Elena"
    ],
    "name:deu_x_preferred":[
        "Santa Elena"
    ],
    "name:eus_x_preferred":[
        "Santa Elena"
    ],
    "name:fra_x_preferred":[
        "Santa Elena"
    ],
    "name:heb_x_preferred":[
        "\u05e1\u05e0\u05d8\u05d4 \u05d0\u05dc\u05e0\u05d4"
    ],
    "name:hun_x_preferred":[
        "Santa Elena"
    ],
    "name:hye_x_preferred":[
        "\u054d\u0561\u0576\u057f\u0561 \u0537\u056c\u0565\u0576\u0561"
    ],
    "name:ita_x_preferred":[
        "Santa Elena"
    ],
    "name:lit_x_preferred":[
        "Santa Elena"
    ],
    "name:nds_x_preferred":[
        "Santa Elena"
    ],
    "name:nld_x_preferred":[
        "Santa Elena"
    ],
    "name:por_x_preferred":[
        "Santa Elena"
    ],
    "name:ron_x_preferred":[
        "Santa Elena"
    ],
    "name:rus_x_preferred":[
        "\u0421\u0430\u043d\u0442\u0430-\u042d\u043b\u0435\u043d\u0430"
    ],
    "name:sco_x_preferred":[
        "Santa Elena"
    ],
    "name:slk_x_preferred":[
        "Santa Elena"
    ],
    "name:spa_x_preferred":[
        "Santa Elena"
    ],
    "name:srp_x_preferred":[
        "\u0421\u0430\u043d\u0442\u0430 \u0415\u043b\u0435\u043d\u0430"
    ],
    "name:swe_x_preferred":[
        "Santa Elena"
    ],
    "name:tgl_x_preferred":[
        "Santa Elena"
    ],
    "name:vie_x_preferred":[
        "Santa Elena"
    ],
    "name:war_x_preferred":[
        "Santa Elena"
    ],
    "wof:name":"Santa Elena",
    "wof:placetype":"locality"
},
  "geometry": {"coordinates":[-89.78333000000001,14.81667],"type":"Point"}
}