{
  "type": "Feature",
  "properties": {
    "gn:admin1_code":"14",
    "gn:asciiname":"Chocoja",
    "gn:country_code":"GT",
    "gn:dem":1849,
    "gn:feature_class":"P",
    "gn:feature_code":"PPL",
    "gn:name":"Chocoj\u00e1",
    "gn:population":0,
    "gn:timezone":"America/Guatemala",
    "iso:country":"GT",
    "name:spa_x_preferred":[
        "Chocoj\u00e1"
    ],
    "wof:name":"Chocoja",
    "wof:placetype":"locality"
},
  "geometry": {"coordinates":[-91.25398,15.10861],"type":"Point"}
}