{
  "type": "Feature",
  "properties": {
    "gn:admin1_code":"17",
    "gn:asciiname":"Cristalina",
    "gn:country_code":"GT",
    "gn:dem":3119,
    "gn:feature_class":"P",
    "gn:feature_code":"PPL",
    "gn:name":"Cristalina",
    "gn:population":0,
    "gn:timezone":"America/Guatemala",
    "iso:country":"GT",
    "name:ara_x_preferred":[
        "\u0628\u0644\u062f\u064a\u0629 \u0643\u0631\u064a\u0633\u062a\u0627\u0644\u064a\u0646\u0627"
    ],
    "name:ben_x_preferred":[
        "\u0995\u09cd\u09b0\u09bf\u09b8\u09cd\u09a4\u09be\u09b2\u09bf\u09a8\u09be"
    ],
    "name:bpy_x_preferred":[
        "\u0995\u09b0\u09bf\u09b8\u099f\u09be\u09b2\u09bf\u09a8\u09be"
    ],
    "name:deu_x_preferred":[
        "Cristalina"
    ],
    "name:ell_x_preferred":[
        "\u039a\u03c1\u03b9\u03c3\u03c4\u03b1\u03bb\u03af\u03bd\u03b1"
    ],
    "name:eml_x_preferred":[
        "Cristalina"
    ],
    "name:epo_x_preferred":[
        "Cristalina"
    ],
    "name:eus_x_preferred":[
        "Cristalina"
    ],
    "name:fas_x_preferred":[
        "\u06a9\u0631\u06cc\u0633\u062a\u0627\u0644\u06cc\u0646\u0627"
    ],
    "name:fra_x_preferred":[
        "Cristalina"
    ],
    "name:heb_x_preferred":[
        "\u05db\u05e8\u05d9\u05e1\u05d8\u05dc\u05d9\u05e0\u05d4"
    ],
    "name:hin_x_preferred":[
        "\u0915\u094d\u0930\u093f\u0938\u094d\u091f\u0932\u093f\u0928\u093e"
    ],
    "name:hye_x_preferred":[
        "\u053f\u0580\u056b\u057d\u057f\u0561\u056c\u056b\u0576\u0561"
    ],
    "name:ind_x_preferred":[
        "Cristalina"
    ],
    "name:ita_x_preferred":[
        "Cristalina"
    ],
    "name:jpn_x_preferred":[
        "\u30af\u30ea\u30b9\u30bf\u30ea\u30ca"
    ],
    "name:kat_x_preferred":[
        "\u10d9\u10e0\u10d8\u10e1\u10e2\u10d0\u10da\u10d8\u10dc\u10d0"
    ],
    "name:kaz_x_preferred":[
        "\u041a\u0440\u0438\u0441\u0442\u0430\u043b\u0438\u043d\u0430"
    ],
    "name:kor_x_preferred":[
        "\ud06c\ub9ac\uc2a4\ud0c8\ub9ac\ub098"
    ],
    "name:mlg_x_preferred":[
        "Cristalina"
    ],
    "name:nld_x_preferred":[
        "Cristalina"
    ],
    "name:nor_x_preferred":[
        "Cristalina"
    ],
    "name:pol_x_preferred":[
        "Cristalina"
    ],
    "name:por_x_preferred":[
        "Cristalina"
    ],
    "name:ron_x_preferred":[
        "Cristalina"
    ],
    "name:rus_x_preferred":[
        "\u041a\u0440\u0438\u0441\u0442\u0430\u043b\u0438\u043d\u0430"
    ],
    "name:spa_x_preferred":[
        "Cristalina"
    ],
    "name:swe_x_preferred":[
        "Cristalina"
    ],
    "name:tur_x_preferred":[
        "Cristalina"
    ],
    "name:ukr_x_preferred":[
        "\u041a\u0440\u0456\u0441\u0442\u0430\u043b\u0456\u043d\u0430"
    ],
    "name:urd_x_preferred":[
        "\u06a9\u0631\u0633\u0679\u0627\u0644\u06cc\u0646\u0627"
    ],
    "name:vie_x_preferred":[
        "Cristalina"
    ],
    "name:vol_x_preferred":[
        "Cristalina"
    ],
    "name:war_x_preferred":[
        "Cristalina"
    ],
    "name:zho_x_preferred":[
        "\u514b\u91cc\u65af\u5854\u5229\u5a1c"
    ],
    "wof:name":"Cristalina",
    "wof:placetype":"locality"
},
  "geometry": {"coordinates":[-91.87698,15.21571],"type":"Point"}
}