{
  "type": "Feature",
  "properties": {
    "gn:admin1_code":"17",
    "gn:asciiname":"Buena Vista El Horizonte",
    "gn:country_code":"GT",
    "gn:dem":2886,
    "gn:feature_class":"P",
    "gn:feature_code":"PPL",
    "gn:name":"Buena Vista El Horizonte",
    "gn:population":0,
    "gn:timezone":"America/Guatemala",
    "iso:country":"GT",
    "name:spa_x_preferred":[
        "Buena Vista El Horizonte"
    ],
    "wof:name":"Buena Vista El Horizonte",
    "wof:placetype":"locality"
},
  "geometry": {"coordinates":[-91.85887,15.08098],"type":"Point"}
}