{
  "type": "Feature",
  "properties": {
    "gn:admin1_code":"01",
    "gn:asciiname":"Setzi",
    "gn:cc2":"GT",
    "gn:country_code":"GT",
    "gn:dem":193,
    "gn:feature_class":"P",
    "gn:feature_code":"PPL",
    "gn:name":"Setz\u00ed",
    "gn:population":0,
    "gn:timezone":"America/Guatemala",
    "iso:country":"GT",
    "name:und_x_variant":[
        "Satz\u00ed",
        "Setz\u00ed"
    ],
    "wof:name":"Setzi",
    "wof:placetype":"locality"
},
  "geometry": {"coordinates":[-89.84999999999999,15.81667],"type":"Point"}
}