{
  "type": "Feature",
  "properties": {
    "gn:admin1_code":"17",
    "gn:asciiname":"Las Barrancas",
    "gn:country_code":"GT",
    "gn:dem":2797,
    "gn:feature_class":"P",
    "gn:feature_code":"PPL",
    "gn:name":"Las Barrancas",
    "gn:population":0,
    "gn:timezone":"America/Guatemala",
    "iso:country":"GT",
    "name:spa_x_preferred":[
        "Las Barrancas"
    ],
    "wof:name":"Las Barrancas",
    "wof:placetype":"locality"
},
  "geometry": {"coordinates":[-92.15658000000001,15.28602],"type":"Point"}
}