{
  "type": "Feature",
  "properties": {
    "gn:admin1_code":"22",
    "gn:asciiname":"La Palmilla",
    "gn:cc2":"GT",
    "gn:country_code":"GT",
    "gn:dem":243,
    "gn:feature_class":"P",
    "gn:feature_code":"PPL",
    "gn:name":"La Palmilla",
    "gn:population":0,
    "gn:timezone":"America/Guatemala",
    "iso:country":"GT",
    "name:und_x_variant":[
        "Palmilla",
        "La Palmilla"
    ],
    "wof:name":"La Palmilla",
    "wof:placetype":"locality"
},
  "geometry": {"coordinates":[-89.75,14.96667],"type":"Point"}
}