{
  "type": "Feature",
  "properties": {
    "gn:admin1_code":"07",
    "gn:asciiname":"San Antonio Las Flores",
    "gn:cc2":"GT",
    "gn:country_code":"GT",
    "gn:dem":1132,
    "gn:feature_class":"P",
    "gn:feature_code":"PPL",
    "gn:name":"San Antonio Las Flores",
    "gn:population":0,
    "gn:timezone":"America/Guatemala",
    "iso:country":"GT",
    "name:und_x_variant":[
        "San Antonio Flores",
        "San Antonio Las Flores"
    ],
    "wof:name":"San Antonio Las Flores",
    "wof:placetype":"locality"
},
  "geometry": {"coordinates":[-90.49889,14.75056],"type":"Point"}
}