{
  "type": "Feature",
  "properties": {
    "gn:admin1_code":"07",
    "gn:asciiname":"Tres Quebradas",
    "gn:country_code":"GT",
    "gn:dem":2357,
    "gn:feature_class":"P",
    "gn:feature_code":"PPL",
    "gn:name":"Tres Quebradas",
    "gn:population":0,
    "gn:timezone":"America/Guatemala",
    "iso:country":"GT",
    "name:ceb_x_preferred":[
        "Tres Quebradas"
    ],
    "name:ita_x_preferred":[
        "Tres Quebradas"
    ],
    "name:swe_x_preferred":[
        "Tres Quebradas"
    ],
    "wof:name":"Tres Quebradas",
    "wof:placetype":"locality"
},
  "geometry": {"coordinates":[-90.33333,14.61667],"type":"Point"}
}