{
  "type": "Feature",
  "properties": {
    "gn:admin1_code":"12",
    "gn:asciiname":"La Polvora",
    "gn:country_code":"GT",
    "gn:dem":168,
    "gn:feature_class":"P",
    "gn:feature_code":"PPL",
    "gn:name":"La P\u00f3lvora",
    "gn:population":0,
    "gn:timezone":"America/Guatemala",
    "iso:country":"GT",
    "name:und_x_variant":[
        "Polvero",
        "La P\u00f3lvora"
    ],
    "wof:name":"La Polvora",
    "wof:placetype":"locality"
},
  "geometry": {"coordinates":[-89.31276,17.0091],"type":"Point"}
}