{
  "type": "Feature",
  "properties": {
    "gn:admin1_code":"17",
    "gn:asciiname":"Tuiquia",
    "gn:country_code":"GT",
    "gn:dem":2415,
    "gn:feature_class":"P",
    "gn:feature_code":"PPL",
    "gn:name":"Tuiqui\u00e1",
    "gn:population":0,
    "gn:timezone":"America/Guatemala",
    "iso:country":"GT",
    "name:spa_x_preferred":[
        "Tuiqui\u00e1"
    ],
    "wof:name":"Tuiquia",
    "wof:placetype":"locality"
},
  "geometry": {"coordinates":[-91.96248,15.12917],"type":"Point"}
}