{
  "type": "Feature",
  "properties": {
    "gn:admin1_code":"08",
    "gn:asciiname":"Tojchoj",
    "gn:country_code":"GT",
    "gn:dem":2681,
    "gn:feature_class":"P",
    "gn:feature_code":"PPL",
    "gn:name":"Tojchoj",
    "gn:population":0,
    "gn:timezone":"America/Guatemala",
    "iso:country":"GT",
    "name:spa_x_preferred":[
        "Tojchoj"
    ],
    "wof:name":"Tojchoj",
    "wof:placetype":"locality"
},
  "geometry": {"coordinates":[-91.58483,15.49504],"type":"Point"}
}