{
  "type": "Feature",
  "properties": {
    "gn:admin1_code":"13",
    "gn:asciiname":"El Durazno",
    "gn:country_code":"GT",
    "gn:dem":2461,
    "gn:feature_class":"P",
    "gn:feature_code":"PPL",
    "gn:name":"El Durazno",
    "gn:population":0,
    "gn:timezone":"America/Guatemala",
    "iso:country":"GT",
    "name:spa_x_preferred":[
        "El Durazno"
    ],
    "wof:name":"El Durazno",
    "wof:placetype":"locality"
},
  "geometry": {"coordinates":[-91.64727000000001,15.1203],"type":"Point"}
}