{
  "type": "Feature",
  "properties": {
    "gn:admin1_code":"08",
    "gn:asciiname":"Eschimal",
    "gn:country_code":"GT",
    "gn:dem":1539,
    "gn:feature_class":"P",
    "gn:feature_code":"PPL",
    "gn:name":"Eschimal",
    "gn:population":0,
    "gn:timezone":"America/Guatemala",
    "iso:country":"GT",
    "name:spa_x_preferred":[
        "Eschimal"
    ],
    "wof:name":"Eschimal",
    "wof:placetype":"locality"
},
  "geometry": {"coordinates":[-91.30882,15.2971],"type":"Point"}
}