{
  "type": "Feature",
  "properties": {
    "gn:admin1_code":"12",
    "gn:asciiname":"Parcelamiento El Tesoro",
    "gn:country_code":"GT",
    "gn:dem":134,
    "gn:feature_class":"P",
    "gn:feature_code":"PPL",
    "gn:name":"Parcelamiento El Tesoro",
    "gn:population":0,
    "gn:timezone":"America/Guatemala",
    "iso:country":"GT",
    "name:spa_x_preferred":[
        "Parcelamiento El Tesoro"
    ],
    "wof:name":"Parcelamiento El Tesoro",
    "wof:placetype":"locality"
},
  "geometry": {"coordinates":[-90.73953,16.79122000000001],"type":"Point"}
}