{
  "type": "Feature",
  "properties": {
    "gn:admin1_code":"08",
    "gn:asciiname":"Yolhuitz",
    "gn:country_code":"GT",
    "gn:dem":1131,
    "gn:feature_class":"P",
    "gn:feature_code":"PPL",
    "gn:name":"Yolhuitz",
    "gn:population":0,
    "gn:timezone":"America/Guatemala",
    "iso:country":"GT",
    "wof:name":"Yolhuitz",
    "wof:placetype":"locality"
},
  "geometry": {"coordinates":[-91.26278000000001,15.86111],"type":"Point"}
}