{
  "type": "Feature",
  "properties": {
    "gn:country":"GT",
    "gn:fcode":"PPL",
    "gn:population":12088,
    "iso:country":"GT",
    "name:ceb_x_preferred":[
        "Sacapulas"
    ],
    "name:eng_x_preferred":[
        "Sacapulas"
    ],
    "name:fra_x_preferred":[
        "Sacapulas"
    ],
    "name:ita_x_preferred":[
        "Sacapulas"
    ],
    "name:jpn_x_preferred":[
        "\u30b5\u30ab\u30d7\u30e9\u30b9"
    ],
    "name:nan_x_preferred":[
        "Sacapulas"
    ],
    "name:nld_x_preferred":[
        "Sacapulas"
    ],
    "name:pol_x_preferred":[
        "Sacapulas"
    ],
    "name:por_x_preferred":[
        "Sacapulas"
    ],
    "name:spa_x_preferred":[
        "Sacapulas"
    ],
    "name:swe_x_preferred":[
        "Sacapulas"
    ],
    "name:urd_x_preferred":[
        "\u0633\u06a9\u067e\u0644\u0627\u0633"
    ],
    "name:zho_x_preferred":[
        "\u85a9\u5361\u666e\u62c9\u65af"
    ],
    "qs:name":"Sacapulas",
    "qs:photos_9r":0,
    "qs:photos_sr":0,
    "qs:pop_sr":"6",
    "wd:wordcount":2975,
    "wof:name":"Sacapulas",
    "wof:placetype":"locality",
    "wof:population":12088
},
  "geometry": {"coordinates":[-91.08722,15.28667],"type":"Point"}
}