{
  "type": "Feature",
  "properties": {
    "gn:admin1_code":"14",
    "gn:asciiname":"Tisumal",
    "gn:country_code":"GT",
    "gn:dem":2956,
    "gn:feature_class":"P",
    "gn:feature_code":"PPL",
    "gn:name":"Tisumal",
    "gn:population":0,
    "gn:timezone":"America/Guatemala",
    "iso:country":"GT",
    "name:spa_x_preferred":[
        "Tisumal"
    ],
    "wof:name":"Tisumal",
    "wof:placetype":"locality"
},
  "geometry": {"coordinates":[-91.23945000000001,15.55018],"type":"Point"}
}