{
  "type": "Feature",
  "properties": {
    "gn:admin1_code":"17",
    "gn:asciiname":"Las Nubes",
    "gn:country_code":"GT",
    "gn:dem":3132,
    "gn:feature_class":"P",
    "gn:feature_code":"PPL",
    "gn:name":"Las Nubes",
    "gn:population":0,
    "gn:timezone":"America/Guatemala",
    "iso:country":"GT",
    "name:spa_x_preferred":[
        "Las Nubes"
    ],
    "wof:name":"Las Nubes",
    "wof:placetype":"locality"
},
  "geometry": {"coordinates":[-92.16849999999999,15.25346],"type":"Point"}
}