{
  "type": "Feature",
  "properties": {
    "gn:gn_country":"GT",
    "gn:gn_fcode":"PPL",
    "gn:gn_pop":3020,
    "gn:population":3020,
    "iso:country":"GT",
    "name:chi_x_preferred":[
        "\u8056\u5730\u7259\u54e5\u5947\u99ac\u723e\u7279\u5357\u6208"
    ],
    "name:dut_x_preferred":[
        "Santiago Chimaltenango"
    ],
    "name:eng_x_preferred":[
        "Santiago Chimaltenango"
    ],
    "name:fre_x_preferred":[
        "Santiago Chimaltenango"
    ],
    "name:ita_x_preferred":[
        "Santiago Chimaltenango"
    ],
    "name:pol_x_preferred":[
        "Santiago Chimaltenango"
    ],
    "name:por_x_preferred":[
        "Santiago Chimaltenango"
    ],
    "name:spa_x_preferred":[
        "Santiago Chimaltenango"
    ],
    "name:swe_x_preferred":[
        "Santiago Chimaltenango"
    ],
    "name:unk_x_variant":[
        "Chimaltenango"
    ],
    "qs_pg:aaroncc":"GT",
    "qs_pg:gn_country":"GT",
    "qs_pg:gn_fcode":"PPL",
    "qs_pg:gn_pop":3020,
    "qs_pg:name":"Santiago Chimaltenango",
    "qs_pg:name_adm0":"Guatemala",
    "qs_pg:name_adm1":"Huehuetenango",
    "qs_pg:photos_9k":1,
    "qs_pg:photos_9r":1,
    "qs_pg:photos_all":20,
    "qs_pg:photos_sr":0,
    "qs_pg:pop_sr":4,
    "qs_pg:qs_pg_placetype":"locality",
    "qs_pg:qs_pg_placetype_gp":"Town",
    "qs_pg:woe_adm0":23424834,
    "woe:adm0_id":23424834,
    "woe:name_adm0":"Guatemala",
    "woe:name_adm1":"Huehuetenango",
    "woe:placetype":"Town",
    "wof:name":"Santiago Chimaltenango",
    "wof:placetype":"locality",
    "wof:population":3020
},
  "geometry": {"coordinates":[-91.71666999999999,15.46667],"type":"Point"}
}