{
  "type": "Feature",
  "properties": {
    "gn:admin1_code":"12",
    "gn:asciiname":"Laguna Cangrejal",
    "gn:country_code":"GT",
    "gn:dem":482,
    "gn:feature_class":"P",
    "gn:feature_code":"PPL",
    "gn:name":"Laguna Cangrejal",
    "gn:population":0,
    "gn:timezone":"America/Guatemala",
    "iso:country":"GT",
    "wof:name":"Laguna Cangrejal",
    "wof:placetype":"locality"
},
  "geometry": {"coordinates":[-89.45889,16.22472],"type":"Point"}
}