{
  "type": "Feature",
  "properties": {
    "gn:admin1_code":"21",
    "gn:asciiname":"Chuachituj",
    "gn:cc2":"GT",
    "gn:country_code":"GT",
    "gn:dem":2157,
    "gn:feature_class":"P",
    "gn:feature_code":"PPL",
    "gn:name":"Chuachituj",
    "gn:population":0,
    "gn:timezone":"America/Guatemala",
    "iso:country":"GT",
    "name:und_x_variant":[
        "Chiuchituj",
        "Chuachituj"
    ],
    "wof:name":"Chuachituj",
    "wof:placetype":"locality"
},
  "geometry": {"coordinates":[-91.28333000000001,14.98333],"type":"Point"}
}