{
  "type": "Feature",
  "properties": {
    "gn:admin1_code":"08",
    "gn:asciiname":"Nueva Concepcion",
    "gn:country_code":"GT",
    "gn:dem":795,
    "gn:feature_class":"P",
    "gn:feature_code":"PPL",
    "gn:name":"Nueva Concepci\u00f3n",
    "gn:population":0,
    "gn:timezone":"America/Guatemala",
    "iso:country":"GT",
    "name:spa_x_preferred":[
        "Nueva Concepci\u00f3n"
    ],
    "wof:name":"Nueva Concepcion",
    "wof:placetype":"locality"
},
  "geometry": {"coordinates":[-91.43461000000001,16.06439],"type":"Point"}
}