{
  "type": "Feature",
  "properties": {
    "iso:country":"GT",
    "name:fra_x_preferred":[
        "Nebaj"
    ],
    "name:pol_x_preferred":[
        "Nebaj"
    ],
    "name:por_x_preferred":[
        "Nebaj"
    ],
    "name:spa_x_preferred":[
        "Nebaj"
    ],
    "name:swe_x_preferred":[
        "Nebaj"
    ],
    "qs:gn_country":"GT",
    "qs:gn_fcode":"PPL",
    "qs:gn_pop":23301,
    "qs:name":"Nebaj",
    "qs:name_adm0":"Guatemala",
    "qs:name_adm1":"Quiche",
    "qs:photos":738,
    "qs:photos_1k":150,
    "qs:photos_9k":3,
    "qs:photos_9r":5,
    "qs:photos_all":738,
    "qs:photos_sr":8,
    "qs:placetype":"Town",
    "qs:pop_sr":"7",
    "qs:woe_adm0":23424834,
    "wof:name":"Nebaj",
    "wof:placetype":"locality",
    "wof:population":23301
},
  "geometry": {"coordinates":[-91.14610999999999,15.40583],"type":"Point"}
}