{
  "type": "Feature",
  "properties": {
    "gn:admin1_code":"13",
    "gn:asciiname":"Paxoj Chiquito",
    "gn:country_code":"GT",
    "gn:dem":2569,
    "gn:feature_class":"P",
    "gn:feature_code":"PPL",
    "gn:name":"Paxoj Chiquito",
    "gn:population":0,
    "gn:timezone":"America/Guatemala",
    "iso:country":"GT",
    "name:spa_x_preferred":[
        "Paxoj Chiquito"
    ],
    "wof:name":"Paxoj Chiquito",
    "wof:placetype":"locality"
},
  "geometry": {"coordinates":[-91.63354,15.05233],"type":"Point"}
}