{
  "type": "Feature",
  "properties": {
    "gn:admin1_code":"08",
    "gn:asciiname":"Joaquin",
    "gn:country_code":"GT",
    "gn:dem":2699,
    "gn:feature_class":"P",
    "gn:feature_code":"PPL",
    "gn:name":"Joaqu\u00edn",
    "gn:population":0,
    "gn:timezone":"America/Guatemala",
    "iso:country":"GT",
    "name:spa_x_preferred":[
        "Joaqu\u00edn"
    ],
    "wof:name":"Joaquin",
    "wof:placetype":"locality"
},
  "geometry": {"coordinates":[-91.62197,15.60157],"type":"Point"}
}