{
  "type": "Feature",
  "properties": {
    "gn:admin1_code":"22",
    "gn:asciiname":"El Chico",
    "gn:country_code":"GT",
    "gn:dem":840,
    "gn:feature_class":"P",
    "gn:feature_code":"PPL",
    "gn:name":"El Chico",
    "gn:population":0,
    "gn:timezone":"America/Guatemala",
    "iso:country":"GT",
    "name:ceb_x_preferred":[
        "El Chico"
    ],
    "name:swe_x_preferred":[
        "El Chico"
    ],
    "wof:name":"El Chico",
    "wof:placetype":"locality"
},
  "geometry": {"coordinates":[-89.83333,15.01667],"type":"Point"}
}