{
  "type": "Feature",
  "properties": {
    "gn:admin1_code":"13",
    "gn:asciiname":"La Troje",
    "gn:cc2":"GT",
    "gn:country_code":"GT",
    "gn:dem":69,
    "gn:feature_class":"P",
    "gn:feature_code":"PPL",
    "gn:name":"La Troje",
    "gn:population":0,
    "gn:timezone":"America/Guatemala",
    "iso:country":"GT",
    "name:und_x_variant":[
        "El Troje",
        "La Troje"
    ],
    "wof:name":"La Troje",
    "wof:placetype":"locality"
},
  "geometry": {"coordinates":[-91.96666999999999,14.58333],"type":"Point"}
}