{
  "type": "Feature",
  "properties": {
    "gn:admin1_code":"08",
    "gn:asciiname":"Nueva Reforma",
    "gn:country_code":"GT",
    "gn:dem":1859,
    "gn:feature_class":"P",
    "gn:feature_code":"PPL",
    "gn:name":"Nueva Reforma",
    "gn:population":0,
    "gn:timezone":"America/Guatemala",
    "iso:country":"GT",
    "name:spa_x_preferred":[
        "Nueva Reforma"
    ],
    "wof:name":"Nueva Reforma",
    "wof:placetype":"locality"
},
  "geometry": {"coordinates":[-92.02628,15.35729],"type":"Point"}
}