{
  "type": "Feature",
  "properties": {
    "gn:admin1_code":"17",
    "gn:asciiname":"La Cuchilla",
    "gn:country_code":"GT",
    "gn:dem":11,
    "gn:feature_class":"P",
    "gn:feature_code":"PPL",
    "gn:name":"La Cuchilla",
    "gn:population":0,
    "gn:timezone":"America/Guatemala",
    "iso:country":"GT",
    "name:spa_x_preferred":[
        "La Cuchilla"
    ],
    "wof:name":"La Cuchilla",
    "wof:placetype":"locality"
},
  "geometry": {"coordinates":[-92.19528,14.55111],"type":"Point"}
}