{
  "type": "Feature",
  "properties": {
    "gn:admin1_code":"11",
    "gn:asciiname":"Ayucinapa",
    "gn:country_code":"GT",
    "gn:dem":503,
    "gn:feature_class":"P",
    "gn:feature_code":"PPL",
    "gn:name":"Ayucinapa",
    "gn:population":0,
    "gn:timezone":"America/Guatemala",
    "iso:country":"GT",
    "wof:name":"Ayucinapa",
    "wof:placetype":"locality"
},
  "geometry": {"coordinates":[-89.71666999999999,14.35],"type":"Point"}
}