{
  "type": "Feature",
  "properties": {
    "iso:country":"GT",
    "name:ceb_x_preferred":[
        "San Rafael La Independencia"
    ],
    "name:eng_x_preferred":[
        "San Rafael La Independencia"
    ],
    "name:fra_x_preferred":[
        "San Rafael La Independencia"
    ],
    "name:ita_x_preferred":[
        "San Rafael la Independencia"
    ],
    "name:nld_x_preferred":[
        "San Rafael La Independencia"
    ],
    "name:pol_x_preferred":[
        "San Rafael La Independencia"
    ],
    "name:por_x_preferred":[
        "San Rafael La Independencia"
    ],
    "name:spa_x_preferred":[
        "San Rafael La Independencia"
    ],
    "name:swe_x_preferred":[
        "San Rafael La Independencia"
    ],
    "name:unk_x_variant":[
        "San Rafael Independencia"
    ],
    "name:zho_x_preferred":[
        "\u8056\u62c9\u6590\u723e\u62c9\u56e0\u5fb7\u5f6d\u767b\u897f\u4e9e"
    ],
    "qs:gn_country":"GT",
    "qs:gn_fcode":"PPL",
    "qs:gn_pop":1059,
    "qs:name":"San Rafael la Independencia",
    "qs:name_adm0":"Guatemala",
    "qs:name_adm1":"Huehuetenango",
    "qs:photos":0,
    "qs:photos_1k":0,
    "qs:photos_9k":0,
    "qs:photos_9r":0,
    "qs:photos_all":0,
    "qs:photos_sr":0,
    "qs:placetype":"Town",
    "qs:pop_sr":"3",
    "qs:woe_adm0":23424834,
    "wd:wordcount":45,
    "wof:name":"San Rafael la Independencia",
    "wof:placetype":"locality",
    "wof:population":1059
},
  "geometry": {"coordinates":[-91.53333000000001,15.71667],"type":"Point"}
}