{
  "type": "Feature",
  "properties": {
    "gn:admin1_code":"17",
    "gn:asciiname":"San Pedro Petz",
    "gn:cc2":"GT",
    "gn:country_code":"GT",
    "gn:dem":2121,
    "gn:feature_class":"P",
    "gn:feature_code":"PPL",
    "gn:name":"San Pedro Petz",
    "gn:population":0,
    "gn:timezone":"America/Guatemala",
    "iso:country":"GT",
    "name:und_x_variant":[
        "Petz",
        "San Pedro Petz"
    ],
    "wof:name":"San Pedro Petz",
    "wof:placetype":"locality"
},
  "geometry": {"coordinates":[-91.78333000000001,14.91667],"type":"Point"}
}