{
  "type": "Feature",
  "properties": {
    "gn:admin1_code":"12",
    "gn:asciiname":"El Caribe",
    "gn:country_code":"GT",
    "gn:dem":55,
    "gn:feature_class":"P",
    "gn:feature_code":"PPLL",
    "gn:name":"El Caribe",
    "gn:population":0,
    "gn:timezone":"America/Guatemala",
    "iso:country":"GT",
    "name:spa_x_preferred":[
        "El Caribe"
    ],
    "wof:name":"El Caribe",
    "wof:placetype":"locality"
},
  "geometry": {"coordinates":[-90.75505,17.25628],"type":"Point"}
}