{
  "type": "Feature",
  "properties": {
    "gn:admin1_code":"08",
    "gn:asciiname":"Las Maravillas",
    "gn:country_code":"GT",
    "gn:dem":1126,
    "gn:feature_class":"P",
    "gn:feature_code":"PPL",
    "gn:name":"Las Maravillas",
    "gn:population":0,
    "gn:timezone":"America/Guatemala",
    "iso:country":"GT",
    "name:spa_x_preferred":[
        "Las Maravillas"
    ],
    "wof:name":"Las Maravillas",
    "wof:placetype":"locality"
},
  "geometry": {"coordinates":[-91.16889,15.76065],"type":"Point"}
}