{
  "type": "Feature",
  "properties": {
    "gn:admin1_code":"21",
    "gn:asciiname":"Caquijuyup",
    "gn:country_code":"GT",
    "gn:dem":2077,
    "gn:feature_class":"P",
    "gn:feature_code":"PPL",
    "gn:name":"Caquijuyup",
    "gn:population":0,
    "gn:timezone":"America/Guatemala",
    "iso:country":"GT",
    "name:spa_x_preferred":[
        "Caquijuyup"
    ],
    "wof:name":"Caquijuyup",
    "wof:placetype":"locality"
},
  "geometry": {"coordinates":[-91.43454,15.12508],"type":"Point"}
}