{
  "type": "Feature",
  "properties": {
    "gn:admin1_code":"10",
    "gn:asciiname":"Morazan",
    "gn:cc2":"GT",
    "gn:country_code":"GT",
    "gn:dem":1005,
    "gn:feature_class":"P",
    "gn:feature_code":"PPL",
    "gn:name":"Moraz\u00e1n",
    "gn:population":0,
    "gn:timezone":"America/Guatemala",
    "iso:country":"GT",
    "name:und_x_variant":[
        "Garay",
        "Moraz\u00e1n"
    ],
    "wof:name":"Morazan",
    "wof:placetype":"locality"
},
  "geometry": {"coordinates":[-89.91667,14.51667],"type":"Point"}
}