{
  "type": "Feature",
  "properties": {
    "iso:country":"GT",
    "name:ceb_x_preferred":[
        "Catarina"
    ],
    "name:eng_x_preferred":[
        "Catarina"
    ],
    "name:ita_x_preferred":[
        "Catarina"
    ],
    "name:nan_x_preferred":[
        "Catarina"
    ],
    "name:nld_x_preferred":[
        "Catarina"
    ],
    "name:pol_x_preferred":[
        "Catarina"
    ],
    "name:por_x_preferred":[
        "Catarina"
    ],
    "name:spa_x_preferred":[
        "Catarina"
    ],
    "name:swe_x_preferred":[
        "Catarina"
    ],
    "name:zho_x_preferred":[
        "\u5361\u5854\u91cc\u5a1c"
    ],
    "qs:gn_country":"GT",
    "qs:gn_fcode":"PPL",
    "qs:gn_pop":3040,
    "qs:name":"Catarina",
    "qs:name_adm0":"Guatemala",
    "qs:name_adm1":"San Marcos",
    "qs:photos":0,
    "qs:photos_1k":0,
    "qs:photos_9k":1,
    "qs:photos_9r":1,
    "qs:photos_all":6,
    "qs:photos_sr":0,
    "qs:placetype":"Town",
    "qs:pop_sr":"4",
    "qs:woe_adm0":23424834,
    "wd:wordcount":98,
    "wof:name":"Catarina",
    "wof:placetype":"locality",
    "wof:population":3040
},
  "geometry": {"coordinates":[-92.08333,14.85],"type":"Point"}
}