{
  "type": "Feature",
  "properties": {
    "gn:admin1_code":"08",
    "gn:asciiname":"Buena Vina",
    "gn:country_code":"GT",
    "gn:dem":1156,
    "gn:feature_class":"P",
    "gn:feature_code":"PPL",
    "gn:name":"Buena Vi\u00f1a",
    "gn:population":0,
    "gn:timezone":"America/Guatemala",
    "iso:country":"GT",
    "name:spa_x_preferred":[
        "Buena Vi\u00f1a"
    ],
    "wof:name":"Buena Vina",
    "wof:placetype":"locality"
},
  "geometry": {"coordinates":[-91.86744,15.58714],"type":"Point"}
}