{
  "type": "Feature",
  "properties": {
    "gn:admin1_code":"08",
    "gn:asciiname":"El Aguacatillo",
    "gn:country_code":"GT",
    "gn:dem":1621,
    "gn:feature_class":"P",
    "gn:feature_code":"PPL",
    "gn:name":"El Aguacatillo",
    "gn:population":0,
    "gn:timezone":"America/Guatemala",
    "iso:country":"GT",
    "name:spa_x_preferred":[
        "El Aguacatillo"
    ],
    "wof:name":"El Aguacatillo",
    "wof:placetype":"locality"
},
  "geometry": {"coordinates":[-91.86053,15.516],"type":"Point"}
}