{
  "type": "Feature",
  "properties": {
    "gn:admin1_code":"06",
    "gn:asciiname":"Tierra Mala",
    "gn:country_code":"GT",
    "gn:dem":5,
    "gn:feature_class":"P",
    "gn:feature_code":"PPL",
    "gn:name":"Tierra Mala",
    "gn:population":0,
    "gn:timezone":"America/Guatemala",
    "iso:country":"GT",
    "wof:name":"Tierra Mala",
    "wof:placetype":"locality"
},
  "geometry": {"coordinates":[-90.86611000000001,13.92111],"type":"Point"}
}