{
  "type": "Feature",
  "properties": {
    "iso:country":"GT",
    "name:unk_x_variant":[
        "Encuentros"
    ],
    "qs:gn_country":"GT",
    "qs:gn_fcode":"PPL",
    "qs:gn_pop":0,
    "qs:name":"Los Encuentros",
    "qs:name_adm0":"Guatemala",
    "qs:name_adm1":"Solola",
    "qs:photos":150,
    "qs:photos_1k":30,
    "qs:photos_9k":1,
    "qs:photos_9r":3,
    "qs:photos_all":150,
    "qs:photos_sr":3,
    "qs:placetype":"Town",
    "qs:pop_sr":"0",
    "qs:woe_adm0":23424834,
    "wof:name":"Los Encuentros",
    "wof:placetype":"locality"
},
  "geometry": {"coordinates":[-91.15000000000001,14.85],"type":"Point"}
}