{
  "type": "Feature",
  "properties": {
    "gn:admin1_code":"17",
    "gn:asciiname":"Santa Elisa",
    "gn:country_code":"GT",
    "gn:dem":523,
    "gn:feature_class":"P",
    "gn:feature_code":"PPL",
    "gn:name":"Santa Elisa",
    "gn:population":0,
    "gn:timezone":"America/Guatemala",
    "iso:country":"GT",
    "name:spa_x_preferred":[
        "Santa Elisa"
    ],
    "wof:name":"Santa Elisa",
    "wof:placetype":"locality"
},
  "geometry": {"coordinates":[-92.13159,14.99165],"type":"Point"}
}