{
  "type": "Feature",
  "properties": {
    "gn:admin1_code":"11",
    "gn:asciiname":"Barra del Jiote",
    "gn:country_code":"GT",
    "gn:dem":5,
    "gn:feature_class":"P",
    "gn:feature_code":"PPL",
    "gn:name":"Barra del Jiote",
    "gn:population":0,
    "gn:timezone":"America/Guatemala",
    "iso:country":"GT",
    "wof:name":"Barra del Jiote",
    "wof:placetype":"locality"
},
  "geometry": {"coordinates":[-90.21611,13.78167],"type":"Point"}
}