{
  "type": "Feature",
  "properties": {
    "gn:admin1_code":"17",
    "gn:asciiname":"Tuiscoque",
    "gn:country_code":"GT",
    "gn:dem":2479,
    "gn:feature_class":"P",
    "gn:feature_code":"PPL",
    "gn:name":"Tuiscoque",
    "gn:population":0,
    "gn:timezone":"America/Guatemala",
    "iso:country":"GT",
    "name:spa_x_preferred":[
        "Tuiscoque"
    ],
    "wof:name":"Tuiscoque",
    "wof:placetype":"locality"
},
  "geometry": {"coordinates":[-92.19584,15.24739],"type":"Point"}
}