{
  "type": "Feature",
  "properties": {
    "gn:admin1_code":"14",
    "gn:asciiname":"Pacaja",
    "gn:country_code":"GT",
    "gn:dem":1918,
    "gn:feature_class":"P",
    "gn:feature_code":"PPLL",
    "gn:name":"Pacaj\u00e1",
    "gn:population":0,
    "gn:timezone":"America/Guatemala",
    "iso:country":"GT",
    "name:spa_x_preferred":[
        "Pacaj\u00e1"
    ],
    "wof:name":"Pacaja",
    "wof:placetype":"locality"
},
  "geometry": {"coordinates":[-91.24137,15.03903],"type":"Point"}
}