{
  "type": "Feature",
  "properties": {
    "gn:admin1_code":"02",
    "gn:asciiname":"Los Encuentros",
    "gn:country_code":"GT",
    "gn:dem":432,
    "gn:feature_class":"P",
    "gn:feature_code":"PPL",
    "gn:name":"Los Encuentros",
    "gn:population":0,
    "gn:timezone":"America/Guatemala",
    "iso:country":"GT",
    "wof:name":"Los Encuentros",
    "wof:placetype":"locality"
},
  "geometry": {"coordinates":[-90.40000000000001,14.88333],"type":"Point"}
}