{
  "type": "Feature",
  "properties": {
    "gn:admin1_code":"10",
    "gn:asciiname":"El Guayabito",
    "gn:country_code":"GT",
    "gn:dem":1205,
    "gn:feature_class":"P",
    "gn:feature_code":"PPL",
    "gn:name":"El Guayabito",
    "gn:population":0,
    "gn:timezone":"America/Guatemala",
    "iso:country":"GT",
    "wof:name":"El Guayabito",
    "wof:placetype":"locality"
},
  "geometry": {"coordinates":[-89.76666999999998,14.68333],"type":"Point"}
}