{
  "type": "Feature",
  "properties": {
    "gn:admin1_code":"08",
    "gn:asciiname":"La Soledad",
    "gn:country_code":"GT",
    "gn:dem":2778,
    "gn:feature_class":"P",
    "gn:feature_code":"PPL",
    "gn:name":"La Soledad",
    "gn:population":0,
    "gn:timezone":"America/Guatemala",
    "iso:country":"GT",
    "name:spa_x_preferred":[
        "La Soledad"
    ],
    "wof:name":"La Soledad",
    "wof:placetype":"locality"
},
  "geometry": {"coordinates":[-92.03937999999999,15.47129],"type":"Point"}
}