{
  "type": "Feature",
  "properties": {
    "gn:admin1_code":"09",
    "gn:asciiname":"Riachuelo",
    "gn:country_code":"GT",
    "gn:dem":55,
    "gn:feature_class":"P",
    "gn:feature_code":"PPL",
    "gn:name":"Riachuelo",
    "gn:population":0,
    "gn:timezone":"America/Guatemala",
    "iso:country":"GT",
    "name:ceb_x_preferred":[
        "Riachuelo"
    ],
    "name:deu_x_preferred":[
        "Riachuelo"
    ],
    "name:fra_x_preferred":[
        "Riachuelo"
    ],
    "name:ita_x_preferred":[
        "Riachuelo"
    ],
    "name:nld_x_preferred":[
        "Riachuelo"
    ],
    "name:nor_x_preferred":[
        "Riachuelo"
    ],
    "name:por_x_preferred":[
        "Riachuelo"
    ],
    "name:rus_x_preferred":[
        "\u0420\u0438\u0430\u0448\u0443\u044d\u043b\u0443"
    ],
    "name:spa_x_preferred":[
        "Riachuelo"
    ],
    "name:swe_x_preferred":[
        "Riachuelo"
    ],
    "name:vol_x_preferred":[
        "Riachuelo"
    ],
    "wof:name":"Riachuelo",
    "wof:placetype":"locality"
},
  "geometry": {"coordinates":[-88.72499999999999,15.45944],"type":"Point"}
}