{
  "type": "Feature",
  "properties": {
    "gn:admin1_code":"22",
    "gn:asciiname":"Guineal",
    "gn:country_code":"GT",
    "gn:dem":717,
    "gn:feature_class":"P",
    "gn:feature_code":"PPL",
    "gn:name":"Guineal",
    "gn:population":0,
    "gn:timezone":"America/Guatemala",
    "iso:country":"GT",
    "wof:name":"Guineal",
    "wof:placetype":"locality"
},
  "geometry": {"coordinates":[-89.38333,15.03333],"type":"Point"}
}