{
  "type": "Feature",
  "properties": {
    "gn:admin1_code":"14",
    "gn:asciiname":"Pacolaj",
    "gn:country_code":"GT",
    "gn:dem":2197,
    "gn:feature_class":"P",
    "gn:feature_code":"PPL",
    "gn:name":"Pacolaj",
    "gn:population":0,
    "gn:timezone":"America/Guatemala",
    "iso:country":"GT",
    "name:spa_x_preferred":[
        "Pacolaj"
    ],
    "wof:name":"Pacolaj",
    "wof:placetype":"locality"
},
  "geometry": {"coordinates":[-91.13929,15.0951],"type":"Point"}
}