{
  "type": "Feature",
  "properties": {
    "gn:admin1_code":"21",
    "gn:asciiname":"Chuijom",
    "gn:country_code":"GT",
    "gn:dem":2222,
    "gn:feature_class":"P",
    "gn:feature_code":"PPL",
    "gn:name":"Chuijom",
    "gn:population":0,
    "gn:timezone":"America/Guatemala",
    "iso:country":"GT",
    "name:spa_x_preferred":[
        "Chuijom"
    ],
    "wof:name":"Chuijom",
    "wof:placetype":"locality"
},
  "geometry": {"coordinates":[-91.3501,15.04809],"type":"Point"}
}