{
  "type": "Feature",
  "properties": {
    "gn:admin1_code":"08",
    "gn:asciiname":"Yichcakchin",
    "gn:country_code":"GT",
    "gn:dem":1114,
    "gn:feature_class":"P",
    "gn:feature_code":"PPL",
    "gn:name":"Yichcakch\u00edn",
    "gn:population":0,
    "gn:timezone":"America/Guatemala",
    "iso:country":"GT",
    "name:spa_x_preferred":[
        "Yichcakch\u00edn"
    ],
    "wof:name":"Yichcakchin",
    "wof:placetype":"locality"
},
  "geometry": {"coordinates":[-91.47806,16.05042000000001],"type":"Point"}
}