{
  "type": "Feature",
  "properties": {
    "gn:admin1_code":"13",
    "gn:asciiname":"Granados",
    "gn:country_code":"GT",
    "gn:dem":364,
    "gn:feature_class":"P",
    "gn:feature_code":"PPL",
    "gn:name":"Granados",
    "gn:population":0,
    "gn:timezone":"America/Guatemala",
    "iso:country":"GT",
    "name:cat_x_preferred":[
        "Granados"
    ],
    "name:ceb_x_preferred":[
        "Granados"
    ],
    "name:deu_x_preferred":[
        "Granados"
    ],
    "name:fra_x_preferred":[
        "Granados"
    ],
    "name:jpn_x_preferred":[
        "\u30b0\u30e9\u30ca\u30c9\u30b9"
    ],
    "name:rus_x_preferred":[
        "\u0413\u0440\u0430\u043d\u0430\u0434\u043e\u0441"
    ],
    "name:spa_x_preferred":[
        "Granados"
    ],
    "name:srp_x_preferred":[
        "\u0413\u0440\u0430\u043d\u0430\u0434\u043e\u0441"
    ],
    "name:swe_x_preferred":[
        "Granados"
    ],
    "wof:name":"Granados",
    "wof:placetype":"locality"
},
  "geometry": {"coordinates":[-91.86667,14.65],"type":"Point"}
}