{
  "type": "Feature",
  "properties": {
    "gn:admin1_code":"13",
    "gn:asciiname":"El Adelanto",
    "gn:country_code":"GT",
    "gn:dem":2475,
    "gn:feature_class":"P",
    "gn:feature_code":"PPL",
    "gn:name":"El Adelanto",
    "gn:population":0,
    "gn:timezone":"America/Guatemala",
    "iso:country":"GT",
    "name:fra_x_preferred":[
        "El Adelanto"
    ],
    "name:ita_x_preferred":[
        "El Adelanto"
    ],
    "name:pol_x_preferred":[
        "El Adelanto"
    ],
    "name:por_x_preferred":[
        "El Adelanto"
    ],
    "name:spa_x_preferred":[
        "El Adelanto"
    ],
    "name:zho_x_preferred":[
        "\u57c3\u723e\u963f\u5fb7\u862d\u6258"
    ],
    "wof:name":"El Adelanto",
    "wof:placetype":"locality"
},
  "geometry": {"coordinates":[-91.56667,14.86667],"type":"Point"}
}