{
  "type": "Feature",
  "properties": {
    "iso:country":"GT",
    "name:chi_x_preferred":[
        "\u970d\u79d1\u5766"
    ],
    "name:dut_x_preferred":[
        "Jocot\u00e1n"
    ],
    "name:eng_x_preferred":[
        "Jocot\u00e1n"
    ],
    "name:fre_x_preferred":[
        "Jocot\u00e1n"
    ],
    "name:ita_x_preferred":[
        "Jocot\u00e1n"
    ],
    "name:pol_x_preferred":[
        "Jocot\u00e1n"
    ],
    "name:por_x_preferred":[
        "Jocot\u00e1n"
    ],
    "name:spa_x_preferred":[
        "Jocot\u00e1n"
    ],
    "name:swe_x_preferred":[
        "Jocot\u00e1n"
    ],
    "qs:gn_pop":0,
    "qs:name":"Jocot\u00e1n",
    "qs:name_adm0":"Guatemala",
    "qs:name_adm1":"Chiquimula",
    "qs:photos":30,
    "qs:photos_1k":6,
    "qs:photos_9k":1,
    "qs:photos_9r":2,
    "qs:photos_all":30,
    "qs:photos_sr":2,
    "qs:placetype":"Town",
    "qs:pop_sr":"0",
    "qs:woe_adm0":23424834,
    "wof:name":"Jocot\u00e1n",
    "wof:placetype":"locality"
},
  "geometry": {"coordinates":[-89.37931500000001,14.820357],"type":"Point"}
}