{
  "type": "Feature",
  "properties": {
    "gn:admin1_code":"21",
    "gn:asciiname":"Pacoxlaj",
    "gn:country_code":"GT",
    "gn:dem":2152,
    "gn:feature_class":"P",
    "gn:feature_code":"PPL",
    "gn:name":"Pacoxlaj",
    "gn:population":0,
    "gn:timezone":"America/Guatemala",
    "iso:country":"GT",
    "name:spa_x_preferred":[
        "Pacoxlaj"
    ],
    "wof:name":"Pacoxlaj",
    "wof:placetype":"locality"
},
  "geometry": {"coordinates":[-91.40978,15.06926],"type":"Point"}
}