{
  "type": "Feature",
  "properties": {
    "gn:admin1_code":"01",
    "gn:asciiname":"Las Pacayas",
    "gn:country_code":"GT",
    "gn:dem":1501,
    "gn:feature_class":"P",
    "gn:feature_code":"PPL",
    "gn:name":"Las Pacayas",
    "gn:population":0,
    "gn:timezone":"America/Guatemala",
    "iso:country":"GT",
    "wof:name":"Las Pacayas",
    "wof:placetype":"locality"
},
  "geometry": {"coordinates":[-90.51667,15.41667],"type":"Point"}
}