{
  "type": "Feature",
  "properties": {
    "gn:admin1_code":"18",
    "gn:asciiname":"Mal Pais",
    "gn:country_code":"GT",
    "gn:dem":1045,
    "gn:feature_class":"P",
    "gn:feature_code":"PPL",
    "gn:name":"Mal Pa\u00eds",
    "gn:population":0,
    "gn:timezone":"America/Guatemala",
    "iso:country":"GT",
    "wof:name":"Mal Pais",
    "wof:placetype":"locality"
},
  "geometry": {"coordinates":[-90.40000000000001,14.35],"type":"Point"}
}