{
  "type": "Feature",
  "properties": {
    "gn:admin1_code":"18",
    "gn:asciiname":"Media Cuesta",
    "gn:country_code":"GT",
    "gn:dem":1410,
    "gn:feature_class":"P",
    "gn:feature_code":"PPL",
    "gn:name":"Media Cuesta",
    "gn:population":0,
    "gn:timezone":"America/Guatemala",
    "iso:country":"GT",
    "wof:name":"Media Cuesta",
    "wof:placetype":"locality"
},
  "geometry": {"coordinates":[-90.11667,14.43333],"type":"Point"}
}