{
  "type": "Feature",
  "properties": {
    "gn:admin1_code":"03",
    "gn:asciiname":"San Jose Las Minas",
    "gn:country_code":"GT",
    "gn:dem":2047,
    "gn:feature_class":"P",
    "gn:feature_code":"PPL",
    "gn:name":"San Jos\u00e9 Las Minas",
    "gn:population":0,
    "gn:timezone":"America/Guatemala",
    "iso:country":"GT",
    "wof:name":"San Jose Las Minas",
    "wof:placetype":"locality"
},
  "geometry": {"coordinates":[-90.83333,14.73333],"type":"Point"}
}