{
  "type": "Feature",
  "properties": {
    "iso:country":"GT",
    "name:ceb_x_preferred":[
        "Nueva Concepci\u00f3n"
    ],
    "name:eng_x_preferred":[
        "Nueva Concepci\u00f3n"
    ],
    "name:fra_x_preferred":[
        "Nueva Concepci\u00f3n"
    ],
    "name:ita_x_preferred":[
        "Nueva Concepci\u00f3n"
    ],
    "name:nan_x_preferred":[
        "Nueva Concepci\u00f3n"
    ],
    "name:nld_x_preferred":[
        "Nueva Concepci\u00f3n"
    ],
    "name:pol_x_preferred":[
        "Nueva Concepci\u00f3n"
    ],
    "name:por_x_preferred":[
        "Nueva Concepci\u00f3n"
    ],
    "name:sco_x_preferred":[
        "Nueva Concepci\u00f3n"
    ],
    "name:spa_x_preferred":[
        "Nueva Concepci\u00f3n"
    ],
    "name:swe_x_preferred":[
        "Nueva Concepci\u00f3n"
    ],
    "name:und_x_variant":[
        "Concepci\u00f3n"
    ],
    "name:urd_x_preferred":[
        "\u0646\u0648\u06cc\u0648\u0627 \u06a9\u0648\u0646\u0633\u06cc\u067e\u0633\u06cc\u0648\u0646\u060c \u0627\u06cc\u0633\u06a9\u0648\u06cc\u0646\u062a\u0644\u0627"
    ],
    "name:urd_x_variant":[
        "\u0646\u0648\u06cc\u0648\u0627 \u06a9\u0648\u0646\u0633\u06cc\u067e\u0633\u06cc\u0648\u0646"
    ],
    "name:yue_x_preferred":[
        "\u65b0\u5eb7\u585e\u666e\u68ee"
    ],
    "name:zho_x_preferred":[
        "\u65b0\u5eb7\u585e\u666e\u897f\u7fc1"
    ],
    "qs:gn_country":"GT",
    "qs:gn_fcode":"PPL",
    "qs:gn_pop":11121,
    "qs:name":"Nueva Concepci\u00f3n",
    "qs:name_adm0":"Guatemala",
    "qs:name_adm1":"Escuintla",
    "qs:photos":0,
    "qs:photos_1k":0,
    "qs:photos_9k":0,
    "qs:photos_9r":0,
    "qs:photos_all":0,
    "qs:photos_sr":0,
    "qs:placetype":"Town",
    "qs:pop_sr":"6",
    "qs:woe_adm0":23424834,
    "wd:wordcount":52,
    "wof:name":"Nueva Concepci\u00f3n",
    "wof:placetype":"locality",
    "wof:population":11121
},
  "geometry": {"coordinates":[-91.3,14.2],"type":"Point"}
}