{
  "type": "Feature",
  "properties": {
    "gn:admin1_code":"11",
    "gn:asciiname":"Poza del Llano",
    "gn:country_code":"GT",
    "gn:dem":37,
    "gn:feature_class":"P",
    "gn:feature_code":"PPL",
    "gn:name":"Poza del Llano",
    "gn:population":0,
    "gn:timezone":"America/Guatemala",
    "iso:country":"GT",
    "wof:name":"Poza del Llano",
    "wof:placetype":"locality"
},
  "geometry": {"coordinates":[-90.11417,13.8775],"type":"Point"}
}