{
  "type": "Feature",
  "properties": {
    "gn:admin1_code":"15",
    "gn:asciiname":"Sibana",
    "gn:country_code":"GT",
    "gn:dem":231,
    "gn:feature_class":"P",
    "gn:feature_code":"PPL",
    "gn:name":"Siban\u00e1",
    "gn:population":0,
    "gn:timezone":"America/Guatemala",
    "iso:country":"GT",
    "wof:name":"Sibana",
    "wof:placetype":"locality"
},
  "geometry": {"coordinates":[-91.75,14.56667],"type":"Point"}
}