{
  "type": "Feature",
  "properties": {
    "gn:admin1_code":"17",
    "gn:asciiname":"Zanjon San Lorenzo Ayutla",
    "gn:country_code":"GT",
    "gn:dem":91,
    "gn:feature_class":"P",
    "gn:feature_code":"PPL",
    "gn:name":"Zanj\u00f3n San Lorenzo Ayutla",
    "gn:population":0,
    "gn:timezone":"America/Guatemala",
    "iso:country":"GT",
    "name:spa_x_preferred":[
        "Zanj\u00f3n San Lorenzo Ayutla"
    ],
    "name:und_x_variant":[
        "San Lorenzo",
        "Zanj\u00f3n San Lorenzo"
    ],
    "wof:name":"Zanjon San Lorenzo Ayutla",
    "wof:placetype":"locality"
},
  "geometry": {"coordinates":[-92.10247,14.77821],"type":"Point"}
}