{
  "type": "Feature",
  "properties": {
    "iso:country":"GT",
    "name:chi_x_preferred":[
        "\u5b54\u585e\u666e\u897f\u7fc1\u7dad\u65af\u5854"
    ],
    "name:dut_x_preferred":[
        "Concepci\u00f3n Huista"
    ],
    "name:eng_x_preferred":[
        "Concepci\u00f3n Huista"
    ],
    "name:fre_x_preferred":[
        "Concepci\u00f3n Huista"
    ],
    "name:ita_x_preferred":[
        "Concepci\u00f3n Huista"
    ],
    "name:pol_x_preferred":[
        "Concepci\u00f3n Huista"
    ],
    "name:por_x_preferred":[
        "Concepci\u00f3n Huista"
    ],
    "name:spa_x_preferred":[
        "Concepci\u00f3n"
    ],
    "name:spa_x_variant":[
        "Concepci\u00f3n Huista"
    ],
    "qs:gn_country":"GT",
    "qs:gn_fcode":"PPL",
    "qs:gn_pop":8925,
    "qs:name":"Concepci\u00f3n",
    "qs:name_adm0":"Guatemala",
    "qs:name_adm1":"Huehuetenango",
    "qs:photos":0,
    "qs:photos_1k":0,
    "qs:photos_9k":1,
    "qs:photos_9r":1,
    "qs:photos_all":17,
    "qs:photos_sr":0,
    "qs:placetype":"Town",
    "qs:pop_sr":"5",
    "qs:woe_adm0":23424834,
    "wof:name":"Concepci\u00f3n",
    "wof:placetype":"locality",
    "wof:population":8925
},
  "geometry": {"coordinates":[-91.68333,15.61667],"type":"Point"}
}