{
  "type": "Feature",
  "properties": {
    "gn:admin1_code":"08",
    "gn:asciiname":"Yalcastan Buena Vista",
    "gn:country_code":"GT",
    "gn:dem":1361,
    "gn:feature_class":"P",
    "gn:feature_code":"PPL",
    "gn:name":"Yalcast\u00e1n Buena Vista",
    "gn:population":0,
    "gn:timezone":"America/Guatemala",
    "iso:country":"GT",
    "name:spa_x_preferred":[
        "Yalcast\u00e1n Buena Vista"
    ],
    "wof:name":"Yalcastan Buena Vista",
    "wof:placetype":"locality"
},
  "geometry": {"coordinates":[-91.60071000000001,16.06295],"type":"Point"}
}