{
  "type": "Feature",
  "properties": {
    "gn:admin1_code":"18",
    "gn:asciiname":"Las Marias",
    "gn:country_code":"GT",
    "gn:dem":32,
    "gn:feature_class":"P",
    "gn:feature_code":"PPL",
    "gn:name":"Las Mar\u00edas",
    "gn:population":0,
    "gn:timezone":"America/Guatemala",
    "iso:country":"GT",
    "wof:name":"Las Marias",
    "wof:placetype":"locality"
},
  "geometry": {"coordinates":[-90.31944,13.96889],"type":"Point"}
}