{
  "type": "Feature",
  "properties": {
    "gn:admin1_code":"17",
    "gn:asciiname":"Santa Marta Melendrez",
    "gn:country_code":"GT",
    "gn:dem":68,
    "gn:feature_class":"P",
    "gn:feature_code":"PPL",
    "gn:name":"Santa Marta Mel\u00e9ndrez",
    "gn:population":0,
    "gn:timezone":"America/Guatemala",
    "iso:country":"GT",
    "name:spa_x_preferred":[
        "Santa Marta Mel\u00e9ndrez"
    ],
    "wof:name":"Santa Marta Melendrez",
    "wof:placetype":"locality"
},
  "geometry": {"coordinates":[-92.07364,14.76198],"type":"Point"}
}