{
  "type": "Feature",
  "properties": {
    "gn:admin1_code":"07",
    "gn:asciiname":"Las Navajas",
    "gn:cc2":"GT",
    "gn:country_code":"GT",
    "gn:dem":1090,
    "gn:feature_class":"P",
    "gn:feature_code":"PPL",
    "gn:name":"Las Navajas",
    "gn:population":0,
    "gn:timezone":"America/Guatemala",
    "iso:country":"GT",
    "name:und_x_variant":[
        "Navajos",
        "Naranjo",
        "Las Navajas"
    ],
    "wof:name":"Las Navajas",
    "wof:placetype":"locality"
},
  "geometry": {"coordinates":[-90.38333,14.75],"type":"Point"}
}