{
  "type": "Feature",
  "properties": {
    "gn:admin1_code":"12",
    "gn:asciiname":"Tzulutlan Uno",
    "gn:country_code":"GT",
    "gn:dem":163,
    "gn:feature_class":"P",
    "gn:feature_code":"PPL",
    "gn:name":"Tzulutl\u00e1n Uno",
    "gn:population":0,
    "gn:timezone":"America/Guatemala",
    "iso:country":"GT",
    "name:spa_x_preferred":[
        "Tzulutl\u00e1n"
    ],
    "name:spa_x_variant":[
        "Tzulutl\u00e1n Uno"
    ],
    "wof:name":"Tzulutlan Uno",
    "wof:placetype":"locality"
},
  "geometry": {"coordinates":[-90.38543,16.0779],"type":"Point"}
}