{
  "type": "Feature",
  "properties": {
    "gn:admin1_code":"01",
    "gn:asciiname":"Chijolom",
    "gn:country_code":"GT",
    "gn:dem":937,
    "gn:feature_class":"P",
    "gn:feature_code":"PPL",
    "gn:name":"Chijolom",
    "gn:population":0,
    "gn:timezone":"America/Guatemala",
    "iso:country":"GT",
    "wof:name":"Chijolom",
    "wof:placetype":"locality"
},
  "geometry": {"coordinates":[-89.93333,15.45],"type":"Point"}
}