{
  "type": "Feature",
  "properties": {
    "gn:admin1_code":"21",
    "gn:asciiname":"Chivisicaja",
    "gn:country_code":"GT",
    "gn:dem":2005,
    "gn:feature_class":"P",
    "gn:feature_code":"PPL",
    "gn:name":"Chivisicaj\u00e1",
    "gn:population":0,
    "gn:timezone":"America/Guatemala",
    "iso:country":"GT",
    "name:spa_x_preferred":[
        "Chivisicaj\u00e1"
    ],
    "wof:name":"Chivisicaja",
    "wof:placetype":"locality"
},
  "geometry": {"coordinates":[-91.2683,15.04569],"type":"Point"}
}