{
  "type": "Feature",
  "properties": {
    "gn:admin1_code":"18",
    "gn:asciiname":"Salitre",
    "gn:cc2":"GT",
    "gn:country_code":"GT",
    "gn:dem":1228,
    "gn:feature_class":"P",
    "gn:feature_code":"PPL",
    "gn:name":"Salitre",
    "gn:population":0,
    "gn:timezone":"America/Guatemala",
    "iso:country":"GT",
    "name:ceb_x_preferred":[
        "Salitre"
    ],
    "name:por_x_preferred":[
        "Salitre"
    ],
    "name:srp_x_preferred":[
        "\u0421\u0430\u043b\u0438\u0442\u0440\u0435"
    ],
    "name:swe_x_preferred":[
        "Salitre"
    ],
    "name:und_x_variant":[
        "El Salitre",
        "Salitre"
    ],
    "wof:name":"Salitre",
    "wof:placetype":"locality"
},
  "geometry": {"coordinates":[-90.36806,14.43333],"type":"Point"}
}