{
  "type": "Feature",
  "properties": {
    "gn:admin1_code":"14",
    "gn:asciiname":"Tzancaguip",
    "gn:country_code":"GT",
    "gn:dem":1980,
    "gn:feature_class":"P",
    "gn:feature_code":"PPL",
    "gn:name":"Tzancag\u00fcip",
    "gn:population":0,
    "gn:timezone":"America/Guatemala",
    "iso:country":"GT",
    "name:spa_x_preferred":[
        "Tzancag\u00fcip"
    ],
    "name:und_x_variant":[
        "Tzancquib"
    ],
    "wof:name":"Tzancaguip",
    "wof:placetype":"locality"
},
  "geometry": {"coordinates":[-91.2299,15.03398],"type":"Point"}
}