{
  "type": "Feature",
  "properties": {
    "iso:country":"GT",
    "name:und_x_variant":[
        "Barillas"
    ],
    "qs:gn_country":"GT",
    "qs:gn_fcode":"PPL",
    "qs:gn_pop":0,
    "qs:name":"Santa Elena Barillas",
    "qs:name_adm0":"Guatemala",
    "qs:name_adm1":"Guatemala",
    "qs:photos":93,
    "qs:photos_1k":19,
    "qs:photos_9k":1,
    "qs:photos_9r":3,
    "qs:photos_all":93,
    "qs:photos_sr":3,
    "qs:placetype":"Town",
    "qs:pop_sr":"3",
    "qs:woe_adm0":23424834,
    "wof:name":"Santa Elena Barillas",
    "wof:placetype":"locality"
},
  "geometry": {"coordinates":[-90.54443999999999,14.405],"type":"Point"}
}