{
  "type": "Feature",
  "properties": {
    "gn:admin1_code":"14",
    "gn:asciiname":"Actzumbal",
    "gn:country_code":"GT",
    "gn:dem":1979,
    "gn:feature_class":"P",
    "gn:feature_code":"PPL",
    "gn:name":"Actzumbal",
    "gn:population":0,
    "gn:timezone":"America/Guatemala",
    "iso:country":"GT",
    "name:spa_x_preferred":[
        "Actzumbal"
    ],
    "wof:name":"Actzumbal",
    "wof:placetype":"locality"
},
  "geometry": {"coordinates":[-91.15741,15.44351],"type":"Point"}
}