{
  "type": "Feature",
  "properties": {
    "gn:admin1_code":"08",
    "gn:asciiname":"Jacalteran",
    "gn:country_code":"GT",
    "gn:dem":2851,
    "gn:feature_class":"P",
    "gn:feature_code":"PPL",
    "gn:name":"Jacalteran",
    "gn:population":0,
    "gn:timezone":"America/Guatemala",
    "iso:country":"GT",
    "name:spa_x_preferred":[
        "Jacalteran"
    ],
    "wof:name":"Jacalteran",
    "wof:placetype":"locality"
},
  "geometry": {"coordinates":[-91.55421,15.80814],"type":"Point"}
}