{
  "type": "Feature",
  "properties": {
    "gn:admin1_code":"17",
    "gn:asciiname":"Tuiquiao",
    "gn:country_code":"GT",
    "gn:dem":2816,
    "gn:feature_class":"P",
    "gn:feature_code":"PPL",
    "gn:name":"Tuiquiao",
    "gn:population":0,
    "gn:timezone":"America/Guatemala",
    "iso:country":"GT",
    "name:spa_x_preferred":[
        "Tuiquiao"
    ],
    "wof:name":"Tuiquiao",
    "wof:placetype":"locality"
},
  "geometry": {"coordinates":[-91.70796,15.04355],"type":"Point"}
}