{
  "type": "Feature",
  "properties": {
    "gn:admin1_code":"22",
    "gn:asciiname":"Cuchilla del Jicaral",
    "gn:country_code":"GT",
    "gn:dem":653,
    "gn:feature_class":"P",
    "gn:feature_code":"PPL",
    "gn:name":"Cuchilla del Jicaral",
    "gn:population":0,
    "gn:timezone":"America/Guatemala",
    "iso:country":"GT",
    "wof:name":"Cuchilla del Jicaral",
    "wof:placetype":"locality"
},
  "geometry": {"coordinates":[-89.46666999999999,14.98333],"type":"Point"}
}