{
  "type": "Feature",
  "properties": {
    "gn:admin1_code":"21",
    "gn:asciiname":"Patzichaj",
    "gn:country_code":"GT",
    "gn:dem":2250,
    "gn:feature_class":"P",
    "gn:feature_code":"PPL",
    "gn:name":"Patzichaj",
    "gn:population":0,
    "gn:timezone":"America/Guatemala",
    "iso:country":"GT",
    "name:spa_x_preferred":[
        "Patzichaj"
    ],
    "wof:name":"Patzichaj",
    "wof:placetype":"locality"
},
  "geometry": {"coordinates":[-91.36134,15.01736],"type":"Point"}
}