{
  "type": "Feature",
  "properties": {
    "gn:admin1_code":"12",
    "gn:asciiname":"La Florida",
    "gn:country_code":"GT",
    "gn:dem":387,
    "gn:feature_class":"P",
    "gn:feature_code":"PPL",
    "gn:name":"La Florida",
    "gn:population":0,
    "gn:timezone":"America/Guatemala",
    "iso:country":"GT",
    "wof:name":"La Florida",
    "wof:placetype":"locality"
},
  "geometry": {"coordinates":[-89.44083000000001,16.20806],"type":"Point"}
}