{
  "type": "Feature",
  "properties": {
    "gn:admin1_code":"04",
    "gn:asciiname":"Amatillo",
    "gn:cc2":"GT",
    "gn:country_code":"GT",
    "gn:dem":887,
    "gn:feature_class":"P",
    "gn:feature_code":"PPL",
    "gn:name":"Amatillo",
    "gn:population":0,
    "gn:timezone":"America/Guatemala",
    "iso:country":"GT",
    "name:und_x_variant":[
        "El Amatillo",
        "Amatillo"
    ],
    "wof:name":"Amatillo",
    "wof:placetype":"locality"
},
  "geometry": {"coordinates":[-89.59999999999999,14.53333],"type":"Point"}
}