{
  "type": "Feature",
  "properties": {
    "gn:admin1_code":"14",
    "gn:asciiname":"El Paso",
    "gn:country_code":"GT",
    "gn:dem":141,
    "gn:feature_class":"P",
    "gn:feature_code":"PPL",
    "gn:name":"El Paso",
    "gn:population":0,
    "gn:timezone":"America/Guatemala",
    "iso:country":"GT",
    "name:spa_x_preferred":[
        "El Paso"
    ],
    "wof:name":"El Paso",
    "wof:placetype":"locality"
},
  "geometry": {"coordinates":[-90.49493,16.00453],"type":"Point"}
}