{
  "type": "Feature",
  "properties": {
    "gn:admin1_code":"11",
    "gn:asciiname":"El Torito",
    "gn:country_code":"GT",
    "gn:dem":234,
    "gn:feature_class":"P",
    "gn:feature_code":"PPL",
    "gn:name":"El Torito",
    "gn:population":0,
    "gn:timezone":"America/Guatemala",
    "iso:country":"GT",
    "name:dan_x_preferred":[
        "El Torito"
    ],
    "name:pol_x_preferred":[
        "El Torito"
    ],
    "name:por_x_preferred":[
        "El Torito"
    ],
    "wof:name":"El Torito",
    "wof:placetype":"locality"
},
  "geometry": {"coordinates":[-90.16110999999999,13.91861],"type":"Point"}
}