{
  "type": "Feature",
  "properties": {
    "gn:admin1_code":"05",
    "gn:asciiname":"Aguirre",
    "gn:country_code":"GT",
    "gn:dem":946,
    "gn:feature_class":"P",
    "gn:feature_code":"PPL",
    "gn:name":"Aguirre",
    "gn:population":0,
    "gn:timezone":"America/Guatemala",
    "iso:country":"GT",
    "wof:name":"Aguirre",
    "wof:placetype":"locality"
},
  "geometry": {"coordinates":[-90.21666999999999,14.73333],"type":"Point"}
}