{
  "type": "Feature",
  "properties": {
    "gn:admin1_code":"11",
    "gn:asciiname":"Los Chivos",
    "gn:country_code":"GT",
    "gn:dem":1047,
    "gn:feature_class":"P",
    "gn:feature_code":"PPL",
    "gn:name":"Los Chivos",
    "gn:population":0,
    "gn:timezone":"America/Guatemala",
    "iso:country":"GT",
    "wof:name":"Los Chivos",
    "wof:placetype":"locality"
},
  "geometry": {"coordinates":[-89.98333000000002,14.28333],"type":"Point"}
}