{
  "type": "Feature",
  "properties": {
    "gn:admin1_code":"17",
    "gn:asciiname":"Tuixoquel",
    "gn:country_code":"GT",
    "gn:dem":2725,
    "gn:feature_class":"P",
    "gn:feature_code":"PPL",
    "gn:name":"Tuixoquel",
    "gn:population":0,
    "gn:timezone":"America/Guatemala",
    "iso:country":"GT",
    "name:spa_x_preferred":[
        "Tuixoquel"
    ],
    "wof:name":"Tuixoquel",
    "wof:placetype":"locality"
},
  "geometry": {"coordinates":[-91.72972,15.13482],"type":"Point"}
}