{
  "type": "Feature",
  "properties": {
    "gn:admin1_code":"07",
    "gn:asciiname":"Las Lomas",
    "gn:cc2":"GT",
    "gn:country_code":"GT",
    "gn:dem":1303,
    "gn:feature_class":"P",
    "gn:feature_code":"PPL",
    "gn:name":"Las Lomas",
    "gn:population":0,
    "gn:timezone":"America/Guatemala",
    "iso:country":"GT",
    "name:ceb_x_preferred":[
        "Las Lomas"
    ],
    "name:deu_x_preferred":[
        "Las Lomas"
    ],
    "name:ita_x_preferred":[
        "Las Lomas"
    ],
    "name:nld_x_preferred":[
        "Las Lomas"
    ],
    "name:por_x_preferred":[
        "Las Lomas"
    ],
    "name:sco_x_preferred":[
        "Las Lomas"
    ],
    "name:spa_x_preferred":[
        "Las Lomas"
    ],
    "name:srp_x_preferred":[
        "\u041b\u0430\u0441 \u041b\u043e\u043c\u0430\u0441"
    ],
    "name:swe_x_preferred":[
        "Las Lomas"
    ],
    "name:und_x_variant":[
        "Lomas"
    ],
    "name:vol_x_preferred":[
        "Las Lomas"
    ],
    "wof:name":"Las Lomas",
    "wof:placetype":"locality"
},
  "geometry": {"coordinates":[-90.48333,14.75],"type":"Point"}
}