{
  "type": "Feature",
  "properties": {
    "gn:admin1_code":"21",
    "gn:asciiname":"Patzam",
    "gn:country_code":"GT",
    "gn:dem":1917,
    "gn:feature_class":"P",
    "gn:feature_code":"PPL",
    "gn:name":"Patzam",
    "gn:population":0,
    "gn:timezone":"America/Guatemala",
    "iso:country":"GT",
    "name:spa_x_preferred":[
        "Patzam"
    ],
    "wof:name":"Patzam",
    "wof:placetype":"locality"
},
  "geometry": {"coordinates":[-91.32558,15.06278],"type":"Point"}
}