{
  "type": "Feature",
  "properties": {
    "gn:admin1_code":"09",
    "gn:asciiname":"Laguna Grande",
    "gn:country_code":"GT",
    "gn:dem":2,
    "gn:feature_class":"P",
    "gn:feature_code":"PPL",
    "gn:name":"Laguna Grande",
    "gn:population":0,
    "gn:timezone":"America/Guatemala",
    "iso:country":"GT",
    "wof:name":"Laguna Grande",
    "wof:placetype":"locality"
},
  "geometry": {"coordinates":[-88.98333000000002,15.88333],"type":"Point"}
}