{
  "type": "Feature",
  "properties": {
    "gn:admin1_code":"13",
    "gn:asciiname":"Agua Caliente",
    "gn:country_code":"GT",
    "gn:dem":2107,
    "gn:feature_class":"P",
    "gn:feature_code":"PPL",
    "gn:name":"Agua Caliente",
    "gn:population":0,
    "gn:timezone":"America/Guatemala",
    "iso:country":"GT",
    "name:bre_x_preferred":[
        "Agua Caliente"
    ],
    "name:ceb_x_preferred":[
        "Agua Caliente"
    ],
    "name:deu_x_preferred":[
        "Agua Caliente"
    ],
    "name:spa_x_preferred":[
        "Agua Caliente"
    ],
    "name:swe_x_preferred":[
        "Agua Caliente"
    ],
    "wof:name":"Agua Caliente",
    "wof:placetype":"locality"
},
  "geometry": {"coordinates":[-91.56802999999999,15.139],"type":"Point"}
}