{
  "type": "Feature",
  "properties": {
    "gn:admin1_code":"17",
    "gn:asciiname":"Tuismo",
    "gn:country_code":"GT",
    "gn:dem":2631,
    "gn:feature_class":"P",
    "gn:feature_code":"PPL",
    "gn:name":"Tuism\u00f3",
    "gn:population":0,
    "gn:timezone":"America/Guatemala",
    "iso:country":"GT",
    "name:spa_x_preferred":[
        "Tuism\u00f3"
    ],
    "wof:name":"Tuismo",
    "wof:placetype":"locality"
},
  "geometry": {"coordinates":[-91.95012,15.26219],"type":"Point"}
}