{
  "type": "Feature",
  "properties": {
    "gn:admin1_code":"04",
    "gn:asciiname":"Granadillas",
    "gn:country_code":"GT",
    "gn:dem":1418,
    "gn:feature_class":"P",
    "gn:feature_code":"PPL",
    "gn:name":"Granadillas",
    "gn:population":0,
    "gn:timezone":"America/Guatemala",
    "iso:country":"GT",
    "wof:name":"Granadillas",
    "wof:placetype":"locality"
},
  "geometry": {"coordinates":[-89.40000000000001,14.48333],"type":"Point"}
}