{
  "type": "Feature",
  "properties": {
    "gn:admin1_code":"04",
    "gn:asciiname":"La Cuestona",
    "gn:country_code":"GT",
    "gn:dem":1207,
    "gn:feature_class":"P",
    "gn:feature_code":"PPL",
    "gn:name":"La Cuestona",
    "gn:population":0,
    "gn:timezone":"America/Guatemala",
    "iso:country":"GT",
    "wof:name":"La Cuestona",
    "wof:placetype":"locality"
},
  "geometry": {"coordinates":[-89.34999999999999,14.51667],"type":"Point"}
}