{
  "type": "Feature",
  "properties": {
    "gn:admin1_code":"02",
    "gn:asciiname":"El Chupadero",
    "gn:country_code":"GT",
    "gn:dem":1231,
    "gn:feature_class":"P",
    "gn:feature_code":"PPL",
    "gn:name":"El Chupadero",
    "gn:population":0,
    "gn:timezone":"America/Guatemala",
    "iso:country":"GT",
    "wof:name":"El Chupadero",
    "wof:placetype":"locality"
},
  "geometry": {"coordinates":[-90.55,14.96667],"type":"Point"}
}