{
  "type": "Feature",
  "properties": {
    "gn:admin1_code":"21",
    "gn:asciiname":"Chuijoj",
    "gn:country_code":"GT",
    "gn:dem":2277,
    "gn:feature_class":"P",
    "gn:feature_code":"PPL",
    "gn:name":"Chuijoj",
    "gn:population":0,
    "gn:timezone":"America/Guatemala",
    "iso:country":"GT",
    "name:spa_x_preferred":[
        "Chuijoj"
    ],
    "wof:name":"Chuijoj",
    "wof:placetype":"locality"
},
  "geometry": {"coordinates":[-91.31847,15.00056],"type":"Point"}
}