{
  "type": "Feature",
  "properties": {
    "gn:admin1_code":"09",
    "gn:asciiname":"Tameja",
    "gn:country_code":"GT",
    "gn:dem":32,
    "gn:feature_class":"P",
    "gn:feature_code":"PPL",
    "gn:name":"Tameja",
    "gn:population":0,
    "gn:timezone":"America/Guatemala",
    "iso:country":"GT",
    "wof:name":"Tameja",
    "wof:placetype":"locality"
},
  "geometry": {"coordinates":[-88.78333000000001,15.73333],"type":"Point"}
}