{
  "type": "Feature",
  "properties": {
    "gn:admin1_code":"18",
    "gn:asciiname":"Las Crucitas",
    "gn:country_code":"GT",
    "gn:dem":1626,
    "gn:feature_class":"P",
    "gn:feature_code":"PPL",
    "gn:name":"Las Crucitas",
    "gn:population":0,
    "gn:timezone":"America/Guatemala",
    "iso:country":"GT",
    "wof:name":"Las Crucitas",
    "wof:placetype":"locality"
},
  "geometry": {"coordinates":[-90.05,14.41667],"type":"Point"}
}