{
  "type": "Feature",
  "properties": {
    "gn:admin1_code":"11",
    "gn:asciiname":"Majada Rafael Lemus",
    "gn:country_code":"GT",
    "gn:dem":623,
    "gn:feature_class":"P",
    "gn:feature_code":"PPL",
    "gn:name":"Majada Rafael Lemus",
    "gn:population":0,
    "gn:timezone":"America/Guatemala",
    "iso:country":"GT",
    "wof:name":"Majada Rafael Lemus",
    "wof:placetype":"locality"
},
  "geometry": {"coordinates":[-89.53333000000001,14.41667],"type":"Point"}
}