{
  "type": "Feature",
  "properties": {
    "gn:admin1_code":"08",
    "gn:asciiname":"Nuevo Progreso",
    "gn:country_code":"GT",
    "gn:dem":2434,
    "gn:feature_class":"P",
    "gn:feature_code":"PPL",
    "gn:name":"Nuevo Progreso",
    "gn:population":0,
    "gn:timezone":"America/Guatemala",
    "iso:country":"GT",
    "name:ceb_x_preferred":[
        "Nuevo Progreso"
    ],
    "name:deu_x_preferred":[
        "Nuevo Progreso"
    ],
    "name:nld_x_preferred":[
        "Nuevo Progreso"
    ],
    "name:rus_x_preferred":[
        "\u041d\u0443\u044d\u0432\u043e-\u041f\u0440\u043e\u0433\u0440\u0435\u0441\u043e"
    ],
    "name:spa_x_preferred":[
        "Nuevo Progreso"
    ],
    "name:srp_x_preferred":[
        "\u041d\u0443\u0435\u0432\u043e \u041f\u0440\u043e\u0433\u0440\u0435\u0441\u043e"
    ],
    "name:swe_x_preferred":[
        "Nuevo Progreso"
    ],
    "wof:name":"Nuevo Progreso",
    "wof:placetype":"locality"
},
  "geometry": {"coordinates":[-91.45444999999999,15.38675],"type":"Point"}
}