{
  "type": "Feature",
  "properties": {
    "iso:country":"GT",
    "name:eng_x_preferred":[
        "San Antonio Sacatep\u00e9quez"
    ],
    "name:fra_x_preferred":[
        "San Antonio Sacatep\u00e9quez"
    ],
    "name:ita_x_preferred":[
        "San Antonio Sacatep\u00e9quez"
    ],
    "name:nld_x_preferred":[
        "San Antonio Sacatep\u00e9quez"
    ],
    "name:pol_x_preferred":[
        "San Antonio Sacatep\u00e9quez"
    ],
    "name:por_x_preferred":[
        "San Antonio Sacatep\u00e9quez"
    ],
    "name:spa_x_preferred":[
        "San Antonio Sacatep\u00e9quez"
    ],
    "name:swe_x_preferred":[
        "San Antonio Sacatep\u00e9quez"
    ],
    "name:unk_x_variant":[
        "San Antonio"
    ],
    "name:zho_x_preferred":[
        "\u8056\u5b89\u6771\u5c3c\u5967\u85a9\u5361\u7279\u4f69\u514b\u65af"
    ],
    "qs:gn_country":"GT",
    "qs:gn_fcode":"PPL",
    "qs:gn_pop":1658,
    "qs:name":"San Antonio Sacatep\u00e9quez",
    "qs:name_adm0":"Guatemala",
    "qs:name_adm1":"San Marcos",
    "qs:photos":0,
    "qs:photos_1k":0,
    "qs:photos_9k":1,
    "qs:photos_9r":1,
    "qs:photos_all":11,
    "qs:photos_sr":0,
    "qs:placetype":"Town",
    "qs:pop_sr":"3",
    "qs:woe_adm0":23424834,
    "wd:wordcount":98,
    "wof:name":"San Antonio Sacatep\u00e9quez",
    "wof:placetype":"locality",
    "wof:population":1658
},
  "geometry": {"coordinates":[-91.73333,14.96667],"type":"Point"}
}