{
  "type": "Feature",
  "properties": {
    "gn:admin1_code":"17",
    "gn:asciiname":"El Paraiso",
    "gn:country_code":"GT",
    "gn:dem":2847,
    "gn:feature_class":"P",
    "gn:feature_code":"PPL",
    "gn:name":"El Paraiso",
    "gn:population":0,
    "gn:timezone":"America/Guatemala",
    "iso:country":"GT",
    "name:spa_x_preferred":[
        "El Paraiso"
    ],
    "wof:name":"El Paraiso",
    "wof:placetype":"locality"
},
  "geometry": {"coordinates":[-91.80441999999999,15.16058],"type":"Point"}
}