{
  "type": "Feature",
  "properties": {
    "gn:admin1_code":"12",
    "gn:asciiname":"Poite Abajo",
    "gn:country_code":"GT",
    "gn:dem":239,
    "gn:feature_class":"P",
    "gn:feature_code":"PPL",
    "gn:name":"Poit\u00e9 Abajo",
    "gn:population":0,
    "gn:timezone":"America/Guatemala",
    "iso:country":"GT",
    "wof:name":"Poite Abajo",
    "wof:placetype":"locality"
},
  "geometry": {"coordinates":[-89.22221999999999,16.14167],"type":"Point"}
}