{
  "type": "Feature",
  "properties": {
    "gn:admin1_code":"12",
    "gn:asciiname":"El Resumidero",
    "gn:country_code":"GT",
    "gn:dem":113,
    "gn:feature_class":"P",
    "gn:feature_code":"PPLL",
    "gn:name":"El Resumidero",
    "gn:population":0,
    "gn:timezone":"America/Guatemala",
    "iso:country":"GT",
    "name:spa_x_preferred":[
        "El Resumidero"
    ],
    "wof:name":"El Resumidero",
    "wof:placetype":"locality"
},
  "geometry": {"coordinates":[-90.02970000000001,17.09018],"type":"Point"}
}