{
  "type": "Feature",
  "properties": {
    "gn:admin1_code":"17",
    "gn:asciiname":"Calven",
    "gn:country_code":"GT",
    "gn:dem":2989,
    "gn:feature_class":"P",
    "gn:feature_code":"PPL",
    "gn:name":"Calven",
    "gn:population":0,
    "gn:timezone":"America/Guatemala",
    "iso:country":"GT",
    "name:spa_x_preferred":[
        "Calven"
    ],
    "wof:name":"Calven",
    "wof:placetype":"locality"
},
  "geometry": {"coordinates":[-91.86123000000001,15.19196],"type":"Point"}
}