{
  "type": "Feature",
  "properties": {
    "gn:admin1_code":"21",
    "gn:asciiname":"Panimasabal",
    "gn:country_code":"GT",
    "gn:dem":2371,
    "gn:feature_class":"P",
    "gn:feature_code":"PPL",
    "gn:name":"Panimasabal",
    "gn:population":0,
    "gn:timezone":"America/Guatemala",
    "iso:country":"GT",
    "name:spa_x_preferred":[
        "Panimasabal"
    ],
    "wof:name":"Panimasabal",
    "wof:placetype":"locality"
},
  "geometry": {"coordinates":[-91.43115,15.03326],"type":"Point"}
}