{
  "type": "Feature",
  "properties": {
    "gn:admin1_code":"17",
    "gn:asciiname":"Tilapa",
    "gn:country_code":"GT",
    "gn:dem":8,
    "gn:feature_class":"P",
    "gn:feature_code":"PPL",
    "gn:name":"Tilapa",
    "gn:population":0,
    "gn:timezone":"America/Guatemala",
    "iso:country":"GT",
    "name:ceb_x_preferred":[
        "Tilapa"
    ],
    "name:epo_x_preferred":[
        "Tilapa"
    ],
    "name:eus_x_preferred":[
        "Tilapa"
    ],
    "name:spa_x_preferred":[
        "Tilapa"
    ],
    "name:srp_x_preferred":[
        "\u041e\u043f\u0448\u0442\u0438\u043d\u0430 \u0422\u0438\u043b\u0430\u043f\u0430"
    ],
    "name:swe_x_preferred":[
        "Tilapa"
    ],
    "name:vie_x_preferred":[
        "Tilapa"
    ],
    "wof:name":"Tilapa",
    "wof:placetype":"locality"
},
  "geometry": {"coordinates":[-92.17255,14.49459],"type":"Point"}
}