{
  "type": "Feature",
  "properties": {
    "gn:admin1_code":"17",
    "gn:asciiname":"Tilapa",
    "gn:country_code":"GT",
    "gn:dem":8,
    "gn:feature_class":"P",
    "gn:feature_code":"PPL",
    "gn:name":"Tilapa",
    "gn:population":0,
    "gn:timezone":"America/Guatemala",
    "iso:country":"GT",
    "name:spa_x_preferred":[
        "Tilapa"
    ],
    "wof:name":"Tilapa",
    "wof:placetype":"locality"
},
  "geometry": {"coordinates":[-92.17255,14.49459],"type":"Point"}
}