{
  "type": "Feature",
  "properties": {
    "gn:admin1_code":"08",
    "gn:asciiname":"Tojchum",
    "gn:country_code":"GT",
    "gn:dem":2172,
    "gn:feature_class":"P",
    "gn:feature_code":"PPL",
    "gn:name":"Tojchum",
    "gn:population":0,
    "gn:timezone":"America/Guatemala",
    "iso:country":"GT",
    "name:spa_x_preferred":[
        "Tojchum"
    ],
    "wof:name":"Tojchum",
    "wof:placetype":"locality"
},
  "geometry": {"coordinates":[-91.66173000000001,15.29894],"type":"Point"}
}