{
  "type": "Feature",
  "properties": {
    "gn:admin1_code":"08",
    "gn:asciiname":"Timajte",
    "gn:country_code":"GT",
    "gn:dem":1638,
    "gn:feature_class":"P",
    "gn:feature_code":"PPL",
    "gn:name":"Timajt\u00e9",
    "gn:population":0,
    "gn:timezone":"America/Guatemala",
    "iso:country":"GT",
    "name:spa_x_preferred":[
        "Timajt\u00e9"
    ],
    "wof:name":"Timajte",
    "wof:placetype":"locality"
},
  "geometry": {"coordinates":[-91.66882,15.88338],"type":"Point"}
}