{
  "type": "Feature",
  "properties": {
    "gn:admin1_code":"08",
    "gn:asciiname":"Cangua",
    "gn:country_code":"GT",
    "gn:dem":2559,
    "gn:feature_class":"P",
    "gn:feature_code":"PPL",
    "gn:name":"Cangu\u00e1",
    "gn:population":0,
    "gn:timezone":"America/Guatemala",
    "iso:country":"GT",
    "name:spa_x_preferred":[
        "Cangu\u00e1"
    ],
    "wof:name":"Cangua",
    "wof:placetype":"locality"
},
  "geometry": {"coordinates":[-91.63755,15.65798],"type":"Point"}
}