{
  "type": "Feature",
  "properties": {
    "gn:admin1_code":"08",
    "gn:asciiname":"Ken Luz Yal Veh",
    "gn:country_code":"GT",
    "gn:dem":2401,
    "gn:feature_class":"P",
    "gn:feature_code":"PPL",
    "gn:name":"Ken Luz Yal Veh",
    "gn:population":0,
    "gn:timezone":"America/Guatemala",
    "iso:country":"GT",
    "name:spa_x_preferred":[
        "Ken Luz Yal Veh"
    ],
    "wof:name":"Ken Luz Yal Veh",
    "wof:placetype":"locality"
},
  "geometry": {"coordinates":[-91.56007,15.74151],"type":"Point"}
}