{
  "type": "Feature",
  "properties": {
    "gn:admin1_code":"17",
    "gn:asciiname":"Cancela",
    "gn:country_code":"GT",
    "gn:dem":2739,
    "gn:feature_class":"P",
    "gn:feature_code":"PPL",
    "gn:name":"Cancel\u00e1",
    "gn:population":0,
    "gn:timezone":"America/Guatemala",
    "iso:country":"GT",
    "name:spa_x_preferred":[
        "Cancel\u00e1"
    ],
    "wof:name":"Cancela",
    "wof:placetype":"locality"
},
  "geometry": {"coordinates":[-91.83136,15.20652],"type":"Point"}
}