{
  "type": "Feature",
  "properties": {
    "gn:admin1_code":"12",
    "gn:asciiname":"El Hule",
    "gn:country_code":"GT",
    "gn:dem":164,
    "gn:feature_class":"P",
    "gn:feature_code":"PPL",
    "gn:name":"El Hule",
    "gn:population":0,
    "gn:timezone":"America/Guatemala",
    "iso:country":"GT",
    "name:spa_x_preferred":[
        "El Hule"
    ],
    "wof:name":"El Hule",
    "wof:placetype":"locality"
},
  "geometry": {"coordinates":[-89.62083,17.47667],"type":"Point"}
}