{
  "type": "Feature",
  "properties": {
    "gn:admin1_code":"02",
    "gn:asciiname":"El Jute",
    "gn:country_code":"GT",
    "gn:dem":1241,
    "gn:feature_class":"P",
    "gn:feature_code":"PPL",
    "gn:name":"El Jute",
    "gn:population":0,
    "gn:timezone":"America/Guatemala",
    "iso:country":"GT",
    "wof:name":"El Jute",
    "wof:placetype":"locality"
},
  "geometry": {"coordinates":[-90.41667,14.96667],"type":"Point"}
}