{
  "type": "Feature",
  "properties": {
    "gn:admin1_code":"17",
    "gn:asciiname":"Xujchay",
    "gn:country_code":"GT",
    "gn:dem":2696,
    "gn:feature_class":"P",
    "gn:feature_code":"PPL",
    "gn:name":"Xujchay",
    "gn:population":0,
    "gn:timezone":"America/Guatemala",
    "iso:country":"GT",
    "wof:name":"Xujchay",
    "wof:placetype":"locality"
},
  "geometry": {"coordinates":[-92.03333000000001,15.21667],"type":"Point"}
}