{
  "type": "Feature",
  "properties": {
    "gn:admin1_code":"15",
    "gn:asciiname":"Morazan",
    "gn:country_code":"GT",
    "gn:dem":276,
    "gn:feature_class":"P",
    "gn:feature_code":"PPL",
    "gn:name":"Moraz\u00e1n",
    "gn:population":0,
    "gn:timezone":"America/Guatemala",
    "iso:country":"GT",
    "wof:name":"Morazan",
    "wof:placetype":"locality"
},
  "geometry": {"coordinates":[-91.68333,14.56667],"type":"Point"}
}