{
  "type": "Feature",
  "properties": {
    "gn:admin1_code":"01",
    "gn:asciiname":"Fray Bartolome de Las Casas",
    "gn:country_code":"GT",
    "gn:dem":180,
    "gn:feature_class":"P",
    "gn:feature_code":"PPLA2",
    "gn:name":"Fray Bartolom\u00e9 de Las Casas",
    "gn:population":0,
    "gn:timezone":"America/Guatemala",
    "iso:country":"GT",
    "name:spa_x_preferred":[
        "Fray Bartolom\u00e9 de Las Casas"
    ],
    "wof:name":"Fray Bartolome de Las Casas",
    "wof:placetype":"locality"
},
  "geometry": {"coordinates":[-89.88930999999999,15.81516],"type":"Point"}
}