{
  "type": "Feature",
  "properties": {
    "gn:admin1_code":"08",
    "gn:asciiname":"Chibacabe",
    "gn:country_code":"GT",
    "gn:dem":1827,
    "gn:feature_class":"P",
    "gn:feature_code":"PPL",
    "gn:name":"Chibacabe",
    "gn:population":0,
    "gn:timezone":"America/Guatemala",
    "iso:country":"GT",
    "name:spa_x_preferred":[
        "Chibacabe"
    ],
    "wof:name":"Chibacabe",
    "wof:placetype":"locality"
},
  "geometry": {"coordinates":[-91.5308,15.31768],"type":"Point"}
}