{
  "type": "Feature",
  "properties": {
    "gn:admin1_code":"08",
    "gn:asciiname":"El Anonal La Montana",
    "gn:country_code":"GT",
    "gn:dem":1555,
    "gn:feature_class":"P",
    "gn:feature_code":"PPL",
    "gn:name":"El Anonal La Monta\u00f1a",
    "gn:population":0,
    "gn:timezone":"America/Guatemala",
    "iso:country":"GT",
    "name:spa_x_preferred":[
        "El Anonal La Monta\u00f1a"
    ],
    "wof:name":"El Anonal La Montana",
    "wof:placetype":"locality"
},
  "geometry": {"coordinates":[-91.82205999999999,15.63822],"type":"Point"}
}