{
  "type": "Feature",
  "properties": {
    "gn:admin1_code":"21",
    "gn:asciiname":"Xecabalcul",
    "gn:country_code":"GT",
    "gn:dem":2750,
    "gn:feature_class":"P",
    "gn:feature_code":"PPL",
    "gn:name":"Xecabalcul",
    "gn:population":0,
    "gn:timezone":"America/Guatemala",
    "iso:country":"GT",
    "name:spa_x_preferred":[
        "Xecabalcul"
    ],
    "wof:name":"Xecabalcul",
    "wof:placetype":"locality"
},
  "geometry": {"coordinates":[-91.50485,15.0684],"type":"Point"}
}