{
  "type": "Feature",
  "properties": {
    "gn:admin1_code":"10",
    "gn:asciiname":"El Rodeito",
    "gn:cc2":"GT",
    "gn:country_code":"GT",
    "gn:dem":927,
    "gn:feature_class":"P",
    "gn:feature_code":"PPL",
    "gn:name":"El Rode\u00edto",
    "gn:population":0,
    "gn:timezone":"America/Guatemala",
    "iso:country":"GT",
    "name:und_x_variant":[
        "Rode\u00edto",
        "El Rode\u00edto"
    ],
    "wof:name":"El Rodeito",
    "wof:placetype":"locality"
},
  "geometry": {"coordinates":[-89.73333000000002,14.51667],"type":"Point"}
}