{
  "type": "Feature",
  "properties": {
    "gn:admin1_code":"10",
    "gn:asciiname":"Agua Caliente",
    "gn:country_code":"GT",
    "gn:dem":970,
    "gn:feature_class":"P",
    "gn:feature_code":"PPL",
    "gn:name":"Agua Caliente",
    "gn:population":0,
    "gn:timezone":"America/Guatemala",
    "iso:country":"GT",
    "wof:name":"Agua Caliente",
    "wof:placetype":"locality"
},
  "geometry": {"coordinates":[-89.75,14.56667],"type":"Point"}
}