{
  "type": "Feature",
  "properties": {
    "gn:admin1_code":"08",
    "gn:asciiname":"Llano Verde",
    "gn:country_code":"GT",
    "gn:dem":1791,
    "gn:feature_class":"P",
    "gn:feature_code":"PPL",
    "gn:name":"Llano Verde",
    "gn:population":0,
    "gn:timezone":"America/Guatemala",
    "iso:country":"GT",
    "name:spa_x_preferred":[
        "Llano Verde"
    ],
    "wof:name":"Llano Verde",
    "wof:placetype":"locality"
},
  "geometry": {"coordinates":[-91.98594,15.43321],"type":"Point"}
}