{
  "type": "Feature",
  "properties": {
    "gn:admin1_code":"13",
    "gn:asciiname":"Recuerdo a Barrios",
    "gn:country_code":"GT",
    "gn:dem":2732,
    "gn:feature_class":"P",
    "gn:feature_code":"PPL",
    "gn:name":"Recuerdo a Barrios",
    "gn:population":0,
    "gn:timezone":"America/Guatemala",
    "iso:country":"GT",
    "name:spa_x_preferred":[
        "Recuerdo a Barrios"
    ],
    "wof:name":"Recuerdo a Barrios",
    "wof:placetype":"locality"
},
  "geometry": {"coordinates":[-91.57929,15.01329],"type":"Point"}
}