{
  "type": "Feature",
  "properties": {
    "gn:admin1_code":"12",
    "gn:asciiname":"Rosa Jamaica",
    "gn:country_code":"GT",
    "gn:dem":155,
    "gn:feature_class":"P",
    "gn:feature_code":"PPL",
    "gn:name":"Rosa Jamaica",
    "gn:population":0,
    "gn:timezone":"America/Guatemala",
    "iso:country":"GT",
    "name:spa_x_preferred":[
        "Rosa Jamaica"
    ],
    "wof:name":"Rosa Jamaica",
    "wof:placetype":"locality"
},
  "geometry": {"coordinates":[-90.26689,16.30071],"type":"Point"}
}