{
  "type": "Feature",
  "properties": {
    "gn:admin1_code":"08",
    "gn:asciiname":"Ixtiapoc",
    "gn:country_code":"GT",
    "gn:dem":2107,
    "gn:feature_class":"P",
    "gn:feature_code":"PPL",
    "gn:name":"Ixtiapoc",
    "gn:population":0,
    "gn:timezone":"America/Guatemala",
    "iso:country":"GT",
    "name:spa_x_preferred":[
        "Ixtiapoc"
    ],
    "wof:name":"Ixtiapoc",
    "wof:placetype":"locality"
},
  "geometry": {"coordinates":[-91.43015,15.62845],"type":"Point"}
}