{
  "type": "Feature",
  "properties": {
    "gn:admin1_code":"12",
    "gn:asciiname":"Balamtun",
    "gn:country_code":"GT",
    "gn:dem":150,
    "gn:feature_class":"P",
    "gn:feature_code":"PPLL",
    "gn:name":"Balamt\u00fan",
    "gn:population":0,
    "gn:timezone":"America/Guatemala",
    "iso:country":"GT",
    "name:spa_x_preferred":[
        "Balamt\u00fan"
    ],
    "wof:name":"Balamtun",
    "wof:placetype":"locality"
},
  "geometry": {"coordinates":[-90.07564000000001,17.02527000000001],"type":"Point"}
}