{
  "type": "Feature",
  "properties": {
    "gn:admin1_code":"22",
    "gn:asciiname":"El Triunfo",
    "gn:country_code":"GT",
    "gn:dem":705,
    "gn:feature_class":"P",
    "gn:feature_code":"PPL",
    "gn:name":"El Triunfo",
    "gn:population":0,
    "gn:timezone":"America/Guatemala",
    "iso:country":"GT",
    "wof:name":"El Triunfo",
    "wof:placetype":"locality"
},
  "geometry": {"coordinates":[-89.78333000000001,14.78333],"type":"Point"}
}