{
  "type": "Feature",
  "properties": {
    "gn:admin1_code":"04",
    "gn:asciiname":"La Prensa",
    "gn:cc2":"GT",
    "gn:country_code":"GT",
    "gn:dem":1140,
    "gn:feature_class":"P",
    "gn:feature_code":"PPL",
    "gn:name":"La Prensa",
    "gn:population":0,
    "gn:timezone":"America/Guatemala",
    "iso:country":"GT",
    "name:deu_x_preferred":[
        "La Prensa"
    ],
    "name:fra_x_preferred":[
        "La Prensa"
    ],
    "name:spa_x_preferred":[
        "La Prensa"
    ],
    "name:und_x_variant":[
        "Prensas"
    ],
    "wof:name":"La Prensa",
    "wof:placetype":"locality"
},
  "geometry": {"coordinates":[-89.26666999999998,14.71667],"type":"Point"}
}