{
  "type": "Feature",
  "properties": {
    "gn:admin1_code":"15",
    "gn:asciiname":"Chiquirines",
    "gn:cc2":"GT",
    "gn:country_code":"GT",
    "gn:dem":13,
    "gn:feature_class":"P",
    "gn:feature_code":"PPL",
    "gn:name":"Chiquirines",
    "gn:population":0,
    "gn:timezone":"America/Guatemala",
    "iso:country":"GT",
    "name:und_x_variant":[
        "Hacienda Los Chiquirines",
        "Chiquirines"
    ],
    "wof:name":"Chiquirines",
    "wof:placetype":"locality"
},
  "geometry": {"coordinates":[-92.05500000000001,14.56583],"type":"Point"}
}