{
  "type": "Feature",
  "properties": {
    "gn:admin1_code":"08",
    "gn:asciiname":"Quingua",
    "gn:country_code":"GT",
    "gn:dem":1629,
    "gn:feature_class":"P",
    "gn:feature_code":"PPL",
    "gn:name":"Quingu\u00e1",
    "gn:population":0,
    "gn:timezone":"America/Guatemala",
    "iso:country":"GT",
    "name:spa_x_preferred":[
        "Quingu\u00e1"
    ],
    "wof:name":"Quingua",
    "wof:placetype":"locality"
},
  "geometry": {"coordinates":[-91.63523000000001,16.04232],"type":"Point"}
}