{
  "type": "Feature",
  "properties": {
    "gn:admin1_code":"11",
    "gn:asciiname":"Cerro Gordo",
    "gn:country_code":"GT",
    "gn:dem":919,
    "gn:feature_class":"P",
    "gn:feature_code":"PPL",
    "gn:name":"Cerro Gordo",
    "gn:population":0,
    "gn:timezone":"America/Guatemala",
    "iso:country":"GT",
    "name:ara_x_preferred":[
        "\u0633\u064a\u0631\u0648 \u062c\u0648\u0631\u062f\u0648"
    ],
    "name:arg_x_preferred":[
        "Cerro Gordo"
    ],
    "name:ben_x_preferred":[
        "\u09b8\u09c7\u09b0\u09b0\u09cb \u0997\u09cb\u09b0\u09a6\u09cb"
    ],
    "name:ceb_x_preferred":[
        "Cerro Gordo"
    ],
    "name:deu_x_preferred":[
        "Cerro Gordo"
    ],
    "name:ell_x_preferred":[
        "\u03a3\u03ad\u03c1\u03c1\u03bf \u0393\u03ba\u03cc\u03c1\u03bd\u03c4\u03bf"
    ],
    "name:eng_x_preferred":[
        "Cerro Gordo"
    ],
    "name:fas_x_preferred":[
        "\u0633\u0631\u0648 \u06af\u0648\u0631\u062f\u0648"
    ],
    "name:fra_x_preferred":[
        "Cerro Gordo"
    ],
    "name:heb_x_preferred":[
        "\u05d4\u05e8 \u05d2\u05d5\u05e8\u05d3\u05d5"
    ],
    "name:hin_x_preferred":[
        "\u0938\u0947\u0930\u094b \u0917\u0949\u0930\u094d\u0921\u094b"
    ],
    "name:hun_x_preferred":[
        "Cerro Gordo"
    ],
    "name:ind_x_preferred":[
        "Cerro Gordo"
    ],
    "name:ita_x_preferred":[
        "Cerro Gordo"
    ],
    "name:jpn_x_preferred":[
        "\u30bb\u30ed\u30fb\u30b4\u30eb\u30c9\u5c71"
    ],
    "name:kor_x_preferred":[
        "\uc138\ub85c \uace0\ub974\ub3c4"
    ],
    "name:nld_x_preferred":[
        "Cerro Gordo"
    ],
    "name:pol_x_preferred":[
        "G\u00f3ra Gordo"
    ],
    "name:pol_x_variant":[
        "Cerro Gordo"
    ],
    "name:por_x_preferred":[
        "Cerro Gordo"
    ],
    "name:rus_x_preferred":[
        "\u0421\u0435\u0440\u0440\u043e-\u0413\u043e\u0440\u0434\u043e"
    ],
    "name:spa_x_preferred":[
        "Cerro Gordo"
    ],
    "name:srp_x_preferred":[
        "\u0421\u0435\u0440\u043e \u0413\u043e\u0440\u0434\u043e"
    ],
    "name:swe_x_preferred":[
        "Cerro Gordo"
    ],
    "name:tur_x_preferred":[
        "Cerro Gordo"
    ],
    "name:ukr_x_preferred":[
        "\u0421\u0435\u0440\u0440\u043e-\u0413\u043e\u0440\u0434\u043e"
    ],
    "name:urd_x_preferred":[
        "\u06a9\u06cc\u0631\u0648 \u06af\u0648\u0631\u062f\u0648"
    ],
    "name:vie_x_preferred":[
        "N\u00fai Gordo"
    ],
    "name:vol_x_preferred":[
        "Cerro Gordo"
    ],
    "name:zho_cn_x_preferred":[
        "\u6208\u591a\u5c71"
    ],
    "name:zho_tw_x_preferred":[
        "\u6208\u591a\u5c71"
    ],
    "wof:name":"Cerro Gordo",
    "wof:placetype":"locality"
},
  "geometry": {"coordinates":[-89.91667,14.28333],"type":"Point"}
}