{
  "type": "Feature",
  "properties": {
    "gn:admin1_code":"11",
    "gn:asciiname":"Cerro Gordo",
    "gn:country_code":"GT",
    "gn:dem":919,
    "gn:feature_class":"P",
    "gn:feature_code":"PPL",
    "gn:name":"Cerro Gordo",
    "gn:population":0,
    "gn:timezone":"America/Guatemala",
    "iso:country":"GT",
    "wof:name":"Cerro Gordo",
    "wof:placetype":"locality"
},
  "geometry": {"coordinates":[-89.91667,14.28333],"type":"Point"}
}