{
  "type": "Feature",
  "properties": {
    "gn:admin1_code":"08",
    "gn:asciiname":"Jolombojop",
    "gn:country_code":"GT",
    "gn:dem":1957,
    "gn:feature_class":"P",
    "gn:feature_code":"PPL",
    "gn:name":"Jolombojop",
    "gn:population":0,
    "gn:timezone":"America/Guatemala",
    "iso:country":"GT",
    "name:spa_x_preferred":[
        "Jolombojop"
    ],
    "wof:name":"Jolombojop",
    "wof:placetype":"locality"
},
  "geometry": {"coordinates":[-91.61255,15.7408],"type":"Point"}
}