{
  "type": "Feature",
  "properties": {
    "gn:admin1_code":"14",
    "gn:asciiname":"Salquil Grande",
    "gn:country_code":"GT",
    "gn:dem":2324,
    "gn:feature_class":"P",
    "gn:feature_code":"PPL",
    "gn:name":"Salquil Grande",
    "gn:population":0,
    "gn:timezone":"America/Guatemala",
    "iso:country":"GT",
    "name:spa_x_preferred":[
        "Salquil Grande"
    ],
    "wof:name":"Salquil Grande",
    "wof:placetype":"locality"
},
  "geometry": {"coordinates":[-91.24144,15.49271],"type":"Point"}
}