{
  "type": "Feature",
  "properties": {
    "gn:admin1_code":"08",
    "gn:asciiname":"Rio Escondido",
    "gn:country_code":"GT",
    "gn:dem":2353,
    "gn:feature_class":"P",
    "gn:feature_code":"PPL",
    "gn:name":"R\u00edo Escondido",
    "gn:population":0,
    "gn:timezone":"America/Guatemala",
    "iso:country":"GT",
    "name:spa_x_preferred":[
        "R\u00edo Escondido"
    ],
    "wof:name":"Rio Escondido",
    "wof:placetype":"locality"
},
  "geometry": {"coordinates":[-91.46102999999999,15.38956],"type":"Point"}
}