{
  "type": "Feature",
  "properties": {
    "gn:admin1_code":"08",
    "gn:asciiname":"Petzal",
    "gn:country_code":"GT",
    "gn:dem":1872,
    "gn:feature_class":"P",
    "gn:feature_code":"PPL",
    "gn:name":"Petzal",
    "gn:population":0,
    "gn:timezone":"America/Guatemala",
    "iso:country":"GT",
    "name:spa_x_preferred":[
        "Petzal"
    ],
    "wof:name":"Petzal",
    "wof:placetype":"locality"
},
  "geometry": {"coordinates":[-91.3515,15.34475],"type":"Point"}
}