{
  "type": "Feature",
  "properties": {
    "gn:admin1_code":"11",
    "gn:asciiname":"Asuncion Grande",
    "gn:country_code":"GT",
    "gn:dem":888,
    "gn:feature_class":"P",
    "gn:feature_code":"PPL",
    "gn:name":"Asunci\u00f3n Grande",
    "gn:population":0,
    "gn:timezone":"America/Guatemala",
    "iso:country":"GT",
    "wof:name":"Asuncion Grande",
    "wof:placetype":"locality"
},
  "geometry": {"coordinates":[-89.78333000000001,14.33333],"type":"Point"}
}