{
  "type": "Feature",
  "properties": {
    "gn:admin1_code":"14",
    "gn:asciiname":"Xaamac",
    "gn:country_code":"GT",
    "gn:dem":1263,
    "gn:feature_class":"P",
    "gn:feature_code":"PPL",
    "gn:name":"Xaamac",
    "gn:population":0,
    "gn:timezone":"America/Guatemala",
    "iso:country":"GT",
    "name:spa_x_preferred":[
        "Xaamac"
    ],
    "wof:name":"Xaamac",
    "wof:placetype":"locality"
},
  "geometry": {"coordinates":[-91.11530999999999,15.61637],"type":"Point"}
}