{
  "type": "Feature",
  "properties": {
    "gn:admin1_code":"08",
    "gn:asciiname":"El Granadillo",
    "gn:country_code":"GT",
    "gn:dem":1566,
    "gn:feature_class":"P",
    "gn:feature_code":"PPL",
    "gn:name":"El Granadillo",
    "gn:population":0,
    "gn:timezone":"America/Guatemala",
    "iso:country":"GT",
    "name:spa_x_preferred":[
        "El Granadillo"
    ],
    "wof:name":"El Granadillo",
    "wof:placetype":"locality"
},
  "geometry": {"coordinates":[-91.73859,15.43771],"type":"Point"}
}