{
  "type": "Feature",
  "properties": {
    "gn:admin1_code":"21",
    "gn:asciiname":"Xejuyub",
    "gn:country_code":"GT",
    "gn:dem":2387,
    "gn:feature_class":"P",
    "gn:feature_code":"PPL",
    "gn:name":"Xejuyub",
    "gn:population":0,
    "gn:timezone":"America/Guatemala",
    "iso:country":"GT",
    "wof:name":"Xejuyub",
    "wof:placetype":"locality"
},
  "geometry": {"coordinates":[-91.48333,14.88333],"type":"Point"}
}