{
  "type": "Feature",
  "properties": {
    "gn:admin1_code":"09",
    "gn:asciiname":"Puntas Hondas",
    "gn:country_code":"GT",
    "gn:dem":13,
    "gn:feature_class":"P",
    "gn:feature_code":"PPL",
    "gn:name":"Puntas Hondas",
    "gn:population":0,
    "gn:timezone":"America/Guatemala",
    "iso:country":"GT",
    "wof:name":"Puntas Hondas",
    "wof:placetype":"locality"
},
  "geometry": {"coordinates":[-89.03333000000001,15.46667],"type":"Point"}
}