{
  "type": "Feature",
  "properties": {
    "gn:admin1_code":"12",
    "gn:asciiname":"El Mocho",
    "gn:country_code":"GT",
    "gn:dem":124,
    "gn:feature_class":"P",
    "gn:feature_code":"PPL",
    "gn:name":"El Mocho",
    "gn:population":0,
    "gn:timezone":"America/Guatemala",
    "iso:country":"GT",
    "name:spa_x_preferred":[
        "El Mocho"
    ],
    "wof:name":"El Mocho",
    "wof:placetype":"locality"
},
  "geometry": {"coordinates":[-90.69681,16.69911],"type":"Point"}
}