{
  "type": "Feature",
  "properties": {
    "gn:admin1_code":"10",
    "gn:asciiname":"Aguijotes",
    "gn:country_code":"GT",
    "gn:dem":2345,
    "gn:feature_class":"P",
    "gn:feature_code":"PPL",
    "gn:name":"Aguijotes",
    "gn:population":0,
    "gn:timezone":"America/Guatemala",
    "iso:country":"GT",
    "wof:name":"Aguijotes",
    "wof:placetype":"locality"
},
  "geometry": {"coordinates":[-90.06667,14.55],"type":"Point"}
}