{
  "type": "Feature",
  "properties": {
    "iso:country":"GT",
    "name:cat_x_preferred":[
        "Monterrico"
    ],
    "name:ita_x_preferred":[
        "Monterrico"
    ],
    "name:pol_x_preferred":[
        "Monterrrico"
    ],
    "name:spa_x_preferred":[
        "Monterrico"
    ],
    "qs:gn_country":"GT",
    "qs:gn_fcode":"PPL",
    "qs:gn_pop":0,
    "qs:name":"Monterrico",
    "qs:name_adm0":"Guatemala",
    "qs:name_adm1":"Santa Rosa",
    "qs:photos":605,
    "qs:photos_1k":123,
    "qs:photos_9k":3,
    "qs:photos_9r":5,
    "qs:photos_all":605,
    "qs:photos_sr":8,
    "qs:placetype":"Town",
    "qs:pop_sr":"0",
    "qs:woe_adm0":23424834,
    "wd:wordcount":34,
    "wof:name":"Monterrico",
    "wof:placetype":"locality"
},
  "geometry": {"coordinates":[-90.48,13.89417],"type":"Point"}
}