{
  "type": "Feature",
  "properties": {
    "gn:admin1_code":"07",
    "gn:asciiname":"El Pueblito",
    "gn:country_code":"GT",
    "gn:dem":1691,
    "gn:feature_class":"P",
    "gn:feature_code":"PPL",
    "gn:name":"El Pueblito",
    "gn:population":0,
    "gn:timezone":"America/Guatemala",
    "iso:country":"GT",
    "name:ceb_x_preferred":[
        "El Pueblito"
    ],
    "name:deu_x_preferred":[
        "El Pueblito"
    ],
    "name:spa_x_preferred":[
        "El Pueblito"
    ],
    "name:srp_x_preferred":[
        "\u0415\u043b \u041f\u0443\u0435\u0431\u043b\u0438\u0442\u043e"
    ],
    "name:swe_x_preferred":[
        "El Pueblito"
    ],
    "wof:name":"El Pueblito",
    "wof:placetype":"locality"
},
  "geometry": {"coordinates":[-90.48333,14.56667],"type":"Point"}
}