{
  "type": "Feature",
  "properties": {
    "gn:admin1_code":"08",
    "gn:asciiname":"Laguna Nueva Linda",
    "gn:country_code":"GT",
    "gn:dem":2413,
    "gn:feature_class":"P",
    "gn:feature_code":"PPL",
    "gn:name":"Laguna Nueva Linda",
    "gn:population":0,
    "gn:timezone":"America/Guatemala",
    "iso:country":"GT",
    "name:spa_x_preferred":[
        "Laguna Nueva Linda"
    ],
    "wof:name":"Laguna Nueva Linda",
    "wof:placetype":"locality"
},
  "geometry": {"coordinates":[-91.38888,15.59613],"type":"Point"}
}