{
  "type": "Feature",
  "properties": {
    "gn:admin1_code":"21",
    "gn:asciiname":"Chutuy",
    "gn:country_code":"GT",
    "gn:dem":2600,
    "gn:feature_class":"P",
    "gn:feature_code":"PPLL",
    "gn:name":"Chutuy",
    "gn:population":0,
    "gn:timezone":"America/Guatemala",
    "iso:country":"GT",
    "name:spa_x_preferred":[
        "Chutuy"
    ],
    "wof:name":"Chutuy",
    "wof:placetype":"locality"
},
  "geometry": {"coordinates":[-91.47555,15.00334],"type":"Point"}
}