{
  "type": "Feature",
  "properties": {
    "gn:admin1_code":"11",
    "gn:asciiname":"El Granadillon",
    "gn:country_code":"GT",
    "gn:dem":693,
    "gn:feature_class":"P",
    "gn:feature_code":"PPL",
    "gn:name":"El Granadill\u00f3n",
    "gn:population":0,
    "gn:timezone":"America/Guatemala",
    "iso:country":"GT",
    "wof:name":"El Granadillon",
    "wof:placetype":"locality"
},
  "geometry": {"coordinates":[-89.84999999999999,14.15],"type":"Point"}
}