{
  "type": "Feature",
  "properties": {
    "iso:country":"GT",
    "name:chi_x_preferred":[
        "\u8056\u4f0a\u723e\u5fb7\u8c50\u7d22\u4f0a\u65af\u5854\u74e6\u574e"
    ],
    "name:dut_x_preferred":[
        "San Ildefonso Ixtahuac\u00e1n"
    ],
    "name:eng_x_preferred":[
        "San Ildefonso Ixtahuac\u00e1n"
    ],
    "name:fra_x_preferred":[
        "San Ildefonso Ixtahuac\u00e1n"
    ],
    "name:fre_x_preferred":[
        "San Ildefonso Ixtahuac\u00e1n"
    ],
    "name:ita_x_preferred":[
        "San Ildefonso Ixtahuac\u00e1n"
    ],
    "name:pol_x_preferred":[
        "Ixtahuac\u00e1n"
    ],
    "name:por_x_preferred":[
        "Ixtahuac\u00e1n"
    ],
    "name:spa_x_preferred":[
        "San Ildefonso Ixtahuac\u00e1n"
    ],
    "name:swe_x_preferred":[
        "Ixtahuac\u00e1n"
    ],
    "name:unk_x_variant":[
        "San Ildefonso"
    ],
    "name:zho_x_preferred":[
        "\u8056\u4f0a\u723e\u5fb7\u8c50\u7d22\u4f0a\u65af\u5854\u74e6\u574e"
    ],
    "qs:gn_country":"GT",
    "qs:gn_fcode":"PPL",
    "qs:gn_pop":3708,
    "qs:name":"Ixtahuac\u00e1n",
    "qs:name_adm0":"Guatemala",
    "qs:name_adm1":"Huehuetenango",
    "qs:photos":0,
    "qs:photos_1k":0,
    "qs:photos_9k":1,
    "qs:photos_9r":1,
    "qs:photos_all":4,
    "qs:photos_sr":0,
    "qs:placetype":"Town",
    "qs:pop_sr":"4",
    "qs:woe_adm0":23424834,
    "wof:name":"Ixtahuac\u00e1n",
    "wof:placetype":"locality",
    "wof:population":3708
},
  "geometry": {"coordinates":[-91.76667,15.41667],"type":"Point"}
}