{
  "type": "Feature",
  "properties": {
    "gn:admin1_code":"19",
    "gn:asciiname":"Chitulul",
    "gn:cc2":"GT",
    "gn:country_code":"GT",
    "gn:dem":1715,
    "gn:feature_class":"P",
    "gn:feature_code":"PPL",
    "gn:name":"Chitulul",
    "gn:population":0,
    "gn:timezone":"America/Guatemala",
    "iso:country":"GT",
    "name:und_x_variant":[
        "Chitutul",
        "Chitulul"
    ],
    "wof:name":"Chitulul",
    "wof:placetype":"locality"
},
  "geometry": {"coordinates":[-91.09999999999999,14.65],"type":"Point"}
}