{
  "type": "Feature",
  "properties": {
    "gn:admin1_code":"12",
    "gn:asciiname":"Ramonales",
    "gn:country_code":"GT",
    "gn:dem":178,
    "gn:feature_class":"P",
    "gn:feature_code":"PPL",
    "gn:name":"Ramonales",
    "gn:population":0,
    "gn:timezone":"America/Guatemala",
    "iso:country":"GT",
    "name:spa_x_preferred":[
        "Ramonales"
    ],
    "wof:name":"Ramonales",
    "wof:placetype":"locality"
},
  "geometry": {"coordinates":[-89.49252,17.05841],"type":"Point"}
}