{
  "type": "Feature",
  "properties": {
    "gn:admin1_code":"07",
    "gn:asciiname":"San Pedrito",
    "gn:country_code":"GT",
    "gn:dem":540,
    "gn:feature_class":"P",
    "gn:feature_code":"PPL",
    "gn:name":"San Pedrito",
    "gn:population":0,
    "gn:timezone":"America/Guatemala",
    "iso:country":"GT",
    "wof:name":"San Pedrito",
    "wof:placetype":"locality"
},
  "geometry": {"coordinates":[-90.40000000000001,14.85],"type":"Point"}
}