{
  "type": "Feature",
  "properties": {
    "gn:admin1_code":"01",
    "gn:asciiname":"Xuctzul",
    "gn:country_code":"GT",
    "gn:dem":228,
    "gn:feature_class":"P",
    "gn:feature_code":"PPL",
    "gn:name":"Xuctzul",
    "gn:population":0,
    "gn:timezone":"America/Guatemala",
    "iso:country":"GT",
    "wof:name":"Xuctzul",
    "wof:placetype":"locality"
},
  "geometry": {"coordinates":[-90.26667,15.88333],"type":"Point"}
}