{
  "type": "Feature",
  "properties": {
    "gn:admin1_code":"17",
    "gn:asciiname":"Palmar",
    "gn:country_code":"GT",
    "gn:dem":2432,
    "gn:feature_class":"P",
    "gn:feature_code":"PPL",
    "gn:name":"Palmar",
    "gn:population":0,
    "gn:timezone":"America/Guatemala",
    "iso:country":"GT",
    "name:ceb_x_preferred":[
        "Palmar"
    ],
    "name:deu_x_preferred":[
        "Palmar"
    ],
    "name:ita_x_preferred":[
        "Palmar"
    ],
    "name:nld_x_preferred":[
        "Palmar"
    ],
    "name:spa_x_preferred":[
        "Palmar"
    ],
    "name:srp_x_preferred":[
        "\u041f\u0430\u043b\u043c\u0430\u0440"
    ],
    "name:swe_x_preferred":[
        "Palmar"
    ],
    "wof:name":"Palmar",
    "wof:placetype":"locality"
},
  "geometry": {"coordinates":[-92.07285,15.23977],"type":"Point"}
}