{
  "type": "Feature",
  "properties": {
    "gn:admin1_code":"21",
    "gn:asciiname":"Xesuc",
    "gn:country_code":"GT",
    "gn:dem":1872,
    "gn:feature_class":"P",
    "gn:feature_code":"PPL",
    "gn:name":"Xesuc",
    "gn:population":0,
    "gn:timezone":"America/Guatemala",
    "iso:country":"GT",
    "name:spa_x_preferred":[
        "Xesuc"
    ],
    "wof:name":"Xesuc",
    "wof:placetype":"locality"
},
  "geometry": {"coordinates":[-91.29725999999999,15.05215],"type":"Point"}
}