{
  "type": "Feature",
  "properties": {
    "gn:admin1_code":"13",
    "gn:asciiname":"Sector Villa Linda",
    "gn:country_code":"GT",
    "gn:dem":118,
    "gn:feature_class":"P",
    "gn:feature_code":"PPL",
    "gn:name":"Sector Villa Linda",
    "gn:population":0,
    "gn:timezone":"America/Guatemala",
    "iso:country":"GT",
    "name:spa_x_preferred":[
        "Sector Villa Linda"
    ],
    "wof:name":"Sector Villa Linda",
    "wof:placetype":"locality"
},
  "geometry": {"coordinates":[-92.01343,14.70896],"type":"Point"}
}