{
  "type": "Feature",
  "properties": {
    "gn:admin1_code":"19",
    "gn:asciiname":"Chirijalima",
    "gn:country_code":"GT",
    "gn:dem":1027,
    "gn:feature_class":"P",
    "gn:feature_code":"PPL",
    "gn:name":"Chirijalim\u00e1",
    "gn:population":0,
    "gn:timezone":"America/Guatemala",
    "iso:country":"GT",
    "wof:name":"Chirijalima",
    "wof:placetype":"locality"
},
  "geometry": {"coordinates":[-91.46666999999999,14.63333],"type":"Point"}
}