{
  "type": "Feature",
  "properties": {
    "gn:admin1_code":"03",
    "gn:asciiname":"Pena de Plata",
    "gn:cc2":"GT",
    "gn:country_code":"GT",
    "gn:dem":672,
    "gn:feature_class":"P",
    "gn:feature_code":"PPL",
    "gn:name":"Pe\u00f1a de Plata",
    "gn:population":0,
    "gn:timezone":"America/Guatemala",
    "iso:country":"GT",
    "name:und_x_variant":[
        "Finca Pe\u00f1a Plata",
        "Pe\u00f1a Plata",
        "Pe\u00f1a de Plata"
    ],
    "wof:name":"Pena de Plata",
    "wof:placetype":"locality"
},
  "geometry": {"coordinates":[-91.08333,14.45],"type":"Point"}
}