{
  "type": "Feature",
  "properties": {
    "gn:admin1_code":"08",
    "gn:asciiname":"Carbonera",
    "gn:country_code":"GT",
    "gn:dem":2042,
    "gn:feature_class":"P",
    "gn:feature_code":"PPL",
    "gn:name":"Carbonera",
    "gn:population":0,
    "gn:timezone":"America/Guatemala",
    "iso:country":"GT",
    "name:ceb_x_preferred":[
        "Carbonera"
    ],
    "name:ita_x_preferred":[
        "Carbonera"
    ],
    "name:lat_x_preferred":[
        "Carbonera"
    ],
    "name:lmo_x_preferred":[
        "Carbonera"
    ],
    "name:spa_x_preferred":[
        "Carbonera"
    ],
    "name:srp_x_preferred":[
        "Carbonera"
    ],
    "name:swe_x_preferred":[
        "Carbonera"
    ],
    "wof:name":"Carbonera",
    "wof:placetype":"locality"
},
  "geometry": {"coordinates":[-91.84827,15.34692],"type":"Point"}
}