{
  "type": "Feature",
  "properties": {
    "gn:admin1_code":"14",
    "gn:asciiname":"Chujuyub",
    "gn:country_code":"GT",
    "gn:dem":2165,
    "gn:feature_class":"P",
    "gn:feature_code":"PPL",
    "gn:name":"Chujuyub",
    "gn:population":0,
    "gn:timezone":"America/Guatemala",
    "iso:country":"GT",
    "name:spa_x_preferred":[
        "Chujuyub"
    ],
    "wof:name":"Chujuyub",
    "wof:placetype":"locality"
},
  "geometry": {"coordinates":[-91.0407,15.09995],"type":"Point"}
}