{
  "type": "Feature",
  "properties": {
    "gn:admin1_code":"21",
    "gn:asciiname":"Payaxu",
    "gn:country_code":"GT",
    "gn:dem":2170,
    "gn:feature_class":"P",
    "gn:feature_code":"PPLL",
    "gn:name":"Payaxu",
    "gn:population":0,
    "gn:timezone":"America/Guatemala",
    "iso:country":"GT",
    "name:spa_x_preferred":[
        "Payaxu"
    ],
    "wof:name":"Payaxu",
    "wof:placetype":"locality"
},
  "geometry": {"coordinates":[-91.39704999999999,15.05348],"type":"Point"}
}