{
  "type": "Feature",
  "properties": {
    "gn:admin1_code":"04",
    "gn:asciiname":"Aceitillal",
    "gn:country_code":"GT",
    "gn:dem":1025,
    "gn:feature_class":"P",
    "gn:feature_code":"PPL",
    "gn:name":"Aceitillal",
    "gn:population":0,
    "gn:timezone":"America/Guatemala",
    "iso:country":"GT",
    "wof:name":"Aceitillal",
    "wof:placetype":"locality"
},
  "geometry": {"coordinates":[-89.51666999999998,14.58333],"type":"Point"}
}