{
  "type": "Feature",
  "properties": {
    "gn:admin1_code":"19",
    "gn:asciiname":"Xeabaj",
    "gn:country_code":"GT",
    "gn:dem":2822,
    "gn:feature_class":"P",
    "gn:feature_code":"PPL",
    "gn:name":"Xeabaj",
    "gn:population":0,
    "gn:timezone":"America/Guatemala",
    "iso:country":"GT",
    "wof:name":"Xeabaj",
    "wof:placetype":"locality"
},
  "geometry": {"coordinates":[-91.38333,14.81667],"type":"Point"}
}