{
  "type": "Feature",
  "properties": {
    "gn:admin1_code":"13",
    "gn:asciiname":"San Martin Chiquito",
    "gn:country_code":"GT",
    "gn:dem":2339,
    "gn:feature_class":"P",
    "gn:feature_code":"PPL",
    "gn:name":"San Mart\u00edn Chiquito",
    "gn:population":0,
    "gn:timezone":"America/Guatemala",
    "iso:country":"GT",
    "wof:name":"San Martin Chiquito",
    "wof:placetype":"locality"
},
  "geometry": {"coordinates":[-91.66667,14.81667],"type":"Point"}
}