{
  "type": "Feature",
  "properties": {
    "gn:admin1_code":"08",
    "gn:asciiname":"Xenaxicul",
    "gn:country_code":"GT",
    "gn:dem":2355,
    "gn:feature_class":"P",
    "gn:feature_code":"PPL",
    "gn:name":"Xenaxicul",
    "gn:population":0,
    "gn:timezone":"America/Guatemala",
    "iso:country":"GT",
    "name:spa_x_preferred":[
        "Xenaxicul"
    ],
    "wof:name":"Xenaxicul",
    "wof:placetype":"locality"
},
  "geometry": {"coordinates":[-91.20556999999999,15.36521],"type":"Point"}
}