{
  "type": "Feature",
  "properties": {
    "gn:admin1_code":"12",
    "gn:asciiname":"Cruce Dos Aguadas",
    "gn:country_code":"GT",
    "gn:dem":157,
    "gn:feature_class":"P",
    "gn:feature_code":"PPL",
    "gn:name":"Cruce Dos Aguadas",
    "gn:population":0,
    "gn:timezone":"America/Guatemala",
    "iso:country":"GT",
    "name:spa_x_preferred":[
        "Cruce Dos Aguadas"
    ],
    "name:spa_x_variant":[
        "Chunill\u00e1"
    ],
    "wof:name":"Cruce Dos Aguadas",
    "wof:placetype":"locality"
},
  "geometry": {"coordinates":[-89.93008,17.14907],"type":"Point"}
}