{
  "type": "Feature",
  "properties": {
    "gn:admin1_code":"11",
    "gn:asciiname":"El Perulero",
    "gn:country_code":"GT",
    "gn:dem":963,
    "gn:feature_class":"P",
    "gn:feature_code":"PPL",
    "gn:name":"El Perulero",
    "gn:population":0,
    "gn:timezone":"America/Guatemala",
    "iso:country":"GT",
    "wof:name":"El Perulero",
    "wof:placetype":"locality"
},
  "geometry": {"coordinates":[-89.81667,14.15],"type":"Point"}
}