{
  "type": "Feature",
  "properties": {
    "gn:admin1_code":"08",
    "gn:asciiname":"La Capilla",
    "gn:country_code":"GT",
    "gn:dem":2072,
    "gn:feature_class":"P",
    "gn:feature_code":"PPL",
    "gn:name":"La Capilla",
    "gn:population":0,
    "gn:timezone":"America/Guatemala",
    "iso:country":"GT",
    "name:spa_x_preferred":[
        "La Capilla"
    ],
    "wof:name":"La Capilla",
    "wof:placetype":"locality"
},
  "geometry": {"coordinates":[-91.40572,15.32902],"type":"Point"}
}