{
  "type": "Feature",
  "properties": {
    "gn:admin1_code":"19",
    "gn:asciiname":"Guineales",
    "gn:country_code":"GT",
    "gn:dem":914,
    "gn:feature_class":"P",
    "gn:feature_code":"PPL",
    "gn:name":"Guineales",
    "gn:population":0,
    "gn:timezone":"America/Guatemala",
    "iso:country":"GT",
    "wof:name":"Guineales",
    "wof:placetype":"locality"
},
  "geometry": {"coordinates":[-91.38333,14.66667],"type":"Point"}
}