{
  "type": "Feature",
  "properties": {
    "gn:admin1_code":"13",
    "gn:asciiname":"Las Conchas",
    "gn:country_code":"GT",
    "gn:dem":84,
    "gn:feature_class":"P",
    "gn:feature_code":"PPL",
    "gn:name":"Las Conchas",
    "gn:population":0,
    "gn:timezone":"America/Guatemala",
    "iso:country":"GT",
    "name:spa_x_preferred":[
        "Hacienda Las Conchas"
    ],
    "name:spa_x_variant":[
        "Las Conchas"
    ],
    "wof:name":"Las Conchas",
    "wof:placetype":"locality"
},
  "geometry": {"coordinates":[-92.04136,14.70301],"type":"Point"}
}