{
  "type": "Feature",
  "properties": {
    "gn:admin1_code":"12",
    "gn:asciiname":"Boca del Monte",
    "gn:country_code":"GT",
    "gn:dem":439,
    "gn:feature_class":"P",
    "gn:feature_code":"PPL",
    "gn:name":"Boca del Monte",
    "gn:population":0,
    "gn:timezone":"America/Guatemala",
    "iso:country":"GT",
    "name:ita_x_preferred":[
        "Boca del Monte"
    ],
    "name:spa_x_preferred":[
        "Boca del Monte"
    ],
    "name:zho_x_preferred":[
        "\u535a\u5361\u5fb7\u5c14\u8499\u7279"
    ],
    "wof:name":"Boca del Monte",
    "wof:placetype":"locality"
},
  "geometry": {"coordinates":[-89.42917,16.47611],"type":"Point"}
}