{
  "type": "Feature",
  "properties": {
    "gn:admin1_code":"12",
    "gn:asciiname":"Boca del Monte",
    "gn:country_code":"GT",
    "gn:dem":439,
    "gn:feature_class":"P",
    "gn:feature_code":"PPL",
    "gn:name":"Boca del Monte",
    "gn:population":0,
    "gn:timezone":"America/Guatemala",
    "iso:country":"GT",
    "wof:name":"Boca del Monte",
    "wof:placetype":"locality"
},
  "geometry": {"coordinates":[-89.42917,16.47611],"type":"Point"}
}