{
  "type": "Feature",
  "properties": {
    "gn:admin1_code":"09",
    "gn:asciiname":"Chinook",
    "gn:country_code":"GT",
    "gn:dem":10,
    "gn:feature_class":"P",
    "gn:feature_code":"PPL",
    "gn:name":"Chinook",
    "gn:population":0,
    "gn:timezone":"America/Guatemala",
    "iso:country":"GT",
    "wof:name":"Chinook",
    "wof:placetype":"locality"
},
  "geometry": {"coordinates":[-88.36667,15.68333],"type":"Point"}
}