{
  "type": "Feature",
  "properties": {
    "gn:admin1_code":"12",
    "gn:asciiname":"San Joaquin",
    "gn:country_code":"GT",
    "gn:dem":158,
    "gn:feature_class":"P",
    "gn:feature_code":"PPL",
    "gn:name":"San Joaqu\u00edn",
    "gn:population":0,
    "gn:timezone":"America/Guatemala",
    "iso:country":"GT",
    "name:ara_x_preferred":[
        "\u0633\u0627\u0646 \u0647\u0648\u0627\u0643\u0648\u064a\u0646"
    ],
    "name:ben_x_preferred":[
        "\u09b8\u09be\u09a8 \u099c\u09cb\u09af\u09bc\u09be\u0995\u09c1\u0987\u09a8"
    ],
    "name:ceb_x_preferred":[
        "San Joaquin"
    ],
    "name:deu_x_preferred":[
        "San Joaquin"
    ],
    "name:ell_x_preferred":[
        "\u03a3\u03b1\u03bd \u03a7\u03bf\u03b1\u03ba\u03af\u03bd"
    ],
    "name:fra_x_preferred":[
        "San Joaquin"
    ],
    "name:heb_x_preferred":[
        "\u05e1\u05df \u05d7\u05d5\u05d0\u05e7\u05d9\u05df"
    ],
    "name:hin_x_preferred":[
        "\u0938\u0948\u0928 \u091c\u094b\u0915\u093f\u0928"
    ],
    "name:hun_x_preferred":[
        "San Joaquin"
    ],
    "name:ind_x_preferred":[
        "San Joaquin"
    ],
    "name:ita_x_preferred":[
        "San Joaquin"
    ],
    "name:nds_x_preferred":[
        "San Joaquin"
    ],
    "name:nld_x_preferred":[
        "San Joaquin"
    ],
    "name:pol_x_preferred":[
        "San Joaquin"
    ],
    "name:por_x_preferred":[
        "San Joaquin"
    ],
    "name:spa_x_preferred":[
        "San Joaqu\u00edn"
    ],
    "name:swe_x_preferred":[
        "San Joaquin River"
    ],
    "name:swe_x_variant":[
        "San Joaquin"
    ],
    "name:tur_x_preferred":[
        "San Joaquin"
    ],
    "name:war_x_preferred":[
        "San Joaquin"
    ],
    "wof:name":"San Joaquin",
    "wof:placetype":"locality"
},
  "geometry": {"coordinates":[-90.25123000000001,16.91699],"type":"Point"}
}