{
  "type": "Feature",
  "properties": {
    "gn:admin1_code":"17",
    "gn:asciiname":"Coxmac",
    "gn:country_code":"GT",
    "gn:dem":2372,
    "gn:feature_class":"P",
    "gn:feature_code":"PPL",
    "gn:name":"Coxmac",
    "gn:population":0,
    "gn:timezone":"America/Guatemala",
    "iso:country":"GT",
    "name:spa_x_preferred":[
        "Coxmac"
    ],
    "wof:name":"Coxmac",
    "wof:placetype":"locality"
},
  "geometry": {"coordinates":[-91.71543,15.08951],"type":"Point"}
}