{
  "type": "Feature",
  "properties": {
    "gn:admin1_code":"08",
    "gn:asciiname":"Cerro Verde",
    "gn:country_code":"GT",
    "gn:dem":1614,
    "gn:feature_class":"P",
    "gn:feature_code":"PPL",
    "gn:name":"Cerro Verde",
    "gn:population":0,
    "gn:timezone":"America/Guatemala",
    "iso:country":"GT",
    "name:spa_x_preferred":[
        "Cerro Verde"
    ],
    "name:spa_x_variant":[
        "Sociedad Minera Cerro Verde"
    ],
    "wof:name":"Cerro Verde",
    "wof:placetype":"locality"
},
  "geometry": {"coordinates":[-92.00773,15.58446],"type":"Point"}
}