{
  "type": "Feature",
  "properties": {
    "gn:admin1_code":"14",
    "gn:asciiname":"Paxiolin",
    "gn:country_code":"GT",
    "gn:dem":1696,
    "gn:feature_class":"P",
    "gn:feature_code":"PPL",
    "gn:name":"Paxiol\u00edn",
    "gn:population":0,
    "gn:timezone":"America/Guatemala",
    "iso:country":"GT",
    "name:spa_x_preferred":[
        "Paxiol\u00edn"
    ],
    "wof:name":"Paxiolin",
    "wof:placetype":"locality"
},
  "geometry": {"coordinates":[-91.31249,15.20487],"type":"Point"}
}