{
  "type": "Feature",
  "properties": {
    "gn:admin1_code":"21",
    "gn:asciiname":"Pino Grande",
    "gn:country_code":"GT",
    "gn:dem":1679,
    "gn:feature_class":"P",
    "gn:feature_code":"PPL",
    "gn:name":"Pino Grande",
    "gn:population":0,
    "gn:timezone":"America/Guatemala",
    "iso:country":"GT",
    "name:spa_x_preferred":[
        "Pino Grande"
    ],
    "wof:name":"Pino Grande",
    "wof:placetype":"locality"
},
  "geometry": {"coordinates":[-91.34087,15.19463],"type":"Point"}
}