{
  "type": "Feature",
  "properties": {
    "gn:admin1_code":"08",
    "gn:asciiname":"Zompopero",
    "gn:country_code":"GT",
    "gn:dem":1578,
    "gn:feature_class":"P",
    "gn:feature_code":"PPL",
    "gn:name":"Zompopero",
    "gn:population":0,
    "gn:timezone":"America/Guatemala",
    "iso:country":"GT",
    "name:spa_x_preferred":[
        "Zompopero"
    ],
    "wof:name":"Zompopero",
    "wof:placetype":"locality"
},
  "geometry": {"coordinates":[-91.79228000000001,15.55905],"type":"Point"}
}