{
  "type": "Feature",
  "properties": {
    "gn:admin1_code":"08",
    "gn:asciiname":"Tihuitz",
    "gn:country_code":"GT",
    "gn:dem":2358,
    "gn:feature_class":"P",
    "gn:feature_code":"PPL",
    "gn:name":"Tihuitz",
    "gn:population":0,
    "gn:timezone":"America/Guatemala",
    "iso:country":"GT",
    "name:spa_x_preferred":[
        "Tihuitz"
    ],
    "wof:name":"Tihuitz",
    "wof:placetype":"locality"
},
  "geometry": {"coordinates":[-91.69804000000001,15.49738],"type":"Point"}
}