{
  "type": "Feature",
  "properties": {
    "gn:admin1_code":"19",
    "gn:asciiname":"Panalachaj",
    "gn:country_code":"GT",
    "gn:dem":1990,
    "gn:feature_class":"P",
    "gn:feature_code":"PPL",
    "gn:name":"Panalachaj",
    "gn:population":0,
    "gn:timezone":"America/Guatemala",
    "iso:country":"GT",
    "wof:name":"Panalachaj",
    "wof:placetype":"locality"
},
  "geometry": {"coordinates":[-91.08333,14.71667],"type":"Point"}
}