{
  "type": "Feature",
  "properties": {
    "gn:admin1_code":"21",
    "gn:asciiname":"Chuiaj",
    "gn:country_code":"GT",
    "gn:dem":2135,
    "gn:feature_class":"P",
    "gn:feature_code":"PPL",
    "gn:name":"Chuiaj",
    "gn:population":0,
    "gn:timezone":"America/Guatemala",
    "iso:country":"GT",
    "name:spa_x_preferred":[
        "Chuiaj"
    ],
    "wof:name":"Chuiaj",
    "wof:placetype":"locality"
},
  "geometry": {"coordinates":[-91.34650000000001,15.03377],"type":"Point"}
}