{
  "type": "Feature",
  "properties": {
    "gn:admin1_code":"09",
    "gn:asciiname":"El Cedro",
    "gn:country_code":"GT",
    "gn:dem":144,
    "gn:feature_class":"P",
    "gn:feature_code":"PPL",
    "gn:name":"El Cedro",
    "gn:population":0,
    "gn:timezone":"America/Guatemala",
    "iso:country":"GT",
    "wof:name":"El Cedro",
    "wof:placetype":"locality"
},
  "geometry": {"coordinates":[-88.76666999999998,15.76667],"type":"Point"}
}