{
  "type": "Feature",
  "properties": {
    "gn:admin1_code":"21",
    "gn:asciiname":"Choacorral",
    "gn:country_code":"GT",
    "gn:dem":2053,
    "gn:feature_class":"P",
    "gn:feature_code":"PPL",
    "gn:name":"Choacorral",
    "gn:population":0,
    "gn:timezone":"America/Guatemala",
    "iso:country":"GT",
    "name:spa_x_preferred":[
        "Choacorral"
    ],
    "wof:name":"Choacorral",
    "wof:placetype":"locality"
},
  "geometry": {"coordinates":[-91.27972,15.03306],"type":"Point"}
}