{
  "type": "Feature",
  "properties": {
    "gn:admin1_code":"01",
    "gn:asciiname":"Seubub",
    "gn:country_code":"GT",
    "gn:dem":1697,
    "gn:feature_class":"P",
    "gn:feature_code":"PPL",
    "gn:name":"Seubub",
    "gn:population":0,
    "gn:timezone":"America/Guatemala",
    "iso:country":"GT",
    "wof:name":"Seubub",
    "wof:placetype":"locality"
},
  "geometry": {"coordinates":[-90.23333,15.45],"type":"Point"}
}