{
  "type": "Feature",
  "properties": {
    "gn:admin1_code":"05",
    "gn:asciiname":"Comaja",
    "gn:country_code":"GT",
    "gn:dem":402,
    "gn:feature_class":"P",
    "gn:feature_code":"PPL",
    "gn:name":"Comaja",
    "gn:population":0,
    "gn:timezone":"America/Guatemala",
    "iso:country":"GT",
    "wof:name":"Comaja",
    "wof:placetype":"locality"
},
  "geometry": {"coordinates":[-90.06056,14.955],"type":"Point"}
}