{
  "type": "Feature",
  "properties": {
    "gn:admin1_code":"08",
    "gn:asciiname":"Nalnate",
    "gn:country_code":"GT",
    "gn:dem":2077,
    "gn:feature_class":"P",
    "gn:feature_code":"PPL",
    "gn:name":"Nalnate",
    "gn:population":0,
    "gn:timezone":"America/Guatemala",
    "iso:country":"GT",
    "name:spa_x_preferred":[
        "Nalnate"
    ],
    "wof:name":"Nalnate",
    "wof:placetype":"locality"
},
  "geometry": {"coordinates":[-91.57113,15.77041],"type":"Point"}
}