{
  "type": "Feature",
  "properties": {
    "gn:admin1_code":"17",
    "gn:asciiname":"La Independencia",
    "gn:country_code":"GT",
    "gn:dem":2764,
    "gn:feature_class":"P",
    "gn:feature_code":"PPL",
    "gn:name":"La Independencia",
    "gn:population":0,
    "gn:timezone":"America/Guatemala",
    "iso:country":"GT",
    "name:spa_x_preferred":[
        "La Independencia"
    ],
    "wof:name":"La Independencia",
    "wof:placetype":"locality"
},
  "geometry": {"coordinates":[-91.84314999999999,15.13041],"type":"Point"}
}