{
  "type": "Feature",
  "properties": {
    "gn:admin1_code":"17",
    "gn:asciiname":"Santa Maria Las Nubes",
    "gn:country_code":"GT",
    "gn:dem":1434,
    "gn:feature_class":"P",
    "gn:feature_code":"PPL",
    "gn:name":"Santa Mar\u00eda Las Nubes",
    "gn:population":0,
    "gn:timezone":"America/Guatemala",
    "iso:country":"GT",
    "name:spa_x_preferred":[
        "Santa Mar\u00eda Las Nubes"
    ],
    "wof:name":"Santa Maria Las Nubes",
    "wof:placetype":"locality"
},
  "geometry": {"coordinates":[-92.04997,15.08768],"type":"Point"}
}