{
  "type": "Feature",
  "properties": {
    "gn:admin1_code":"08",
    "gn:asciiname":"Champic",
    "gn:country_code":"GT",
    "gn:dem":3173,
    "gn:feature_class":"P",
    "gn:feature_code":"PPL",
    "gn:name":"Champic",
    "gn:population":0,
    "gn:timezone":"America/Guatemala",
    "iso:country":"GT",
    "name:spa_x_preferred":[
        "Champic"
    ],
    "wof:name":"Champic",
    "wof:placetype":"locality"
},
  "geometry": {"coordinates":[-91.48412,15.44367],"type":"Point"}
}