{
  "type": "Feature",
  "properties": {
    "gn:admin1_code":"12",
    "gn:asciiname":"El Mollejon",
    "gn:country_code":"GT",
    "gn:dem":120,
    "gn:feature_class":"P",
    "gn:feature_code":"PPL",
    "gn:name":"El Mollej\u00f3n",
    "gn:population":0,
    "gn:timezone":"America/Guatemala",
    "iso:country":"GT",
    "name:spa_x_preferred":[
        "El Mollej\u00f3n"
    ],
    "wof:name":"El Mollejon",
    "wof:placetype":"locality"
},
  "geometry": {"coordinates":[-90.40454,16.36289],"type":"Point"}
}