{
  "type": "Feature",
  "properties": {
    "gn:admin1_code":"08",
    "gn:asciiname":"Cantetaj",
    "gn:country_code":"GT",
    "gn:dem":2239,
    "gn:feature_class":"P",
    "gn:feature_code":"PPL",
    "gn:name":"Cantetaj",
    "gn:population":0,
    "gn:timezone":"America/Guatemala",
    "iso:country":"GT",
    "name:spa_x_preferred":[
        "Cantetaj"
    ],
    "wof:name":"Cantetaj",
    "wof:placetype":"locality"
},
  "geometry": {"coordinates":[-91.53967,15.68705],"type":"Point"}
}