{
  "type": "Feature",
  "properties": {
    "gn:admin1_code":"08",
    "gn:asciiname":"Ixcantzan",
    "gn:country_code":"GT",
    "gn:dem":1563,
    "gn:feature_class":"P",
    "gn:feature_code":"PPL",
    "gn:name":"Ixcantz\u00e1n",
    "gn:population":0,
    "gn:timezone":"America/Guatemala",
    "iso:country":"GT",
    "name:spa_x_preferred":[
        "Ixcantz\u00e1n"
    ],
    "name:und_x_variant":[
        "Finca Ixcantz\u00e1n"
    ],
    "wof:name":"Ixcantzan",
    "wof:placetype":"locality"
},
  "geometry": {"coordinates":[-91.47244000000001,16.00233],"type":"Point"}
}