{
  "type": "Feature",
  "properties": {
    "gn:admin1_code":"14",
    "gn:asciiname":"Sanxan",
    "gn:country_code":"GT",
    "gn:dem":1756,
    "gn:feature_class":"P",
    "gn:feature_code":"PPL",
    "gn:name":"Sanx\u00e1n",
    "gn:population":0,
    "gn:timezone":"America/Guatemala",
    "iso:country":"GT",
    "name:spa_x_preferred":[
        "Sanx\u00e1n"
    ],
    "name:und_x_variant":[
        "San Xan"
    ],
    "wof:name":"Sanxan",
    "wof:placetype":"locality"
},
  "geometry": {"coordinates":[-91.29395,15.20207],"type":"Point"}
}