{
  "type": "Feature",
  "properties": {
    "gn:admin1_code":"08",
    "gn:asciiname":"Tzula",
    "gn:country_code":"GT",
    "gn:dem":2043,
    "gn:feature_class":"P",
    "gn:feature_code":"PPL",
    "gn:name":"Tzul\u00e1",
    "gn:population":0,
    "gn:timezone":"America/Guatemala",
    "iso:country":"GT",
    "name:spa_x_preferred":[
        "Tzul\u00e1"
    ],
    "wof:name":"Tzula",
    "wof:placetype":"locality"
},
  "geometry": {"coordinates":[-91.58916000000001,15.73178],"type":"Point"}
}