{
  "type": "Feature",
  "properties": {
    "gn:admin1_code":"04",
    "gn:asciiname":"Jute",
    "gn:country_code":"GT",
    "gn:dem":700,
    "gn:feature_class":"P",
    "gn:feature_code":"PPL",
    "gn:name":"Jute",
    "gn:population":0,
    "gn:timezone":"America/Guatemala",
    "iso:country":"GT",
    "wof:name":"Jute",
    "wof:placetype":"locality"
},
  "geometry": {"coordinates":[-89.23333000000002,14.88333],"type":"Point"}
}