{
  "type": "Feature",
  "properties": {
    "gn:admin1_code":"04",
    "gn:asciiname":"Jute",
    "gn:country_code":"GT",
    "gn:dem":700,
    "gn:feature_class":"P",
    "gn:feature_code":"PPL",
    "gn:name":"Jute",
    "gn:population":0,
    "gn:timezone":"America/Guatemala",
    "iso:country":"GT",
    "name:ara_x_preferred":[
        "\u062c\u0648\u062a"
    ],
    "name:ben_x_preferred":[
        "\u09aa\u09be\u099f"
    ],
    "name:bre_x_preferred":[
        "Jut"
    ],
    "name:ces_x_preferred":[
        "Juta"
    ],
    "name:dan_x_preferred":[
        "Jute"
    ],
    "name:deu_x_preferred":[
        "Jute"
    ],
    "name:epo_x_preferred":[
        "Juto"
    ],
    "name:est_x_preferred":[
        "D\u017euut"
    ],
    "name:fas_x_preferred":[
        "\u0686\u062a\u0627\u06cc\u06cc"
    ],
    "name:fin_x_preferred":[
        "Juutti"
    ],
    "name:heb_x_preferred":[
        "\u05d9\u05d5\u05d8\u05d4"
    ],
    "name:hin_x_preferred":[
        "\u091c\u0942\u091f"
    ],
    "name:hrv_x_preferred":[
        "Juta"
    ],
    "name:hun_x_preferred":[
        "Juta"
    ],
    "name:ita_x_preferred":[
        "Juta"
    ],
    "name:kan_x_preferred":[
        "\u0cb8\u0cc6\u0ca3\u0cac\u0cc1"
    ],
    "name:kor_x_preferred":[
        "\ud669\ub9c8\ud3ec"
    ],
    "name:lit_x_preferred":[
        "D\u017eiutas"
    ],
    "name:mal_x_preferred":[
        "\u0d1a\u0d23\u0d02"
    ],
    "name:mya_x_preferred":[
        "\u1002\u102f\u1014\u103a\u101c\u103b\u103e\u1031\u102c\u103a\u1015\u1004\u103a"
    ],
    "name:nds_x_preferred":[
        "Jute"
    ],
    "name:nld_x_preferred":[
        "Jute"
    ],
    "name:nno_x_preferred":[
        "Jute"
    ],
    "name:nor_x_preferred":[
        "Jute"
    ],
    "name:pan_x_preferred":[
        "\u0a2a\u0a1f\u0a38\u0a28"
    ],
    "name:pol_x_preferred":[
        "Juta"
    ],
    "name:rus_x_preferred":[
        "\u0414\u0436\u0443\u0442"
    ],
    "name:sco_x_preferred":[
        "Juit"
    ],
    "name:slk_x_preferred":[
        "Juta"
    ],
    "name:srp_x_preferred":[
        "Industrija jute"
    ],
    "name:swe_x_preferred":[
        "Jute"
    ],
    "name:tam_x_preferred":[
        "\u0b9a\u0ba3\u0bb2\u0bcd"
    ],
    "name:tel_x_preferred":[
        "\u0c1c\u0c28\u0c2a\u0c28\u0c3e\u0c30"
    ],
    "name:tur_x_preferred":[
        "J\u00fct"
    ],
    "name:ukr_x_preferred":[
        "\u0414\u0436\u0443\u0442"
    ],
    "name:urd_x_preferred":[
        "\u067e\u0679 \u0633\u0646"
    ],
    "wof:name":"Jute",
    "wof:placetype":"locality"
},
  "geometry": {"coordinates":[-89.23333000000002,14.88333],"type":"Point"}
}