{
  "type": "Feature",
  "properties": {
    "gn:admin1_code":"17",
    "gn:asciiname":"Tojchish Candelaria",
    "gn:country_code":"GT",
    "gn:dem":3005,
    "gn:feature_class":"P",
    "gn:feature_code":"PPL",
    "gn:name":"Tojchish Candelaria",
    "gn:population":0,
    "gn:timezone":"America/Guatemala",
    "iso:country":"GT",
    "name:spa_x_preferred":[
        "Tojchish Candelaria"
    ],
    "wof:name":"Tojchish Candelaria",
    "wof:placetype":"locality"
},
  "geometry": {"coordinates":[-92.01738,15.19003],"type":"Point"}
}