{
  "type": "Feature",
  "properties": {
    "gn:admin1_code":"08",
    "gn:asciiname":"El Mojon",
    "gn:country_code":"GT",
    "gn:dem":924,
    "gn:feature_class":"P",
    "gn:feature_code":"PPL",
    "gn:name":"El Moj\u00f3n",
    "gn:population":0,
    "gn:timezone":"America/Guatemala",
    "iso:country":"GT",
    "name:spa_x_preferred":[
        "El Moj\u00f3n"
    ],
    "wof:name":"El Mojon",
    "wof:placetype":"locality"
},
  "geometry": {"coordinates":[-91.82268999999999,15.66894],"type":"Point"}
}