{
  "type": "Feature",
  "properties": {
    "gn:admin1_code":"07",
    "gn:asciiname":"Las Lomas",
    "gn:cc2":"GT",
    "gn:country_code":"GT",
    "gn:dem":1277,
    "gn:feature_class":"P",
    "gn:feature_code":"PPL",
    "gn:name":"Las Lomas",
    "gn:population":0,
    "gn:timezone":"America/Guatemala",
    "iso:country":"GT",
    "name:und_x_variant":[
        "Lomas",
        "Las Lomas"
    ],
    "wof:name":"Las Lomas",
    "wof:placetype":"locality"
},
  "geometry": {"coordinates":[-90.48333,14.73333],"type":"Point"}
}