{
  "type": "Feature",
  "properties": {
    "gn:admin1_code":"11",
    "gn:asciiname":"El Saral",
    "gn:cc2":"GT",
    "gn:country_code":"GT",
    "gn:dem":827,
    "gn:feature_class":"P",
    "gn:feature_code":"PPL",
    "gn:name":"El Saral",
    "gn:population":0,
    "gn:timezone":"America/Guatemala",
    "iso:country":"GT",
    "name:und_x_variant":[
        "El Zaral",
        "El Saral"
    ],
    "wof:name":"El Saral",
    "wof:placetype":"locality"
},
  "geometry": {"coordinates":[-89.76666999999998,14.11667],"type":"Point"}
}