{
  "type": "Feature",
  "properties": {
    "gn:admin1_code":"17",
    "gn:asciiname":"Loma Linda",
    "gn:country_code":"GT",
    "gn:dem":2560,
    "gn:feature_class":"P",
    "gn:feature_code":"PPL",
    "gn:name":"Loma Linda",
    "gn:population":0,
    "gn:timezone":"America/Guatemala",
    "iso:country":"GT",
    "name:spa_x_preferred":[
        "Loma Linda"
    ],
    "wof:name":"Loma Linda",
    "wof:placetype":"locality"
},
  "geometry": {"coordinates":[-91.81874000000001,15.30495],"type":"Point"}
}