{
  "type": "Feature",
  "properties": {
    "gn:admin1_code":"04",
    "gn:asciiname":"La Montana",
    "gn:country_code":"GT",
    "gn:dem":1036,
    "gn:feature_class":"P",
    "gn:feature_code":"PPL",
    "gn:name":"La Monta\u00f1a",
    "gn:population":0,
    "gn:timezone":"America/Guatemala",
    "iso:country":"GT",
    "wof:name":"La Montana",
    "wof:placetype":"locality"
},
  "geometry": {"coordinates":[-89.41667,14.73333],"type":"Point"}
}