{
  "type": "Feature",
  "properties": {
    "gn:admin1_code":"01",
    "gn:admin2_code":"3598414.0",
    "gn:asciiname":"Playitas",
    "gn:country_code":"GT",
    "gn:dem":140,
    "gn:feature_class":"P",
    "gn:feature_code":"PPL",
    "gn:name":"Playitas",
    "gn:population":0,
    "gn:timezone":"America/Guatemala",
    "iso:country":"GT",
    "name:por_x_preferred":[
        "Las Playitas"
    ],
    "wof:name":"Playitas",
    "wof:placetype":"locality"
},
  "geometry": {"coordinates":[-90.45207000000001,16.01331],"type":"Point"}
}