{
  "type": "Feature",
  "properties": {
    "gn:admin1_code":"17",
    "gn:asciiname":"Vega del Carmen",
    "gn:country_code":"GT",
    "gn:dem":2430,
    "gn:feature_class":"P",
    "gn:feature_code":"PPL",
    "gn:name":"Vega del Carmen",
    "gn:population":0,
    "gn:timezone":"America/Guatemala",
    "iso:country":"GT",
    "name:spa_x_preferred":[
        "Vega del Carmen"
    ],
    "wof:name":"Vega del Carmen",
    "wof:placetype":"locality"
},
  "geometry": {"coordinates":[-92.03825000000001,15.2355],"type":"Point"}
}