{
  "type": "Feature",
  "properties": {
    "gn:admin1_code":"08",
    "gn:asciiname":"Tajal",
    "gn:country_code":"GT",
    "gn:dem":2444,
    "gn:feature_class":"P",
    "gn:feature_code":"PPL",
    "gn:name":"Taj\u00e1l",
    "gn:population":0,
    "gn:timezone":"America/Guatemala",
    "iso:country":"GT",
    "name:spa_x_preferred":[
        "Taj\u00e1l"
    ],
    "wof:name":"Tajal",
    "wof:placetype":"locality"
},
  "geometry": {"coordinates":[-91.39610999999999,15.56361],"type":"Point"}
}