{
  "type": "Feature",
  "properties": {
    "gn:admin1_code":"12",
    "gn:asciiname":"Quebrada Seca",
    "gn:country_code":"GT",
    "gn:dem":121,
    "gn:feature_class":"P",
    "gn:feature_code":"PPL",
    "gn:name":"Quebrada Seca",
    "gn:population":0,
    "gn:timezone":"America/Guatemala",
    "iso:country":"GT",
    "wof:name":"Quebrada Seca",
    "wof:placetype":"locality"
},
  "geometry": {"coordinates":[-89.28333000000001,15.98333],"type":"Point"}
}