{
  "type": "Feature",
  "properties": {
    "gn:admin1_code":"12",
    "gn:asciiname":"El Ramonal",
    "gn:country_code":"GT",
    "gn:dem":296,
    "gn:feature_class":"P",
    "gn:feature_code":"PPL",
    "gn:name":"El Ramonal",
    "gn:population":0,
    "gn:timezone":"America/Guatemala",
    "iso:country":"GT",
    "name:spa_x_preferred":[
        "El Ramonal"
    ],
    "wof:name":"El Ramonal",
    "wof:placetype":"locality"
},
  "geometry": {"coordinates":[-89.76155,17.06772],"type":"Point"}
}