{
  "type": "Feature",
  "properties": {
    "gn:admin1_code":"08",
    "gn:asciiname":"Santa Alicia",
    "gn:country_code":"GT",
    "gn:dem":1553,
    "gn:feature_class":"P",
    "gn:feature_code":"PPL",
    "gn:name":"Santa Alicia",
    "gn:population":0,
    "gn:timezone":"America/Guatemala",
    "iso:country":"GT",
    "name:spa_x_preferred":[
        "Santa Alicia"
    ],
    "wof:name":"Santa Alicia",
    "wof:placetype":"locality"
},
  "geometry": {"coordinates":[-91.29712000000001,15.72765],"type":"Point"}
}