{
  "type": "Feature",
  "properties": {
    "gn:admin1_code":"21",
    "gn:asciiname":"Chaguacan",
    "gn:country_code":"GT",
    "gn:dem":2146,
    "gn:feature_class":"P",
    "gn:feature_code":"PPLL",
    "gn:name":"Chaguac\u00e1n",
    "gn:population":0,
    "gn:timezone":"America/Guatemala",
    "iso:country":"GT",
    "name:spa_x_preferred":[
        "Chaguac\u00e1n"
    ],
    "wof:name":"Chaguacan",
    "wof:placetype":"locality"
},
  "geometry": {"coordinates":[-91.39274,15.07242],"type":"Point"}
}