{
  "type": "Feature",
  "properties": {
    "gn:admin1_code":"08",
    "gn:asciiname":"El Cementerio",
    "gn:country_code":"GT",
    "gn:dem":2173,
    "gn:feature_class":"P",
    "gn:feature_code":"PPL",
    "gn:name":"El Cementerio",
    "gn:population":0,
    "gn:timezone":"America/Guatemala",
    "iso:country":"GT",
    "name:spa_x_preferred":[
        "El Cementerio"
    ],
    "wof:name":"El Cementerio",
    "wof:placetype":"locality"
},
  "geometry": {"coordinates":[-91.64593000000001,15.44374],"type":"Point"}
}