{
  "type": "Feature",
  "properties": {
    "gn:admin1_code":"12",
    "gn:asciiname":"Secoyob",
    "gn:country_code":"GT",
    "gn:dem":291,
    "gn:feature_class":"P",
    "gn:feature_code":"PPL",
    "gn:name":"Secoyob",
    "gn:population":0,
    "gn:timezone":"America/Guatemala",
    "iso:country":"GT",
    "wof:name":"Secoyob",
    "wof:placetype":"locality"
},
  "geometry": {"coordinates":[-89.32528000000001,16.03167],"type":"Point"}
}