{
  "type": "Feature",
  "properties": {
    "gn:admin1_code":"14",
    "gn:asciiname":"Xesic Cuatro",
    "gn:country_code":"GT",
    "gn:dem":2236,
    "gn:feature_class":"P",
    "gn:feature_code":"PPL",
    "gn:name":"Xesic Cuatro",
    "gn:population":0,
    "gn:timezone":"America/Guatemala",
    "iso:country":"GT",
    "name:spa_x_preferred":[
        "Xesic Cuatro"
    ],
    "wof:name":"Xesic Cuatro",
    "wof:placetype":"locality"
},
  "geometry": {"coordinates":[-91.13527999999999,15.08085],"type":"Point"}
}