{
  "type": "Feature",
  "properties": {
    "gn:admin1_code":"08",
    "gn:asciiname":"Bacau",
    "gn:country_code":"GT",
    "gn:dem":2169,
    "gn:feature_class":"P",
    "gn:feature_code":"PPL",
    "gn:name":"Baca\u00fa",
    "gn:population":0,
    "gn:timezone":"America/Guatemala",
    "iso:country":"GT",
    "name:spa_x_preferred":[
        "Baca\u00fa"
    ],
    "wof:name":"Bacau",
    "wof:placetype":"locality"
},
  "geometry": {"coordinates":[-91.43980999999999,15.63668],"type":"Point"}
}