{
  "type": "Feature",
  "properties": {
    "gn:admin1_code":"14",
    "gn:asciiname":"El Tablon",
    "gn:country_code":"GT",
    "gn:dem":1717,
    "gn:feature_class":"P",
    "gn:feature_code":"PPL",
    "gn:name":"El Tabl\u00f3n",
    "gn:population":0,
    "gn:timezone":"America/Guatemala",
    "iso:country":"GT",
    "name:spa_x_preferred":[
        "El Tabl\u00f3n"
    ],
    "wof:name":"El Tablon",
    "wof:placetype":"locality"
},
  "geometry": {"coordinates":[-91.19849000000001,15.21759],"type":"Point"}
}