{
  "type": "Feature",
  "properties": {
    "gn:admin1_code":"07",
    "gn:asciiname":"El Platanar",
    "gn:country_code":"GT",
    "gn:dem":1782,
    "gn:feature_class":"P",
    "gn:feature_code":"PPL",
    "gn:name":"El Platanar",
    "gn:population":0,
    "gn:timezone":"America/Guatemala",
    "iso:country":"GT",
    "wof:name":"El Platanar",
    "wof:placetype":"locality"
},
  "geometry": {"coordinates":[-90.41667,14.58333],"type":"Point"}
}