{
  "type": "Feature",
  "properties": {
    "gn:admin1_code":"17",
    "gn:asciiname":"Tuiscab",
    "gn:country_code":"GT",
    "gn:dem":2659,
    "gn:feature_class":"P",
    "gn:feature_code":"PPL",
    "gn:name":"Tuiscab",
    "gn:population":0,
    "gn:timezone":"America/Guatemala",
    "iso:country":"GT",
    "name:spa_x_preferred":[
        "Tuiscab"
    ],
    "wof:name":"Tuiscab",
    "wof:placetype":"locality"
},
  "geometry": {"coordinates":[-91.77073,15.22945],"type":"Point"}
}