{
  "type": "Feature",
  "properties": {
    "gn:admin1_code":"07",
    "gn:asciiname":"Las Canes",
    "gn:country_code":"GT",
    "gn:dem":1191,
    "gn:feature_class":"P",
    "gn:feature_code":"PPL",
    "gn:name":"Las Canes",
    "gn:population":0,
    "gn:timezone":"America/Guatemala",
    "iso:country":"GT",
    "wof:name":"Las Canes",
    "wof:placetype":"locality"
},
  "geometry": {"coordinates":[-90.58333,14.83333],"type":"Point"}
}