{
  "type": "Feature",
  "properties": {
    "iso:country":"GT",
    "name:cat_x_preferred":[
        "San Diego"
    ],
    "name:ceb_x_preferred":[
        "San Diego"
    ],
    "name:deu_x_preferred":[
        "San Diego"
    ],
    "name:eng_x_preferred":[
        "San Diego"
    ],
    "name:fra_x_preferred":[
        "San Diego"
    ],
    "name:glg_x_preferred":[
        "San Diego"
    ],
    "name:ita_x_preferred":[
        "San Diego"
    ],
    "name:nld_x_preferred":[
        "San Diego"
    ],
    "name:pol_x_preferred":[
        "San Diego"
    ],
    "name:por_x_preferred":[
        "San Diego"
    ],
    "name:spa_x_preferred":[
        "San Diego"
    ],
    "name:swe_x_preferred":[
        "San Diego"
    ],
    "name:zho_x_preferred":[
        "\u8056\u5730\u7259\u54e5"
    ],
    "qs:gn_country":"GT",
    "qs:gn_fcode":"PPL",
    "qs:gn_pop":557,
    "qs:name":"San Diego",
    "qs:name_adm0":"Guatemala",
    "qs:name_adm1":"Zacapa",
    "qs:photos":0,
    "qs:photos_1k":0,
    "qs:photos_9k":0,
    "qs:photos_9r":0,
    "qs:photos_all":0,
    "qs:photos_sr":0,
    "qs:placetype":"Town",
    "qs:pop_sr":"2",
    "qs:woe_adm0":23424834,
    "wd:wordcount":30,
    "wof:name":"San Diego",
    "wof:placetype":"locality",
    "wof:population":557
},
  "geometry": {"coordinates":[-89.78333000000001,14.78333],"type":"Point"}
}