{
  "type": "Feature",
  "properties": {
    "iso:country":"GT",
    "name:chi_x_preferred":[
        "\u5854\u5361\u7d0d"
    ],
    "name:deu_x_preferred":[
        "Tacan\u00e1"
    ],
    "name:dut_x_preferred":[
        "Tacan\u00e1"
    ],
    "name:eng_x_preferred":[
        "Tacan\u00e1"
    ],
    "name:fra_x_preferred":[
        "Tacan\u00e1"
    ],
    "name:fre_x_preferred":[
        "Tacan\u00e1"
    ],
    "name:ger_x_preferred":[
        "Tacan\u00e1"
    ],
    "name:ita_x_preferred":[
        "Tacan\u00e1"
    ],
    "name:pol_x_preferred":[
        "Tacan\u00e1"
    ],
    "name:por_x_preferred":[
        "Tacan\u00e1"
    ],
    "name:spa_x_preferred":[
        "Tacan\u00e1"
    ],
    "name:swe_x_preferred":[
        "Tacan\u00e1"
    ],
    "name:zho_x_preferred":[
        "\u5854\u5361\u7d0d"
    ],
    "qs:gn_country":"GT",
    "qs:gn_fcode":"PPL",
    "qs:gn_pop":6438,
    "qs:name":"Tacan\u00e1",
    "qs:name_adm0":"Guatemala",
    "qs:name_adm1":"San Marcos",
    "qs:photos":0,
    "qs:photos_1k":0,
    "qs:photos_9k":1,
    "qs:photos_9r":1,
    "qs:photos_all":8,
    "qs:photos_sr":0,
    "qs:placetype":"Town",
    "qs:pop_sr":"5",
    "qs:woe_adm0":23424834,
    "wd:wordcount":635,
    "wof:name":"Tacan\u00e1",
    "wof:placetype":"locality",
    "wof:population":6438
},
  "geometry": {"coordinates":[-92.08333,15.23333],"type":"Point"}
}