{
  "type": "Feature",
  "properties": {
    "gn:admin1_code":"06",
    "gn:asciiname":"San Isidro Boton Blanco",
    "gn:country_code":"GT",
    "gn:dem":26,
    "gn:feature_class":"P",
    "gn:feature_code":"PPL",
    "gn:name":"San Isidro Bot\u00f3n Blanco",
    "gn:population":0,
    "gn:timezone":"America/Guatemala",
    "iso:country":"GT",
    "wof:name":"San Isidro Boton Blanco",
    "wof:placetype":"locality"
},
  "geometry": {"coordinates":[-90.9075,13.99833],"type":"Point"}
}