{
  "type": "Feature",
  "properties": {
    "gn:admin1_code":"05",
    "gn:asciiname":"Tres Puentes",
    "gn:country_code":"GT",
    "gn:dem":711,
    "gn:feature_class":"P",
    "gn:feature_code":"PPL",
    "gn:name":"Tres Puentes",
    "gn:population":0,
    "gn:timezone":"America/Guatemala",
    "iso:country":"GT",
    "wof:name":"Tres Puentes",
    "wof:placetype":"locality"
},
  "geometry": {"coordinates":[-90.13333,14.78333],"type":"Point"}
}