{
  "type": "Feature",
  "properties": {
    "gn:admin1_code":"14",
    "gn:asciiname":"Buen Camino",
    "gn:country_code":"GT",
    "gn:dem":243,
    "gn:feature_class":"P",
    "gn:feature_code":"PPL",
    "gn:name":"Buen Camino",
    "gn:population":0,
    "gn:timezone":"America/Guatemala",
    "iso:country":"GT",
    "name:spa_x_preferred":[
        "Buen Camino"
    ],
    "wof:name":"Buen Camino",
    "wof:placetype":"locality"
},
  "geometry": {"coordinates":[-91.04127,15.8233],"type":"Point"}
}