{
  "type": "Feature",
  "properties": {
    "gn:admin1_code":"21",
    "gn:asciiname":"Chocanuleu",
    "gn:country_code":"GT",
    "gn:dem":2109,
    "gn:feature_class":"P",
    "gn:feature_code":"PPL",
    "gn:name":"Chocanuleu",
    "gn:population":0,
    "gn:timezone":"America/Guatemala",
    "iso:country":"GT",
    "name:spa_x_preferred":[
        "Chocanuleu"
    ],
    "wof:name":"Chocanuleu",
    "wof:placetype":"locality"
},
  "geometry": {"coordinates":[-91.46898,15.12819],"type":"Point"}
}