{
  "type": "Feature",
  "properties": {
    "gn:admin1_code":"14",
    "gn:asciiname":"Tujolom",
    "gn:country_code":"GT",
    "gn:dem":2398,
    "gn:feature_class":"P",
    "gn:feature_code":"PPL",
    "gn:name":"Tujolom",
    "gn:population":0,
    "gn:timezone":"America/Guatemala",
    "iso:country":"GT",
    "name:spa_x_preferred":[
        "Tujolom"
    ],
    "wof:name":"Tujolom",
    "wof:placetype":"locality"
},
  "geometry": {"coordinates":[-91.22968,15.4916],"type":"Point"}
}