{
  "type": "Feature",
  "properties": {
    "gn:admin1_code":"08",
    "gn:asciiname":"Chalhuitz",
    "gn:country_code":"GT",
    "gn:dem":2518,
    "gn:feature_class":"P",
    "gn:feature_code":"PPL",
    "gn:name":"Chalhuitz",
    "gn:population":0,
    "gn:timezone":"America/Guatemala",
    "iso:country":"GT",
    "name:spa_x_preferred":[
        "Chalhuitz"
    ],
    "wof:name":"Chalhuitz",
    "wof:placetype":"locality"
},
  "geometry": {"coordinates":[-91.61400999999999,15.58597],"type":"Point"}
}