{
  "type": "Feature",
  "properties": {
    "gn:admin1_code":"17",
    "gn:asciiname":"El Durazno",
    "gn:country_code":"GT",
    "gn:dem":2564,
    "gn:feature_class":"P",
    "gn:feature_code":"PPL",
    "gn:name":"El Durazno",
    "gn:population":0,
    "gn:timezone":"America/Guatemala",
    "iso:country":"GT",
    "name:ceb_x_preferred":[
        "El Durazno"
    ],
    "name:spa_x_preferred":[
        "El Durazno"
    ],
    "name:swe_x_preferred":[
        "El Durazno"
    ],
    "wof:name":"El Durazno",
    "wof:placetype":"locality"
},
  "geometry": {"coordinates":[-91.68482,15.05499],"type":"Point"}
}