{
  "type": "Feature",
  "properties": {
    "gn:admin1_code":"07",
    "gn:asciiname":"El Cangrejito",
    "gn:country_code":"GT",
    "gn:dem":1627,
    "gn:feature_class":"P",
    "gn:feature_code":"PPL",
    "gn:name":"El Cangrejito",
    "gn:population":0,
    "gn:timezone":"America/Guatemala",
    "iso:country":"GT",
    "wof:name":"El Cangrejito",
    "wof:placetype":"locality"
},
  "geometry": {"coordinates":[-90.34999999999999,14.65],"type":"Point"}
}