{
  "type": "Feature",
  "properties": {
    "gn:admin1_code":"22",
    "gn:asciiname":"Pexja",
    "gn:cc2":"GT",
    "gn:country_code":"GT",
    "gn:dem":649,
    "gn:feature_class":"P",
    "gn:feature_code":"PPL",
    "gn:name":"Pexj\u00e1",
    "gn:population":0,
    "gn:timezone":"America/Guatemala",
    "iso:country":"GT",
    "name:und_x_variant":[
        "Pashj\u00e1",
        "Pexj\u00e1"
    ],
    "wof:name":"Pexja",
    "wof:placetype":"locality"
},
  "geometry": {"coordinates":[-89.23333000000002,14.96667],"type":"Point"}
}