{
  "type": "Feature",
  "properties": {
    "iso:country":"GT",
    "name:ceb_x_preferred":[
        "Esquipulas Palo Gordo"
    ],
    "name:eng_x_preferred":[
        "Esquipulas Palo Gordo"
    ],
    "name:fra_x_preferred":[
        "Esquipulas Palo Gordo"
    ],
    "name:ita_x_preferred":[
        "Esquipulas Palo Gordo"
    ],
    "name:nan_x_preferred":[
        "Esquipulas Palo Gordo"
    ],
    "name:nld_x_preferred":[
        "Esquipulas Palo Gordo"
    ],
    "name:pol_x_preferred":[
        "Esquipulas Palo Gordo"
    ],
    "name:por_x_preferred":[
        "Esquipulas Palo Gordo"
    ],
    "name:spa_x_preferred":[
        "Esquipulas Palo Gordo"
    ],
    "name:swe_x_preferred":[
        "Esquipulas Palo Gordo"
    ],
    "name:und_x_variant":[
        "Palo Gordo"
    ],
    "name:zho_x_preferred":[
        "\u57c3\u65af\u57fa\u666e\u62c9\u65af\u5e15\u6d1b\u6208\u723e\u591a"
    ],
    "qs:gn_country":"GT",
    "qs:gn_fcode":"PPLA2",
    "qs:gn_pop":1533,
    "qs:name":"Esquipulas Palo Gordo",
    "qs:name_adm0":"Guatemala",
    "qs:name_adm1":"San Marcos",
    "qs:photos":0,
    "qs:photos_1k":0,
    "qs:photos_9k":0,
    "qs:photos_9r":0,
    "qs:photos_all":0,
    "qs:photos_sr":0,
    "qs:placetype":"Town",
    "qs:pop_sr":"3",
    "qs:woe_adm0":23424834,
    "wd:wordcount":392,
    "wof:name":"Esquipulas Palo Gordo",
    "wof:placetype":"locality",
    "wof:population":1533
},
  "geometry": {"coordinates":[-91.81667,14.93333],"type":"Point"}
}