{
  "type": "Feature",
  "properties": {
    "gn:admin1_code":"14",
    "gn:asciiname":"Llano del Pericon",
    "gn:country_code":"GT",
    "gn:dem":1779,
    "gn:feature_class":"P",
    "gn:feature_code":"PPL",
    "gn:name":"Llano del Peric\u00f3n",
    "gn:population":0,
    "gn:timezone":"America/Guatemala",
    "iso:country":"GT",
    "name:spa_x_preferred":[
        "Llano del Peric\u00f3n"
    ],
    "wof:name":"Llano del Pericon",
    "wof:placetype":"locality"
},
  "geometry": {"coordinates":[-91.24078,15.23879],"type":"Point"}
}