{
  "type": "Feature",
  "properties": {
    "gn:admin1_code":"21",
    "gn:asciiname":"Xolcachelaj",
    "gn:country_code":"GT",
    "gn:dem":2792,
    "gn:feature_class":"P",
    "gn:feature_code":"PPL",
    "gn:name":"Xolcachelaj",
    "gn:population":0,
    "gn:timezone":"America/Guatemala",
    "iso:country":"GT",
    "name:spa_x_preferred":[
        "Xolcachelaj"
    ],
    "wof:name":"Xolcachelaj",
    "wof:placetype":"locality"
},
  "geometry": {"coordinates":[-91.51345999999999,15.05087],"type":"Point"}
}