{
  "type": "Feature",
  "properties": {
    "gn:admin1_code":"22",
    "gn:asciiname":"Cimarron",
    "gn:country_code":"GT",
    "gn:dem":929,
    "gn:feature_class":"P",
    "gn:feature_code":"PPL",
    "gn:name":"Cimarr\u00f3n",
    "gn:population":0,
    "gn:timezone":"America/Guatemala",
    "iso:country":"GT",
    "wof:name":"Cimarron",
    "wof:placetype":"locality"
},
  "geometry": {"coordinates":[-89.59999999999999,14.86667],"type":"Point"}
}