{
  "type": "Feature",
  "properties": {
    "gn:admin1_code":"08",
    "gn:asciiname":"El Matasano",
    "gn:country_code":"GT",
    "gn:dem":2220,
    "gn:feature_class":"P",
    "gn:feature_code":"PPL",
    "gn:name":"El Matasano",
    "gn:population":0,
    "gn:timezone":"America/Guatemala",
    "iso:country":"GT",
    "name:spa_x_preferred":[
        "El Matasano"
    ],
    "wof:name":"El Matasano",
    "wof:placetype":"locality"
},
  "geometry": {"coordinates":[-91.90452000000001,15.54943],"type":"Point"}
}