{
  "type": "Feature",
  "properties": {
    "iso:country":"GT",
    "name:cat_x_preferred":[
        "Joyabaj"
    ],
    "name:ceb_x_preferred":[
        "Joyabaj"
    ],
    "name:eng_x_preferred":[
        "Joyabaj"
    ],
    "name:eus_x_preferred":[
        "Joyabaj"
    ],
    "name:fra_x_preferred":[
        "Joyabaj"
    ],
    "name:ita_x_preferred":[
        "Joyabaj"
    ],
    "name:nan_x_preferred":[
        "Joyabaj"
    ],
    "name:nld_x_preferred":[
        "Joyabaj"
    ],
    "name:pol_x_preferred":[
        "Joyabaj"
    ],
    "name:por_x_preferred":[
        "Joyabaj"
    ],
    "name:spa_x_preferred":[
        "Joyabaj"
    ],
    "name:swe_x_preferred":[
        "Joyabaj"
    ],
    "name:zho_x_preferred":[
        "\u970d\u4e9e\u74e6\u8d6b"
    ],
    "qs:gn_country":"GT",
    "qs:gn_fcode":"PPL",
    "qs:gn_pop":13164,
    "qs:name":"Joyabaj",
    "qs:name_adm0":"Guatemala",
    "qs:name_adm1":"Quiche",
    "qs:photos":0,
    "qs:photos_1k":0,
    "qs:photos_9k":1,
    "qs:photos_9r":1,
    "qs:photos_all":7,
    "qs:photos_sr":0,
    "qs:placetype":"Town",
    "qs:pop_sr":"6",
    "qs:woe_adm0":23424834,
    "wof:name":"Joyabaj",
    "wof:placetype":"locality",
    "wof:population":13164
},
  "geometry": {"coordinates":[-90.80611,14.995],"type":"Point"}
}