{
  "type": "Feature",
  "properties": {
    "gn:admin1_code":"08",
    "gn:asciiname":"Chejoj",
    "gn:country_code":"GT",
    "gn:dem":2514,
    "gn:feature_class":"P",
    "gn:feature_code":"PPL",
    "gn:name":"Chejoj",
    "gn:population":0,
    "gn:timezone":"America/Guatemala",
    "iso:country":"GT",
    "name:spa_x_preferred":[
        "Chejoj"
    ],
    "wof:name":"Chejoj",
    "wof:placetype":"locality"
},
  "geometry": {"coordinates":[-91.5958,15.43334],"type":"Point"}
}