{
  "type": "Feature",
  "properties": {
    "gn:admin1_code":"14",
    "gn:asciiname":"Tzanxan",
    "gn:country_code":"GT",
    "gn:dem":1684,
    "gn:feature_class":"P",
    "gn:feature_code":"PPL",
    "gn:name":"Tzanxan",
    "gn:population":0,
    "gn:timezone":"America/Guatemala",
    "iso:country":"GT",
    "name:spa_x_preferred":[
        "Tzanxan"
    ],
    "wof:name":"Tzanxan",
    "wof:placetype":"locality"
},
  "geometry": {"coordinates":[-91.31259,15.20659],"type":"Point"}
}