{
  "type": "Feature",
  "properties": {
    "gn:admin1_code":"13",
    "gn:asciiname":"Chirijquiac",
    "gn:cc2":"GT",
    "gn:country_code":"GT",
    "gn:dem":2785,
    "gn:feature_class":"P",
    "gn:feature_code":"PPL",
    "gn:name":"Chirijquiac",
    "gn:population":0,
    "gn:timezone":"America/Guatemala",
    "iso:country":"GT",
    "name:und_x_variant":[
        "Chirijquiaj",
        "Chiriquiac",
        "Chirijquiac"
    ],
    "wof:name":"Chirijquiac",
    "wof:placetype":"locality"
},
  "geometry": {"coordinates":[-91.41667,14.83333],"type":"Point"}
}