{
  "type": "Feature",
  "properties": {
    "gn:admin1_code":"18",
    "gn:asciiname":"Las Margaritas",
    "gn:country_code":"GT",
    "gn:dem":52,
    "gn:feature_class":"P",
    "gn:feature_code":"PPL",
    "gn:name":"Las Margaritas",
    "gn:population":0,
    "gn:timezone":"America/Guatemala",
    "iso:country":"GT",
    "wof:name":"Las Margaritas",
    "wof:placetype":"locality"
},
  "geometry": {"coordinates":[-90.29028,13.99694],"type":"Point"}
}