{
  "type": "Feature",
  "properties": {
    "gn:admin1_code":"09",
    "gn:asciiname":"Tenedores",
    "gn:country_code":"GT",
    "gn:dem":26,
    "gn:feature_class":"P",
    "gn:feature_code":"PPL",
    "gn:name":"Tenedores",
    "gn:population":0,
    "gn:timezone":"America/Guatemala",
    "iso:country":"GT",
    "wof:name":"Tenedores",
    "wof:placetype":"locality"
},
  "geometry": {"coordinates":[-88.63333,15.55],"type":"Point"}
}