{
  "type": "Feature",
  "properties": {
    "gn:admin1_code":"21",
    "gn:asciiname":"Buenos Aires",
    "gn:country_code":"GT",
    "gn:dem":1984,
    "gn:feature_class":"P",
    "gn:feature_code":"PPLL",
    "gn:name":"Buenos Aires",
    "gn:population":0,
    "gn:timezone":"America/Guatemala",
    "iso:country":"GT",
    "name:spa_x_preferred":[
        "Buenos Aires"
    ],
    "wof:name":"Buenos Aires",
    "wof:placetype":"locality"
},
  "geometry": {"coordinates":[-91.32726,15.08177],"type":"Point"}
}