{
  "type": "Feature",
  "properties": {
    "gn:admin1_code":"01",
    "gn:asciiname":"Secansin",
    "gn:country_code":"GT",
    "gn:dem":1519,
    "gn:feature_class":"P",
    "gn:feature_code":"PPL",
    "gn:name":"Secans\u00edn",
    "gn:population":0,
    "gn:timezone":"America/Guatemala",
    "iso:country":"GT",
    "wof:name":"Secansin",
    "wof:placetype":"locality"
},
  "geometry": {"coordinates":[-89.86667,15.46667],"type":"Point"}
}