{
  "type": "Feature",
  "properties": {
    "gn:admin1_code":"17",
    "gn:asciiname":"Barranca de Galvez",
    "gn:country_code":"GT",
    "gn:dem":2483,
    "gn:feature_class":"P",
    "gn:feature_code":"PPL",
    "gn:name":"Barranca de Galvez",
    "gn:population":0,
    "gn:timezone":"America/Guatemala",
    "iso:country":"GT",
    "name:spa_x_preferred":[
        "Barranca de Galvez"
    ],
    "name:und_x_variant":[
        "Barrancas de G\u00e1lvez"
    ],
    "wof:name":"Barranca de Galvez",
    "wof:placetype":"locality"
},
  "geometry": {"coordinates":[-91.86614,15.02092],"type":"Point"}
}