{
  "type": "Feature",
  "properties": {
    "gn:admin1_code":"13",
    "gn:asciiname":"Calel",
    "gn:country_code":"GT",
    "gn:dem":2709,
    "gn:feature_class":"P",
    "gn:feature_code":"PPL",
    "gn:name":"Calel",
    "gn:population":0,
    "gn:timezone":"America/Guatemala",
    "iso:country":"GT",
    "name:spa_x_preferred":[
        "Calel"
    ],
    "wof:name":"Calel",
    "wof:placetype":"locality"
},
  "geometry": {"coordinates":[-91.56784,15.09246],"type":"Point"}
}