{
  "type": "Feature",
  "properties": {
    "gn:admin1_code":"04",
    "gn:asciiname":"Duraznal",
    "gn:country_code":"GT",
    "gn:dem":1496,
    "gn:feature_class":"P",
    "gn:feature_code":"PPL",
    "gn:name":"Duraznal",
    "gn:population":0,
    "gn:timezone":"America/Guatemala",
    "iso:country":"GT",
    "wof:name":"Duraznal",
    "wof:placetype":"locality"
},
  "geometry": {"coordinates":[-89.36667,14.51667],"type":"Point"}
}