{
  "type": "Feature",
  "properties": {
    "gn:admin1_code":"07",
    "gn:asciiname":"Sacojito",
    "gn:country_code":"GT",
    "gn:dem":1314,
    "gn:feature_class":"P",
    "gn:feature_code":"PPL",
    "gn:name":"Sacojito",
    "gn:population":0,
    "gn:timezone":"America/Guatemala",
    "iso:country":"GT",
    "wof:name":"Sacojito",
    "wof:placetype":"locality"
},
  "geometry": {"coordinates":[-90.51667,14.71667],"type":"Point"}
}