{
  "type": "Feature",
  "properties": {
    "gn:admin1_code":"08",
    "gn:asciiname":"Cancabal",
    "gn:country_code":"GT",
    "gn:dem":1712,
    "gn:feature_class":"P",
    "gn:feature_code":"PPL",
    "gn:name":"Cancabal",
    "gn:population":0,
    "gn:timezone":"America/Guatemala",
    "iso:country":"GT",
    "name:spa_x_preferred":[
        "Cancabal"
    ],
    "name:und_x_variant":[
        "Canc\u00e1bal"
    ],
    "wof:name":"Cancabal",
    "wof:placetype":"locality"
},
  "geometry": {"coordinates":[-91.43619,15.23951],"type":"Point"}
}