{
  "type": "Feature",
  "properties": {
    "gn:admin1_code":"11",
    "gn:asciiname":"Las Hilitas",
    "gn:country_code":"GT",
    "gn:dem":658,
    "gn:feature_class":"P",
    "gn:feature_code":"PPL",
    "gn:name":"Las Hilitas",
    "gn:population":0,
    "gn:timezone":"America/Guatemala",
    "iso:country":"GT",
    "wof:name":"Las Hilitas",
    "wof:placetype":"locality"
},
  "geometry": {"coordinates":[-90.07139000000002,13.98611],"type":"Point"}
}