{
  "type": "Feature",
  "properties": {
    "gn:admin1_code":"17",
    "gn:asciiname":"Toquian Chico",
    "gn:country_code":"GT",
    "gn:dem":1839,
    "gn:feature_class":"P",
    "gn:feature_code":"PPL",
    "gn:name":"Toqui\u00e1n Chico",
    "gn:population":0,
    "gn:timezone":"America/Guatemala",
    "iso:country":"GT",
    "name:spa_x_preferred":[
        "Toqui\u00e1n Chico"
    ],
    "name:und_x_variant":[
        "Tojqui\u00e1n Chico"
    ],
    "wof:name":"Toquian Chico",
    "wof:placetype":"locality"
},
  "geometry": {"coordinates":[-91.95265000000001,15.05856],"type":"Point"}
}