{
  "type": "Feature",
  "properties": {
    "gn:admin1_code":"22",
    "gn:asciiname":"El Naranjo",
    "gn:country_code":"GT",
    "gn:dem":1047,
    "gn:feature_class":"P",
    "gn:feature_code":"PPL",
    "gn:name":"El Naranjo",
    "gn:population":0,
    "gn:timezone":"America/Guatemala",
    "iso:country":"GT",
    "wof:name":"El Naranjo",
    "wof:placetype":"locality"
},
  "geometry": {"coordinates":[-89.40000000000001,14.98333],"type":"Point"}
}