{
  "type": "Feature",
  "properties": {
    "gn:admin1_code":"07",
    "gn:asciiname":"Azacualpilla",
    "gn:country_code":"GT",
    "gn:dem":1070,
    "gn:feature_class":"P",
    "gn:feature_code":"PPL",
    "gn:name":"Azacualpilla",
    "gn:population":0,
    "gn:timezone":"America/Guatemala",
    "iso:country":"GT",
    "wof:name":"Azacualpilla",
    "wof:placetype":"locality"
},
  "geometry": {"coordinates":[-90.36667,14.71667],"type":"Point"}
}