{
  "type": "Feature",
  "properties": {
    "gn:admin1_code":"10",
    "gn:asciiname":"Pino Zapaton",
    "gn:cc2":"GT",
    "gn:country_code":"GT",
    "gn:dem":1662,
    "gn:feature_class":"P",
    "gn:feature_code":"PPL",
    "gn:name":"Pino Zapat\u00f3n",
    "gn:population":0,
    "gn:timezone":"America/Guatemala",
    "iso:country":"GT",
    "name:und_x_variant":[
        "Pino Zacat\u00f3n",
        "Pino Zapat\u00f3n"
    ],
    "wof:name":"Pino Zapaton",
    "wof:placetype":"locality"
},
  "geometry": {"coordinates":[-90.05,14.45],"type":"Point"}
}