{
  "type": "Feature",
  "properties": {
    "gn:admin1_code":"11",
    "gn:asciiname":"Los Bordos",
    "gn:country_code":"GT",
    "gn:dem":13,
    "gn:feature_class":"P",
    "gn:feature_code":"PPL",
    "gn:name":"Los Bordos",
    "gn:population":0,
    "gn:timezone":"America/Guatemala",
    "iso:country":"GT",
    "wof:name":"Los Bordos",
    "wof:placetype":"locality"
},
  "geometry": {"coordinates":[-90.11611000000001,13.79583],"type":"Point"}
}