{
  "type": "Feature",
  "properties": {
    "gn:gn_country":"GT",
    "gn:gn_fcode":"PPL",
    "gn:gn_pop":7465,
    "gn:population":7465,
    "iso:country":"GT",
    "qs_pg:aaroncc":"GT",
    "qs_pg:gn_country":"GT",
    "qs_pg:gn_fcode":"PPL",
    "qs_pg:gn_pop":7465,
    "qs_pg:name":"Chahal",
    "qs_pg:photos_9r":0,
    "qs_pg:photos_sr":0,
    "qs_pg:pop_sr":5,
    "qs_pg:qs_pg_placetype":"locality",
    "wof:name":"Chahal",
    "wof:placetype":"locality",
    "wof:population":7465
},
  "geometry": {"coordinates":[-89.60432,15.79561],"type":"Point"}
}