{
  "type": "Feature",
  "properties": {
    "gn:admin1_code":"17",
    "gn:asciiname":"El Jicaro",
    "gn:country_code":"GT",
    "gn:dem":2839,
    "gn:feature_class":"P",
    "gn:feature_code":"PPL",
    "gn:name":"El J\u00edcaro",
    "gn:population":0,
    "gn:timezone":"America/Guatemala",
    "iso:country":"GT",
    "name:spa_x_preferred":[
        "El J\u00edcaro"
    ],
    "wof:name":"El Jicaro",
    "wof:placetype":"locality"
},
  "geometry": {"coordinates":[-91.78523,15.06915],"type":"Point"}
}