{
  "type": "Feature",
  "properties": {
    "gn:admin1_code":"08",
    "gn:asciiname":"Las Espinas",
    "gn:country_code":"GT",
    "gn:dem":1823,
    "gn:feature_class":"P",
    "gn:feature_code":"PPL",
    "gn:name":"Las Espinas",
    "gn:population":0,
    "gn:timezone":"America/Guatemala",
    "iso:country":"GT",
    "name:spa_x_preferred":[
        "Las Espinas"
    ],
    "wof:name":"Las Espinas",
    "wof:placetype":"locality"
},
  "geometry": {"coordinates":[-91.51833000000001,15.25915],"type":"Point"}
}