{
  "type": "Feature",
  "properties": {
    "gn:admin1_code":"17",
    "gn:asciiname":"Cancil",
    "gn:country_code":"GT",
    "gn:dem":2501,
    "gn:feature_class":"P",
    "gn:feature_code":"PPL",
    "gn:name":"Cancil",
    "gn:population":0,
    "gn:timezone":"America/Guatemala",
    "iso:country":"GT",
    "name:spa_x_preferred":[
        "Cancil"
    ],
    "wof:name":"Cancil",
    "wof:placetype":"locality"
},
  "geometry": {"coordinates":[-91.7192,15.20528],"type":"Point"}
}