{
  "type": "Feature",
  "properties": {
    "gn:admin1_code":"12",
    "gn:asciiname":"Mactun",
    "gn:country_code":"GT",
    "gn:dem":51,
    "gn:feature_class":"P",
    "gn:feature_code":"PPL",
    "gn:name":"Mactun",
    "gn:population":0,
    "gn:timezone":"America/Guatemala",
    "iso:country":"GT",
    "name:spa_x_preferred":[
        "Mactun"
    ],
    "wof:name":"Mactun",
    "wof:placetype":"locality"
},
  "geometry": {"coordinates":[-90.69665999999999,17.37967],"type":"Point"}
}