{
  "type": "Feature",
  "properties": {
    "gn:admin1_code":"12",
    "gn:asciiname":"Cumbre",
    "gn:country_code":"GT",
    "gn:dem":402,
    "gn:feature_class":"P",
    "gn:feature_code":"PPL",
    "gn:name":"Cumbre",
    "gn:population":0,
    "gn:timezone":"America/Guatemala",
    "iso:country":"GT",
    "name:ceb_x_preferred":[
        "Cumbre"
    ],
    "name:nld_x_preferred":[
        "Cumbre"
    ],
    "name:nor_x_preferred":[
        "Cumbre"
    ],
    "name:swe_x_preferred":[
        "Cumbre"
    ],
    "name:vie_x_preferred":[
        "Cumbre"
    ],
    "name:war_x_preferred":[
        "Cumbre"
    ],
    "wof:name":"Cumbre",
    "wof:placetype":"locality"
},
  "geometry": {"coordinates":[-89.00667,16.39722],"type":"Point"}
}