{
  "type": "Feature",
  "properties": {
    "gn:admin1_code":"17",
    "gn:asciiname":"Los Cerezos",
    "gn:country_code":"GT",
    "gn:dem":2746,
    "gn:feature_class":"P",
    "gn:feature_code":"PPL",
    "gn:name":"Los Cerezos",
    "gn:population":0,
    "gn:timezone":"America/Guatemala",
    "iso:country":"GT",
    "name:spa_x_preferred":[
        "Los Cerezos"
    ],
    "wof:name":"Los Cerezos",
    "wof:placetype":"locality"
},
  "geometry": {"coordinates":[-91.81879000000001,15.20049],"type":"Point"}
}