{
  "type": "Feature",
  "properties": {
    "gn:admin1_code":"05",
    "gn:asciiname":"El Pino",
    "gn:country_code":"GT",
    "gn:dem":958,
    "gn:feature_class":"P",
    "gn:feature_code":"PPL",
    "gn:name":"El Pino",
    "gn:population":0,
    "gn:timezone":"America/Guatemala",
    "iso:country":"GT",
    "name:ast_x_preferred":[
        "El Pino"
    ],
    "name:ceb_x_preferred":[
        "El Pino"
    ],
    "name:deu_x_preferred":[
        "El Pino"
    ],
    "name:glg_x_preferred":[
        "O Pino"
    ],
    "name:spa_x_preferred":[
        "El Pino"
    ],
    "name:srp_x_preferred":[
        "\u0415\u043b \u041f\u0438\u043d\u043e"
    ],
    "name:swe_x_preferred":[
        "El Pino"
    ],
    "wof:name":"El Pino",
    "wof:placetype":"locality"
},
  "geometry": {"coordinates":[-90.21666999999999,14.83333],"type":"Point"}
}