{
  "type": "Feature",
  "properties": {
    "gn:admin1_code":"14",
    "gn:asciiname":"Camanibal",
    "gn:country_code":"GT",
    "gn:dem":2162,
    "gn:feature_class":"P",
    "gn:feature_code":"PPL",
    "gn:name":"Camanibal",
    "gn:population":0,
    "gn:timezone":"America/Guatemala",
    "iso:country":"GT",
    "wof:name":"Camanibal",
    "wof:placetype":"locality"
},
  "geometry": {"coordinates":[-91.08333,14.91667],"type":"Point"}
}