{
  "type": "Feature",
  "properties": {
    "gn:admin1_code":"17",
    "gn:asciiname":"Julcan",
    "gn:country_code":"GT",
    "gn:dem":2561,
    "gn:feature_class":"P",
    "gn:feature_code":"PPL",
    "gn:name":"Julc\u00e1n",
    "gn:population":0,
    "gn:timezone":"America/Guatemala",
    "iso:country":"GT",
    "name:spa_x_preferred":[
        "Julc\u00e1n"
    ],
    "wof:name":"Julcan",
    "wof:placetype":"locality"
},
  "geometry": {"coordinates":[-91.86502,15.15438],"type":"Point"}
}