{
  "type": "Feature",
  "properties": {
    "gn:admin1_code":"07",
    "gn:admin2_code":"3595529.0",
    "gn:asciiname":"Sabana Arriba",
    "gn:country_code":"GT",
    "gn:dem":1451,
    "gn:feature_class":"P",
    "gn:feature_code":"PPL",
    "gn:name":"Sabana Arriba",
    "gn:population":0,
    "gn:timezone":"America/Guatemala",
    "iso:country":"GT",
    "wof:name":"Sabana Arriba",
    "wof:placetype":"locality"
},
  "geometry": {"coordinates":[-90.48649,14.63657],"type":"Point"}
}