{
  "type": "Feature",
  "properties": {
    "gn:admin1_code":"08",
    "gn:asciiname":"El Rancho",
    "gn:country_code":"GT",
    "gn:dem":3751,
    "gn:feature_class":"P",
    "gn:feature_code":"PPL",
    "gn:name":"El Rancho",
    "gn:population":0,
    "gn:timezone":"America/Guatemala",
    "iso:country":"GT",
    "wof:name":"El Rancho",
    "wof:placetype":"locality"
},
  "geometry": {"coordinates":[-91.56667,15.51667],"type":"Point"}
}