{
  "type": "Feature",
  "properties": {
    "iso:country":"GT",
    "name:ceb_x_preferred":[
        "Conguaco"
    ],
    "name:eng_x_preferred":[
        "Conguaco"
    ],
    "name:fra_x_preferred":[
        "Conguaco"
    ],
    "name:ita_x_preferred":[
        "Conguaco"
    ],
    "name:nan_x_preferred":[
        "Conguaco"
    ],
    "name:nld_x_preferred":[
        "Conguaco"
    ],
    "name:pol_x_preferred":[
        "Conguaco"
    ],
    "name:por_x_preferred":[
        "Conguaco"
    ],
    "name:spa_x_preferred":[
        "Conguaco"
    ],
    "name:swe_x_preferred":[
        "Conguaco"
    ],
    "name:zho_x_preferred":[
        "\u5b54\u74dc\u79d1"
    ],
    "qs:gn_country":"GT",
    "qs:gn_fcode":"PPL",
    "qs:gn_pop":3415,
    "qs:name":"Conguaco",
    "qs:name_adm0":"Guatemala",
    "qs:name_adm1":"Jutiapa",
    "qs:photos":0,
    "qs:photos_1k":0,
    "qs:photos_9k":1,
    "qs:photos_9r":1,
    "qs:photos_all":1,
    "qs:photos_sr":0,
    "qs:placetype":"Town",
    "qs:pop_sr":"4",
    "qs:woe_adm0":23424834,
    "wd:wordcount":27,
    "wof:name":"Conguaco",
    "wof:placetype":"locality",
    "wof:population":3415
},
  "geometry": {"coordinates":[-90.03111,14.04417],"type":"Point"}
}