{
  "type": "Feature",
  "properties": {
    "gn:admin1_code":"09",
    "gn:asciiname":"Guitarra",
    "gn:cc2":"GT",
    "gn:country_code":"GT",
    "gn:dem":23,
    "gn:feature_class":"P",
    "gn:feature_code":"PPL",
    "gn:name":"Guitarra",
    "gn:population":0,
    "gn:timezone":"America/Guatemala",
    "iso:country":"GT",
    "name:spa_x_preferred":[
        "Guitarra"
    ],
    "name:und_x_variant":[
        "La Guitarra",
        "Guitarra"
    ],
    "wof:name":"Guitarra",
    "wof:placetype":"locality"
},
  "geometry": {"coordinates":[-89.28333000000001,15.83333],"type":"Point"}
}