{
  "type": "Feature",
  "properties": {
    "gn:admin1_code":"08",
    "gn:asciiname":"Canquintic",
    "gn:country_code":"GT",
    "gn:dem":1679,
    "gn:feature_class":"P",
    "gn:feature_code":"PPL",
    "gn:name":"Canquintic",
    "gn:population":0,
    "gn:timezone":"America/Guatemala",
    "iso:country":"GT",
    "name:und_x_variant":[
        "Caquintie",
        "Canquintic"
    ],
    "wof:name":"Canquintic",
    "wof:placetype":"locality"
},
  "geometry": {"coordinates":[-91.65683,15.90064],"type":"Point"}
}