{
  "type": "Feature",
  "properties": {
    "gn:admin1_code":"11",
    "gn:asciiname":"Laguna de Briotis",
    "gn:cc2":"GT",
    "gn:country_code":"GT",
    "gn:dem":1332,
    "gn:feature_class":"P",
    "gn:feature_code":"PPL",
    "gn:name":"Laguna de Briotis",
    "gn:population":0,
    "gn:timezone":"America/Guatemala",
    "iso:country":"GT",
    "name:und_x_variant":[
        "Laguneta Briotis",
        "Laguna de Briotis"
    ],
    "wof:name":"Laguna de Briotis",
    "wof:placetype":"locality"
},
  "geometry": {"coordinates":[-90.05,14.05],"type":"Point"}
}