{
  "type": "Feature",
  "properties": {
    "gn:admin1_code":"14",
    "gn:asciiname":"Potreritos",
    "gn:country_code":"GT",
    "gn:dem":1502,
    "gn:feature_class":"P",
    "gn:feature_code":"PPL",
    "gn:name":"Potreritos",
    "gn:population":0,
    "gn:timezone":"America/Guatemala",
    "iso:country":"GT",
    "name:spa_x_preferred":[
        "Potreritos"
    ],
    "wof:name":"Potreritos",
    "wof:placetype":"locality"
},
  "geometry": {"coordinates":[-91.14099,15.62277],"type":"Point"}
}