{
  "type": "Feature",
  "properties": {
    "gn:admin1_code":"14",
    "gn:asciiname":"Cajixay",
    "gn:cc2":"GT",
    "gn:country_code":"GT",
    "gn:dem":1773,
    "gn:feature_class":"P",
    "gn:feature_code":"PPL",
    "gn:name":"Cajixay",
    "gn:population":0,
    "gn:timezone":"America/Guatemala",
    "iso:country":"GT",
    "name:und_x_variant":[
        "Cajixaj",
        "Cajixay"
    ],
    "wof:name":"Cajixay",
    "wof:placetype":"locality"
},
  "geometry": {"coordinates":[-90.93333,15.43333],"type":"Point"}
}