{
  "type": "Feature",
  "properties": {
    "gn:admin1_code":"14",
    "gn:asciiname":"Choaxan",
    "gn:country_code":"GT",
    "gn:dem":1819,
    "gn:feature_class":"P",
    "gn:feature_code":"PPL",
    "gn:name":"Choax\u00e1n",
    "gn:population":0,
    "gn:timezone":"America/Guatemala",
    "iso:country":"GT",
    "wof:name":"Choaxan",
    "wof:placetype":"locality"
},
  "geometry": {"coordinates":[-90.98333,15.01667],"type":"Point"}
}