{
  "type": "Feature",
  "properties": {
    "gn:admin1_code":"08",
    "gn:asciiname":"Tzimaj",
    "gn:country_code":"GT",
    "gn:dem":2879,
    "gn:feature_class":"P",
    "gn:feature_code":"PPL",
    "gn:name":"Tzimaj",
    "gn:population":0,
    "gn:timezone":"America/Guatemala",
    "iso:country":"GT",
    "name:spa_x_preferred":[
        "Tzimaj"
    ],
    "wof:name":"Tzimaj",
    "wof:placetype":"locality"
},
  "geometry": {"coordinates":[-91.54555999999999,15.42919],"type":"Point"}
}