{
  "type": "Feature",
  "properties": {
    "gn:admin1_code":"01",
    "gn:asciiname":"Canruja",
    "gn:country_code":"GT",
    "gn:dem":204,
    "gn:feature_class":"P",
    "gn:feature_code":"PPL",
    "gn:name":"Canruj\u00e1",
    "gn:population":0,
    "gn:timezone":"America/Guatemala",
    "iso:country":"GT",
    "wof:name":"Canruja",
    "wof:placetype":"locality"
},
  "geometry": {"coordinates":[-90.28333000000001,15.85],"type":"Point"}
}