{
  "type": "Feature",
  "properties": {
    "gn:admin1_code":"17",
    "gn:asciiname":"Suchiate",
    "gn:country_code":"GT",
    "gn:dem":1647,
    "gn:feature_class":"P",
    "gn:feature_code":"PPL",
    "gn:name":"Suchiate",
    "gn:population":0,
    "gn:timezone":"America/Guatemala",
    "iso:country":"GT",
    "name:ceb_x_preferred":[
        "R\u00edo Suchiate"
    ],
    "name:deu_x_preferred":[
        "R\u00edo Suchiate"
    ],
    "name:fas_x_preferred":[
        "\u0631\u0648\u062f \u0633\u0648\u0686\u06cc\u0627\u062a\u0647"
    ],
    "name:fra_x_preferred":[
        "Suchiate"
    ],
    "name:lit_x_preferred":[
        "Su\u010diat\u0117"
    ],
    "name:nld_x_preferred":[
        "Suchiate"
    ],
    "name:pol_x_preferred":[
        "Suchiate"
    ],
    "name:por_x_preferred":[
        "Rio Suchiate"
    ],
    "name:rus_x_preferred":[
        "\u0421\u0443\u0447\u044c\u044f\u0442\u0435"
    ],
    "name:spa_x_preferred":[
        "R\u00edo Suchiate"
    ],
    "name:swe_x_preferred":[
        "R\u00edo Suchiate"
    ],
    "name:tgk_x_preferred":[
        "\u0421\u0443\u0447\u0438\u0430\u0442\u0435"
    ],
    "name:zho_x_preferred":[
        "\u8607\u6070\u7279\u6cb3"
    ],
    "wof:name":"Suchiate",
    "wof:placetype":"locality"
},
  "geometry": {"coordinates":[-92.01554,15.10711],"type":"Point"}
}