{
  "type": "Feature",
  "properties": {
    "gn:admin1_code":"17",
    "gn:asciiname":"Suchiate",
    "gn:country_code":"GT",
    "gn:dem":1647,
    "gn:feature_class":"P",
    "gn:feature_code":"PPL",
    "gn:name":"Suchiate",
    "gn:population":0,
    "gn:timezone":"America/Guatemala",
    "iso:country":"GT",
    "wof:name":"Suchiate",
    "wof:placetype":"locality"
},
  "geometry": {"coordinates":[-92.01554,15.10711],"type":"Point"}
}