{
  "type": "Feature",
  "properties": {
    "iso:country":"GT",
    "name:cat_x_preferred":[
        "Santa Cruz de Barillas"
    ],
    "name:eng_x_preferred":[
        "Santa Cruz Barillas"
    ],
    "name:fra_x_preferred":[
        "Santa Cruz Barillas"
    ],
    "name:ita_x_preferred":[
        "Barillas"
    ],
    "name:nld_x_preferred":[
        "Santa Cruz Barillas"
    ],
    "name:pol_x_preferred":[
        "Santa Cruz Barillas"
    ],
    "name:por_x_preferred":[
        "Santa Cruz Barillas"
    ],
    "name:spa_x_preferred":[
        "Santa Cruz Barillas"
    ],
    "name:zho_x_preferred":[
        "\u8056\u514b\u9b6f\u65af\u5df4\u91cc\u4e9e\u65af"
    ],
    "qs:gn_country":"GT",
    "qs:gn_fcode":"PPL",
    "qs:gn_pop":14100,
    "qs:name":"Barillas",
    "qs:name_adm0":"Guatemala",
    "qs:name_adm1":"Huehuetenango",
    "qs:photos":0,
    "qs:photos_1k":0,
    "qs:photos_9k":1,
    "qs:photos_9r":1,
    "qs:photos_all":2,
    "qs:photos_sr":0,
    "qs:placetype":"Town",
    "qs:pop_sr":"6",
    "qs:woe_adm0":23424834,
    "wof:name":"Barillas",
    "wof:placetype":"locality",
    "wof:population":14100
},
  "geometry": {"coordinates":[-91.31583000000001,15.80361],"type":"Point"}
}