{
  "type": "Feature",
  "properties": {
    "gn:admin1_code":"08",
    "gn:asciiname":"Poza",
    "gn:country_code":"GT",
    "gn:dem":2178,
    "gn:feature_class":"P",
    "gn:feature_code":"PPL",
    "gn:name":"Poza",
    "gn:population":0,
    "gn:timezone":"America/Guatemala",
    "iso:country":"GT",
    "name:spa_x_preferred":[
        "Poza"
    ],
    "wof:name":"Poza",
    "wof:placetype":"locality"
},
  "geometry": {"coordinates":[-91.68832,15.71044],"type":"Point"}
}