{
  "type": "Feature",
  "properties": {
    "gn:admin1_code":"12",
    "gn:asciiname":"El Arenal",
    "gn:cc2":"GT",
    "gn:country_code":"GT",
    "gn:dem":102,
    "gn:feature_class":"P",
    "gn:feature_code":"PPL",
    "gn:name":"El Arenal",
    "gn:population":0,
    "gn:timezone":"America/Guatemala",
    "iso:country":"GT",
    "name:und_x_variant":[
        "Arenal",
        "El Arenal"
    ],
    "wof:name":"El Arenal",
    "wof:placetype":"locality"
},
  "geometry": {"coordinates":[-89.1525,17.02417],"type":"Point"}
}