{
  "type": "Feature",
  "properties": {
    "gn:admin1_code":"14",
    "gn:asciiname":"Parraxtut",
    "gn:country_code":"GT",
    "gn:dem":1737,
    "gn:feature_class":"P",
    "gn:feature_code":"PPL",
    "gn:name":"Parraxtut",
    "gn:population":0,
    "gn:timezone":"America/Guatemala",
    "iso:country":"GT",
    "name:spa_x_preferred":[
        "Parraxtut"
    ],
    "wof:name":"Parraxtut",
    "wof:placetype":"locality"
},
  "geometry": {"coordinates":[-91.17471999999999,15.33988],"type":"Point"}
}