{
  "type": "Feature",
  "properties": {
    "iso:country":"GT",
    "name:fra_x_preferred":[
        "San Juan Tecuaco"
    ],
    "name:ita_x_preferred":[
        "San Juan Tecuaco"
    ],
    "name:pol_x_preferred":[
        "San Juan Tecuaco"
    ],
    "name:por_x_preferred":[
        "San Juan Tecuaco"
    ],
    "name:spa_x_preferred":[
        "San Juan Tecuaco"
    ],
    "name:swe_x_preferred":[
        "San Juan Tecuaco"
    ],
    "name:unk_x_variant":[
        "Tecuaco"
    ],
    "name:zho_x_preferred":[
        "\u8056\u80e1\u5b89\u7279\u5938\u79d1"
    ],
    "qs:gn_country":"GT",
    "qs:gn_fcode":"PPL",
    "qs:gn_pop":2210,
    "qs:name":"San Juan Tecuaco",
    "qs:name_adm0":"Guatemala",
    "qs:name_adm1":"Santa Rosa",
    "qs:photos":0,
    "qs:photos_1k":0,
    "qs:photos_9k":0,
    "qs:photos_9r":0,
    "qs:photos_all":0,
    "qs:photos_sr":0,
    "qs:placetype":"Town",
    "qs:pop_sr":"4",
    "qs:woe_adm0":23424834,
    "wd:wordcount":219,
    "wof:name":"San Juan Tecuaco",
    "wof:placetype":"locality",
    "wof:population":2210
},
  "geometry": {"coordinates":[-90.26111,14.08222],"type":"Point"}
}