{
  "type": "Feature",
  "properties": {
    "gn:admin1_code":"17",
    "gn:asciiname":"Xolhuitz",
    "gn:country_code":"GT",
    "gn:dem":2272,
    "gn:feature_class":"P",
    "gn:feature_code":"PPL",
    "gn:name":"Xolhuitz",
    "gn:population":0,
    "gn:timezone":"America/Guatemala",
    "iso:country":"GT",
    "name:spa_x_preferred":[
        "Xolhuitz"
    ],
    "wof:name":"Xolhuitz",
    "wof:placetype":"locality"
},
  "geometry": {"coordinates":[-92.00673999999999,15.07579],"type":"Point"}
}