{
  "type": "Feature",
  "properties": {
    "gn:admin1_code":"17",
    "gn:asciiname":"Chininguitz",
    "gn:country_code":"GT",
    "gn:dem":2386,
    "gn:feature_class":"P",
    "gn:feature_code":"PPL",
    "gn:name":"Chininguitz",
    "gn:population":0,
    "gn:timezone":"America/Guatemala",
    "iso:country":"GT",
    "name:spa_x_preferred":[
        "Chininguitz"
    ],
    "wof:name":"Chininguitz",
    "wof:placetype":"locality"
},
  "geometry": {"coordinates":[-91.74599000000001,15.21003],"type":"Point"}
}