{
  "type": "Feature",
  "properties": {
    "gn:admin1_code":"14",
    "gn:asciiname":"Candelaria Valle Tres",
    "gn:country_code":"GT",
    "gn:dem":288,
    "gn:feature_class":"P",
    "gn:feature_code":"PPL",
    "gn:name":"Candelaria Valle Tres",
    "gn:population":0,
    "gn:timezone":"America/Guatemala",
    "iso:country":"GT",
    "name:spa_x_preferred":[
        "Candelaria Valle Tres"
    ],
    "wof:name":"Candelaria Valle Tres",
    "wof:placetype":"locality"
},
  "geometry": {"coordinates":[-91.09326,15.78265],"type":"Point"}
}