{
  "type": "Feature",
  "properties": {
    "gn:admin1_code":"12",
    "gn:asciiname":"El Subin",
    "gn:country_code":"GT",
    "gn:dem":124,
    "gn:feature_class":"P",
    "gn:feature_code":"PPL",
    "gn:name":"El Sub\u00edn",
    "gn:population":0,
    "gn:timezone":"America/Guatemala",
    "iso:country":"GT",
    "name:spa_x_preferred":[
        "El Sub\u00edn"
    ],
    "wof:name":"El Subin",
    "wof:placetype":"locality"
},
  "geometry": {"coordinates":[-90.18286000000001,16.63697],"type":"Point"}
}