{
  "type": "Feature",
  "properties": {
    "gn:admin1_code":"08",
    "gn:asciiname":"Pocobastic",
    "gn:country_code":"GT",
    "gn:dem":1571,
    "gn:feature_class":"P",
    "gn:feature_code":"PPL",
    "gn:name":"Pocobastic",
    "gn:population":0,
    "gn:timezone":"America/Guatemala",
    "iso:country":"GT",
    "name:spa_x_preferred":[
        "Pocobastic"
    ],
    "wof:name":"Pocobastic",
    "wof:placetype":"locality"
},
  "geometry": {"coordinates":[-91.72196,16.06818],"type":"Point"}
}