{
  "type": "Feature",
  "properties": {
    "gn:admin1_code":"04",
    "gn:asciiname":"Caulote",
    "gn:cc2":"GT",
    "gn:country_code":"GT",
    "gn:dem":743,
    "gn:feature_class":"P",
    "gn:feature_code":"PPL",
    "gn:name":"Caulote",
    "gn:population":0,
    "gn:timezone":"America/Guatemala",
    "iso:country":"GT",
    "name:und_x_variant":[
        "Caulotes",
        "Caulote"
    ],
    "wof:name":"Caulote",
    "wof:placetype":"locality"
},
  "geometry": {"coordinates":[-89.45,14.65],"type":"Point"}
}