{
  "type": "Feature",
  "properties": {
    "gn:admin1_code":"17",
    "gn:asciiname":"Los Gomez",
    "gn:country_code":"GT",
    "gn:dem":1326,
    "gn:feature_class":"P",
    "gn:feature_code":"PPL",
    "gn:name":"Los G\u00f3mez",
    "gn:population":0,
    "gn:timezone":"America/Guatemala",
    "iso:country":"GT",
    "name:spa_x_preferred":[
        "Los G\u00f3mez"
    ],
    "wof:name":"Los Gomez",
    "wof:placetype":"locality"
},
  "geometry": {"coordinates":[-91.96092,15.00759],"type":"Point"}
}