{
  "type": "Feature",
  "properties": {
    "gn:admin1_code":"12",
    "gn:asciiname":"Granja San Miguel",
    "gn:country_code":"GT",
    "gn:dem":154,
    "gn:feature_class":"P",
    "gn:feature_code":"PPL",
    "gn:name":"Granja San Miguel",
    "gn:population":0,
    "gn:timezone":"America/Guatemala",
    "iso:country":"GT",
    "name:spa_x_preferred":[
        "Granja San Miguel"
    ],
    "wof:name":"Granja San Miguel",
    "wof:placetype":"locality"
},
  "geometry": {"coordinates":[-89.23611,17.02833],"type":"Point"}
}