{
  "type": "Feature",
  "properties": {
    "gn:admin1_code":"11",
    "gn:asciiname":"Tempisque",
    "gn:cc2":"GT",
    "gn:country_code":"GT",
    "gn:dem":1006,
    "gn:feature_class":"P",
    "gn:feature_code":"PPL",
    "gn:name":"Tempisque",
    "gn:population":0,
    "gn:timezone":"America/Guatemala",
    "iso:country":"GT",
    "name:und_x_variant":[
        "El Tempisque",
        "Tempisque"
    ],
    "wof:name":"Tempisque",
    "wof:placetype":"locality"
},
  "geometry": {"coordinates":[-89.63333,14.48333],"type":"Point"}
}