{
  "type": "Feature",
  "properties": {
    "gn:admin1_code":"17",
    "gn:asciiname":"Ixchol",
    "gn:country_code":"GT",
    "gn:dem":2341,
    "gn:feature_class":"P",
    "gn:feature_code":"PPL",
    "gn:name":"Ixchol",
    "gn:population":0,
    "gn:timezone":"America/Guatemala",
    "iso:country":"GT",
    "name:spa_x_preferred":[
        "Ixchol"
    ],
    "wof:name":"Ixchol",
    "wof:placetype":"locality"
},
  "geometry": {"coordinates":[-91.74588,15.25615],"type":"Point"}
}