{
  "type": "Feature",
  "properties": {
    "gn:admin1_code":"08",
    "gn:asciiname":"Tzapocolaj",
    "gn:country_code":"GT",
    "gn:dem":3265,
    "gn:feature_class":"P",
    "gn:feature_code":"PPL",
    "gn:name":"Tzapocolaj",
    "gn:population":0,
    "gn:timezone":"America/Guatemala",
    "iso:country":"GT",
    "name:spa_x_preferred":[
        "Tzapocolaj"
    ],
    "wof:name":"Tzapocolaj",
    "wof:placetype":"locality"
},
  "geometry": {"coordinates":[-91.39173,15.503],"type":"Point"}
}