{
  "type": "Feature",
  "properties": {
    "iso:country":"GT",
    "name:ceb_x_preferred":[
        "Chicacao"
    ],
    "name:eng_x_preferred":[
        "Chicacao"
    ],
    "name:fra_x_preferred":[
        "Chicacao"
    ],
    "name:ita_x_preferred":[
        "Chicacao"
    ],
    "name:nan_x_preferred":[
        "Chicacao"
    ],
    "name:nld_x_preferred":[
        "Chicacao"
    ],
    "name:pol_x_preferred":[
        "Chicacao"
    ],
    "name:por_x_preferred":[
        "Chicacao"
    ],
    "name:spa_x_preferred":[
        "Chicacao"
    ],
    "name:swe_x_preferred":[
        "Chicacao"
    ],
    "name:urd_x_preferred":[
        "\u0634\u06cc\u06a9\u0627\u06a9\u0627\u0648"
    ],
    "name:zho_x_preferred":[
        "\u5947\u5361\u8003"
    ],
    "qs:gn_country":"GT",
    "qs:gn_fcode":"PPL",
    "qs:gn_pop":20426,
    "qs:name":"Chicacao",
    "qs:name_adm0":"Guatemala",
    "qs:name_adm1":"Suchitepequez",
    "qs:photos":0,
    "qs:photos_1k":0,
    "qs:photos_9k":1,
    "qs:photos_9r":1,
    "qs:photos_all":1,
    "qs:photos_sr":0,
    "qs:placetype":"Town",
    "qs:pop_sr":"7",
    "qs:woe_adm0":23424834,
    "wd:wordcount":61,
    "wof:name":"Chicacao",
    "wof:placetype":"locality",
    "wof:population":20426
},
  "geometry": {"coordinates":[-91.31667,14.53333],"type":"Point"}
}