{
  "type": "Feature",
  "properties": {
    "gn:admin1_code":"03",
    "gn:asciiname":"El Tanque",
    "gn:country_code":"GT",
    "gn:dem":1920,
    "gn:feature_class":"P",
    "gn:feature_code":"PPL",
    "gn:name":"El Tanque",
    "gn:population":0,
    "gn:timezone":"America/Guatemala",
    "iso:country":"GT",
    "name:ara_x_preferred":[
        "\u0625\u0644 \u062a\u0627\u0646\u0643\u064a"
    ],
    "name:cat_x_preferred":[
        "El Tanque"
    ],
    "name:ces_x_preferred":[
        "El Tanque"
    ],
    "name:deu_x_preferred":[
        "El Tanque"
    ],
    "name:eus_x_preferred":[
        "El Tanque"
    ],
    "name:fra_x_preferred":[
        "El Tanque"
    ],
    "name:glg_x_preferred":[
        "El Tanque"
    ],
    "name:hun_x_preferred":[
        "El Tanque"
    ],
    "name:ind_x_preferred":[
        "El Tanque"
    ],
    "name:ita_x_preferred":[
        "El Tanque"
    ],
    "name:lat_x_preferred":[
        "El Tanque"
    ],
    "name:msa_x_preferred":[
        "El Tanque"
    ],
    "name:nld_x_preferred":[
        "El Tanque"
    ],
    "name:oci_x_preferred":[
        "El Tanque"
    ],
    "name:pol_x_preferred":[
        "El Tanque"
    ],
    "name:por_x_preferred":[
        "El Tanque"
    ],
    "name:rus_x_preferred":[
        "\u042d\u043b\u044c-\u0422\u0430\u043d\u043a\u0435"
    ],
    "name:spa_x_preferred":[
        "El Tanque"
    ],
    "name:sqi_x_preferred":[
        "El Tanque"
    ],
    "name:ukr_x_preferred":[
        "\u0415\u043b\u044c-\u0422\u0430\u043d\u043a\u0435"
    ],
    "name:uzb_x_preferred":[
        "El Tanque"
    ],
    "name:war_x_preferred":[
        "El Tanque"
    ],
    "name:zho_x_preferred":[
        "\u57c3\u5c14\u5766\u514b"
    ],
    "wof:name":"El Tanque",
    "wof:placetype":"locality"
},
  "geometry": {"coordinates":[-90.86667,14.88333],"type":"Point"}
}