{
  "type": "Feature",
  "properties": {
    "gn:admin1_code":"03",
    "gn:asciiname":"El Tanque",
    "gn:country_code":"GT",
    "gn:dem":1920,
    "gn:feature_class":"P",
    "gn:feature_code":"PPL",
    "gn:name":"El Tanque",
    "gn:population":0,
    "gn:timezone":"America/Guatemala",
    "iso:country":"GT",
    "wof:name":"El Tanque",
    "wof:placetype":"locality"
},
  "geometry": {"coordinates":[-90.86667,14.88333],"type":"Point"}
}