{
  "type": "Feature",
  "properties": {
    "gn:admin1_code":"17",
    "gn:asciiname":"La Democracia",
    "gn:country_code":"GT",
    "gn:dem":274,
    "gn:feature_class":"P",
    "gn:feature_code":"PPL",
    "gn:name":"La Democracia",
    "gn:population":0,
    "gn:timezone":"America/Guatemala",
    "iso:country":"GT",
    "name:spa_x_preferred":[
        "La Democracia"
    ],
    "wof:name":"La Democracia",
    "wof:placetype":"locality"
},
  "geometry": {"coordinates":[-92.09077000000001,14.88602],"type":"Point"}
}