{
  "type": "Feature",
  "properties": {
    "gn:admin1_code":"14",
    "gn:asciiname":"Tzanimacabaj",
    "gn:country_code":"GT",
    "gn:dem":2272,
    "gn:feature_class":"P",
    "gn:feature_code":"PPL",
    "gn:name":"Tzanimacabaj",
    "gn:population":0,
    "gn:timezone":"America/Guatemala",
    "iso:country":"GT",
    "wof:name":"Tzanimacabaj",
    "wof:placetype":"locality"
},
  "geometry": {"coordinates":[-91.06667,14.88333],"type":"Point"}
}