{
  "type": "Feature",
  "properties": {
    "gn:admin1_code":"08",
    "gn:asciiname":"Yulchen",
    "gn:country_code":"GT",
    "gn:dem":2295,
    "gn:feature_class":"P",
    "gn:feature_code":"PPL",
    "gn:name":"Yulch\u00e9n",
    "gn:population":0,
    "gn:timezone":"America/Guatemala",
    "iso:country":"GT",
    "name:spa_x_preferred":[
        "Yulch\u00e9n"
    ],
    "wof:name":"Yulchen",
    "wof:placetype":"locality"
},
  "geometry": {"coordinates":[-91.42448,15.65222],"type":"Point"}
}