{
  "type": "Feature",
  "properties": {
    "iso:country":"GT",
    "name:ceb_x_preferred":[
        "Chiquimulilla"
    ],
    "name:deu_x_preferred":[
        "Chiquimulilla"
    ],
    "name:eng_x_preferred":[
        "Chiquimulilla"
    ],
    "name:fra_x_preferred":[
        "Chiquimulilla"
    ],
    "name:ita_x_preferred":[
        "Chiquimulilla"
    ],
    "name:jpn_x_preferred":[
        "\u30c1\u30ad\u30e0\u30ea\u30ea\u30e3"
    ],
    "name:nld_x_preferred":[
        "Chiquimulilla"
    ],
    "name:pol_x_preferred":[
        "Chiquimulilla"
    ],
    "name:por_x_preferred":[
        "Chiquimulilla"
    ],
    "name:spa_x_preferred":[
        "Chiquimulilla"
    ],
    "name:swe_x_preferred":[
        "Chiquimulilla"
    ],
    "name:urd_x_preferred":[
        "\u0686\u06cc\u06a9\u0648\u06cc\u0645\u0648\u0644\u06cc\u0627"
    ],
    "name:zho_x_preferred":[
        "\u5947\u57fa\u7a46\u5229\u4e9e"
    ],
    "qs:gn_country":"GT",
    "qs:gn_fcode":"PPL",
    "qs:gn_pop":12842,
    "qs:name":"Chiquimulilla",
    "qs:name_adm0":"Guatemala",
    "qs:name_adm1":"Santa Rosa",
    "qs:photos":11,
    "qs:photos_1k":2,
    "qs:photos_9k":1,
    "qs:photos_9r":1,
    "qs:photos_all":11,
    "qs:photos_sr":1,
    "qs:placetype":"Town",
    "qs:pop_sr":"6",
    "qs:woe_adm0":23424834,
    "wd:wordcount":115,
    "wof:name":"Chiquimulilla",
    "wof:placetype":"locality",
    "wof:population":12842
},
  "geometry": {"coordinates":[-90.37667,14.08583],"type":"Point"}
}