{
  "type": "Feature",
  "properties": {
    "gn:admin1_code":"21",
    "gn:asciiname":"Pamesabal",
    "gn:country_code":"GT",
    "gn:dem":2279,
    "gn:feature_class":"P",
    "gn:feature_code":"PPL",
    "gn:name":"Pamesabal",
    "gn:population":0,
    "gn:timezone":"America/Guatemala",
    "iso:country":"GT",
    "name:spa_x_preferred":[
        "Pamesabal"
    ],
    "wof:name":"Pamesabal",
    "wof:placetype":"locality"
},
  "geometry": {"coordinates":[-91.37344,15.02256],"type":"Point"}
}