{
  "type": "Feature",
  "properties": {
    "gn:admin1_code":"08",
    "gn:asciiname":"Yalan Camposanto",
    "gn:country_code":"GT",
    "gn:dem":2084,
    "gn:feature_class":"P",
    "gn:feature_code":"PPL",
    "gn:name":"Yalan Camposanto",
    "gn:population":0,
    "gn:timezone":"America/Guatemala",
    "iso:country":"GT",
    "name:spa_x_preferred":[
        "Yalan Camposanto"
    ],
    "wof:name":"Yalan Camposanto",
    "wof:placetype":"locality"
},
  "geometry": {"coordinates":[-91.61365000000001,15.78669],"type":"Point"}
}