{
  "type": "Feature",
  "properties": {
    "gn:admin1_code":"04",
    "gn:asciiname":"Pericos",
    "gn:country_code":"GT",
    "gn:dem":710,
    "gn:feature_class":"P",
    "gn:feature_code":"PPL",
    "gn:name":"Pericos",
    "gn:population":0,
    "gn:timezone":"America/Guatemala",
    "iso:country":"GT",
    "wof:name":"Pericos",
    "wof:placetype":"locality"
},
  "geometry": {"coordinates":[-89.16667,14.68333],"type":"Point"}
}