{
  "type": "Feature",
  "properties": {
    "gn:admin1_code":"08",
    "gn:asciiname":"Mayalan",
    "gn:country_code":"GT",
    "gn:dem":244,
    "gn:feature_class":"P",
    "gn:feature_code":"PPL",
    "gn:name":"Mayal\u00e1n",
    "gn:population":0,
    "gn:timezone":"America/Guatemala",
    "iso:country":"GT",
    "name:spa_x_preferred":[
        "Mayal\u00e1n"
    ],
    "wof:name":"Mayalan",
    "wof:placetype":"locality"
},
  "geometry": {"coordinates":[-91.08376,15.94256],"type":"Point"}
}