{
  "type": "Feature",
  "properties": {
    "gn:admin1_code":"08",
    "gn:asciiname":"Los Mangales",
    "gn:country_code":"GT",
    "gn:dem":575,
    "gn:feature_class":"P",
    "gn:feature_code":"PPL",
    "gn:name":"Los Mangales",
    "gn:population":0,
    "gn:timezone":"America/Guatemala",
    "iso:country":"GT",
    "name:spa_x_preferred":[
        "Los Mangales"
    ],
    "wof:name":"Los Mangales",
    "wof:placetype":"locality"
},
  "geometry": {"coordinates":[-91.19006,15.84097],"type":"Point"}
}