{
  "type": "Feature",
  "properties": {
    "gn:admin1_code":"08",
    "gn:asciiname":"Siete Pinos",
    "gn:country_code":"GT",
    "gn:dem":2180,
    "gn:feature_class":"P",
    "gn:feature_code":"PPLL",
    "gn:name":"Siete Pinos",
    "gn:population":0,
    "gn:timezone":"America/Guatemala",
    "iso:country":"GT",
    "name:spa_x_preferred":[
        "Siete Pinos"
    ],
    "wof:name":"Siete Pinos",
    "wof:placetype":"locality"
},
  "geometry": {"coordinates":[-91.37282,15.58608],"type":"Point"}
}