{
  "type": "Feature",
  "properties": {
    "gn:admin1_code":"12",
    "gn:asciiname":"Los Tres Reyes",
    "gn:country_code":"GT",
    "gn:dem":62,
    "gn:feature_class":"P",
    "gn:feature_code":"PPL",
    "gn:name":"Los Tres Reyes",
    "gn:population":0,
    "gn:timezone":"America/Guatemala",
    "iso:country":"GT",
    "name:epo_x_preferred":[
        "Los Tres Reyes"
    ],
    "name:spa_x_preferred":[
        "Los Tres Reyes"
    ],
    "wof:name":"Los Tres Reyes",
    "wof:placetype":"locality"
},
  "geometry": {"coordinates":[-90.64118000000001,17.51418],"type":"Point"}
}