{
  "type": "Feature",
  "properties": {
    "gn:admin1_code":"14",
    "gn:asciiname":"Tzujil",
    "gn:country_code":"GT",
    "gn:dem":2402,
    "gn:feature_class":"P",
    "gn:feature_code":"PPL",
    "gn:name":"Tzujil",
    "gn:population":0,
    "gn:timezone":"America/Guatemala",
    "iso:country":"GT",
    "name:spa_x_preferred":[
        "Tzujil"
    ],
    "name:und_x_variant":[
        "Sichugil"
    ],
    "wof:name":"Tzujil",
    "wof:placetype":"locality"
},
  "geometry": {"coordinates":[-91.16793,15.19506],"type":"Point"}
}