{
  "type": "Feature",
  "properties": {
    "gn:admin1_code":"17",
    "gn:asciiname":"El Triunfo",
    "gn:country_code":"GT",
    "gn:dem":2765,
    "gn:feature_class":"P",
    "gn:feature_code":"PPL",
    "gn:name":"El Triunfo",
    "gn:population":0,
    "gn:timezone":"America/Guatemala",
    "iso:country":"GT",
    "name:ceb_x_preferred":[
        "El Triunfo"
    ],
    "name:deu_x_preferred":[
        "El Triunfo"
    ],
    "name:ita_x_preferred":[
        "El Triunfo"
    ],
    "name:nld_x_preferred":[
        "El Triunfo"
    ],
    "name:pol_x_preferred":[
        "El Triunfo"
    ],
    "name:rus_x_preferred":[
        "\u042d\u043b\u044c-\u0422\u0440\u0438\u0443\u043d\u0444\u043e"
    ],
    "name:spa_x_preferred":[
        "El Triunfo"
    ],
    "name:srp_x_preferred":[
        "\u0415\u043b \u0422\u0440\u0438\u0443\u043d\u0444\u043e"
    ],
    "name:swe_x_preferred":[
        "El Triunfo"
    ],
    "wof:name":"El Triunfo",
    "wof:placetype":"locality"
},
  "geometry": {"coordinates":[-91.88036,15.11084],"type":"Point"}
}