{
  "type": "Feature",
  "properties": {
    "gn:admin1_code":"21",
    "gn:asciiname":"Santa Maria Jocopilas",
    "gn:country_code":"GT",
    "gn:dem":1766,
    "gn:feature_class":"P",
    "gn:feature_code":"PPL",
    "gn:name":"Santa Mar\u00eda Jocopilas",
    "gn:population":0,
    "gn:timezone":"America/Guatemala",
    "iso:country":"GT",
    "name:spa_x_preferred":[
        "Santa Mar\u00eda Jocopilas"
    ],
    "wof:name":"Santa Maria Jocopilas",
    "wof:placetype":"locality"
},
  "geometry": {"coordinates":[-91.3283,15.16863],"type":"Point"}
}