{
  "type": "Feature",
  "properties": {
    "gn:admin1_code":"08",
    "gn:asciiname":"Ampliacion Nueva Reforma",
    "gn:country_code":"GT",
    "gn:dem":1503,
    "gn:feature_class":"P",
    "gn:feature_code":"PPL",
    "gn:name":"Ampliaci\u00f3n Nueva Reforma",
    "gn:population":0,
    "gn:timezone":"America/Guatemala",
    "iso:country":"GT",
    "name:spa_x_preferred":[
        "Ampliaci\u00f3n Nueva Reforma"
    ],
    "wof:name":"Ampliacion Nueva Reforma",
    "wof:placetype":"locality"
},
  "geometry": {"coordinates":[-92.09204,15.45003],"type":"Point"}
}