{
  "type": "Feature",
  "properties": {
    "gn:admin1_code":"06",
    "gn:asciiname":"Los Pacheco",
    "gn:country_code":"GT",
    "gn:dem":21,
    "gn:feature_class":"P",
    "gn:feature_code":"PPL",
    "gn:name":"Los Pacheco",
    "gn:population":0,
    "gn:timezone":"America/Guatemala",
    "iso:country":"GT",
    "wof:name":"Los Pacheco",
    "wof:placetype":"locality"
},
  "geometry": {"coordinates":[-90.82666999999999,13.985],"type":"Point"}
}