{
  "type": "Feature",
  "properties": {
    "gn:admin1_code":"08",
    "gn:asciiname":"Los Guayabales",
    "gn:country_code":"GT",
    "gn:dem":1256,
    "gn:feature_class":"P",
    "gn:feature_code":"PPL",
    "gn:name":"Los Guayabales",
    "gn:population":0,
    "gn:timezone":"America/Guatemala",
    "iso:country":"GT",
    "name:spa_x_preferred":[
        "Los Guayabales"
    ],
    "wof:name":"Los Guayabales",
    "wof:placetype":"locality"
},
  "geometry": {"coordinates":[-92.01549,15.41638],"type":"Point"}
}