{
  "type": "Feature",
  "properties": {
    "gn:admin1_code":"08",
    "gn:asciiname":"Tuishoch",
    "gn:country_code":"GT",
    "gn:dem":3412,
    "gn:feature_class":"P",
    "gn:feature_code":"PPL",
    "gn:name":"Tuishoch",
    "gn:population":0,
    "gn:timezone":"America/Guatemala",
    "iso:country":"GT",
    "name:spa_x_preferred":[
        "Tuishoch"
    ],
    "wof:name":"Tuishoch",
    "wof:placetype":"locality"
},
  "geometry": {"coordinates":[-91.50407,15.50869],"type":"Point"}
}