{
  "type": "Feature",
  "properties": {
    "gn:admin1_code":"08",
    "gn:asciiname":"Chinaca",
    "gn:country_code":"GT",
    "gn:dem":2027,
    "gn:feature_class":"P",
    "gn:feature_code":"PPL",
    "gn:name":"Chinac\u00e1",
    "gn:population":0,
    "gn:timezone":"America/Guatemala",
    "iso:country":"GT",
    "name:spa_x_preferred":[
        "Chinac\u00e1"
    ],
    "wof:name":"Chinaca",
    "wof:placetype":"locality"
},
  "geometry": {"coordinates":[-91.42762,15.31588],"type":"Point"}
}