{
  "type": "Feature",
  "properties": {
    "gn:admin1_code":"17",
    "gn:asciiname":"Taxcontze",
    "gn:country_code":"GT",
    "gn:dem":1357,
    "gn:feature_class":"P",
    "gn:feature_code":"PPL",
    "gn:name":"Taxcontz\u00e9",
    "gn:population":0,
    "gn:timezone":"America/Guatemala",
    "iso:country":"GT",
    "name:spa_x_preferred":[
        "Taxcontz\u00e9"
    ],
    "wof:name":"Taxcontze",
    "wof:placetype":"locality"
},
  "geometry": {"coordinates":[-92.05898999999999,15.04591],"type":"Point"}
}