{
  "type": "Feature",
  "properties": {
    "gn:admin1_code":"08",
    "gn:asciiname":"La Hamaca",
    "gn:country_code":"GT",
    "gn:dem":1172,
    "gn:feature_class":"P",
    "gn:feature_code":"PPL",
    "gn:name":"La Hamaca",
    "gn:population":0,
    "gn:timezone":"America/Guatemala",
    "iso:country":"GT",
    "name:spa_x_preferred":[
        "La Hamaca"
    ],
    "wof:name":"La Hamaca",
    "wof:placetype":"locality"
},
  "geometry": {"coordinates":[-91.83976,15.52158],"type":"Point"}
}