{
  "type": "Feature",
  "properties": {
    "gn:admin1_code":"10",
    "gn:asciiname":"Lazareto",
    "gn:country_code":"GT",
    "gn:dem":1368,
    "gn:feature_class":"P",
    "gn:feature_code":"PPL",
    "gn:name":"Lazareto",
    "gn:population":0,
    "gn:timezone":"America/Guatemala",
    "iso:country":"GT",
    "wof:name":"Lazareto",
    "wof:placetype":"locality"
},
  "geometry": {"coordinates":[-89.98333000000002,14.63333],"type":"Point"}
}