{
  "type": "Feature",
  "properties": {
    "gn:admin1_code":"08",
    "gn:asciiname":"Guiya",
    "gn:country_code":"GT",
    "gn:dem":2485,
    "gn:feature_class":"P",
    "gn:feature_code":"PPL",
    "gn:name":"G\u00fciy\u00e1",
    "gn:population":0,
    "gn:timezone":"America/Guatemala",
    "iso:country":"GT",
    "name:spa_x_preferred":[
        "G\u00fciy\u00e1"
    ],
    "wof:name":"Guiya",
    "wof:placetype":"locality"
},
  "geometry": {"coordinates":[-91.85223999999999,15.47688],"type":"Point"}
}